Workbook

Sheet DM Inputs
B2: Discovery Mode & Marketplace Assumptions | C2: FY'24 | D2: FY'25 | E2: FY'26E | F2: FY'27E | H2: Notes
B4: Case selector (repoint to Valuation!$C$3 when the tabs are added to the model) | C4: Base | H4: Drives the FY'26E-FY'27E paths in section E. Bear = adverse for SPOT (autoplay surfaces shrink, enrollment capped, Marquee flat); Bull = the street-style continuation.
B6: A. Group revenue, €M (denominator for basis points)
B7: Total revenue | C7: 15673 | D7: 17186 | E7: 19500 | F7: 21300 | H7: FY'24-FY'25: Form 20-F (FY'25 Premium 15,350, Ad-Supported 1,836). FY'26E-FY'27E: same placeholders as the audiobook tabs; link to IS total revenue.
B8: % y/y growth | D8: =D7/C7-1 -> 0.096535443 | E8: =E7/D7-1 -> 0.13464448 | F8: =F7/E7-1 -> 0.092307692 | H8: Marketplace gross profit must grow at least this fast to hold its margin contribution flat.
B10: B. Reported gross margin and reference points
B11: Consolidated gross margin | C11: 0.301 | D11: 0.32 | E11: 0.332 | F11: 0.345 | H11: FY'24: 30.1% (Q1-Q4 27.6/29.2/31.1/32.2 weighted). FY'25: 32.0% (20-F; Q4 33.1%). FY'26E-FY'27E: consensus placeholders, link to the consensus tab.
B12: Premium gross margin | C12: 0.33 | D12: 0.34 | H12: 20-F: 29% FY'23, 33% FY'24, 34% FY'25; Q2-26 35%. Discovery Mode accrues almost entirely here ('music royalty costs net of certain marketplace programs').
B13: Latest quarter: Q2-26 reported (FY'26E col) and Q3-26 guided (FY'27E col) | E13: 0.334 | F13: 0.329 | H13: Q2-26 letter: 33.4%, +193 bp y/y; Q3-26 guide 32.9% on €5.0bn revenue.
B14: 2030 target: gross margin, low end (FY'24 col) and high end (FY'25 col) | C14: 0.35 | D14: 0.4 | H14: Investor Day 21 May 2026: 35-40% gross margin by 2030, mid-teens revenue CAGR, operating margin above 20%.
B15: Consensus y/y gross-margin expansion, bp (context) | E15: 120 | F15: 130 | H15: Placeholders: 33.2% vs 32.0% and ~34.5% vs 33.2%. Link to the consensus tab (same cells as the audiobook tabs).
B16: Non-marketplace y/y gross-margin expansion, bp (pricing, audiobooks, podcasts, ad mix) | E16: 100 | F16: 80 | H16: Placeholder so the illustrative path on the bridge lands near H1-26 actuals (33.0-33.4%) and the Q3 guide under the Base case. Replace with the model's own GM build excluding marketplace.
B18: C. Marketplace disclosures (Discovery Mode + Marquee + Showcase), €M
B19: Marketplace gross profit contribution, 2021 | C19: 160 | H19: Investor Day 8 Jun 2022: 'more than €160 million' in 2021 (under €20 million in 2018). Treated as the floor.
B20: Marketplace gross profit, 2025 as a multiple of 2021 | C20: 4 | H20: Investor Day 21 May 2026: 2025 marketplace gross profit was four times 2021. Implies a ~41% CAGR 2021-25.
B21: Marketplace gross profit, €M | C21: ='DM Inputs'!$C$19*'DM Inputs'!$C$20^(3/4) -> 452.54834 | D21: ='DM Inputs'!$C$19*'DM Inputs'!$C$20 -> 640 | H21: FY'25 = 2021 x multiple (floor). FY'24 is not disclosed: interpolated at the 2021-25 CAGR, so the FY'25 y/y effect on the bridge is an estimate.
B22: Discovery Mode share of marketplace gross profit (FY'25 col) | D22: 0.8 | H22: KEY LEVER. Not disclosed. Marquee/Showcase are booked as Ad-Supported revenue and that whole segment earned only €330M of gross profit in FY'25 (20-F), which caps them at roughly €150-250M and puts Discovery Mode at 60-80% of marketplace. Used in 'DM share' calibration mode to solve the enrolled share on the bridge; ignored in 'Measured s' mode.
B23: Calibration mode, FY'25: 'DM share' solves s from the share above; 'Measured s' solves the share from the measured s in section E | D23: DM share | H23: The FY'25 identity D = pool x e x s x discount has one free variable. Type exactly 'DM share' or 'Measured s'. Never overwrite the solved cell on the bridge (D12): that breaks the identity and makes FY'25 look like a decline against FY'24.
B25: D. Music royalty pool, €M (the pool the Discovery Mode discount is taken from)
B26: Royalties paid to music rights holders | C26: 9250 | D26: 10100 | E26: ='DM Inputs'!$E$7*$D$27 -> 11459.909 | F26: ='DM Inputs'!$F$7*$D$27 -> 12517.747 | H26: Loud & Clear: $10bn in 2024 and $11bn in 2025, converted at ~1.08 / ~1.09. After all discounts, so the pre-discount pool is ~3% higher. FY'26E-FY'27E scale with revenue at the FY'25 ratio (royalties are the greater of a % of revenue and per-subscriber minimums).
B27: as % of total revenue | C27: =C26/'DM Inputs'!$C$7 -> 0.59018695 | D27: =D26/'DM Inputs'!$D$7 -> 0.58768765 | E27: =E26/'DM Inputs'!$E$7 -> 0.58768765 | F27: =F26/'DM Inputs'!$F$7 -> 0.58768765
B29: E. Discovery Mode structural levers
B30: DM royalty discount on DM-context streams | C30: 0.3 | D30: 0.3 | E30: 0.3 | F30: 0.3 | H30: Program term: the rights holder accepts a 30% lower royalty on streams served in Radio, Autoplay and (from Jan 2024) Mixes. Set a lower FY'27E value to model a claw-back at the major-label renewals.
B31: e: share of all streams served from DM-eligible surfaces (Radio + Autoplay + Mixes), FY'25 | D31: 0.33 | H31: KEY LEVER (Topic 3). Not disclosed. The 2018 prospectus put Spotify-programmed listening at ~30% before Autoplay became default-on and before Smart Shuffle and the Mixes expansion; Spotify says 33% of discoveries happen in algorithmic contexts. Range 25-35%. 'Autoplay growth' moves this lever.
B32: e, FY'26E-FY'27E (active case) = FY'25 + case change below | E32: =$D$31+IF('DM Inputs'!$C$4="Bear",E33,IF('DM Inputs'!$C$4="Bull",E35,E34)) -> 0.335 | F32: =$D$31+IF('DM Inputs'!$C$4="Bear",F33,IF('DM Inputs'!$C$4="Bull",F35,F34)) -> 0.34 | H32: Bull: autoplay / programmed listening keeps gaining share and new surfaces (Smart Shuffle, DJ sessions) are added. Base: slow drift (Reddit mentions of autoplay/recs peaked in 2025; DJ/Smart Shuffle discussion halved since 2024; Smart Shuffle removable from Apr-25). Bear: no growth, or surfaces lose share (users disable autoplay, AI-slop clean-up trims recommendation volume). Case rows are changes vs FY'25 in points.
B33: Bear | E33: 0 | F33: 0.01
B34: Base | E34: 0.005 | F34: 0.01
B35: Bull | E35: 0.015 | F35: 0.02
B36: Measured s, FY'25: enrolled share of eligible-surface streams from sampling (used only in 'Measured s' mode) | D36: 0.33 | H36: Spotify burner-account method (tools/dm_autoplay): share of tracks served in Autoplay / Radio sessions that are Discovery Mode-enrolled, weighted by plays. Enter the sampled figure here and switch the calibration mode in section C; the bridge then back-solves the DM share of marketplace.
B37: s: enrolled share of eligible-surface streams, FY'25 (active) | D37: ='DM GM Bridge'!$D$12 -> 0.51205121 | H37: KEY LEVER (Topic 2). In 'DM share' mode this is solved on the bridge: s = Discovery Mode gross profit / (pool x e x discount). In 'Measured s' mode it is the measured figure above. Do not type over this cell or bridge D12.
B38: s, FY'26E-FY'27E (active case) = FY'25 + case change below | E38: =$D$37+IF('DM Inputs'!$C$4="Bear",E39,IF('DM Inputs'!$C$4="Bull",E41,E40)) -> 0.51205121 | F38: =$D$37+IF('DM Inputs'!$C$4="Bear",F39,IF('DM Inputs'!$C$4="Bull",F41,F40)) -> 0.52205121 | H38: Bull: enrollment keeps rising. Base: creeps up because staying in is defensive (opting out cut radio/autoplay streams 50-70% in the charted cases) even as the lift fades. Bear: flat to down (label pushback, Congressional scrutiny, lifts too small to justify 30%). Case rows are changes vs FY'25 in points, so they stay valid whichever calibration mode is on.
B39: Bear | E39: -0.01 | F39: -0.005
B40: Base | E40: 0 | F40: 0.01
B41: Bull | E41: 0.01 | F41: 0.025
B42: Marquee + Showcase gross profit growth, % y/y (active case) | E42: =IF('DM Inputs'!$C$4="Bear",E43,IF('DM Inputs'!$C$4="Bull",E45,E44)) -> 0.1 | F42: =IF('DM Inputs'!$C$4="Bear",F43,IF('DM Inputs'!$C$4="Bull",F45,F44)) -> 0.1 | H42: Marquee (sponsored recommendation, CPC) and Showcase (home banner) sold to labels; near-100% margin Ad-Supported revenue. Bull +20% (extends 2021-25); Base +10% (below revenue growth, so a small drag in bp); Bear flat.
B43: Bear | E43: 0 | F43: 0
B44: Base | E44: 0.1 | F44: 0.1
B45: Bull | E45: 0.2 | F45: 0.2
B47: Colour key: blue = hard-coded input (notes give source or derivation); light gold = forecast assumption, case-driven cell or placeholder to link to the model; yellow = key lever; black = formula.

Sheet DM GM Bridge
B2: Discovery Mode & Marketplace Gross Margin Bridge | C2: FY'24 | D2: FY'25 | E2: FY'26E | F2: FY'27E | H2: Notes
B4: € in millions unless stated. M = D + Q: D = Discovery Mode royalty discount retained (a reduction of cost of revenue), Q = Marquee and Showcase gross profit (Ad-Supported revenue). Discovery Mode reallocates a fixed pool of Radio / Autoplay / Mixes slots; it does not create streams, so D = pool x e x s x discount whether or not the artist gains.
B6: 1. Calibration at FY'25 (values in the FY'25 column)
B7: Marketplace gross profit (disclosed: 4x 2021) | C7: ='DM Inputs'!$C$21 -> 452.54834 | D7: ='DM Inputs'!$D$21 -> 640 | H7: FY'24 interpolated, FY'25 floor; see inputs section C.
B8: Discovery Mode share of marketplace gross profit (input in 'DM share' mode; solved in 'Measured s' mode) | D8: =IF('DM Inputs'!$D$23="Measured s",IF(D7=0,0,'DM Inputs'!$D$26*'DM Inputs'!$D$31*'DM Inputs'!$D$36*'DM Inputs'!$D$30/D7),'DM Inputs'!$D$22) -> 0.8 | H8: Calibration mode is set on the inputs tab (section C). FY'24 uses the same share, so both years sit on one definition.
B9: D: Discovery Mode gross profit | C9: =C7*D8 -> 362.03867 | D9: =D7*D8 -> 512 | H9: FY'24 at the same share: estimate.
B10: Q: Marquee + Showcase gross profit | C10: =C7-C9 -> 90.509668 | D10: =D7-D9 -> 128
B11: Royalty pool on eligible surfaces = pool x e | D11: ='DM Inputs'!$D$26*'DM Inputs'!$D$31 -> 3333
B12: s: enrolled share of eligible-surface streams = D / (pool x e x discount), or the measured figure | D12: =IF('DM Inputs'!$D$23="Measured s",'DM Inputs'!$D$36,IF(D11*'DM Inputs'!$D$30=0,0,D9/(D11*'DM Inputs'!$D$30))) -> 0.51205121 | H12: Topic 2 of the triangulation matrix. Solved cell: do not type over it. Above 100% means the DM share or e is set too high.
B13: DM-context enrolled streams as a share of all streams = e x s | D13: ='DM Inputs'!$D$31*D12 -> 0.1689769 | H13: 'Share of streams via Discovery Mode' as the calls will phrase it.
B14: Ceiling: D at 100% enrollment of today's surfaces | D14: =D11*'DM Inputs'!$D$30 -> 999.9
B15: Remaining runway at today's surfaces and discount, €M | D15: =D14-D9 -> 487.9 | H15: The whole remaining Discovery Mode lever, before any new surface or a bigger discount.
B16: as bp of FY'25 revenue | D16: =D15/'DM Inputs'!$D$7*10000 -> 283.89387
B18: 2. Discovery Mode Gross Profit (D)
B19: e: eligible-surface share of streams | D19: ='DM Inputs'!$D$31 -> 0.33 | E19: ='DM Inputs'!$E$32 -> 0.335 | F19: ='DM Inputs'!$F$32 -> 0.34 | H19: FY'26E-FY'27E follow the case selector on the inputs tab.
B20: s: enrolled share of eligible-surface streams | D20: =D12 -> 0.51205121 | E20: ='DM Inputs'!$E$38 -> 0.51205121 | F20: ='DM Inputs'!$F$38 -> 0.52205121
B21: e x s: enrolled DM-context streams, share of all streams | D21: =D19*D20 -> 0.1689769 | E21: =E19*E20 -> 0.17153715 | F21: =F19*F20 -> 0.17749741
B22: Music royalty pool | C22: ='DM Inputs'!$C$26 -> 9250 | D22: ='DM Inputs'!$D$26 -> 10100 | E22: ='DM Inputs'!$E$26 -> 11459.909 | F22: ='DM Inputs'!$F$26 -> 12517.747
B23: DM royalty discount | C23: ='DM Inputs'!$C$30 -> 0.3 | D23: ='DM Inputs'!$D$30 -> 0.3 | E23: ='DM Inputs'!$E$30 -> 0.3 | F23: ='DM Inputs'!$F$30 -> 0.3
B24: D: Discovery Mode gross profit = pool x e x s x discount | C24: =C9 -> 362.03867 | D24: =D22*D21*D23 -> 512 | E24: =E22*E21*E23 -> 589.74006 | F24: =F22*F21*F23 -> 666.5603 | H24: FY'24 from the marketplace estimate (section 1); FY'25 reproduces the calibration by construction.
B26: 3. Marquee + Showcase Gross Profit (Q)
B27: % y/y Growth | D27: =D10/C10-1 -> 0.41421356 | E27: ='DM Inputs'!$E$42 -> 0.1 | F27: ='DM Inputs'!$F$42 -> 0.1 | H27: FY'25 implied by the interpolation; FY'26E-FY'27E follow the case selector.
B28: Q: Marquee + Showcase gross profit | C28: =C10 -> 90.509668 | D28: =D10 -> 128 | E28: =D28*(1+E27) -> 140.8 | F28: =E28*(1+F27) -> 154.88
B30: 4. Marketplace Contribution to Gross Profit and Gross Margin
B31: D: Discovery Mode gross profit | C31: =C24 -> 362.03867 | D31: =D24 -> 512 | E31: =E24 -> 589.74006 | F31: =F24 -> 666.5603
B32: Q: Marquee + Showcase gross profit | C32: =C28 -> 90.509668 | D32: =D28 -> 128 | E32: =E28 -> 140.8 | F32: =F28 -> 154.88
B33: Marketplace Contribution to Gross Profit (M) | C33: =C31+C32 -> 452.54834 | D33: =D31+D32 -> 640 | E33: =E31+E32 -> 730.54006 | F33: =F31+F32 -> 821.4403 | H33: Level. Already inside reported FY'24-FY'25 gross profit; for the forecast use the y/y effect row below, not this level.
B34: Total Revenue | C34: ='DM Inputs'!$C$7 -> 15673 | D34: ='DM Inputs'!$D$7 -> 17186 | E34: ='DM Inputs'!$E$7 -> 19500 | F34: ='DM Inputs'!$F$7 -> 21300
B35: % Contribution to Gross Margin, bp | C35: =C33/C34*10000 -> 288.74392 | D35: =D33/D34*10000 -> 372.39614 | E35: =E33/E34*10000 -> 374.63593 | F35: =F33/F34*10000 -> 385.65272 | H35: Level: what marketplace does to gross margin in each year versus no marketplace.
B36: Y/y Change in Contribution, €M | D36: =D33-C33 -> 187.45166 | E36: =E33-D33 -> 90.540063 | F36: =F33-E33 -> 90.900237
B37: Y/y Gross Margin Effect, bp | D37: =D35-C35 -> 83.65222 | E37: =E35-D35 -> 2.2397935 | F37: =F35-E35 -> 11.016793 | H37: Add to the model's y/y gross-margin expansion from other drivers (negative = drag). FY'25 is an estimate of what marketplace contributed to the +190 bp reported; management says about a third of expansion came from the music business.
B38: of which Discovery Mode (change in D), bp | D38: =(D31/D34-C31/C34)*10000 -> 66.921776 | E38: =(E31/E34-D31/D34)*10000 -> 4.5138926 | F38: =(F31/F34-E31/E34)*10000 -> 10.508307
B39: of which Marquee + Showcase (change in Q), bp | D39: =D37-D38 -> 16.730444 | E39: =E37-E38 -> -2.2740991 | F39: =F37-F38 -> 0.50848682
B40: Implied marketplace gross profit growth, % y/y | D40: =D33/C33-1 -> 0.41421356 | E40: =E33/D33-1 -> 0.14146885 | F40: =F33/E33-1 -> 0.12442882 | H40: 2021-25 disclosed CAGR ~41%.
B41: Growth needed to hold the contribution flat = revenue growth, % y/y | D41: ='DM Inputs'!$D$8 -> 0.096535443 | E41: ='DM Inputs'!$E$8 -> 0.13464448 | F41: ='DM Inputs'!$F$8 -> 0.092307692 | H41: Gross margin is a ratio: a marketplace growing slower than this is a drag in bp while still growing in euros.
B42: Consensus y/y gross-margin expansion, bp (context) | E42: ='DM Inputs'!$E$15 -> 120 | F42: ='DM Inputs'!$F$15 -> 130
B43: Marketplace effect as % of consensus expansion (context) | E43: =IF(E42=0,0,E37/E42) -> 0.018664946 | F43: =IF(F42=0,0,F37/F42) -> 0.084744565 | H43: Positive = marketplace supplies that share of the expansion the Street expects; negative = it eats into it.
B45: 5. Illustrative gross-margin path (context; replace the non-marketplace placeholder with the model's own build)
B46: Reported (FY'24-FY'25) / consensus (FY'26E-FY'27E) gross margin | C46: ='DM Inputs'!$C$11 -> 0.301 | D46: ='DM Inputs'!$D$11 -> 0.32 | E46: ='DM Inputs'!$E$11 -> 0.332 | F46: ='DM Inputs'!$F$11 -> 0.345
B47: Non-marketplace y/y expansion, bp (placeholder from inputs) | E47: ='DM Inputs'!$E$16 -> 100 | F47: ='DM Inputs'!$F$16 -> 80
B48: Illustrative gross margin = prior year + non-marketplace + marketplace effect | C48: ='DM Inputs'!$C$11 -> 0.301 | D48: ='DM Inputs'!$D$11 -> 0.32 | E48: =D48+(E47+E37)/10000 -> 0.33022398 | F48: =E48+(F47+F37)/10000 -> 0.33932566
B49: Gap to consensus, bp | E49: =(E48-E46)*10000 -> -17.760207 | F49: =(F48-F46)*10000 -> -56.743413
B50: Reference: 2030 target range | C50: ='DM Inputs'!$C$14 -> 0.35 | D50: ='DM Inputs'!$D$14 -> 0.4 | H50: Low end in the FY'24 column, high end in the FY'25 column; direction marker only.
B52: 6. The three cases side by side (computed from the scenario rows on the inputs tab; independent of the selector)
B53: Bull: D, Discovery Mode gross profit | C53: =C24 -> 362.03867 | D53: =D24 -> 512 | E53: =E22*(D19+'DM Inputs'!$E$35)*(D20+'DM Inputs'!$E$41)*E23 -> 619.20525 | F53: =F22*(D19+'DM Inputs'!$F$35)*(D20+'DM Inputs'!$F$41)*F23 -> 705.88047
B54: Bull: Q, Marquee + Showcase gross profit | C54: =C28 -> 90.509668 | D54: =D28 -> 128 | E54: =D54*(1+'DM Inputs'!$E$45) -> 153.6 | F54: =E54*(1+'DM Inputs'!$F$45) -> 184.32
B55: Bull: M = D + Q | C55: =C53+C54 -> 452.54834 | D55: =D53+D54 -> 640 | E55: =E53+E54 -> 772.80525 | F55: =F53+F54 -> 890.20047
B56: Bull: y/y gross margin effect, bp | D56: =D37 -> 83.65222 | E56: =(E55/E34-D55/D34)*10000 -> 23.914248 | F56: =(F55/F34-E55/E34)*10000 -> 21.624107
B57: Bull: illustrative gross margin | C57: ='DM Inputs'!$C$11 -> 0.301 | D57: ='DM Inputs'!$D$11 -> 0.32 | E57: =D57+(E47+E56)/10000 -> 0.33239142 | F57: =E57+(F47+F56)/10000 -> 0.34255384 | H57: Surfaces and enrollment both keep rising; marketplace keeps adding margin.
B59: Base: D, Discovery Mode gross profit | C59: =C24 -> 362.03867 | D59: =D24 -> 512 | E59: =E22*(D19+'DM Inputs'!$E$34)*(D20+'DM Inputs'!$E$40)*E23 -> 589.74006 | F59: =F22*(D19+'DM Inputs'!$F$34)*(D20+'DM Inputs'!$F$40)*F23 -> 666.5603
B60: Base: Q, Marquee + Showcase gross profit | C60: =C28 -> 90.509668 | D60: =D28 -> 128 | E60: =D60*(1+'DM Inputs'!$E$44) -> 140.8 | F60: =E60*(1+'DM Inputs'!$F$44) -> 154.88
B61: Base: M = D + Q | C61: =C59+C60 -> 452.54834 | D61: =D59+D60 -> 640 | E61: =E59+E60 -> 730.54006 | F61: =F59+F60 -> 821.4403
B62: Base: y/y gross margin effect, bp | D62: =D37 -> 83.65222 | E62: =(E61/E34-D61/D34)*10000 -> 2.2397935 | F62: =(F61/F34-E61/E34)*10000 -> 11.016793
B63: Base: illustrative gross margin | C63: ='DM Inputs'!$C$11 -> 0.301 | D63: ='DM Inputs'!$D$11 -> 0.32 | E63: =D63+(E47+E62)/10000 -> 0.33022398 | F63: =E63+(F47+F62)/10000 -> 0.33932566 | H63: What the two datasets describe: slow drift in surfaces, enrollment creeping up because staying in is defensive; marketplace roughly neutral to slightly positive for the margin path.
B65: Bear: D, Discovery Mode gross profit | C65: =C24 -> 362.03867 | D65: =D24 -> 512 | E65: =E22*(D19+'DM Inputs'!$E$33)*(D20+'DM Inputs'!$E$39)*E23 -> 569.59266 | F65: =F22*(D19+'DM Inputs'!$F$33)*(D20+'DM Inputs'!$F$39)*F23 -> 647.40815
B66: Bear: Q, Marquee + Showcase gross profit | C66: =C28 -> 90.509668 | D66: =D28 -> 128 | E66: =D66*(1+'DM Inputs'!$E$43) -> 128 | F66: =E66*(1+'DM Inputs'!$F$43) -> 128
B67: Bear: M = D + Q | C67: =C65+C66 -> 452.54834 | D67: =D65+D66 -> 640 | E67: =E65+E66 -> 697.59266 | F67: =F65+F66 -> 775.40815
B68: Bear: y/y gross margin effect, bp | D68: =D37 -> 83.65222 | E68: =(E67/E34-D67/D34)*10000 -> -14.656309 | F68: =(F67/F34-E67/E34)*10000 -> 6.3015569
B69: Bear: illustrative gross margin | C69: ='DM Inputs'!$C$11 -> 0.301 | D69: ='DM Inputs'!$D$11 -> 0.32 | E69: =D69+(E47+E68)/10000 -> 0.32853437 | F69: =E69+(F47+F68)/10000 -> 0.33716452 | H69: Enrollment slips and Marquee stalls; marketplace becomes a drag because it grows slower than revenue.

Sheet DM Sensitivity
B2: Discovery Mode Sensitivities
B4: FY'27E Discovery Mode contribution to gross margin, bp, for e (rows) x s (columns). Uses the FY'27E royalty pool, discount and revenue from the bridge. Compare with the FY'25 level at the bottom.
B5: e \ s | C5: 0.4 | D5: 0.5 | E5: 0.6 | F5: 0.7 | G5: 0.8 | H5: 0.9 | I5: 1
B6: 0.12 | C6: ='DM GM Bridge'!$F$22*$B6*C$5*'DM GM Bridge'!$F$23/'DM GM Bridge'!$F$34*10000 -> 84.627022 | D6: ='DM GM Bridge'!$F$22*$B6*D$5*'DM GM Bridge'!$F$23/'DM GM Bridge'!$F$34*10000 -> 105.78378 | E6: ='DM GM Bridge'!$F$22*$B6*E$5*'DM GM Bridge'!$F$23/'DM GM Bridge'!$F$34*10000 -> 126.94053 | F6: ='DM GM Bridge'!$F$22*$B6*F$5*'DM GM Bridge'!$F$23/'DM GM Bridge'!$F$34*10000 -> 148.09729 | G6: ='DM GM Bridge'!$F$22*$B6*G$5*'DM GM Bridge'!$F$23/'DM GM Bridge'!$F$34*10000 -> 169.25404 | H6: ='DM GM Bridge'!$F$22*$B6*H$5*'DM GM Bridge'!$F$23/'DM GM Bridge'!$F$34*10000 -> 190.4108 | I6: ='DM GM Bridge'!$F$22*$B6*I$5*'DM GM Bridge'!$F$23/'DM GM Bridge'!$F$34*10000 -> 211.56755
B7: 0.15 | C7: ='DM GM Bridge'!$F$22*$B7*C$5*'DM GM Bridge'!$F$23/'DM GM Bridge'!$F$34*10000 -> 105.78378 | D7: ='DM GM Bridge'!$F$22*$B7*D$5*'DM GM Bridge'!$F$23/'DM GM Bridge'!$F$34*10000 -> 132.22972 | E7: ='DM GM Bridge'!$F$22*$B7*E$5*'DM GM Bridge'!$F$23/'DM GM Bridge'!$F$34*10000 -> 158.67567 | F7: ='DM GM Bridge'!$F$22*$B7*F$5*'DM GM Bridge'!$F$23/'DM GM Bridge'!$F$34*10000 -> 185.12161 | G7: ='DM GM Bridge'!$F$22*$B7*G$5*'DM GM Bridge'!$F$23/'DM GM Bridge'!$F$34*10000 -> 211.56755 | H7: ='DM GM Bridge'!$F$22*$B7*H$5*'DM GM Bridge'!$F$23/'DM GM Bridge'!$F$34*10000 -> 238.0135 | I7: ='DM GM Bridge'!$F$22*$B7*I$5*'DM GM Bridge'!$F$23/'DM GM Bridge'!$F$34*10000 -> 264.45944
B8: 0.18 | C8: ='DM GM Bridge'!$F$22*$B8*C$5*'DM GM Bridge'!$F$23/'DM GM Bridge'!$F$34*10000 -> 126.94053 | D8: ='DM GM Bridge'!$F$22*$B8*D$5*'DM GM Bridge'!$F$23/'DM GM Bridge'!$F$34*10000 -> 158.67567 | E8: ='DM GM Bridge'!$F$22*$B8*E$5*'DM GM Bridge'!$F$23/'DM GM Bridge'!$F$34*10000 -> 190.4108 | F8: ='DM GM Bridge'!$F$22*$B8*F$5*'DM GM Bridge'!$F$23/'DM GM Bridge'!$F$34*10000 -> 222.14593 | G8: ='DM GM Bridge'!$F$22*$B8*G$5*'DM GM Bridge'!$F$23/'DM GM Bridge'!$F$34*10000 -> 253.88107 | H8: ='DM GM Bridge'!$F$22*$B8*H$5*'DM GM Bridge'!$F$23/'DM GM Bridge'!$F$34*10000 -> 285.6162 | I8: ='DM GM Bridge'!$F$22*$B8*I$5*'DM GM Bridge'!$F$23/'DM GM Bridge'!$F$34*10000 -> 317.35133
B9: 0.21 | C9: ='DM GM Bridge'!$F$22*$B9*C$5*'DM GM Bridge'!$F$23/'DM GM Bridge'!$F$34*10000 -> 148.09729 | D9: ='DM GM Bridge'!$F$22*$B9*D$5*'DM GM Bridge'!$F$23/'DM GM Bridge'!$F$34*10000 -> 185.12161 | E9: ='DM GM Bridge'!$F$22*$B9*E$5*'DM GM Bridge'!$F$23/'DM GM Bridge'!$F$34*10000 -> 222.14593 | F9: ='DM GM Bridge'!$F$22*$B9*F$5*'DM GM Bridge'!$F$23/'DM GM Bridge'!$F$34*10000 -> 259.17025 | G9: ='DM GM Bridge'!$F$22*$B9*G$5*'DM GM Bridge'!$F$23/'DM GM Bridge'!$F$34*10000 -> 296.19458 | H9: ='DM GM Bridge'!$F$22*$B9*H$5*'DM GM Bridge'!$F$23/'DM GM Bridge'!$F$34*10000 -> 333.2189 | I9: ='DM GM Bridge'!$F$22*$B9*I$5*'DM GM Bridge'!$F$23/'DM GM Bridge'!$F$34*10000 -> 370.24322
B10: 0.24 | C10: ='DM GM Bridge'!$F$22*$B10*C$5*'DM GM Bridge'!$F$23/'DM GM Bridge'!$F$34*10000 -> 169.25404 | D10: ='DM GM Bridge'!$F$22*$B10*D$5*'DM GM Bridge'!$F$23/'DM GM Bridge'!$F$34*10000 -> 211.56755 | E10: ='DM GM Bridge'!$F$22*$B10*E$5*'DM GM Bridge'!$F$23/'DM GM Bridge'!$F$34*10000 -> 253.88107 | F10: ='DM GM Bridge'!$F$22*$B10*F$5*'DM GM Bridge'!$F$23/'DM GM Bridge'!$F$34*10000 -> 296.19458 | G10: ='DM GM Bridge'!$F$22*$B10*G$5*'DM GM Bridge'!$F$23/'DM GM Bridge'!$F$34*10000 -> 338.50809 | H10: ='DM GM Bridge'!$F$22*$B10*H$5*'DM GM Bridge'!$F$23/'DM GM Bridge'!$F$34*10000 -> 380.8216 | I10: ='DM GM Bridge'!$F$22*$B10*I$5*'DM GM Bridge'!$F$23/'DM GM Bridge'!$F$34*10000 -> 423.13511
B11: FY'25 Discovery Mode contribution, bp (bridge) | C11: ='DM GM Bridge'!D24/'DM GM Bridge'!D34*10000 -> 297.91691
B12: FY'25 e and s (bridge) | C12: ='DM GM Bridge'!D19 -> 0.33 | D12: ='DM GM Bridge'!D20 -> 0.51205121
B13: Reading: each 10 pt of enrolled share is worth pool x e x 10% x discount / revenue (roughly 55 bp in FY'27E at e = 33%); with e and s flat the lever adds nothing further in bp. Cells beyond s = 100% are impossible.
B15: Implied FY'25 enrolled share s for e (rows) x Discovery Mode share of marketplace gross profit (columns). The expert-call answers on Topics 2 and 3 should land in one of these cells; above 100% is impossible.
B16: e \ DM share of marketplace GP | C16: 0.35 | D16: 0.45 | E16: 0.55 | F16: 0.65
B17: 0.12 | C17: =IF($B17*'DM Inputs'!$D$30=0,0,('DM Inputs'!$D$21*C$16)/('DM Inputs'!$D$26*$B17*'DM Inputs'!$D$30)) -> 0.61606161 | D17: =IF($B17*'DM Inputs'!$D$30=0,0,('DM Inputs'!$D$21*D$16)/('DM Inputs'!$D$26*$B17*'DM Inputs'!$D$30)) -> 0.79207921 | E17: =IF($B17*'DM Inputs'!$D$30=0,0,('DM Inputs'!$D$21*E$16)/('DM Inputs'!$D$26*$B17*'DM Inputs'!$D$30)) -> 0.96809681 | F17: =IF($B17*'DM Inputs'!$D$30=0,0,('DM Inputs'!$D$21*F$16)/('DM Inputs'!$D$26*$B17*'DM Inputs'!$D$30)) -> 1.1441144
B18: 0.15 | C18: =IF($B18*'DM Inputs'!$D$30=0,0,('DM Inputs'!$D$21*C$16)/('DM Inputs'!$D$26*$B18*'DM Inputs'!$D$30)) -> 0.49284928 | D18: =IF($B18*'DM Inputs'!$D$30=0,0,('DM Inputs'!$D$21*D$16)/('DM Inputs'!$D$26*$B18*'DM Inputs'!$D$30)) -> 0.63366337 | E18: =IF($B18*'DM Inputs'!$D$30=0,0,('DM Inputs'!$D$21*E$16)/('DM Inputs'!$D$26*$B18*'DM Inputs'!$D$30)) -> 0.77447745 | F18: =IF($B18*'DM Inputs'!$D$30=0,0,('DM Inputs'!$D$21*F$16)/('DM Inputs'!$D$26*$B18*'DM Inputs'!$D$30)) -> 0.91529153
B19: 0.18 | C19: =IF($B19*'DM Inputs'!$D$30=0,0,('DM Inputs'!$D$21*C$16)/('DM Inputs'!$D$26*$B19*'DM Inputs'!$D$30)) -> 0.41070774 | D19: =IF($B19*'DM Inputs'!$D$30=0,0,('DM Inputs'!$D$21*D$16)/('DM Inputs'!$D$26*$B19*'DM Inputs'!$D$30)) -> 0.52805281 | E19: =IF($B19*'DM Inputs'!$D$30=0,0,('DM Inputs'!$D$21*E$16)/('DM Inputs'!$D$26*$B19*'DM Inputs'!$D$30)) -> 0.64539787 | F19: =IF($B19*'DM Inputs'!$D$30=0,0,('DM Inputs'!$D$21*F$16)/('DM Inputs'!$D$26*$B19*'DM Inputs'!$D$30)) -> 0.76274294
B20: 0.21 | C20: =IF($B20*'DM Inputs'!$D$30=0,0,('DM Inputs'!$D$21*C$16)/('DM Inputs'!$D$26*$B20*'DM Inputs'!$D$30)) -> 0.3520352 | D20: =IF($B20*'DM Inputs'!$D$30=0,0,('DM Inputs'!$D$21*D$16)/('DM Inputs'!$D$26*$B20*'DM Inputs'!$D$30)) -> 0.45261669 | E20: =IF($B20*'DM Inputs'!$D$30=0,0,('DM Inputs'!$D$21*E$16)/('DM Inputs'!$D$26*$B20*'DM Inputs'!$D$30)) -> 0.55319818 | F20: =IF($B20*'DM Inputs'!$D$30=0,0,('DM Inputs'!$D$21*F$16)/('DM Inputs'!$D$26*$B20*'DM Inputs'!$D$30)) -> 0.65377966
B21: 0.24 | C21: =IF($B21*'DM Inputs'!$D$30=0,0,('DM Inputs'!$D$21*C$16)/('DM Inputs'!$D$26*$B21*'DM Inputs'!$D$30)) -> 0.3080308 | D21: =IF($B21*'DM Inputs'!$D$30=0,0,('DM Inputs'!$D$21*D$16)/('DM Inputs'!$D$26*$B21*'DM Inputs'!$D$30)) -> 0.3960396 | E21: =IF($B21*'DM Inputs'!$D$30=0,0,('DM Inputs'!$D$21*E$16)/('DM Inputs'!$D$26*$B21*'DM Inputs'!$D$30)) -> 0.4840484 | F21: =IF($B21*'DM Inputs'!$D$30=0,0,('DM Inputs'!$D$21*F$16)/('DM Inputs'!$D$26*$B21*'DM Inputs'!$D$30)) -> 0.57205721
B23: FY'27E y/y marketplace gross margin effect, bp, for the active case with e (rows) x s (columns) in FY'27E; Q and FY'26E held at the active case.
B24: e \ s | C24: 0.4 | D24: 0.5 | E24: 0.6 | F24: 0.7 | G24: 0.8 | H24: 0.9 | I24: 1
B25: 0.12 | C25: =(('DM GM Bridge'!$F$22*$B25*C$24*'DM GM Bridge'!$F$23+'DM GM Bridge'!$F$28)/'DM GM Bridge'!$F$34-'DM GM Bridge'!$E$35/10000)*10000 -> -217.29529 | D25: =(('DM GM Bridge'!$F$22*$B25*D$24*'DM GM Bridge'!$F$23+'DM GM Bridge'!$F$28)/'DM GM Bridge'!$F$34-'DM GM Bridge'!$E$35/10000)*10000 -> -196.13854 | E25: =(('DM GM Bridge'!$F$22*$B25*E$24*'DM GM Bridge'!$F$23+'DM GM Bridge'!$F$28)/'DM GM Bridge'!$F$34-'DM GM Bridge'!$E$35/10000)*10000 -> -174.98178 | F25: =(('DM GM Bridge'!$F$22*$B25*F$24*'DM GM Bridge'!$F$23+'DM GM Bridge'!$F$28)/'DM GM Bridge'!$F$34-'DM GM Bridge'!$E$35/10000)*10000 -> -153.82503 | G25: =(('DM GM Bridge'!$F$22*$B25*G$24*'DM GM Bridge'!$F$23+'DM GM Bridge'!$F$28)/'DM GM Bridge'!$F$34-'DM GM Bridge'!$E$35/10000)*10000 -> -132.66827 | H25: =(('DM GM Bridge'!$F$22*$B25*H$24*'DM GM Bridge'!$F$23+'DM GM Bridge'!$F$28)/'DM GM Bridge'!$F$34-'DM GM Bridge'!$E$35/10000)*10000 -> -111.51152 | I25: =(('DM GM Bridge'!$F$22*$B25*I$24*'DM GM Bridge'!$F$23+'DM GM Bridge'!$F$28)/'DM GM Bridge'!$F$34-'DM GM Bridge'!$E$35/10000)*10000 -> -90.35476
B26: 0.15 | C26: =(('DM GM Bridge'!$F$22*$B26*C$24*'DM GM Bridge'!$F$23+'DM GM Bridge'!$F$28)/'DM GM Bridge'!$F$34-'DM GM Bridge'!$E$35/10000)*10000 -> -196.13854 | D26: =(('DM GM Bridge'!$F$22*$B26*D$24*'DM GM Bridge'!$F$23+'DM GM Bridge'!$F$28)/'DM GM Bridge'!$F$34-'DM GM Bridge'!$E$35/10000)*10000 -> -169.69259 | E26: =(('DM GM Bridge'!$F$22*$B26*E$24*'DM GM Bridge'!$F$23+'DM GM Bridge'!$F$28)/'DM GM Bridge'!$F$34-'DM GM Bridge'!$E$35/10000)*10000 -> -143.24665 | F26: =(('DM GM Bridge'!$F$22*$B26*F$24*'DM GM Bridge'!$F$23+'DM GM Bridge'!$F$28)/'DM GM Bridge'!$F$34-'DM GM Bridge'!$E$35/10000)*10000 -> -116.8007 | G26: =(('DM GM Bridge'!$F$22*$B26*G$24*'DM GM Bridge'!$F$23+'DM GM Bridge'!$F$28)/'DM GM Bridge'!$F$34-'DM GM Bridge'!$E$35/10000)*10000 -> -90.35476 | H26: =(('DM GM Bridge'!$F$22*$B26*H$24*'DM GM Bridge'!$F$23+'DM GM Bridge'!$F$28)/'DM GM Bridge'!$F$34-'DM GM Bridge'!$E$35/10000)*10000 -> -63.908815 | I26: =(('DM GM Bridge'!$F$22*$B26*I$24*'DM GM Bridge'!$F$23+'DM GM Bridge'!$F$28)/'DM GM Bridge'!$F$34-'DM GM Bridge'!$E$35/10000)*10000 -> -37.462871
B27: 0.18 | C27: =(('DM GM Bridge'!$F$22*$B27*C$24*'DM GM Bridge'!$F$23+'DM GM Bridge'!$F$28)/'DM GM Bridge'!$F$34-'DM GM Bridge'!$E$35/10000)*10000 -> -174.98178 | D27: =(('DM GM Bridge'!$F$22*$B27*D$24*'DM GM Bridge'!$F$23+'DM GM Bridge'!$F$28)/'DM GM Bridge'!$F$34-'DM GM Bridge'!$E$35/10000)*10000 -> -143.24665 | E27: =(('DM GM Bridge'!$F$22*$B27*E$24*'DM GM Bridge'!$F$23+'DM GM Bridge'!$F$28)/'DM GM Bridge'!$F$34-'DM GM Bridge'!$E$35/10000)*10000 -> -111.51152 | F27: =(('DM GM Bridge'!$F$22*$B27*F$24*'DM GM Bridge'!$F$23+'DM GM Bridge'!$F$28)/'DM GM Bridge'!$F$34-'DM GM Bridge'!$E$35/10000)*10000 -> -79.776382 | G27: =(('DM GM Bridge'!$F$22*$B27*G$24*'DM GM Bridge'!$F$23+'DM GM Bridge'!$F$28)/'DM GM Bridge'!$F$34-'DM GM Bridge'!$E$35/10000)*10000 -> -48.041249 | H27: =(('DM GM Bridge'!$F$22*$B27*H$24*'DM GM Bridge'!$F$23+'DM GM Bridge'!$F$28)/'DM GM Bridge'!$F$34-'DM GM Bridge'!$E$35/10000)*10000 -> -16.306116 | I27: =(('DM GM Bridge'!$F$22*$B27*I$24*'DM GM Bridge'!$F$23+'DM GM Bridge'!$F$28)/'DM GM Bridge'!$F$34-'DM GM Bridge'!$E$35/10000)*10000 -> 15.429018
B28: 0.21 | C28: =(('DM GM Bridge'!$F$22*$B28*C$24*'DM GM Bridge'!$F$23+'DM GM Bridge'!$F$28)/'DM GM Bridge'!$F$34-'DM GM Bridge'!$E$35/10000)*10000 -> -153.82503 | D28: =(('DM GM Bridge'!$F$22*$B28*D$24*'DM GM Bridge'!$F$23+'DM GM Bridge'!$F$28)/'DM GM Bridge'!$F$34-'DM GM Bridge'!$E$35/10000)*10000 -> -116.8007 | E28: =(('DM GM Bridge'!$F$22*$B28*E$24*'DM GM Bridge'!$F$23+'DM GM Bridge'!$F$28)/'DM GM Bridge'!$F$34-'DM GM Bridge'!$E$35/10000)*10000 -> -79.776382 | F28: =(('DM GM Bridge'!$F$22*$B28*F$24*'DM GM Bridge'!$F$23+'DM GM Bridge'!$F$28)/'DM GM Bridge'!$F$34-'DM GM Bridge'!$E$35/10000)*10000 -> -42.75206 | G28: =(('DM GM Bridge'!$F$22*$B28*G$24*'DM GM Bridge'!$F$23+'DM GM Bridge'!$F$28)/'DM GM Bridge'!$F$34-'DM GM Bridge'!$E$35/10000)*10000 -> -5.7277379 | H28: =(('DM GM Bridge'!$F$22*$B28*H$24*'DM GM Bridge'!$F$23+'DM GM Bridge'!$F$28)/'DM GM Bridge'!$F$34-'DM GM Bridge'!$E$35/10000)*10000 -> 31.296584 | I28: =(('DM GM Bridge'!$F$22*$B28*I$24*'DM GM Bridge'!$F$23+'DM GM Bridge'!$F$28)/'DM GM Bridge'!$F$34-'DM GM Bridge'!$E$35/10000)*10000 -> 68.320906
B29: 0.24 | C29: =(('DM GM Bridge'!$F$22*$B29*C$24*'DM GM Bridge'!$F$23+'DM GM Bridge'!$F$28)/'DM GM Bridge'!$F$34-'DM GM Bridge'!$E$35/10000)*10000 -> -132.66827 | D29: =(('DM GM Bridge'!$F$22*$B29*D$24*'DM GM Bridge'!$F$23+'DM GM Bridge'!$F$28)/'DM GM Bridge'!$F$34-'DM GM Bridge'!$E$35/10000)*10000 -> -90.35476 | E29: =(('DM GM Bridge'!$F$22*$B29*E$24*'DM GM Bridge'!$F$23+'DM GM Bridge'!$F$28)/'DM GM Bridge'!$F$34-'DM GM Bridge'!$E$35/10000)*10000 -> -48.041249 | F29: =(('DM GM Bridge'!$F$22*$B29*F$24*'DM GM Bridge'!$F$23+'DM GM Bridge'!$F$28)/'DM GM Bridge'!$F$34-'DM GM Bridge'!$E$35/10000)*10000 -> -5.7277379 | G29: =(('DM GM Bridge'!$F$22*$B29*G$24*'DM GM Bridge'!$F$23+'DM GM Bridge'!$F$28)/'DM GM Bridge'!$F$34-'DM GM Bridge'!$E$35/10000)*10000 -> 36.585773 | H29: =(('DM GM Bridge'!$F$22*$B29*H$24*'DM GM Bridge'!$F$23+'DM GM Bridge'!$F$28)/'DM GM Bridge'!$F$34-'DM GM Bridge'!$E$35/10000)*10000 -> 78.899284 | I29: =(('DM GM Bridge'!$F$22*$B29*I$24*'DM GM Bridge'!$F$23+'DM GM Bridge'!$F$28)/'DM GM Bridge'!$F$34-'DM GM Bridge'!$E$35/10000)*10000 -> 121.2128

Sheet DM Evidence
B2: What the Two Datasets Say, Mapped to the Levers | C2: 2023 | D2: 2024 | E2: 2025 | F2: 2026 YTD | H2: Notes
B4: Every number on this tab is a link to 'DM Data Sentiment', 'DM Data Campaigns' or 'DM Data Artist Reports'. Column G names the lever on the inputs tab the item informs: e = eligible-surface share (autoplay), s = enrolled share, quality = engagement of DM streams, backlash = regulatory / listener risk.
B6: 1. Autoplay / recommendation discussion, r/spotify + r/truespotify (lever: e)
B7: Posts about autoplay / recommendations, share of all posts | C7: ='DM Data Sentiment'!C9 -> 0.071119091 | D7: ='DM Data Sentiment'!D9 -> 0.099231772 | E7: ='DM Data Sentiment'!E9 -> 0.11836966 | F7: ='DM Data Sentiment'!F9 -> 0.10285303 | G7: e | H7: Rose through 2025 and slipped in 2026 YTD. Weak evidence of a plateau: the 2026 archive is thin after June and total subreddit volume is falling.
B8: Posts mentioning DJ / daylist / Smart Shuffle, share of topic posts | C8: ='DM Data Sentiment'!C27 -> 0.1975798 | D8: ='DM Data Sentiment'!D27 -> 0.17202348 | E8: ='DM Data Sentiment'!E27 -> 0.14341014 | F8: ='DM Data Sentiment'!F27 -> 0.15967366 | G8: e | H8: The AI DJ / Smart Shuffle novelty is fading: mention share down from 20% to 14-16%, and Smart Shuffle became removable in April 2025 (959-upvote post).
B9: Posts mentioning Discover Weekly / Release Radar, share of topic posts | C9: ='DM Data Sentiment'!C25 -> 0.076569998 | D9: ='DM Data Sentiment'!D25 -> 0.079932923 | E9: ='DM Data Sentiment'!E25 -> 0.10451613 | F9: ='DM Data Sentiment'!F25 -> 0.0998446 | G9: e
B10: Posts on AI-generated music, share of topic posts | C10: ='DM Data Sentiment'!C17 -> 0.0031295639 | D10: ='DM Data Sentiment'!D17 -> 0.0060089435 | E10: ='DM Data Sentiment'!E17 -> 0.031152074 | F10: ='DM Data Sentiment'!F17 -> 0.046231546 | G10: e (quality) | H10: From 0.3% to 4.6%. The clean-up Spotify announced in Sept 2025 (AI labels, spam filter) trims recommendation inventory: the main channel by which e could fall.
B11: Posts on repetitive / same songs, share of topic posts | C11: ='DM Data Sentiment'!C13 -> 0.0538285 | D11: ='DM Data Sentiment'!D13 -> 0.067635551 | E11: ='DM Data Sentiment'!E13 -> 0.071520737 | F11: ='DM Data Sentiment'!F13 -> 0.090909091 | G11: quality | H11: The listener-side symptom of low-intent DM streams; rising every year.
B12: Posts on paid / pushed content (Discovery Mode, payola, sponsored), share of topic posts | C12: ='DM Data Sentiment'!C21 -> 0.0050073023 | D12: ='DM Data Sentiment'!D21 -> 0.012437116 | E12: ='DM Data Sentiment'!E21 -> 0.010138249 | F12: ='DM Data Sentiment'!F21 -> 0.018259518 | G12: backlash | H12: Small but at its highest in 2026. Listeners do not see the program by name (one post in 4,000 says 'discovery mode'); they see 'sponsored recs'.
B14: 2. Sentiment of the scored sample, 1,000 posts per year (lever: e, churn)
B15: Share negative, headline | C15: ='DM Data Sentiment'!C34 -> 0.34 | D15: ='DM Data Sentiment'!D34 -> 0.366 | E15: ='DM Data Sentiment'!E34 -> 0.391 | F15: ='DM Data Sentiment'!F34 -> 0.424
B16: Share negative, intact posts only (the cleaner series) | C16: ='DM Data Sentiment'!C40 -> 0.37940379 | D16: ='DM Data Sentiment'!D40 -> 0.39206534 | E16: ='DM Data Sentiment'!E40 -> 0.39854318 | F16: ='DM Data Sentiment'!F40 -> 0.43546695 | G16: e, churn | H16: Removed posts score ~21% negative vs ~40% for intact ones and were 26% of the 2023 sample but 4-5% in 2025-26. On intact posts the deterioration is ~5-6 pt, not 8; still rising, 2026 H1 the worst half, 2026 Q3 back to 39%.
B17: Net sentiment, pp | C17: ='DM Data Sentiment'!C36 -> -10.8 | D17: ='DM Data Sentiment'!D36 -> -12 | E17: ='DM Data Sentiment'!E36 -> -11.2 | F17: ='DM Data Sentiment'!F36 -> -18.2
B18: Share of scored posts with cancel / switch language | C18: ='DM Data Sentiment'!C42 -> 0.006 | D18: ='DM Data Sentiment'!D42 -> 0.014 | E18: ='DM Data Sentiment'!E42 -> 0.012 | F18: ='DM Data Sentiment'!F42 -> 0.024 | G18: churn | H18: 56 posts in total; directional only.
B19: Discovery love posts, share positive | C19: ='DM Data Sentiment'!C61 -> 0.71428571 | D19: ='DM Data Sentiment'!D61 -> 0.44444444 | E19: ='DM Data Sentiment'!E61 -> 0.70588235 | F19: ='DM Data Sentiment'!F61 -> 0.68 | H19: The pro-recommendation pocket is stable: the base is polarising, not uniformly souring.
B20: DJ / daylist / Smart Shuffle posts, share negative | C20: ='DM Data Sentiment'!C60 -> 0.51243781 | D20: ='DM Data Sentiment'!D60 -> 0.53448276 | E20: ='DM Data Sentiment'!E60 -> 0.56944444 | F20: ='DM Data Sentiment'!F60 -> 0.59281437
B21: Discover Weekly / Release Radar posts, share negative | C21: ='DM Data Sentiment'!C58 -> 0.4375 | D21: ='DM Data Sentiment'!D58 -> 0.53947368 | E21: ='DM Data Sentiment'!E58 -> 0.5862069 | F21: ='DM Data Sentiment'!F58 -> 0.60185185
B23: 3. Discovery Mode efficacy, artist side (levers: s, quality) | C23: Value | D23: n | G23: Lever
B24: Median Spotify-reported lift, campaigns Aug 2023 - Nov 2024 | C24: ='DM Data Campaigns'!H14 -> 4.0591695 | D24: =COUNT('DM Data Campaigns'!H4:H7) -> 4 | G24: s | H24: Lift = DM-context streams in campaign / prior 28 days - 1. Direction consistent with a crowded pool; magnitude not evidence (n = 4 vs 3).
B25: Median Spotify-reported lift, campaigns Jan 2025 - Jul 2026 | C25: ='DM Data Campaigns'!H15 -> 0.77991651 | D25: =COUNT('DM Data Campaigns'!H8:H10) -> 3 | G25: s | H25: Billboard reports the same fade from managers: 200-300% gains in year one, 20-30% later.
B26: Saves + playlist adds per Discovery Mode listener, median | C26: ='DM Data Campaigns'!L18 -> 0.012422383 | D26: =COUNT('DM Data Campaigns'!L4:L12) -> 8 | G26: quality | H26: Spotify's own intent metric; 0.7-4.8% per campaign, latest (Sep 2026) the lowest.
B27: Saves per listener, artists' overall audience, median | C27: ='DM Data Campaigns'!L28 -> 0.19854954 | D27: =COUNT('DM Data Campaigns'!L24:L27) -> 4 | G27: quality | H27: Different definition, so an order of magnitude: DM streams are ~16x lower intent. They still carry a royalty, at 70%.
B28: Overall audience keeps the song this many times more often | C28: ='DM Data Campaigns'!L29 -> 15.983208 | G28: quality
B29: Share of first-hand reports that went up: artists under 10k listeners | C29: ='DM Data Artist Reports'!H33 -> 1 | D29: ='DM Data Artist Reports'!G33 -> 8 | G29: s | H29: All eight small artists went up; the long tail keeps enrolling.
B30: Share of first-hand reports that went up: artists 10k+ listeners | C30: ='DM Data Artist Reports'!H36 -> 0.38888889 | D30: ='DM Data Artist Reports'!G36 -> 18 | G30: s | H30: Above 10k it is a coin flip; mid-size independents are the enrollment that can leave.
B31: Share of first-hand reports that went up: all | C31: ='DM Data Artist Reports'!H50 -> 0.55714286 | D31: ='DM Data Artist Reports'!H43 -> 70 | G31: s
B32: First-hand reports saying Discover Weekly / algorithmic streams fell after opting in | C32: ='DM Data Artist Reports'!H48 -> 12 | D32: ='DM Data Artist Reports'!H43 -> 70 | G32: s | H32: The 'suppression' complaint: enrolling may trade editorial / Discover Weekly reach for Radio / Autoplay reach.
B33: DM-context streams as share of an enrolled established artist's streams, median | C33: ='DM Data Artist Reports'!H62 -> 0.039396552 | D33: =COUNT('DM Data Artist Reports'!H54:H57) -> 4 | G33: e | H33: 3.5-5% for 500k+ monthly-stream artists; 33-50% for catalog-heavy or tiny artists.
B34: Switching Discovery Mode off: average change in radio / autoplay streams (two charted cases) | C34: ='DM Data Campaigns'!H39 -> -0.60714286 | D34: =COUNT('DM Data Campaigns'!H35,'DM Data Campaigns'!H36) -> 2 | G34: s (defensive) | H34: Enrollment has become defensive, which supports enrollment creeping up even as the lift fades: good for s, bad for the program's reputation.
B35: Artist pairs: up / down in 2023 (early rollout) | C35: ='DM Data Artist Reports'!D25 -> 1 | D35: ='DM Data Artist Reports'!E25 -> 5 | G35: s | H35: The 18 numeric pairs trend toward 'Up' over time (mix shift toward small artists); they cannot support the time claim either way.
B36: Artist pairs: up / down in 2025-26 | C36: ='DM Data Artist Reports'!D27+'DM Data Artist Reports'!D28 -> 3 | D36: ='DM Data Artist Reports'!E27+'DM Data Artist Reports'!E28 -> 0 | G36: s
B38: Both datasets support the direction (plateauing autoplay salience, fading lift, defensive enrollment) but not magnitudes: self-selected Reddit samples, tiny n on the campaign side, a tone model that is not aspect-based. Treat them as inputs to the Base-case paths, worth about a point a year on e, and as the reason s is modelled as creeping rather than compounding.

Sheet DM Data Sentiment
B2: Autoplay & Recommendation Discussion on Reddit, by Year | C2: 2023 | D2: 2024 | E2: 2025 | F2: 2026 YTD | H2: Notes
B4: Every post in r/spotify and r/truespotify, Jan 2023 - Oct 1 2026 (210,365 posts; Arctic Shift archive; posts only, no comments). Topic posts match the filter in the notes column below and are at least 20 characters. 2026 covers Jan 1 - Oct 1 and the archive thins out after June.
B6: A. Corpus by year (full population)
B7: All posts | C7: 67394 | D7: 72114 | E7: 45831 | F7: 25026 | H7: Counts from the archive.
B8: Posts about autoplay / recommendations | C8: 4793 | D8: 7156 | E8: 5425 | F8: 2574 | H8: Topic filter: auto-?play|algorithm|\balgo\b|recommend|\brecs\b|suggest(ed|ions)|discover weekly|release radar|daylist|smart shuffle|spotify dj|\bthe dj\b|\bai dj\b|\bdj x\b|made for you|daily mix|\bradio\b|on repeat|enhance
B9: share of all posts | C9: =C8/C7 -> 0.071119091 | D9: =D8/D7 -> 0.099231772 | E9: =E8/E7 -> 0.11836966 | F9: =F8/F7 -> 0.10285303
B11: B. Themes by year (keyword patterns on topic posts; a post can carry several themes)
B12: Repetitive / same songs | C12: 258 | D12: 484 | E12: 388 | F12: 234 | H12: Pattern: same (songs?|artists?|stuff|music|tracks?|\d+)|repetitiv|over and over|keeps? playing|on loop|recycl
B13: share of topic posts | C13: =C12/C8 -> 0.0538285 | D13: =D12/D8 -> 0.067635551 | E13: =E12/E8 -> 0.071520737 | F13: =F12/F8 -> 0.090909091
B14: Bad or off-taste recs | C14: 40 | D14: 54 | E14: 47 | F14: 19 | H14: Pattern: (bad|terrible|awful|garbage|trash|horrible|worse|worst|useless|shit|broken)\s+(\w+\s+)?(recommend|algorithm|algo|recs|suggestions|autoplay)|doesn'?t know (me|my)|not my (taste|style|genre)|nothing (new|i like)|ruin(ed|ing|s)? my
B15: share of topic posts | C15: =C14/C8 -> 0.0083455039 | D15: =D14/D8 -> 0.0075461151 | E15: =E14/E8 -> 0.0086635945 | F15: =F14/F8 -> 0.0073815074
B16: AI-generated music | C16: 15 | D16: 43 | E16: 169 | F16: 119 | H16: Pattern: \bai[- ](music|songs?|generated|slop|artists?|tracks?|bands?)\b|ai-made|fake (artists?|bands?)
B17: share of topic posts | C17: =C16/C8 -> 0.0031295639 | D17: =D16/D8 -> 0.0060089435 | E17: =E16/E8 -> 0.031152074 | F17: =F16/F8 -> 0.046231546
B18: Autoplay control (can't turn off) | C18: 21 | D18: 29 | E18: 23 | F18: 7 | H18: Pattern: (turn(ing)? off|disable|stop|get rid of)\s+(the\s+)?auto-?play|auto-?play (keeps|won'?t|can'?t|turns? (itself )?back)|without (my )?(permission|asking)
B19: share of topic posts | C19: =C18/C8 -> 0.0043813895 | D19: =D18/D8 -> 0.0040525433 | E19: =E18/E8 -> 0.0042396313 | F19: =F18/F8 -> 0.0027195027
B20: Paid / pushed content | C20: 24 | D20: 89 | E20: 55 | F20: 47 | H20: Pattern: discovery mode|payola|\bpushed\b|promoted|sponsored|paid (to|for) (push|promot)|pay to
B21: share of topic posts | C21: =C20/C8 -> 0.0050073023 | D21: =D20/D8 -> 0.012437116 | E21: =E20/E8 -> 0.010138249 | F21: =F20/F8 -> 0.018259518
B22: Discovery love | C22: 58 | D22: 81 | E22: 104 | F22: 52 | H22: Pattern: (love|great|amazing|best|awesome|good)\s+(\w+\s+)?(discover weekly|daylist|recommend|algorithm|algo|recs|radio|dj)|discovered (so many|a lot|new)|found (so many|new|great)
B23: share of topic posts | C23: =C22/C8 -> 0.012100981 | D23: =D22/D8 -> 0.011319173 | E23: =E22/E8 -> 0.019170507 | F23: =F22/F8 -> 0.02020202
B24: Feature: Discover Weekly / Release Radar | C24: 367 | D24: 572 | E24: 567 | F24: 257 | H24: Pattern: discover weekly|release radar
B25: share of topic posts | C25: =C24/C8 -> 0.076569998 | D25: =D24/D8 -> 0.079932923 | E25: =E24/E8 -> 0.10451613 | F25: =F24/F8 -> 0.0998446
B26: Feature: DJ / daylist / Smart Shuffle | C26: 947 | D26: 1231 | E26: 778 | F26: 411 | H26: Pattern: spotify dj|\bthe dj\b|\bai dj\b|daylist|smart shuffle
B27: share of topic posts | C27: =C26/C8 -> 0.1975798 | D27: =D26/D8 -> 0.17202348 | E27: =E26/E8 -> 0.14341014 | F27: =F26/F8 -> 0.15967366
B29: C. Scored sample (COUNTIFS on 'DM Data Scored Posts'; cardiffnlp/twitter-roberta-base-sentiment-latest, overall tone)
B30: Posts scored | C30: =COUNTIFS('DM Data Scored Posts'!$C$4:$C$4003,2023) -> 1000 | D30: =COUNTIFS('DM Data Scored Posts'!$C$4:$C$4003,2024) -> 1000 | E30: =COUNTIFS('DM Data Scored Posts'!$C$4:$C$4003,2025) -> 1000 | F30: =COUNTIFS('DM Data Scored Posts'!$C$4:$C$4003,2026) -> 1000
B31: Negative | C31: =COUNTIFS('DM Data Scored Posts'!$C$4:$C$4003,2023,'DM Data Scored Posts'!$G$4:$G$4003,"negative") -> 340 | D31: =COUNTIFS('DM Data Scored Posts'!$C$4:$C$4003,2024,'DM Data Scored Posts'!$G$4:$G$4003,"negative") -> 366 | E31: =COUNTIFS('DM Data Scored Posts'!$C$4:$C$4003,2025,'DM Data Scored Posts'!$G$4:$G$4003,"negative") -> 391 | F31: =COUNTIFS('DM Data Scored Posts'!$C$4:$C$4003,2026,'DM Data Scored Posts'!$G$4:$G$4003,"negative") -> 424
B32: Neutral | C32: =COUNTIFS('DM Data Scored Posts'!$C$4:$C$4003,2023,'DM Data Scored Posts'!$G$4:$G$4003,"neutral") -> 428 | D32: =COUNTIFS('DM Data Scored Posts'!$C$4:$C$4003,2024,'DM Data Scored Posts'!$G$4:$G$4003,"neutral") -> 388 | E32: =COUNTIFS('DM Data Scored Posts'!$C$4:$C$4003,2025,'DM Data Scored Posts'!$G$4:$G$4003,"neutral") -> 330 | F32: =COUNTIFS('DM Data Scored Posts'!$C$4:$C$4003,2026,'DM Data Scored Posts'!$G$4:$G$4003,"neutral") -> 334
B33: Positive | C33: =COUNTIFS('DM Data Scored Posts'!$C$4:$C$4003,2023,'DM Data Scored Posts'!$G$4:$G$4003,"positive") -> 232 | D33: =COUNTIFS('DM Data Scored Posts'!$C$4:$C$4003,2024,'DM Data Scored Posts'!$G$4:$G$4003,"positive") -> 246 | E33: =COUNTIFS('DM Data Scored Posts'!$C$4:$C$4003,2025,'DM Data Scored Posts'!$G$4:$G$4003,"positive") -> 279 | F33: =COUNTIFS('DM Data Scored Posts'!$C$4:$C$4003,2026,'DM Data Scored Posts'!$G$4:$G$4003,"positive") -> 242
B34: Share negative, all scored posts | C34: =C31/C30 -> 0.34 | D34: =D31/D30 -> 0.366 | E34: =E31/E30 -> 0.391 | F34: =F31/F30 -> 0.424
B35: Share positive, all scored posts | C35: =C33/C30 -> 0.232 | D35: =D33/D30 -> 0.246 | E35: =E33/E30 -> 0.279 | F35: =F33/F30 -> 0.242
B36: Net sentiment, pp (positive minus negative share) | C36: =(C33-C31)/C30*100 -> -10.8 | D36: =(D33-D31)/D30*100 -> -12 | E36: =(E33-E31)/E30*100 -> -11.2 | F36: =(F33-F31)/F30*100 -> -18.2
B37: Removed / deleted posts in sample (title only) | C37: =COUNTIFS('DM Data Scored Posts'!$C$4:$C$4003,2023,'DM Data Scored Posts'!$S$4:$S$4003,1) -> 262 | D37: =COUNTIFS('DM Data Scored Posts'!$C$4:$C$4003,2024,'DM Data Scored Posts'!$S$4:$S$4003,1) -> 143 | E37: =COUNTIFS('DM Data Scored Posts'!$C$4:$C$4003,2025,'DM Data Scored Posts'!$S$4:$S$4003,1) -> 39 | F37: =COUNTIFS('DM Data Scored Posts'!$C$4:$C$4003,2026,'DM Data Scored Posts'!$S$4:$S$4003,1) -> 47 | H37: Post body shows [removed] or [deleted]; the model scores the title alone.
B38: of which negative | C38: =COUNTIFS('DM Data Scored Posts'!$C$4:$C$4003,2023,'DM Data Scored Posts'!$S$4:$S$4003,1,'DM Data Scored Posts'!$G$4:$G$4003,"negative") -> 60 | D38: =COUNTIFS('DM Data Scored Posts'!$C$4:$C$4003,2024,'DM Data Scored Posts'!$S$4:$S$4003,1,'DM Data Scored Posts'!$G$4:$G$4003,"negative") -> 30 | E38: =COUNTIFS('DM Data Scored Posts'!$C$4:$C$4003,2025,'DM Data Scored Posts'!$S$4:$S$4003,1,'DM Data Scored Posts'!$G$4:$G$4003,"negative") -> 8 | F38: =COUNTIFS('DM Data Scored Posts'!$C$4:$C$4003,2026,'DM Data Scored Posts'!$S$4:$S$4003,1,'DM Data Scored Posts'!$G$4:$G$4003,"negative") -> 9
B39: share negative among removed / deleted | C39: =IF(C37=0,0,C38/C37) -> 0.22900763 | D39: =IF(D37=0,0,D38/D37) -> 0.20979021 | E39: =IF(E37=0,0,E38/E37) -> 0.20512821 | F39: =IF(F37=0,0,F38/F37) -> 0.19148936
B40: Share negative, intact posts only | C40: =(C31-C38)/(C30-C37) -> 0.37940379 | D40: =(D31-D38)/(D30-D37) -> 0.39206534 | E40: =(E31-E38)/(E30-E37) -> 0.39854318 | F40: =(F31-F38)/(F30-F37) -> 0.43546695 | H40: The cleaner series: removed posts score ~21% negative vs ~40% for intact ones and were a quarter of the 2023 sample.
B41: Posts with cancel / switch language | C41: =COUNTIFS('DM Data Scored Posts'!$C$4:$C$4003,2023,'DM Data Scored Posts'!$T$4:$T$4003,1) -> 6 | D41: =COUNTIFS('DM Data Scored Posts'!$C$4:$C$4003,2024,'DM Data Scored Posts'!$T$4:$T$4003,1) -> 14 | E41: =COUNTIFS('DM Data Scored Posts'!$C$4:$C$4003,2025,'DM Data Scored Posts'!$T$4:$T$4003,1) -> 12 | F41: =COUNTIFS('DM Data Scored Posts'!$C$4:$C$4003,2026,'DM Data Scored Posts'!$T$4:$T$4003,1) -> 24 | H41: Regex: cancel | unsubscrib | switch(ed|ing) to (apple|tidal|youtube|deezer|qobuz|amazon) | goodbye spotify | leaving spotify | moved to (apple|tidal|youtube). Flag computed in Python from the full post text.
B42: share of scored posts | C42: =C41/C30 -> 0.006 | D42: =D41/D30 -> 0.014 | E42: =E41/E30 -> 0.012 | F42: =F41/F30 -> 0.024
B44: Share negative within theme (scored posts carrying the theme) | C44: 2023 | D44: 2024 | E44: 2025 | F44: 2026 YTD
B45: Repetitive / same songs: posts in sample | C45: =COUNTIFS('DM Data Scored Posts'!$C$4:$C$4003,2023,'DM Data Scored Posts'!$K$4:$K$4003,"Yes") -> 54 | D45: =COUNTIFS('DM Data Scored Posts'!$C$4:$C$4003,2024,'DM Data Scored Posts'!$K$4:$K$4003,"Yes") -> 57 | E45: =COUNTIFS('DM Data Scored Posts'!$C$4:$C$4003,2025,'DM Data Scored Posts'!$K$4:$K$4003,"Yes") -> 81 | F45: =COUNTIFS('DM Data Scored Posts'!$C$4:$C$4003,2026,'DM Data Scored Posts'!$K$4:$K$4003,"Yes") -> 89
B46: share negative | C46: =IF(C45=0,0,COUNTIFS('DM Data Scored Posts'!$C$4:$C$4003,2023,'DM Data Scored Posts'!$K$4:$K$4003,"Yes",'DM Data Scored Posts'!$G$4:$G$4003,"negative")/C45) -> 0.62962963 | D46: =IF(D45=0,0,COUNTIFS('DM Data Scored Posts'!$C$4:$C$4003,2024,'DM Data Scored Posts'!$K$4:$K$4003,"Yes",'DM Data Scored Posts'!$G$4:$G$4003,"negative")/D45) -> 0.71929825 | E46: =IF(E45=0,0,COUNTIFS('DM Data Scored Posts'!$C$4:$C$4003,2025,'DM Data Scored Posts'!$K$4:$K$4003,"Yes",'DM Data Scored Posts'!$G$4:$G$4003,"negative")/E45) -> 0.74074074 | F46: =IF(F45=0,0,COUNTIFS('DM Data Scored Posts'!$C$4:$C$4003,2026,'DM Data Scored Posts'!$K$4:$K$4003,"Yes",'DM Data Scored Posts'!$G$4:$G$4003,"negative")/F45) -> 0.65168539
B47: Bad or off-taste recs: posts in sample | C47: =COUNTIFS('DM Data Scored Posts'!$C$4:$C$4003,2023,'DM Data Scored Posts'!$L$4:$L$4003,"Yes") -> 10 | D47: =COUNTIFS('DM Data Scored Posts'!$C$4:$C$4003,2024,'DM Data Scored Posts'!$L$4:$L$4003,"Yes") -> 10 | E47: =COUNTIFS('DM Data Scored Posts'!$C$4:$C$4003,2025,'DM Data Scored Posts'!$L$4:$L$4003,"Yes") -> 11 | F47: =COUNTIFS('DM Data Scored Posts'!$C$4:$C$4003,2026,'DM Data Scored Posts'!$L$4:$L$4003,"Yes") -> 4
B48: share negative | C48: =IF(C47=0,0,COUNTIFS('DM Data Scored Posts'!$C$4:$C$4003,2023,'DM Data Scored Posts'!$L$4:$L$4003,"Yes",'DM Data Scored Posts'!$G$4:$G$4003,"negative")/C47) -> 0.7 | D48: =IF(D47=0,0,COUNTIFS('DM Data Scored Posts'!$C$4:$C$4003,2024,'DM Data Scored Posts'!$L$4:$L$4003,"Yes",'DM Data Scored Posts'!$G$4:$G$4003,"negative")/D47) -> 0.8 | E48: =IF(E47=0,0,COUNTIFS('DM Data Scored Posts'!$C$4:$C$4003,2025,'DM Data Scored Posts'!$L$4:$L$4003,"Yes",'DM Data Scored Posts'!$G$4:$G$4003,"negative")/E47) -> 0.63636364 | F48: =IF(F47=0,0,COUNTIFS('DM Data Scored Posts'!$C$4:$C$4003,2026,'DM Data Scored Posts'!$L$4:$L$4003,"Yes",'DM Data Scored Posts'!$G$4:$G$4003,"negative")/F47) -> 1
B49: AI-generated music: posts in sample | C49: =COUNTIFS('DM Data Scored Posts'!$C$4:$C$4003,2023,'DM Data Scored Posts'!$M$4:$M$4003,"Yes") -> 2 | D49: =COUNTIFS('DM Data Scored Posts'!$C$4:$C$4003,2024,'DM Data Scored Posts'!$M$4:$M$4003,"Yes") -> 8 | E49: =COUNTIFS('DM Data Scored Posts'!$C$4:$C$4003,2025,'DM Data Scored Posts'!$M$4:$M$4003,"Yes") -> 33 | F49: =COUNTIFS('DM Data Scored Posts'!$C$4:$C$4003,2026,'DM Data Scored Posts'!$M$4:$M$4003,"Yes") -> 41
B50: share negative | C50: =IF(C49=0,0,COUNTIFS('DM Data Scored Posts'!$C$4:$C$4003,2023,'DM Data Scored Posts'!$M$4:$M$4003,"Yes",'DM Data Scored Posts'!$G$4:$G$4003,"negative")/C49) -> 0.5 | D50: =IF(D49=0,0,COUNTIFS('DM Data Scored Posts'!$C$4:$C$4003,2024,'DM Data Scored Posts'!$M$4:$M$4003,"Yes",'DM Data Scored Posts'!$G$4:$G$4003,"negative")/D49) -> 0.75 | E50: =IF(E49=0,0,COUNTIFS('DM Data Scored Posts'!$C$4:$C$4003,2025,'DM Data Scored Posts'!$M$4:$M$4003,"Yes",'DM Data Scored Posts'!$G$4:$G$4003,"negative")/E49) -> 0.66666667 | F50: =IF(F49=0,0,COUNTIFS('DM Data Scored Posts'!$C$4:$C$4003,2026,'DM Data Scored Posts'!$M$4:$M$4003,"Yes",'DM Data Scored Posts'!$G$4:$G$4003,"negative")/F49) -> 0.65853659
B51: Autoplay control (can't turn off): posts in sample | C51: =COUNTIFS('DM Data Scored Posts'!$C$4:$C$4003,2023,'DM Data Scored Posts'!$N$4:$N$4003,"Yes") -> 2 | D51: =COUNTIFS('DM Data Scored Posts'!$C$4:$C$4003,2024,'DM Data Scored Posts'!$N$4:$N$4003,"Yes") -> 6 | E51: =COUNTIFS('DM Data Scored Posts'!$C$4:$C$4003,2025,'DM Data Scored Posts'!$N$4:$N$4003,"Yes") -> 6 | F51: =COUNTIFS('DM Data Scored Posts'!$C$4:$C$4003,2026,'DM Data Scored Posts'!$N$4:$N$4003,"Yes") -> 4
B52: share negative | C52: =IF(C51=0,0,COUNTIFS('DM Data Scored Posts'!$C$4:$C$4003,2023,'DM Data Scored Posts'!$N$4:$N$4003,"Yes",'DM Data Scored Posts'!$G$4:$G$4003,"negative")/C51) -> 0.5 | D52: =IF(D51=0,0,COUNTIFS('DM Data Scored Posts'!$C$4:$C$4003,2024,'DM Data Scored Posts'!$N$4:$N$4003,"Yes",'DM Data Scored Posts'!$G$4:$G$4003,"negative")/D51) -> 0.66666667 | E52: =IF(E51=0,0,COUNTIFS('DM Data Scored Posts'!$C$4:$C$4003,2025,'DM Data Scored Posts'!$N$4:$N$4003,"Yes",'DM Data Scored Posts'!$G$4:$G$4003,"negative")/E51) -> 1 | F52: =IF(F51=0,0,COUNTIFS('DM Data Scored Posts'!$C$4:$C$4003,2026,'DM Data Scored Posts'!$N$4:$N$4003,"Yes",'DM Data Scored Posts'!$G$4:$G$4003,"negative")/F51) -> 0.75
B53: Paid / pushed content: posts in sample | C53: =COUNTIFS('DM Data Scored Posts'!$C$4:$C$4003,2023,'DM Data Scored Posts'!$O$4:$O$4003,"Yes") -> 5 | D53: =COUNTIFS('DM Data Scored Posts'!$C$4:$C$4003,2024,'DM Data Scored Posts'!$O$4:$O$4003,"Yes") -> 15 | E53: =COUNTIFS('DM Data Scored Posts'!$C$4:$C$4003,2025,'DM Data Scored Posts'!$O$4:$O$4003,"Yes") -> 10 | F53: =COUNTIFS('DM Data Scored Posts'!$C$4:$C$4003,2026,'DM Data Scored Posts'!$O$4:$O$4003,"Yes") -> 19
B54: share negative | C54: =IF(C53=0,0,COUNTIFS('DM Data Scored Posts'!$C$4:$C$4003,2023,'DM Data Scored Posts'!$O$4:$O$4003,"Yes",'DM Data Scored Posts'!$G$4:$G$4003,"negative")/C53) -> 0.6 | D54: =IF(D53=0,0,COUNTIFS('DM Data Scored Posts'!$C$4:$C$4003,2024,'DM Data Scored Posts'!$O$4:$O$4003,"Yes",'DM Data Scored Posts'!$G$4:$G$4003,"negative")/D53) -> 0.73333333 | E54: =IF(E53=0,0,COUNTIFS('DM Data Scored Posts'!$C$4:$C$4003,2025,'DM Data Scored Posts'!$O$4:$O$4003,"Yes",'DM Data Scored Posts'!$G$4:$G$4003,"negative")/E53) -> 0.4 | F54: =IF(F53=0,0,COUNTIFS('DM Data Scored Posts'!$C$4:$C$4003,2026,'DM Data Scored Posts'!$O$4:$O$4003,"Yes",'DM Data Scored Posts'!$G$4:$G$4003,"negative")/F53) -> 0.42105263
B55: Discovery love: posts in sample | C55: =COUNTIFS('DM Data Scored Posts'!$C$4:$C$4003,2023,'DM Data Scored Posts'!$P$4:$P$4003,"Yes") -> 14 | D55: =COUNTIFS('DM Data Scored Posts'!$C$4:$C$4003,2024,'DM Data Scored Posts'!$P$4:$P$4003,"Yes") -> 9 | E55: =COUNTIFS('DM Data Scored Posts'!$C$4:$C$4003,2025,'DM Data Scored Posts'!$P$4:$P$4003,"Yes") -> 17 | F55: =COUNTIFS('DM Data Scored Posts'!$C$4:$C$4003,2026,'DM Data Scored Posts'!$P$4:$P$4003,"Yes") -> 25
B56: share negative | C56: =IF(C55=0,0,COUNTIFS('DM Data Scored Posts'!$C$4:$C$4003,2023,'DM Data Scored Posts'!$P$4:$P$4003,"Yes",'DM Data Scored Posts'!$G$4:$G$4003,"negative")/C55) -> 0.14285714 | D56: =IF(D55=0,0,COUNTIFS('DM Data Scored Posts'!$C$4:$C$4003,2024,'DM Data Scored Posts'!$P$4:$P$4003,"Yes",'DM Data Scored Posts'!$G$4:$G$4003,"negative")/D55) -> 0.33333333 | E56: =IF(E55=0,0,COUNTIFS('DM Data Scored Posts'!$C$4:$C$4003,2025,'DM Data Scored Posts'!$P$4:$P$4003,"Yes",'DM Data Scored Posts'!$G$4:$G$4003,"negative")/E55) -> 0.17647059 | F56: =IF(F55=0,0,COUNTIFS('DM Data Scored Posts'!$C$4:$C$4003,2026,'DM Data Scored Posts'!$P$4:$P$4003,"Yes",'DM Data Scored Posts'!$G$4:$G$4003,"negative")/F55) -> 0.2
B57: Feature: Discover Weekly / Release Radar: posts in sample | C57: =COUNTIFS('DM Data Scored Posts'!$C$4:$C$4003,2023,'DM Data Scored Posts'!$Q$4:$Q$4003,"Yes") -> 64 | D57: =COUNTIFS('DM Data Scored Posts'!$C$4:$C$4003,2024,'DM Data Scored Posts'!$Q$4:$Q$4003,"Yes") -> 76 | E57: =COUNTIFS('DM Data Scored Posts'!$C$4:$C$4003,2025,'DM Data Scored Posts'!$Q$4:$Q$4003,"Yes") -> 87 | F57: =COUNTIFS('DM Data Scored Posts'!$C$4:$C$4003,2026,'DM Data Scored Posts'!$Q$4:$Q$4003,"Yes") -> 108
B58: share negative | C58: =IF(C57=0,0,COUNTIFS('DM Data Scored Posts'!$C$4:$C$4003,2023,'DM Data Scored Posts'!$Q$4:$Q$4003,"Yes",'DM Data Scored Posts'!$G$4:$G$4003,"negative")/C57) -> 0.4375 | D58: =IF(D57=0,0,COUNTIFS('DM Data Scored Posts'!$C$4:$C$4003,2024,'DM Data Scored Posts'!$Q$4:$Q$4003,"Yes",'DM Data Scored Posts'!$G$4:$G$4003,"negative")/D57) -> 0.53947368 | E58: =IF(E57=0,0,COUNTIFS('DM Data Scored Posts'!$C$4:$C$4003,2025,'DM Data Scored Posts'!$Q$4:$Q$4003,"Yes",'DM Data Scored Posts'!$G$4:$G$4003,"negative")/E57) -> 0.5862069 | F58: =IF(F57=0,0,COUNTIFS('DM Data Scored Posts'!$C$4:$C$4003,2026,'DM Data Scored Posts'!$Q$4:$Q$4003,"Yes",'DM Data Scored Posts'!$G$4:$G$4003,"negative")/F57) -> 0.60185185
B59: Feature: DJ / daylist / Smart Shuffle: posts in sample | C59: =COUNTIFS('DM Data Scored Posts'!$C$4:$C$4003,2023,'DM Data Scored Posts'!$R$4:$R$4003,"Yes") -> 201 | D59: =COUNTIFS('DM Data Scored Posts'!$C$4:$C$4003,2024,'DM Data Scored Posts'!$R$4:$R$4003,"Yes") -> 174 | E59: =COUNTIFS('DM Data Scored Posts'!$C$4:$C$4003,2025,'DM Data Scored Posts'!$R$4:$R$4003,"Yes") -> 144 | F59: =COUNTIFS('DM Data Scored Posts'!$C$4:$C$4003,2026,'DM Data Scored Posts'!$R$4:$R$4003,"Yes") -> 167
B60: share negative | C60: =IF(C59=0,0,COUNTIFS('DM Data Scored Posts'!$C$4:$C$4003,2023,'DM Data Scored Posts'!$R$4:$R$4003,"Yes",'DM Data Scored Posts'!$G$4:$G$4003,"negative")/C59) -> 0.51243781 | D60: =IF(D59=0,0,COUNTIFS('DM Data Scored Posts'!$C$4:$C$4003,2024,'DM Data Scored Posts'!$R$4:$R$4003,"Yes",'DM Data Scored Posts'!$G$4:$G$4003,"negative")/D59) -> 0.53448276 | E60: =IF(E59=0,0,COUNTIFS('DM Data Scored Posts'!$C$4:$C$4003,2025,'DM Data Scored Posts'!$R$4:$R$4003,"Yes",'DM Data Scored Posts'!$G$4:$G$4003,"negative")/E59) -> 0.56944444 | F60: =IF(F59=0,0,COUNTIFS('DM Data Scored Posts'!$C$4:$C$4003,2026,'DM Data Scored Posts'!$R$4:$R$4003,"Yes",'DM Data Scored Posts'!$G$4:$G$4003,"negative")/F59) -> 0.59281437
B61: Discovery love: share positive | C61: =IF(C55=0,0,COUNTIFS('DM Data Scored Posts'!$C$4:$C$4003,2023,'DM Data Scored Posts'!$P$4:$P$4003,"Yes",'DM Data Scored Posts'!$G$4:$G$4003,"positive")/C55) -> 0.71428571 | D61: =IF(D55=0,0,COUNTIFS('DM Data Scored Posts'!$C$4:$C$4003,2024,'DM Data Scored Posts'!$P$4:$P$4003,"Yes",'DM Data Scored Posts'!$G$4:$G$4003,"positive")/D55) -> 0.44444444 | E61: =IF(E55=0,0,COUNTIFS('DM Data Scored Posts'!$C$4:$C$4003,2025,'DM Data Scored Posts'!$P$4:$P$4003,"Yes",'DM Data Scored Posts'!$G$4:$G$4003,"positive")/E55) -> 0.70588235 | F61: =IF(F55=0,0,COUNTIFS('DM Data Scored Posts'!$C$4:$C$4003,2026,'DM Data Scored Posts'!$P$4:$P$4003,"Yes",'DM Data Scored Posts'!$G$4:$G$4003,"positive")/F55) -> 0.68 | H61: The pro-recommendation pocket: stable at ~1-2% of topic posts, mostly positive.
B63: Caveats: keyword themes are approximate ('radio', 'the DJ' match unrelated uses); the model scores overall tone, not tone toward the algorithm, and misreads sarcasm; counts are from the archive and fall with subreddit activity, so use shares. Reproduce: autoplay.py -> export_autoplay_excel.py (earlier session).

Sheet DM Data Scored Posts
B2: Scored autoplay / recommendation posts, r/spotify + r/truespotify (random sample of up to 1,000 per year, 2023 - Oct 1 2026)
B3: Date | C3: Year | D3: Subreddit | E3: Post text (title. body; first 150 chars) | F3: Upvotes | G3: Sentiment | H3: P(negative) | I3: P(neutral) | J3: P(positive) | K3: Repetitive / same songs | L3: Bad or off-taste recs | M3: AI-generated music | N3: Autoplay control (can't turn off) | O3: Paid / pushed content | P3: Discovery love | Q3: Feature: Discover Weekly / Release Radar | R3: Feature: DJ / daylist / Smart Shuffle | S3: Removed / deleted (1 = yes) | T3: Cancel / switch language (1 = yes) | U3: Reddit link
B4: 44927.387 | C4: =YEAR(B4) -> 2023 | D4: truespotify | E4: Is the Spotify layout intentionally confusing?. I grew up with the internet and I'm very adept at navigating new websites and apps etc.. So this is no | F4: 10 | G4: negative | H4: 0.4884 | I4: 0.4306 | J4: 0.081 | Q4: Yes | S4: 0 | T4: 0 | U4: https://www.reddit.com/comments/100fzhz
B5: 44927.614 | C5: =YEAR(B5) -> 2023 | D5: spotify | E5: Recommendations not working in the playlist. [removed] | F5: 1 | G5: negative | H5: 0.6663 | I5: 0.3224 | J5: 0.0114 | S5: 1 | T5: 0 | U5: https://www.reddit.com/comments/100l2dv
B6: 44929.182 | C6: =YEAR(B6) -> 2023 | D6: spotify | E6: Upbeat party ambient and conversation aide / presence amplifier - ambitious background grooves. [ Designed as a "start and forget" playlist for weeken | F6: 3 | G6: positive | H6: 0.0064 | I6: 0.4817 | J6: 0.5119 | S6: 0 | T6: 0 | U6: https://www.reddit.com/comments/101xy9b
B7: 44929.234 | C7: =YEAR(B7) -> 2023 | D7: spotify | E7: music recommendation. [removed] | F7: 1 | G7: neutral | H7: 0.0085 | I7: 0.9002 | J7: 0.0914 | S7: 1 | T7: 0 | U7: https://www.reddit.com/comments/101zgfc
B8: 44930.209 | C8: =YEAR(B8) -> 2023 | D8: spotify | E8: Why won't my disovery weekly change genres? For an entire year now it's only recommended Japanese Instrumental.. [removed] | F8: 1 | G8: negative | H8: 0.8488 | I8: 0.1425 | J8: 0.0087 | S8: 1 | T8: 0 | U8: https://www.reddit.com/comments/102uj2h
B9: 44930.641 | C9: =YEAR(B9) -> 2023 | D9: spotify | E9: French Songs or Songs related to France. HEllo, i'm preparing an episode of my podcast related to France, do you have any suggestions about songs in F | F9: 2 | G9: neutral | H9: 0.0084 | I9: 0.7345 | J9: 0.2571 | S9: 0 | T9: 0 | U9: https://www.reddit.com/comments/103680r
B10: 44930.673 | C10: =YEAR(B10) -> 2023 | D10: spotify | E10: A very sincere f*** you to the people calling their album Daily Mix 1. [removed] | F10: 5 | G10: negative | H10: 0.8743 | I10: 0.1161 | J10: 0.0096 | S10: 1 | T10: 0 | U10: https://www.reddit.com/comments/1037c0h
B11: 44932.927 | C11: =YEAR(B11) -> 2023 | D11: spotify | E11: Best recommendations? Yes but no. It’s so bad…. [removed] | F11: 1 | G11: negative | H11: 0.9302 | I11: 0.0609 | J11: 0.0089 | P11: Yes | S11: 1 | T11: 0 | U11: https://www.reddit.com/comments/10579e6
B12: 44933.873 | C12: =YEAR(B12) -> 2023 | D12: spotify | E12: Anyone know what the deal with these playlists are? Literally never seen them recommended and in the 'made for you' section. [removed] | F12: 1 | G12: negative | H12: 0.7817 | I12: 0.2089 | J12: 0.0094 | S12: 1 | T12: 0 | U12: https://www.reddit.com/comments/105zg9d
B13: 44935.732 | C13: =YEAR(B13) -> 2023 | D13: spotify | E13: Any way to fix my discover weekly?. [removed] | F13: 1 | G13: neutral | H13: 0.4219 | I13: 0.5596 | J13: 0.0185 | Q13: Yes | S13: 1 | T13: 0 | U13: https://www.reddit.com/comments/107kedw
B14: 44936.22 | C14: =YEAR(B14) -> 2023 | D14: spotify | E14: Is there a way to stop Spotify from playing suggested songs?. [removed] | F14: 2 | G14: neutral | H14: 0.3464 | I14: 0.6407 | J14: 0.0129 | S14: 1 | T14: 0 | U14: https://www.reddit.com/comments/1081eob
B15: 44936.571 | C15: =YEAR(B15) -> 2023 | D15: spotify | E15: ‌I want to make a radio that plays from like ten artists that I specify.. [removed] | F15: 1 | G15: neutral | H15: 0.0104 | I15: 0.8672 | J15: 0.1224 | S15: 1 | T15: 0 | U15: https://www.reddit.com/comments/108a3zn
B16: 44936.676 | C16: =YEAR(B16) -> 2023 | D16: spotify | E16: Anyone recommend a dreamy playlist including/like the song snowfall by øneheart. | F16: 3 | G16: neutral | H16: 0.0089 | I16: 0.7208 | J16: 0.2702 | S16: 0 | T16: 0 | U16: https://www.reddit.com/comments/108dm17
B17: 44936.787 | C17: =YEAR(B17) -> 2023 | D17: truespotify | E17: After 1 year of development we launched Smores to help you discover new music on Spotify faster. No ads, no accounts, no tracking, full recommendation | F17: 33 | G17: positive | H17: 0.0025 | I17: 0.0979 | J17: 0.8996 | S17: 0 | T17: 0 | U17: https://www.reddit.com/comments/108hm56
B18: 44937.29 | C18: =YEAR(B18) -> 2023 | D18: truespotify | E18: hey guys!!!! spotify has audiobooks!!!! did you want to see more music recommendations? too bad!!! enjoy the crazy rich asians audiobook instead!!!! 😝 | F18: 52 | G18: positive | H18: 0.0058 | I18: 0.0498 | J18: 0.9444 | S18: 0 | T18: 0 | U18: https://www.reddit.com/comments/108y8zh
B19: 44938.686 | C19: =YEAR(B19) -> 2023 | D19: spotify | E19: Spotify music recommendations feature. Hello, yesterday I discovered a new feature in the music recommendations feature, I’m not sure what I pressed o | F19: 14 | G19: positive | H19: 0.0039 | I19: 0.3589 | J19: 0.6372 | S19: 0 | T19: 0 | U19: https://www.reddit.com/comments/10a3rno
B20: 44938.81 | C20: =YEAR(B20) -> 2023 | D20: spotify | E20: Why is Spotify only playing recommended songs, my playlist is definitely long enough?. | F20: 1 | G20: negative | H20: 0.7637 | I20: 0.2149 | J20: 0.0215 | S20: 0 | T20: 0 | U20: https://www.reddit.com/comments/10a876h
B21: 44939.673 | C21: =YEAR(B21) -> 2023 | D21: spotify | E21: I introduce to you all 'Indie Bangers'. All things banging in indie rock; meticulously scouted, lovingly compiled and regularly updated. An incredible | F21: 1 | G21: positive | H21: 0.0018 | I21: 0.0221 | J21: 0.9761 | S21: 0 | T21: 0 | U21: https://www.reddit.com/comments/10ay88c
B22: 44940.086 | C22: =YEAR(B22) -> 2023 | D22: truespotify | E22: Enhance not working - every time I try to do so, this message pops up. The app was just updated and it hasn’t helped. What should I do?. | F22: 10 | G22: negative | H22: 0.8694 | I22: 0.1229 | J22: 0.0078 | S22: 0 | T22: 0 | U22: https://www.reddit.com/comments/10bcgfw
B23: 44942.123 | C23: =YEAR(B23) -> 2023 | D23: spotify | E23: collection of ethereal songs in different languages [also open for suggestions pls!]. | F23: 2 | G23: positive | H23: 0.0054 | I23: 0.2962 | J23: 0.6984 | S23: 0 | T23: 0 | U23: https://www.reddit.com/comments/10d35e6
B24: 44942.467 | C24: =YEAR(B24) -> 2023 | D24: truespotify | E24: Until 2 days ago, "play spotify" on google home would play whatever I'd been listening to last on my phone through GH, now it just plays some random s | F24: 5 | G24: neutral | H24: 0.1854 | I24: 0.6475 | J24: 0.1671 | S24: 0 | T24: 0 | U24: https://www.reddit.com/comments/10dby0u
B25: 44942.585 | C25: =YEAR(B25) -> 2023 | D25: spotify | E25: Spotify song recommendations that fits their vibe. I’m trying to make a lore between these two. | F25: 1 | G25: positive | H25: 0.0095 | I25: 0.4896 | J25: 0.5009 | S25: 0 | T25: 0 | U25: https://www.reddit.com/comments/10dfb5j
B26: 44942.752 | C26: =YEAR(B26) -> 2023 | D26: spotify | E26: What Do You Think Of My Constantly Growing Playlist. It's Completely Random and Includes Like Almost Every Genre (Indie, Metal, Pop, Rap, ...). Let Me | F26: 1 | G26: neutral | H26: 0.007 | I26: 0.54 | J26: 0.453 | S26: 0 | T26: 0 | U26: https://www.reddit.com/comments/10dmf60
B27: 44943.141 | C27: =YEAR(B27) -> 2023 | D27: spotify | E27: How would you rate your Spotify Discover Weekly Playlist?. [removed] | F27: 1 | G27: neutral | H27: 0.0102 | I27: 0.9037 | J27: 0.0861 | Q27: Yes | S27: 1 | T27: 0 | U27: https://www.reddit.com/comments/10e1g00
B28: 44943.441 | C28: =YEAR(B28) -> 2023 | D28: spotify | E28: Why can't enhance i my favourite songs?. [removed] | F28: 1 | G28: negative | H28: 0.8528 | I28: 0.1342 | J28: 0.0129 | S28: 1 | T28: 0 | U28: https://www.reddit.com/comments/10e949y
B29: 44943.972 | C29: =YEAR(B29) -> 2023 | D29: spotify | E29: Making a Non rap songs that went Platinum in the Hood, playlist and need suggestions!!. Check out the [playlist]( leave some suggestions! Ill add them | F29: 1 | G29: neutral | H29: 0.0135 | I29: 0.6304 | J29: 0.3561 | S29: 0 | T29: 0 | U29: https://www.reddit.com/comments/10eqyk2
B30: 44943.978 | C30: =YEAR(B30) -> 2023 | D30: spotify | E30: A justified rant about the Spotify random algorithm. [removed] | F30: 1 | G30: neutral | H30: 0.4146 | I30: 0.5367 | J30: 0.0488 | S30: 1 | T30: 0 | U30: https://www.reddit.com/comments/10er6o0
B31: 44944.028 | C31: =YEAR(B31) -> 2023 | D31: spotify | E31: looking for recommendations! Indie/folky playlist :). | F31: 3 | G31: positive | H31: 0.0035 | I31: 0.1611 | J31: 0.8354 | S31: 0 | T31: 0 | U31: https://www.reddit.com/comments/10esy6b
B32: 44944.18 | C32: =YEAR(B32) -> 2023 | D32: spotify | E32: Album Listening Night #181. Each playlist will typically have 2 albums from our community's suggestions. Playlists start with an intro song and includ | F32: 1 | G32: neutral | H32: 0.0034 | I32: 0.8387 | J32: 0.1579 | S32: 0 | T32: 0 | U32: https://www.reddit.com/comments/10exrjs
B33: 44944.563 | C33: =YEAR(B33) -> 2023 | D33: spotify | E33: I'm really new to Spotify so always looking for positive criticism and suggestions but don't be rude! Linked below is my Spotify profile which has ple | F33: 1 | G33: positive | H33: 0.0049 | I33: 0.0836 | J33: 0.9115 | S33: 1 | T33: 0 | U33: https://www.reddit.com/comments/10f7g3f
B34: 44944.755 | C34: =YEAR(B34) -> 2023 | D34: spotify | E34: My phonk playlist with my all time favorite tracks. Drift | House | Atmospheric | Aggressive | Chill. Would appreciate if you took a look or recommend | F34: 1 | G34: positive | H34: 0.0034 | I34: 0.0931 | J34: 0.9035 | S34: 0 | T34: 0 | U34: https://www.reddit.com/comments/10fe592
B35: 44945.292 | C35: =YEAR(B35) -> 2023 | D35: spotify | E35: Why is it shuffling on browser for radio EVEN WHEN SHUFFLE IS DISABLED >:(. [removed] | F35: 0 | G35: negative | H35: 0.8739 | I35: 0.1202 | J35: 0.0059 | S35: 1 | T35: 0 | U35: https://www.reddit.com/comments/10fv7j9
B36: 44945.591 | C36: =YEAR(B36) -> 2023 | D36: spotify | E36: A$AP Rocky Wavy Radio. | F36: 1 | G36: neutral | H36: 0.0081 | I36: 0.5624 | J36: 0.4295 | S36: 0 | T36: 0 | U36: https://www.reddit.com/comments/10g2oj5
B37: 44946.045 | C37: =YEAR(B37) -> 2023 | D37: spotify | E37: My distaste for playing suggested songs.. [removed] | F37: 3 | G37: negative | H37: 0.7397 | I37: 0.2495 | J37: 0.0108 | S37: 1 | T37: 0 | U37: https://www.reddit.com/comments/10giz6l
B38: 44946.12 | C38: =YEAR(B38) -> 2023 | D38: spotify | E38: Easy going playlist. Like and recommendations are appreciated. [deleted] | F38: 1 | G38: positive | H38: 0.0088 | I38: 0.2672 | J38: 0.7239 | S38: 1 | T38: 0 | U38: https://www.reddit.com/comments/10glda1
B39: 44946.523 | C39: =YEAR(B39) -> 2023 | D39: spotify | E39: It's time to bleed! If you have any suggestions within these genres, please let me know!. [deleted] | F39: 1 | G39: neutral | H39: 0.1245 | I39: 0.6279 | J39: 0.2477 | S39: 1 | T39: 0 | U39: https://www.reddit.com/comments/10gvu40
... B51: 44951.009 | C51: =YEAR(B51) -> 2023 | D51: spotify | E51: Playlist not playing when enhanced?. [removed] | F51: 27 | G51: negative | H51: 0.6143 | I51: 0.376 | J51: 0.0097 | S51: 1 | T51: 0 | U51: https://www.reddit.com/comments/10kkryf
B52: 44952.362 | C52: =YEAR(B52) -> 2023 | D52: spotify | E52: Smart shuffle sucks. Is there a way to completely disable the smart shuffle option? whenever I wanna go from shuffle to just play my playlists in orde | F52: 5 | G52: negative | H52: 0.9195 | I52: 0.0743 | J52: 0.0062 | R52: Yes | S52: 0 | T52: 0 | U52: https://www.reddit.com/comments/10lne4i
B53: 44953.769 | C53: =YEAR(B53) -> 2023 | D53: truespotify | E53: Every week, scam artists distribute music with much bigger names attached fake to their songs, and it slips through Spotify's Release Radar. To make t | F53: 139 | G53: negative | H53: 0.8836 | I53: 0.1098 | J53: 0.0066 | Q53: Yes | S53: 0 | T53: 0 | U53: https://www.reddit.com/comments/10ms1t2
B54: 44953.79 | C54: =YEAR(B54) -> 2023 | D54: spotify | E54: A playlist which i created with a mix of genres (trapsoul and pop mostly). I'm trying to find some new songs but the playlist radio recommends me song | F54: 2 | G54: neutral | H54: 0.094 | I54: 0.7105 | J54: 0.1955 | S54: 1 | T54: 0 | U54: https://www.reddit.com/comments/10mssxs
B55: 44953.847 | C55: =YEAR(B55) -> 2023 | D55: spotify | E55: Playing recommended songs for you same songs everytime. [removed] | F55: 1 | G55: neutral | H55: 0.2287 | I55: 0.723 | J55: 0.0483 | K55: Yes | S55: 1 | T55: 0 | U55: https://www.reddit.com/comments/10muwuz
B56: 44953.911 | C56: =YEAR(B56) -> 2023 | D56: spotify | E56: Unknown artists posting music under already well established artists names and appearing in weekly release radar.. [removed] | F56: 7 | G56: neutral | H56: 0.0708 | I56: 0.9039 | J56: 0.0254 | Q56: Yes | S56: 1 | T56: 0 | U56: https://www.reddit.com/comments/10mx6qz
B57: 44953.974 | C57: =YEAR(B57) -> 2023 | D57: spotify | E57: First time posting, just a playlist of some chill songs I like. Recommend some songs, always looking for more.. [deleted] | F57: 2 | G57: positive | H57: 0.0051 | I57: 0.1536 | J57: 0.8413 | S57: 1 | T57: 0 | U57: https://www.reddit.com/comments/10mzepi
B58: 44954.592 | C58: =YEAR(B58) -> 2023 | D58: spotify | E58: How do I find all the playlists curated for me coz today I saw this alt z playlist my friend was listening to.. I searched it up and it was curated fo | F58: 1 | G58: neutral | H58: 0.4187 | I58: 0.5509 | J58: 0.0303 | S58: 0 | T58: 0 | U58: https://www.reddit.com/comments/10ng03k
B59: 44954.886 | C59: =YEAR(B59) -> 2023 | D59: spotify | E59: relatively new to current hiphop, this my current playlist, please recommend more!. | F59: 1 | G59: positive | H59: 0.0047 | I59: 0.1411 | J59: 0.8542 | S59: 0 | T59: 0 | U59: https://www.reddit.com/comments/10nprsx
B60: 44955.732 | C60: =YEAR(B60) -> 2023 | D60: spotify | E60: Is there a limit to how many songs can be in an enhanced playlist for shuffle to activate?. [removed] | F60: 1 | G60: neutral | H60: 0.0222 | I60: 0.9499 | J60: 0.0279 | S60: 1 | T60: 0 | U60: https://www.reddit.com/comments/10od9zk
B61: 44955.838 | C61: =YEAR(B61) -> 2023 | D61: spotify | E61: Easy going 70/80s music! Likes and recommendations are appreciated!. [deleted] | F61: 1 | G61: positive | H61: 0.0051 | I61: 0.1354 | J61: 0.8595 | S61: 1 | T61: 0 | U61: https://www.reddit.com/comments/10oh36b
B62: 44956.174 | C62: =YEAR(B62) -> 2023 | D62: spotify | E62: How often do the On Repeat and Repeat Rewind playlists update?. [removed] | F62: 1 | G62: neutral | H62: 0.0074 | I62: 0.9607 | J62: 0.0319 | S62: 1 | T62: 0 | U62: https://www.reddit.com/comments/10osasp
B63: 44956.218 | C63: =YEAR(B63) -> 2023 | D63: spotify | E63: Probably a dumb question, but how do I access the thumbs up/thumbs down radio on iOS?. [deleted] | F63: 1 | G63: neutral | H63: 0.2939 | I63: 0.6747 | J63: 0.0314 | S63: 1 | T63: 0 | U63: https://www.reddit.com/comments/10otjf1
B64: 44956.364 | C64: =YEAR(B64) -> 2023 | D64: truespotify | E64: Reset Discover Weekly and Release Radar?. Anyone know if it's possible to reset these playlists? For a good while now, there's been little new on eith | F64: 19 | G64: negative | H64: 0.5202 | I64: 0.4598 | J64: 0.02 | Q64: Yes | S64: 0 | T64: 0 | U64: https://www.reddit.com/comments/10ox2os
B65: 44956.664 | C65: =YEAR(B65) -> 2023 | D65: spotify | E65: need new music. any suggestions?. [removed] | F65: 1 | G65: neutral | H65: 0.0304 | I65: 0.7873 | J65: 0.1823 | S65: 1 | T65: 0 | U65: https://www.reddit.com/comments/10p69zs
B66: 44957.902 | C66: =YEAR(B66) -> 2023 | D66: spotify | E66: Happy to share this EDM/Summer playlist which I listen to when I'm hanging out with my friends! Would love to hear your thoughts & suggestions :). | F66: 2 | G66: positive | H66: 0.0015 | I66: 0.023 | J66: 0.9755 | S66: 0 | T66: 0 | U66: https://www.reddit.com/comments/10qbbk1
B67: 44958.001 | C67: =YEAR(B67) -> 2023 | D67: spotify | E67: I’m convinced that Spotify playlists only contain music that would be on the radio.. [removed] | F67: 1 | G67: negative | H67: 0.5927 | I67: 0.3897 | J67: 0.0176 | S67: 1 | T67: 0 | U67: https://www.reddit.com/comments/10qes6c
B68: 44958.189 | C68: =YEAR(B68) -> 2023 | D68: spotify | E68: TIL You can manipulate your Good Morning/Good Evening recommendations by playing things from the Web Player.. [removed] | F68: 2 | G68: neutral | H68: 0.0489 | I68: 0.8572 | J68: 0.0939 | P68: Yes | S68: 1 | T68: 0 | U68: https://www.reddit.com/comments/10qkkjd
B69: 44958.389 | C69: =YEAR(B69) -> 2023 | D69: spotify | E69: Late Night Chill - An ultimate Chillout playlist for the late night vibes. Would love to hear your thoughts & recommendations :). | F69: 1 | G69: positive | H69: 0.0016 | I69: 0.0351 | J69: 0.9634 | S69: 0 | T69: 0 | U69: https://www.reddit.com/comments/10qp4y2
B70: 44958.539 | C70: =YEAR(B70) -> 2023 | D70: spotify | E70: TRIPPY playlist.. Guys.. i think i made my **best playlist**... that's so Trippy, like ur going to the **space**. 🥴rlyyy \- **link**: [ ***Let me know | F70: 1 | G70: positive | H70: 0.0044 | I70: 0.0193 | J70: 0.9763 | S70: 0 | T70: 0 | U70: https://www.reddit.com/comments/10qu39v
B71: 44959.273 | C71: =YEAR(B71) -> 2023 | D71: spotify | E71: Call Me a Fool Radio. | F71: 1 | G71: negative | H71: 0.6544 | I71: 0.3121 | J71: 0.0335 | S71: 0 | T71: 0 | U71: https://www.reddit.com/comments/10rj1hq
B72: 44960.066 | C72: =YEAR(B72) -> 2023 | D72: spotify | E72: Hey guys! I did an experiment looking at algorithmic bias in the Spotify program and this video is a very brief introduction. I have been trying to sp | F72: 1 | G72: neutral | H72: 0.094 | I72: 0.6606 | J72: 0.2453 | S72: 0 | T72: 0 | U72: https://www.reddit.com/comments/10s7dbn
B73: 44961.327 | C73: =YEAR(B73) -> 2023 | D73: spotify | E73: Is there a way to disable audiobook recommendations? I've got no interest in being advertised to on an app I'm already paying £17 a month for.. [remov | F73: 1 | G73: negative | H73: 0.8656 | I73: 0.1259 | J73: 0.0085 | S73: 1 | T73: 0 | U73: https://www.reddit.com/comments/10t8gqh
B74: 44961.389 | C74: =YEAR(B74) -> 2023 | D74: spotify | E74: Drum & Bass - A playlist I am working on containing only Liquid/Melodic/Chill DNB. Would love to hear your recommendations :). | F74: 2 | G74: positive | H74: 0.0016 | I74: 0.0638 | J74: 0.9345 | S74: 0 | T74: 0 | U74: https://www.reddit.com/comments/10tb7xp
B75: 44962.02 | C75: =YEAR(B75) -> 2023 | D75: truespotify | E75: Spotify Daily Mix is no different than Favorites on shuffle nowadays. | F75: 76 | G75: neutral | H75: 0.2425 | I75: 0.6969 | J75: 0.0606 | S75: 0 | T75: 0 | U75: https://www.reddit.com/comments/10tw0da
B76: 44962.282 | C76: =YEAR(B76) -> 2023 | D76: spotify | E76: Looking for your music suggestions for a instrumental playlist!. [deleted] | F76: 6 | G76: neutral | H76: 0.0139 | I76: 0.7913 | J76: 0.1947 | S76: 1 | T76: 0 | U76: https://www.reddit.com/comments/10u65fa
B77: 44962.692 | C77: =YEAR(B77) -> 2023 | D77: truespotify | E77: Love Discover Weekly? Never Miss a Mix Again!. [removed] | F77: 1 | G77: positive | H77: 0.0026 | I77: 0.0284 | J77: 0.969 | P77: Yes | Q77: Yes | S77: 1 | T77: 0 | U77: https://www.reddit.com/comments/10ugqti
B78: 44962.831 | C78: =YEAR(B78) -> 2023 | D78: truespotify | E78: Spotify feels stagnant. Lately I've been feeling a sense of boredom with Spotify, it feels like the algorithm is stuck. I rarely get to discover new s | F78: 8 | G78: negative | H78: 0.8714 | I78: 0.1173 | J78: 0.0113 | Q78: Yes | S78: 0 | T78: 0 | U78: https://www.reddit.com/comments/10ulqp2
B79: 44963.682 | C79: =YEAR(B79) -> 2023 | D79: spotify | E79: Battle of the Bands: Super Bowl edition via Spotify radio. My radio show did a battle of the bands of Philly versus Kansas City bands! Loving the radi | F79: 1 | G79: positive | H79: 0.0021 | I79: 0.0258 | J79: 0.9721 | S79: 0 | T79: 0 | U79: https://www.reddit.com/comments/10vapqz
B80: 44964.552 | C80: =YEAR(B80) -> 2023 | D80: spotify | E80: Is there a way to get recommendation lists that aren't like 80% songs I already added to my liked songs?. [removed] | F80: 5 | G80: neutral | H80: 0.0919 | I80: 0.8408 | J80: 0.0672 | S80: 1 | T80: 0 | U80: https://www.reddit.com/comments/10w1jbi
B81: 44964.813 | C81: =YEAR(B81) -> 2023 | D81: spotify | E81: I have 999 songs in my liked songs (which is my main plalist) - what should be my 1000th?. suggest some songs best ones I will add (my favourite/main | F81: 24 | G81: neutral | H81: 0.0078 | I81: 0.4974 | J81: 0.4948 | S81: 0 | T81: 0 | U81: https://www.reddit.com/comments/10wapu8
B82: 44964.89 | C82: =YEAR(B82) -> 2023 | D82: spotify | E82: How do Spotify Radio channels work?. [removed] | F82: 3 | G82: neutral | H82: 0.0275 | I82: 0.9554 | J82: 0.017 | S82: 1 | T82: 0 | U82: https://www.reddit.com/comments/10wdiy0
B83: 44965.763 | C83: =YEAR(B83) -> 2023 | D83: spotify | E83: Reporting a playlist / playlist owner. How do I report a playlist owner that is asking for money in exchange for guaranteed placement? Fairly sure thi | F83: 27 | G83: negative | H83: 0.5544 | I83: 0.424 | J83: 0.0216 | O83: Yes | S83: 0 | T83: 0 | U83: https://www.reddit.com/comments/10x6kb7
B84: 44965.879 | C84: =YEAR(B84) -> 2023 | D84: truespotify | E84: Spotify now lets you exclude certain playlists from its recommendations. | F84: 91 | G84: neutral | H84: 0.4169 | I84: 0.5594 | J84: 0.0237 | S84: 0 | T84: 0 | U84: https://www.reddit.com/comments/10xaral
B85: 44965.972 | C85: =YEAR(B85) -> 2023 | D85: truespotify | E85: Made for you gone??. I’ve been using Spotify for years and i listen to music everyday. Why does it seem like my listening data is gone?? | F85: 4 | G85: negative | H85: 0.5937 | I85: 0.3558 | J85: 0.0505 | S85: 0 | T85: 0 | U85: https://www.reddit.com/comments/10xeb3t
B86: 44966.422 | C86: =YEAR(B86) -> 2023 | D86: spotify | E86: 5 reasons to choose Spotify over Apple Music in 2023. I've been a music streaming fan since 2015 when Apple Music arrived in my country, but the entir | F86: 257 | G86: negative | H86: 0.4601 | I86: 0.3471 | J86: 0.1928 | S86: 0 | T86: 0 | U86: https://www.reddit.com/comments/10xr670
B87: 44966.908 | C87: =YEAR(B87) -> 2023 | D87: spotify | E87: Indie Hip Hop | New & Undiscovered Artists - artists with less than 30k monthly listeners but radio-ready production.. | F87: 1 | G87: neutral | H87: 0.0268 | I87: 0.8764 | J87: 0.0968 | S87: 0 | T87: 0 | U87: https://www.reddit.com/comments/10y799z
B88: 44967.755 | C88: =YEAR(B88) -> 2023 | D88: spotify | E88: MIC Radio Love Songs. | F88: 1 | G88: positive | H88: 0.0047 | I88: 0.467 | J88: 0.5283 | S88: 0 | T88: 0 | U88: https://www.reddit.com/comments/10yyko0
B89: 44967.935 | C89: =YEAR(B89) -> 2023 | D89: spotify | E89: Working on this awesome Summer Dance playlist for myself. Happy to share it here, and hopefully get some cool suggestions! Let me know what you think | F89: 1 | G89: positive | H89: 0.0013 | I89: 0.0128 | J89: 0.9859 | S89: 0 | T89: 0 | U89: https://www.reddit.com/comments/10z4ud6
B90: 44968.429 | C90: =YEAR(B90) -> 2023 | D90: spotify | E90: Need some playlist organisation advice. Hi guys, I have been struggling with creating good, functional playlists for some time now. I know many posted | F90: 2 | G90: negative | H90: 0.6045 | I90: 0.3571 | J90: 0.0384 | S90: 0 | T90: 0 | U90: https://www.reddit.com/comments/10zhs2f
B91: 44968.471 | C91: =YEAR(B91) -> 2023 | D91: spotify | E91: Introducing Best of Discover Weekly - a simple way to save your favorites, automatically [Request for Feedback]. [removed] | F91: 1 | G91: positive | H91: 0.0026 | I91: 0.2546 | J91: 0.7429 | P91: Yes | Q91: Yes | S91: 1 | T91: 0 | U91: https://www.reddit.com/comments/10zkto2
B92: 44969.748 | C92: =YEAR(B92) -> 2023 | D92: spotify | E92: Women of metal - non screaming playlist (updated regularly - feel free to make new suggestions). [deleted] | F92: 113 | G92: neutral | H92: 0.0134 | I92: 0.7816 | J92: 0.205 | S92: 1 | T92: 0 | U92: https://www.reddit.com/comments/110ltac
B93: 44969.811 | C93: =YEAR(B93) -> 2023 | D93: spotify | E93: i want some music recommendations. i listen to a lot of different genres most of the songs i listen to (but not all) are [here]( . i personally prefer | F93: 7 | G93: positive | H93: 0.0152 | I93: 0.4119 | J93: 0.5729 | S93: 0 | T93: 0 | U93: https://www.reddit.com/comments/110nyvh
B94: 44970.283 | C94: =YEAR(B94) -> 2023 | D94: spotify | E94: You CAN Customize your Good Morning/Afternoon/Evening feed. Here's how:. My recommendations weren't ever changing, no matter what I listened to or for | F94: 5 | G94: neutral | H94: 0.1277 | I94: 0.7344 | J94: 0.138 | S94: 0 | T94: 0 | U94: https://www.reddit.com/comments/1111rnp
B95: 44970.953 | C95: =YEAR(B95) -> 2023 | D95: spotify | E95: Any songs that have the same vibe? Please recommend! :). [deleted] | F95: 1 | G95: positive | H95: 0.0045 | I95: 0.1254 | J95: 0.8701 | S95: 1 | T95: 0 | U95: https://www.reddit.com/comments/111mmwj
B96: 44971.019 | C96: =YEAR(B96) -> 2023 | D96: spotify | E96: Recommendations are making me mad. 🤬. [removed] | F96: 1 | G96: negative | H96: 0.9465 | I96: 0.0473 | J96: 0.0062 | S96: 1 | T96: 0 | U96: https://www.reddit.com/comments/111ou3t
B97: 44971.021 | C97: =YEAR(B97) -> 2023 | D97: spotify | E97: Recommended songs…. [removed] | F97: 1 | G97: neutral | H97: 0.0099 | I97: 0.8696 | J97: 0.1205 | S97: 1 | T97: 0 | U97: https://www.reddit.com/comments/111owh1
B98: 44971.752 | C98: =YEAR(B98) -> 2023 | D98: spotify | E98: The recommended tracks section is terrible and has gone downhill… help?. [removed] | F98: 1 | G98: negative | H98: 0.9502 | I98: 0.0444 | J98: 0.0053 | S98: 1 | T98: 0 | U98: https://www.reddit.com/comments/112bsni
B99: 44971.894 | C99: =YEAR(B99) -> 2023 | D99: spotify | E99: Grizzly Beatz Radio. | F99: 0 | G99: neutral | H99: 0.0156 | I99: 0.7606 | J99: 0.2237 | S99: 0 | T99: 0 | U99: https://www.reddit.com/comments/112gn1a
B100: 44971.991 | C100: =YEAR(B100) -> 2023 | D100: spotify | E100: Spotify doesn’t go past this screen when opening app. I have uninstalled and reinstalled with no fix. Any suggestions?. | F100: 1 | G100: negative | H100: 0.8377 | I100: 0.1533 | J100: 0.009 | S100: 0 | T100: 0 | U100: https://www.reddit.com/comments/112juun
B101: 44973.244 | C101: =YEAR(B101) -> 2023 | D101: spotify | E101: Song Suggestions for Playlist?. [removed] | F101: 1 | G101: neutral | H101: 0.0106 | I101: 0.9315 | J101: 0.0579 | S101: 1 | T101: 0 | U101: https://www.reddit.com/comments/113jc9l
B102: 44973.415 | C102: =YEAR(B102) -> 2023 | D102: spotify | E102: A playlist for the lonely. If you have suggestions within these genres, please let me know!. [deleted] | F102: 0 | G102: neutral | H102: 0.0356 | I102: 0.6893 | J102: 0.2751 | S102: 1 | T102: 0 | U102: https://www.reddit.com/comments/113n2g5
B103: 44973.593 | C103: =YEAR(B103) -> 2023 | D103: spotify | E103: suggestions? please like the playlist if you find it good :). [deleted] | F103: 0 | G103: positive | H103: 0.004 | I103: 0.039 | J103: 0.957 | S103: 1 | T103: 0 | U103: https://www.reddit.com/comments/113rkp5
... B115: 44978.691 | C115: =YEAR(B115) -> 2023 | D115: truespotify | E115: 3rd party radio/algorithm for discovering music on spotify?. Spotify keeps recommending me songs I already removed/or are already in the playlist. I k | F115: 12 | G115: negative | H115: 0.5698 | I115: 0.4107 | J115: 0.0195 | S115: 0 | T115: 0 | U115: https://www.reddit.com/comments/1188vwq
B116: 44979.722 | C116: =YEAR(B116) -> 2023 | D116: truespotify | E116: Spotify DJ. [deleted] | F116: 0 | G116: neutral | H116: 0.0634 | I116: 0.9117 | J116: 0.0249 | R116: Yes | S116: 1 | T116: 0 | U116: https://www.reddit.com/comments/1195dxs
B117: 44979.867 | C117: =YEAR(B117) -> 2023 | D117: spotify | E117: Soft Rock Radio Hits From The 70’s & Early 80’s. [deleted] | F117: 1 | G117: neutral | H117: 0.006 | I117: 0.9285 | J117: 0.0656 | S117: 1 | T117: 0 | U117: https://www.reddit.com/comments/119cc95
B118: 44979.953 | C118: =YEAR(B118) -> 2023 | D118: truespotify | E118: my home good morning/good evening stuck at a same thing. so its just hasnt changed for over a month, stuck on phone pc everywhere. idk what to do, any | F118: 1 | G118: negative | H118: 0.8879 | I118: 0.1056 | J118: 0.0065 | S118: 0 | T118: 0 | U118: https://www.reddit.com/comments/119gndo
B119: 44980.028 | C119: =YEAR(B119) -> 2023 | D119: truespotify | E119: why is this recommended to me if ive never listened to anything like it or any podcasts at all?. [deleted] | F119: 9 | G119: negative | H119: 0.7902 | I119: 0.1995 | J119: 0.0103 | S119: 1 | T119: 0 | U119: https://www.reddit.com/comments/119jb13
B120: 44980.724 | C120: =YEAR(B120) -> 2023 | D120: spotify | E120: Besides making a new account for my child is there a way for me to not get songs like this in my suggestions?. [removed] | F120: 1 | G120: neutral | H120: 0.4374 | I120: 0.5408 | J120: 0.0218 | S120: 1 | T120: 0 | U120: https://www.reddit.com/comments/11a3762
B121: 44980.788 | C121: =YEAR(B121) -> 2023 | D121: truespotify | E121: Has Spotify ever dipped into live radio?. SiriusXM style. Like if you want to listen to indie radio, it's not your own personalized radio that Spotify | F121: 8 | G121: neutral | H121: 0.0228 | I121: 0.5856 | J121: 0.3917 | S121: 0 | T121: 0 | U121: https://www.reddit.com/comments/11a5ib0
B122: 44980.83 | C122: =YEAR(B122) -> 2023 | D122: spotify | E122: Recommended playlist rant.... [deleted] | F122: 0 | G122: neutral | H122: 0.1558 | I122: 0.7973 | J122: 0.0468 | S122: 1 | T122: 0 | U122: https://www.reddit.com/comments/11a6zbp
B123: 44981.928 | C123: =YEAR(B123) -> 2023 | D123: spotify | E123: Best way to remove stagnant recommendations from the home tab? I’m still being served Holiday music, and it’s almost March.. | F123: 3 | G123: negative | H123: 0.5996 | I123: 0.3635 | J123: 0.0369 | S123: 0 | T123: 0 | U123: https://www.reddit.com/comments/11b3skz
...

Sheet DM Data Campaigns
B2: Spotify for Artists Campaign Reports: Discovery Mode-context Streams, Before vs During | O2: Notes
B3: Campaign | C3: Month | D3: Source (r/musicmarketing id) | E3: Songs enrolled | F3: DM-context streams, campaign | G3: DM-context streams, prior 28 days | H3: Reported lift | I3: Era | J3: Campaign listeners | K3: New listeners | L3: Saves + adds per listener | M3: Songs that gained | N3: Songs reported | O3: Note
B4: Aug 2023 | C4: 45139 | D4: 15woi7w | F4: 445475 | G4: 91662 | H4: =IF(G4="","",F4/G4-1) -> 3.8599747 | I4: =IF(YEAR(C4)<=2024,"2023-24","2025-26") -> 2023-24 | J4: 192090 | K4: 105307 | L4: 0.010573169 | O4: Aug 1-20 only; 'results insane'
B5: Oct 2024 (a) | C5: 45566 | D5: 1g1fk0o | E5: 8 | F5: 5658 | G5: 1076 | H5: =IF(G5="","",F5/G5-1) -> 4.2583643 | I5: =IF(YEAR(C5)<=2024,"2023-24","2025-26") -> 2023-24 | J5: 4755 | L5: 0.011987382 | M5: 8 | N5: 8
B6: Oct 2024 (b) | C6: 45566 | D6: 1geig0k | E6: 4 | F6: 3011 | G6: 359 | H6: =IF(G6="","",F6/G6-1) -> 7.3871866 | I6: =IF(YEAR(C6)<=2024,"2023-24","2025-26") -> 2023-24 | J6: 1723 | K6: 932 | L6: 0.048171793 | M6: 3 | N6: 4
B7: Nov 2024 | C7: 45597 | D7: 1h46nzy | E7: 4 | F7: 46995 | G7: 16336 | H7: =IF(G7="","",F7/G7-1) -> 1.8767752 | I7: =IF(YEAR(C7)<=2024,"2023-24","2025-26") -> 2023-24 | J7: 25167 | K7: 21328 | L7: 0.010728335 | O7: ~25k monthly listeners
B8: Jan 2025 | C8: 45658 | D8: 1ig7963 (text) | E8: 1 | F8: 7404 | G8: 4777 | H8: =IF(G8="","",F8/G8-1) -> 0.54992673 | I8: =IF(YEAR(C8)<=2024,"2023-24","2025-26") -> 2025-26 | O8: Spotify reported +55% lift, but the same song's TOTAL streams fell from ~46k/month (Oct-Dec) to 43k in Jan
B9: Oct 2025 | C9: 45931 | D9: 1omcbrg | E9: 7 | F9: 39156 | G9: 10195 | H9: =IF(G9="","",F9/G9-1) -> 2.8407062 | I9: =IF(YEAR(C9)<=2024,"2023-24","2025-26") -> 2025-26 | J9: 27807 | L9: 0.017333765 | M9: 7 | N9: 7
B10: Jul 2026 | C10: 46204 | D10: 1uy70w1 (text) | E10: 3 | F10: 7675 | G10: 4312 | H10: =IF(G10="","",F10/G10-1) -> 0.77991651 | I10: =IF(YEAR(C10)<=2024,"2023-24","2025-26") -> 2025-26 | J10: 5911 | K10: 5243 | L10: 0.012857385 | M10: 3 | N10: 3
B11: Dec 2023 | C11: 45261 | D11: 18lveoc | E11: 6 | F11: 1816 | H11: =IF(G11="","",F11/G11-1) | I11: =IF(YEAR(C11)<=2024,"2023-24","2025-26") -> 2023-24 | J11: 1306 | L11: 0.018376723 | M11: 2 | N11: 6 | O11: 4 of 6 songs got 0 DM streams (incl. top songs)
B12: Sep 2026 | C12: 46266 | D12: 1wu7cam | E12: 7 | F12: 27994 | H12: =IF(G12="","",F12/G12-1) | I12: =IF(YEAR(C12)<=2024,"2023-24","2025-26") -> 2025-26 | J12: 22689 | L12: 0.0068315043 | O12: Intent 0.19-1.10% per song
B14: Median reported lift, campaigns Aug 2023 - Nov 2024 | H14: =MEDIAN(H4:H7) -> 4.0591695 | I14: =COUNT(H4:H7)&" campaigns" -> 4 campaigns | O14: n = 4 vs 3: not statistically meaningful (rank test p ~ 0.1) and the metric rewards songs with a tiny prior base (the 7.4x campaign had 359 prior streams). Direction, not magnitude.
B15: Median reported lift, campaigns Jan 2025 - Jul 2026 | H15: =MEDIAN(H8:H10) -> 0.77991651 | I15: =COUNT(H8:H10)&" campaigns" -> 3 campaigns
B16: Median reported lift, all campaigns with a before figure | H16: =MEDIAN(H4:H10) -> 2.8407062
B17: Latest campaign lift as a share of the earliest | H17: =H10/H4 -> 0.20205223
B18: Median saves + adds per Discovery Mode listener (all campaign reports) | L18: =MEDIAN(L4:L12) -> 0.012422383 | O18: Spotify's own 'intent' measure for a Discovery Mode song: (saves + playlist adds) / campaign listeners.
B20: Reported lift = campaign streams / prior-28-day streams - 1. Where the screenshot showed only the lift, the prior figure is streams / (1 + lift). Counts cover Radio, Autoplay and Mixes only: they do not show whether total streams rose (the Jan 2025 artist checked: Spotify reported +55%, total streams fell). Source: screenshots posted to r/musicmarketing, read by hand.
B22: Artists' overall audience: saves per listener (Spotify for Artists dashboards)
B23: Artist | D23: Source | L23: Saves per listener
B24: Artist 17gqiej, 12 months | D24: 17gqiej | L24: 0.24525392
B25: Artist 1q4bb7s, all time | D25: 1q4bb7s | L25: 0.18248588
B26: Artist 1rvflj9, 12 months | D26: 1rvflj9 | L26: 0.21461319
B27: Kublaii (1hn3dhf), 12 months | D27: 1hn3dhf | L27: 0.080622942
B28: Median saves per listener, overall audience | L28: =MEDIAN(L24:L27) -> 0.19854954 | O28: Saves only, 12 months, different artists: read against the campaign rate as an order of magnitude, not a like-for-like.
B29: Overall audience keeps the song this many times more often | L29: =L28/L18 -> 15.983208
B31: What happened when Discovery Mode was switched on or off (artists' own graphs)
B32: Source | C32: Change | D32: Measure | F32: Before | G32: After | H32: Change | O32: What happened
B33: 1and042 | C33: DM on (Apr 2023) | D33: Radio & autoplay listeners / day | F33: 70 | G33: 900 | H33: =IF(OR(F33="",G33=""),"",G33/F33-1) -> 11.857143 | O33: ~70/day before -> ~400 right after -> ~900-1,200 a year later; weekly releases throughout.
B34: 1q4bb7s | C34: DM on (Dec 1, 2025) | D34: Artist streams / month | F34: 195000 | G34: 280000 | H34: =IF(OR(F34="",G34=""),"",G34/F34-1) -> 0.43589744 | O34: Nov ~195k -> Dec ~280k (back to Oct level). Song-level daily streams: 2,646 -> ~4,500; 270 -> ~900; 553 -> ~1,300. Popularity of 4 promoted songs +4-6 points, top song -2. Followers/day unchanged.
B35: 1rvflj9 | C35: DM off (Oct 2025) then on | D35: Radio & autoplay streams / day | F35: 7000 | G35: 2000 | H35: =IF(OR(F35="",G35=""),"",G35/F35-1) -> -0.71428571 | O35: ~6-9k/day Jul-Sep with DM -> ~2k/day in October with DM off -> 6-11k/day after re-enrolling. Then an ~80% collapse in Mar 2026 with DM on.
B36: 1r4op37 (text) | C36: DM off | D36: Song streams / day | F36: 1000 | G36: 500 | H36: =IF(OR(F36="",G36=""),"",G36/F36-1) -> -0.5 | O36: Spotify flagged the song 'not recommended'; removing it halved daily streams.
B37: ksx3w9s (text) | C37: DM off | D37: Radio streams / month | F37: 150 | G37: 4000 | H37: =IF(OR(F37="",G37=""),"",G37/F37-1) -> 25.666667 | O37: Opposite case: 150 DM streams in last DM month; 4k radio the month after leaving.
B38: 1t81jjd | C38: DM off + Meta ads | D38: Song radio streams (28 days) | G38: 74 | H38: =IF(OR(F38="",G38=""),"",G38/F38-1) | O38: 7 of 12 songs had fallen to 0-100 radio streams in DM; after opting out, radio stayed at 74 even with ads (saves +270%).
B39: Average change when switched off, the two charted radio / autoplay cases | H39: =AVERAGE(H35,H36) -> -0.60714286 | O39: Artists who stay enrolled describe it as defensive (re-enrolled out of fear; 'would not take it out again'). For a first-time enrollee the pitch has become 'pay 30% to avoid losing ground'.

Sheet DM Data Artist Reports
B2: Artists' Own Before / After Numbers and Hand-coded Corpus (r/musicmarketing, Oct 2020 - Oct 2026) | L2: Notes
B3: Date posted | C3: Year | D3: Measure | E3: Monthly listeners at start | F3: Size band | G3: Before | H3: After | I3: Change | J3: Direction | K3: Source | L3: What the artist said
B4: 45212 | C4: =YEAR(B4) -> 2023 | D4: Monthly listeners | E4: 37500 | F4: =IF(E4="","not stated",IF(E4<10000,"Under 10k",IF(E4<50000,"10k-50k","50k+"))) -> 10k-50k | G4: 37500 | H4: 19000 | I4: =H4/G4-1 -> -0.49333333 | J4: =IF(ABS(I4)<0.05,"Flat",IF(I4>0,"Up","Down")) -> Down | K4: 176v311/k2zctt7/k3tx6dh | L4: Organic 35-40k listeners; after 3 months of DM down to 19k, no follows/saves from DM, Fans Also Like 'destroyed'.
B5: 45213 | C5: =YEAR(B5) -> 2023 | D5: Monthly listeners | E5: 80000 | F5: =IF(E5="","not stated",IF(E5<10000,"Under 10k",IF(E5<50000,"10k-50k","50k+"))) -> 50k+ | G5: 80000 | H5: 52000 | I5: =H5/G5-1 -> -0.35 | J5: =IF(ABS(I5)<0.05,"Flat",IF(I5>0,"Up","Down")) -> Down | K5: k4ox17o | L5: Discover Weekly streams fell, radio rose; saves/adds from DM 'terrible'.
B6: 45213 | C6: =YEAR(B6) -> 2023 | D6: Monthly listeners | E6: 80000 | F6: =IF(E6="","not stated",IF(E6<10000,"Under 10k",IF(E6<50000,"10k-50k","50k+"))) -> 50k+ | G6: 80000 | H6: 40000 | I6: =H6/G6-1 -> -0.5 | J6: =IF(ABS(I6)<0.05,"Flat",IF(I6>0,"Up","Down")) -> Down | K6: k4pk3ug | L6: Blames Spotify pushing Discover Weekly less after DM.
B7: 45226 | C7: =YEAR(B7) -> 2023 | D7: Radio streams / month | F7: =IF(E7="","not stated",IF(E7<10000,"Under 10k",IF(E7<50000,"10k-50k","50k+"))) -> not stated | G7: 1800 | H7: 20000 | I7: =H7/G7-1 -> 10.111111 | J7: =IF(ABS(I7)<0.05,"Flat",IF(I7>0,"Up","Down")) -> Up | K7: k6lhdlu | L7: Radio ~1,800/month before DM -> ~20,000/month after several months (releases weekly).
B8: 45240 | C8: =YEAR(B8) -> 2023 | D8: Monthly listeners | E8: 30000 | F8: =IF(E8="","not stated",IF(E8<10000,"Under 10k",IF(E8<50000,"10k-50k","50k+"))) -> 10k-50k | G8: 30000 | H8: 8700 | I8: =H8/G8-1 -> -0.71 | J8: =IF(ABS(I8)<0.05,"Flat",IF(I8>0,"Up","Down")) -> Down | K8: k79yvek | L8: One song on DM in Sept (0.90% intent); skipped Oct and Discover Weekly 'suppressed'; re-enrolled out of fear.
B9: 45261 | C9: =YEAR(B9) -> 2023 | D9: Monthly listeners | E9: 30000 | F9: =IF(E9="","not stated",IF(E9<10000,"Under 10k",IF(E9<50000,"10k-50k","50k+"))) -> 10k-50k | G9: 30000 | H9: 5000 | I9: =H9/G9-1 -> -0.83333333 | J9: =IF(ABS(I9)<0.05,"Flat",IF(I9>0,"Up","Down")) -> Down | K9: kbb4arn | L9: Beta: first campaign gave a bump; second campaign listeners fell 30k -> 5k (normal range 10-20k).
B10: 45349 | C10: =YEAR(B10) -> 2024 | D10: Streams / month | F10: =IF(E10="","not stated",IF(E10<10000,"Under 10k",IF(E10<50000,"10k-50k","50k+"))) -> not stated | G10: 10000 | H10: 50000 | I10: =H10/G10-1 -> 4 | J10: =IF(ABS(I10)<0.05,"Flat",IF(I10>0,"Up","Down")) -> Up | K10: kspq2mj | L10: 'Totally down to discovery mode'; not every song works.
B11: 45352 | C11: =YEAR(B11) -> 2024 | D11: Streams / day | F11: =IF(E11="","not stated",IF(E11<10000,"Under 10k",IF(E11<50000,"10k-50k","50k+"))) -> not stated | G11: 40000 | H11: 15000 | I11: =H11/G11-1 -> -0.625 | J11: =IF(ABS(I11)<0.05,"Flat",IF(I11>0,"Up","Down")) -> Down | K11: 1b43vbm | L11: Song at ~40k/day; fell the month it was enrolled and never recovered; also pulled from Discover Weekly.
B12: 45352 | C12: =YEAR(B12) -> 2024 | D12: Radio streams / month | F12: =IF(E12="","not stated",IF(E12<10000,"Under 10k",IF(E12<50000,"10k-50k","50k+"))) -> not stated | G12: 4000 | H12: 150 | I12: =H12/G12-1 -> -0.9625 | J12: =IF(ABS(I12)<0.05,"Flat",IF(I12>0,"Up","Down")) -> Down | K12: ksx3w9s | L12: Last DM month: 150 streams; month without DM: 4k on radio alone.
B13: 45352 | C13: =YEAR(B13) -> 2024 | D13: Monthly listeners | E13: 2000 | F13: =IF(E13="","not stated",IF(E13<10000,"Under 10k",IF(E13<50000,"10k-50k","50k+"))) -> Under 10k | G13: 2000 | H13: 7500 | I13: =H13/G13-1 -> 2.75 | J13: =IF(ABS(I13)<0.05,"Flat",IF(I13>0,"Up","Down")) -> Up | K13: kszo2zz
B14: 45364 | C14: =YEAR(B14) -> 2024 | D14: Streams / month | F14: =IF(E14="","not stated",IF(E14<10000,"Under 10k",IF(E14<50000,"10k-50k","50k+"))) -> not stated | G14: 1000000 | H14: 300000 | I14: =H14/G14-1 -> -0.7 | J14: =IF(ABS(I14)<0.05,"Flat",IF(I14>0,"Up","Down")) -> Down | K14: ktmj79o | L14: ~1M streams/month -> 300k 'literally overnight'; never came back after stopping.
B15: 45518 | C15: =YEAR(B15) -> 2024 | D15: Discover Weekly streams / week | F15: =IF(E15="","not stated",IF(E15<10000,"Under 10k",IF(E15<50000,"10k-50k","50k+"))) -> not stated | G15: 5000 | H15: 190 | I15: =H15/G15-1 -> -0.962 | J15: =IF(ABS(I15)<0.05,"Flat",IF(I15>0,"Up","Down")) -> Down | K15: li52lv4/lve66bg | L15: Best track ~5k DW streams/week; 3 weeks on DM = 567 DW streams total; took 4 months to recover.
B16: 45649 | C16: =YEAR(B16) -> 2024 | D16: Monthly listeners | E16: 25000 | F16: =IF(E16="","not stated",IF(E16<10000,"Under 10k",IF(E16<50000,"10k-50k","50k+"))) -> 10k-50k | G16: 25000 | H16: 60000 | I16: =H16/G16-1 -> 1.4 | J16: =IF(ABS(I16)<0.05,"Flat",IF(I16>0,"Up","Down")) -> Up | K16: m3i1jez | L16: ~30k DM streams month 1, 40k month 2.
B17: 45653 | C17: =YEAR(B17) -> 2024 | D17: Monthly listeners | E17: 5000 | F17: =IF(E17="","not stated",IF(E17<10000,"Under 10k",IF(E17<50000,"10k-50k","50k+"))) -> Under 10k | G17: 5000 | H17: 44000 | I17: =H17/G17-1 -> 7.8 | J17: =IF(ABS(I17)<0.05,"Flat",IF(I17>0,"Up","Down")) -> Up | K17: m3ys1wz | L17: Meta ads + DM; much of growth via radio.
B18: 45690 | C18: =YEAR(B18) -> 2025 | D18: Streams / month | E18: 60000 | F18: =IF(E18="","not stated",IF(E18<10000,"Under 10k",IF(E18<50000,"10k-50k","50k+"))) -> 50k+ | G18: 36655 | H18: 36549 | I18: =H18/G18-1 -> -0.0028918292 | J18: =IF(ABS(I18)<0.05,"Flat",IF(I18>0,"Up","Down")) -> Flat | K18: 1ig7963 | L18: Song A: Dec 36,655 streams -> Jan 36,549 while Spotify reported +69% lift. Song B: ~46k/month -> 43k while Spotify credited 7,404 DM streams (+55%).
B19: 45909 | C19: =YEAR(B19) -> 2025 | D19: Monthly listeners | E19: 10000 | F19: =IF(E19="","not stated",IF(E19<10000,"Under 10k",IF(E19<50000,"10k-50k","50k+"))) -> 10k-50k | G19: 10000 | H19: 20000 | I19: =H19/G19-1 -> 1 | J19: =IF(ABS(I19)<0.05,"Flat",IF(I19>0,"Up","Down")) -> Up | K19: nd42847
B20: 45909 | C20: =YEAR(B20) -> 2025 | D20: Monthly listeners | E20: 100 | F20: =IF(E20="","not stated",IF(E20<10000,"Under 10k",IF(E20<50000,"10k-50k","50k+"))) -> Under 10k | G20: 100 | H20: 700 | I20: =H20/G20-1 -> 6 | J20: =IF(ABS(I20)<0.05,"Flat",IF(I20>0,"Up","Down")) -> Up | K20: nd5w63f | L20: One track on DM ~800 streams/month; fans at shows cite it.
B21: 46067 | C21: =YEAR(B21) -> 2026 | D21: Streams / day | E21: 100000 | F21: =IF(E21="","not stated",IF(E21<10000,"Under 10k",IF(E21<50000,"10k-50k","50k+"))) -> 50k+ | G21: 500 | H21: 1000 | I21: =H21/G21-1 -> 1 | J21: =IF(ABS(I21)<0.05,"Flat",IF(I21>0,"Up","Down")) -> Up | K21: 1r4op37 | L21: Taking the song OUT of DM cut it from ~1,000 to ~500 streams/day; 'would not take it out again'.
B23: Direction by year posted (these 18 numeric pairs)
B24: Year | D24: Up | E24: Down | F24: Flat | G24: Total | H24: Avg listeners at start, Down cases
B25: 2023 | D25: =COUNTIFS($C$4:$C$21,B25,$J$4:$J$21,"Up") -> 1 | E25: =COUNTIFS($C$4:$C$21,B25,$J$4:$J$21,"Down") -> 5 | F25: =COUNTIFS($C$4:$C$21,B25,$J$4:$J$21,"Flat") -> 0 | G25: =SUM(D25:F25) -> 6 | H25: =IFERROR(AVERAGEIFS($E$4:$E$21,$C$4:$C$21,B25,$J$4:$J$21,"Down"),"size not stated") -> 51500
B26: 2024 | D26: =COUNTIFS($C$4:$C$21,B26,$J$4:$J$21,"Up") -> 4 | E26: =COUNTIFS($C$4:$C$21,B26,$J$4:$J$21,"Down") -> 4 | F26: =COUNTIFS($C$4:$C$21,B26,$J$4:$J$21,"Flat") -> 0 | G26: =SUM(D26:F26) -> 8 | H26: =IFERROR(AVERAGEIFS($E$4:$E$21,$C$4:$C$21,B26,$J$4:$J$21,"Down"),"size not stated") -> size not stated
B27: 2025 | D27: =COUNTIFS($C$4:$C$21,B27,$J$4:$J$21,"Up") -> 2 | E27: =COUNTIFS($C$4:$C$21,B27,$J$4:$J$21,"Down") -> 0 | F27: =COUNTIFS($C$4:$C$21,B27,$J$4:$J$21,"Flat") -> 1 | G27: =SUM(D27:F27) -> 3 | H27: =IFERROR(AVERAGEIFS($E$4:$E$21,$C$4:$C$21,B27,$J$4:$J$21,"Down"),"size not stated") -> size not stated
B28: 2026 | D28: =COUNTIFS($C$4:$C$21,B28,$J$4:$J$21,"Up") -> 1 | E28: =COUNTIFS($C$4:$C$21,B28,$J$4:$J$21,"Down") -> 0 | F28: =COUNTIFS($C$4:$C$21,B28,$J$4:$J$21,"Flat") -> 0 | G28: =SUM(D28:F28) -> 1 | H28: =IFERROR(AVERAGEIFS($E$4:$E$21,$C$4:$C$21,B28,$J$4:$J$21,"Down"),"size not stated") -> size not stated
B29: Caveat: by year these pairs trend toward 'Up', not away from it. The 2023 losers were all 30k-80k-listener artists in the early rollout; most later winners are small artists. Read it as a change in who posts, not proof the program improved.
B31: Direction by audience size at the start (all first-hand reports that stated a size, n = 26; hand-coded)
B32: Size band | D32: Up | E32: Mixed / flat | F32: Down | G32: Total | H32: Share up
B33: Under 10k | D33: 8 | E33: 0 | F33: 0 | G33: =SUM(D33:F33) -> 8 | H33: =D33/G33 -> 1
B34: 10k-50k | D34: 4 | E34: 1 | F34: 4 | G34: =SUM(D34:F34) -> 9 | H34: =D34/G34 -> 0.44444444
B35: 50k+ | D35: 3 | E35: 3 | F35: 3 | G35: =SUM(D35:F35) -> 9 | H35: =D35/G35 -> 0.33333333
B36: 10k and above | D36: =SUM(D34:D35) -> 7 | E36: =SUM(E34:E35) -> 4 | F36: =SUM(F34:F35) -> 7 | G36: =SUM(G34:G35) -> 18 | H36: =D36/G36 -> 0.38888889
B38: Corpus (hand-coded from 130 Discovery Mode threads and 1,953 comments; second-hand stories excluded; repeat comments by one person merged)
B39: r/musicmarketing posts since Oct 2020 (Arctic Shift archive) | H39: 27088
B40: Posts mentioning Discovery Mode | H40: 130
B41: Comments in those threads | H41: 1953
B42: Artist experiences coded | H42: 73
B43: of which first-hand | H43: 70
B44: first-hand: streams went up | H44: 39
B45: first-hand: streams went down | H45: 21
B46: first-hand: mixed | H46: 7
B47: first-hand: flat | H47: 3
B48: First-hand reports saying Discover Weekly / algorithmic streams fell after opting in | H48: 12
B49: Spotify for Artists screenshots read (7 more had been deleted) | H49: 35
B50: Share of first-hand reports that went up | H50: =H44/H43 -> 0.55714286
B52: Discovery Mode share of an artist's monthly streams (as reported)
B53: Source id | D53: Artist type | H53: Share | L53: Note
B54: m8up79g | D54: Established (500k+ monthly streams) | H54: 0.034965035
B55: lzx6qd3 | D55: Established (500k+ monthly streams) | H55: 0.04
B56: m3ivdij | D56: Established (500k+ monthly streams) | H56: 0.038793103
B57: m49nghw | D57: Established (500k+ monthly streams) | H57: 0.05
B58: 1deqxiz (range 5-15%) | D58: Range 5-15% | H58: 0.1
B59: mkxt4r8 | D59: Catalog-heavy or small | H59: 0.33333333
B60: m3suhdk | D60: Catalog-heavy or small | H60: 0.33333333
B61: m3su5uz (best month) | D61: Catalog-heavy or small | H61: 0.5
B62: Median, established artists only | H62: =MEDIAN(H54:H57) -> 0.039396552 | L62: The source workbook's 7.5% 'median' mixes both groups; use this for an enrolled established artist.
B63: Median, all reports | H63: =MEDIAN(H54:H61) -> 0.075
B65: Intent rate per song quoted by artists (saves + adds / listeners), order as extracted
B66: Intent 1 | H66: 0.015
B67: Intent 2 | H67: 0.009
B68: Intent 3 | H68: 0.02
B69: Intent 4 | H69: 0.0266
B70: Intent 5 | H70: 0.01
B71: Intent 6 | H71: 0.0079
B72: Intent 7 | H72: 0.01
B73: Intent 8 | H73: 0.0121
B74: Intent 9 | H74: 0.004
B75: Intent 10 | H75: 0.007
B76: Intent 11 | H76: 0.009
B77: Median | H77: =MEDIAN(H66:H76) -> 0.01
B79: Spotify-reported 'stream lift' figures quoted in posts (order as extracted; undated; the list mixes multiples such as 2.77 with percentages such as 20, so no median is taken)
B80: Lift 1 | H80: 2.77
B81: Lift 2 | H81: 9.15
B82: Lift 3 | H82: 11.92
B83: Lift 4 | H83: 1.5
B84: Lift 5 | H84: 20
B85: Lift 6 | H85: 30
B86: Lift 7 | H86: 60
B87: Lift 8 | H87: 1.53
B88: Lift 9 | H88: 0.69
B89: Lift 10 | H89: 0.55
B90: Lift 11 | H90: 0.78
B91: Lift 12 | H91: 2.14
B92: Lift 13 | H92: 1.69
B94: Self-selected stories: people post when results surprise. Discovery Mode's start often coincides with releases, ads or TikTok moments, and the algorithm changes over time (several artists report platform-wide drops in 2026). Not a controlled experiment; 35 screenshots read (7 deleted).
