Workbook

Sheet GM Waterfall
B1: FY25 | C1: FY26 | D1: FY27 | E1: FY28 | F1: FY29 | G1: FY30
A2: Revenue | B2: =RPM!Q58 -> 17186 | C2: =RPM!V58 -> 19410 | D2: =RPM!AA58 -> 21172 | E2: =RPM!AB58 -> 23166 | F2: =RPM!AC58 -> 25017 | G2: =RPM!AD58 -> 26482 | H2: RPM row 58 (total revenue).
A3: Label % | B3: 0.5 | C3: =B3 -> 0.5 | D3: =C3 -> 0.5 | E3: =D3 -> 0.5 | F3: =E3 -> 0.5 | G3: =F3 -> 0.5 | H3: Recording-royalty rate before Discovery Mode, % of total revenue, blended across tiers. Major-label Premium headline ~52%, independents ~50%, ad tier on the greater of revenue share or per-stream minimums. Chosen so that royalties after the DM haircut land on Loud & Clear's €10.1bn (58.8% of 2025 revenue). Held flat.
A4: Publisher % | B4: 0.11 | C4: =B4 -> 0.11 | D4: =C4 -> 0.11 | E4: =D4 -> 0.11 | F4: =E4 -> 0.11 | G4: =F4 -> 0.11 | H4: Mechanical + performance royalties, % of total revenue. US Premium statutory all-in 15.25% (Phonorecords IV, 2025) less the bundle discount since Mar-24; non-US nearer 10-13%. Not reduced by Discovery Mode. Held flat.
A5: Royalties | B5: =B2*(B3+B4) -> 10483.46 | C5: =C2*(C3+C4) -> 11840.1 | D5: =D2*(D3+D4) -> 12914.92 | E5: =E2*(E3+E4) -> 14131.26 | F5: =F2*(F3+F4) -> 15260.37 | G5: =G2*(G3+G4) -> 16154.02 | H5: Revenue x (label % + publisher %): the royalty pool before the Discovery Mode haircut.
A7: Discovery Mode Eligible Streams | B7: ='DM Inputs'!D30 -> 0.512 | C7: ='DM Inputs'!E31 -> 0.52 | D7: ='DM Inputs'!F31 -> 0.525 | E7: =D7+(D7-C7)*2/3 -> 0.52833333 | F7: =E7+(D7-C7)*1/3 -> 0.53 | G7: =F7 -> 0.53 | H7: % of streams served in Radio / Autoplay / Mixes. FY25 = DM Inputs D30; FY26-FY27 = the active case rows on DM Inputs (E31, F31); FY28 adds two thirds of the FY27 step, FY29 one third, FY30 flat.
A8: DM % of DM-eligible streams | B8: ='DM Inputs'!D35 -> 0.33 | C8: ='DM Inputs'!E36 -> 0.33 | D8: ='DM Inputs'!F36 -> 0.335 | E8: =D8+(D8-C8)*2/3 -> 0.33833333 | F8: =E8+(D8-C8)*1/3 -> 0.34 | G8: =F8 -> 0.34 | H8: % of eligible-context streams that are Discovery Mode streams. FY25 = DM Inputs D35; FY26-FY27 = DM Inputs E36, F36; same fade to flat by FY30.
A9: DM haircut | B9: 0.3 | C9: =B9 -> 0.3 | D9: =C9 -> 0.3 | E9: =D9 -> 0.3 | F9: =E9 -> 0.3 | G9: =F9 -> 0.3 | H9: Program term: 30% lower recording royalty on DM-context streams. Held flat; lower a later year to model a claw-back at label renewals.
A10: DM royalties | B10: =B2*B3*B7*B8 -> 1451.8733 | C10: =C2*C3*C7*C8 -> 1665.378 | D10: =D2*D3*D7*D8 -> 1861.8128 | E10: =E2*E3*E7*E8 -> 2070.4934 | F10: =F2*F3*F7*F8 -> 2254.0317 | G10: =G2*G3*G7*G8 -> 2386.0282 | H10: Label royalties attributable to Discovery Mode streams before the haircut = revenue x label % x eligible share x DM share. Publishing is not discounted, so only the label line is in scope.
A11: DM netted royalties | B11: =B10*(1-B9) -> 1016.3113 | C11: =C10*(1-C9) -> 1165.7646 | D11: =D10*(1-D9) -> 1303.2689 | E11: =E10*(1-E9) -> 1449.3454 | F11: =F10*(1-F9) -> 1577.8222 | G11: =G10*(1-G9) -> 1670.2197 | H11: What is actually paid on those streams = DM royalties x (1 - haircut).
A13: Audiobook licensing | B13: ='Audiobook GM Bridge'!D41 -> 300.2 | C13: ='Audiobook GM Bridge'!E41 -> 429.286 | D13: ='Audiobook GM Bridge'!F41 -> 558.072 | E13: =D13*(1+E14) -> 669.6864 | F13: =E13*(1+F14) -> 770.13936 | G13: =F13*(1+G14) -> 847.1533 | H13: FY25-FY27 from the audiobook bridge (row 41, cost paid to book publishers). FY28-FY30 grown at the rates below.
A14: % y/y growth | C14: =C13/B13-1 -> 0.43 | D14: =D13/C13-1 -> 0.30000047 | E14: 0.2 | F14: 0.15 | G14: 0.1 | H14: FY28-FY30: inputs, decelerating from the audiobook tab's FY27 rate.
A16: Other cost of revenue (payment fees, podcasts, delivery) | B16: =-IS!AA12-(B5-B10+B11+B13) -> 1341.902 | C16: =C2*$B$16/$B$2 -> 1515.5544 | D16: =D2*$B$16/$B$2 -> 1653.1333 | E16: =E2*$B$16/$B$2 -> 1808.827 | F16: =F2*$B$16/$B$2 -> 1953.3552 | G16: =G2*$B$16/$B$2 -> 2067.744 | H16: Added so FY25 ties to reported cost of revenue (IS 2025, €11,690M): the plug is payment processing (~3% of revenue), podcast content and production (~2%), streaming delivery, hosting and support (~2%). Held at the FY25 % of revenue. Delete this row for the pure royalty waterfall; FY25 gross margin then reads ~39% instead of 32%.
A18: COGS | B18: =B5-B10+B11+B13+B16 -> 11690 | C18: =C5-C10+C11+C13+C16 -> 13285.327 | D18: =D5-D10+D11+D13+D16 -> 14567.581 | E18: =E5-E10+E11+E13+E16 -> 15988.625 | F18: =F5-F10+F11+F13+F16 -> 17307.655 | G18: =G5-G10+G11+G13+G16 -> 18353.109 | H18: Royalties - DM royalties + DM netted royalties + audiobook licensing + other.
A19: Gross profit | B19: =B2-B18 -> 5496 | C19: =C2-C18 -> 6124.673 | D19: =D2-D18 -> 6604.4185 | E19: =E2-E18 -> 7177.3746 | F19: =F2-F18 -> 7709.345 | G19: =G2-G18 -> 8128.8912
A20: Gross margin % | B20: =B19/B2 -> 0.31979518 | C20: =C19/C2 -> 0.31554214 | D20: =D19/D2 -> 0.31194117 | E20: =E19/E2 -> 0.30982365 | F20: =F19/F2 -> 0.30816425 | G20: =G19/G2 -> 0.30695911
A22: Memo
A23: Reported COGS (IS) | B23: =-IS!AA12 -> 11690 | H23: FY25 20-F / IS. FY25 gross margin reproduces 32.0% by construction.
A24: Royalties after Discovery Mode, % of revenue | B24: =(B5-B10+B11)/B2 -> 0.584656 | C24: =(C5-C10+C11)/C2 -> 0.58426 | D24: =(D5-D10+D11)/D2 -> 0.58361875 | E24: =(E5-E10+E11)/E2 -> 0.58318708 | F24: =(F5-F10+F11)/F2 -> 0.58297 | G24: =(G5-G10+G11)/G2 -> 0.58297 | H24: Check against Loud & Clear: €10.1bn paid to the music industry in 2025 = 58.8% of revenue.
A25: Discovery Mode saving | B25: =B10-B11 -> 435.56198 | C25: =C10-C11 -> 499.6134 | D25: =D10-D11 -> 558.54382 | E25: =E10-E11 -> 621.14803 | F25: =F10-F11 -> 676.20951 | G25: =G10-G11 -> 715.80846 | H25: DM royalties - DM netted royalties = the cost-of-revenue reduction.
A26: as bp of gross margin | B26: =(B10-B11)/B2*10000 -> 253.44 | C26: =(C10-C11)/C2*10000 -> 257.4 | D26: =(D10-D11)/D2*10000 -> 263.8125 | E26: =(E10-E11)/E2*10000 -> 268.12917 | F26: =(F10-F11)/F2*10000 -> 270.3 | G26: =(G10-G11)/G2*10000 -> 270.3
A27: Gross margin % with no Discovery Mode | B27: =(B2-B18-(B10-B11))/B2 -> 0.29445118 | C27: =(C2-C18-(C10-C11))/C2 -> 0.28980214 | D27: =(D2-D18-(D10-D11))/D2 -> 0.28555992 | E27: =(E2-E18-(E10-E11))/E2 -> 0.28301073 | F27: =(F2-F18-(F10-F11))/F2 -> 0.28113425 | G27: =(G2-G18-(G10-G11))/G2 -> 0.27992911
A28: Blue = input; gold = held flat / case-driven / fade; black = formula. After pasting into the model, Find & Replace "[SPOT_GM_Waterfall_Tab.xlsx]" with nothing so links point at the model's own tabs; the stub sheets in this file are not needed there.

Sheet RPM
B2: STUB | Q2: FY25 | V2: FY26 | AA2: FY27 | AB2: FY28 | AC2: FY29 | AD2: FY30
B58: Total Revenue | Q58: 17186 | V58: 19410 | AA58: 21172 | AB58: 23166 | AC58: 25017 | AD58: 26482

Sheet DM Inputs
B2: STUB
D30: 0.512
E31: 0.52 | F31: 0.525
D35: 0.33
E36: 0.33 | F36: 0.335

Sheet Audiobook GM Bridge
B2: STUB
B41: C: Licensing cost paid to book publishers | D41: 300.2 | E41: 429.286 | F41: 558.072

Sheet IS
B2: STUB
AA3: 2025
B12: Cost of Revenue | AA12: -11690
