Workbook

Sheet Cover
B11: Company Information
B12: Company Name | C12: FTAI Aviation
B13: Ticker | C13: NASDAQ: FTAI
B15: Share price (10.2.26) | C15: =DCF!K18
B16: Diluted shares outstanding (mm) | C16: =DCF!K16
B17: Market Capitalization ($mm) | C17: =C15*C16
B18: (-) Cash & Equivalents ($mm) | C18: =DCF!K14*-1
B19: (+) Total Debt ($mm) | C19: =DCF!K12*-1
B20: (+) Preferred Equity ($mm) | C20: =DCF!K13*-1
B21: Enterprise Value ($mm) | C21: =SUM(C17:C20)
B23: Key
B24: Hardcodes | C24: BLUE
B25: Calculations | C25: BLACK
B26: Linked | C26: GREEN
B27: Key assumption / fill in | C27: YELLOW
B29: 1-Year Valuation (Oct-27)
B30: 1-year target (active case) | C30: ='1Y Valuation'!F24
B31: Return | C31: ='1Y Valuation'!F26
B32: Probability-weighted target | C32: ='1Y Valuation'!J11
B33: Reward / risk | C33: ='1Y Valuation'!J13

Sheet DCF
B2: Case Selector
B3: Toggle | C3: Base | P3: Sensitivity: Implied Share Price
Q4: Terminal Growth Rate
C5: 2026E | D5: 2027E | E5: 2028E | F5: 2029E | G5: 2030E | H5: 2031E | J5: Perpetuity Growth Method | M5: Exit Multiple Method | P5: =K17 | Q5: 0.02 | R5: 0.025 | S5: 0.03 | T5: 0.035 | U5: 0.04
B6: Present Value Bridge | J6: WACC | K6: ='WACC Calculation'!B20 | M6: WACC | N6: =K6 | P6: =ROUND($K$6*200,0)/200+(-0.01) | Q6: =(SUMPRODUCT($C$9:$H$9/(1+$P6)^$C$10:$H$10)+('Operating Model'!$I$29*(1+Q$5)-Q$5*'Operating Model'!$I$58)/($P6-Q$5)/(1+$P6)^$H$10+$K$12+$K$13+$K$14)/$K$16 | R6: =(SUMPRODUCT($C$9:$H$9/(1+$P6)^$C$10:$H$10)+('Operating Model'!$I$29*(1+R$5)-R$5*'Operating Model'!$I$58)/($P6-R$5)/(1+$P6)^$H$10+$K$12+$K$13+$K$14)/$K$16 | S6: =(SUMPRODUCT($C$9:$H$9/(1+$P6)^$C$10:$H$10)+('Operating Model'!$I$29*(1+S$5)-S$5*'Operating Model'!$I$58)/($P6-S$5)/(1+$P6)^$H$10+$K$12+$K$13+$K$14)/$K$16 | T6: =(SUMPRODUCT($C$9:$H$9/(1+$P6)^$C$10:$H$10)+('Operating Model'!$I$29*(1+T$5)-T$5*'Operating Model'!$I$58)/($P6-T$5)/(1+$P6)^$H$10+$K$12+$K$13+$K$14)/$K$16 | U6: =(SUMPRODUCT($C$9:$H$9/(1+$P6)^$C$10:$H$10)+('Operating Model'!$I$29*(1+U$5)-U$5*'Operating Model'!$I$58)/($P6-U$5)/(1+$P6)^$H$10+$K$12+$K$13+$K$14)/$K$16
B7: UFCF | C7: ='Operating Model'!D69 | D7: ='Operating Model'!E69 | E7: ='Operating Model'!F69 | F7: ='Operating Model'!G69 | G7: ='Operating Model'!H69 | H7: ='Operating Model'!I69 | J7: PV of Projected UFCF | K7: =SUM(C12:H12) | M7: PV of Projected UFCF | N7: =K7 | P7: =ROUND($K$6*200,0)/200+(-0.005) | Q7: =(SUMPRODUCT($C$9:$H$9/(1+$P7)^$C$10:$H$10)+('Operating Model'!$I$29*(1+Q$5)-Q$5*'Operating Model'!$I$58)/($P7-Q$5)/(1+$P7)^$H$10+$K$12+$K$13+$K$14)/$K$16 | R7: =(SUMPRODUCT($C$9:$H$9/(1+$P7)^$C$10:$H$10)+('Operating Model'!$I$29*(1+R$5)-R$5*'Operating Model'!$I$58)/($P7-R$5)/(1+$P7)^$H$10+$K$12+$K$13+$K$14)/$K$16 | S7: =(SUMPRODUCT($C$9:$H$9/(1+$P7)^$C$10:$H$10)+('Operating Model'!$I$29*(1+S$5)-S$5*'Operating Model'!$I$58)/($P7-S$5)/(1+$P7)^$H$10+$K$12+$K$13+$K$14)/$K$16 | T7: =(SUMPRODUCT($C$9:$H$9/(1+$P7)^$C$10:$H$10)+('Operating Model'!$I$29*(1+T$5)-T$5*'Operating Model'!$I$58)/($P7-T$5)/(1+$P7)^$H$10+$K$12+$K$13+$K$14)/$K$16 | U7: =(SUMPRODUCT($C$9:$H$9/(1+$P7)^$C$10:$H$10)+('Operating Model'!$I$29*(1+U$5)-U$5*'Operating Model'!$I$58)/($P7-U$5)/(1+$P7)^$H$10+$K$12+$K$13+$K$14)/$K$16
B8: Year Fraction | C8: =$K$21 | D8: 1 | E8: 1 | F8: 1 | G8: 1 | H8: 1 | J8: Terminal Growth Rate | K8: 0.03 | M8: Final Year Adj. EBITDA | N8: =H14 | O8: WACC | P8: =ROUND($K$6*200,0)/200+(0) | Q8: =(SUMPRODUCT($C$9:$H$9/(1+$P8)^$C$10:$H$10)+('Operating Model'!$I$29*(1+Q$5)-Q$5*'Operating Model'!$I$58)/($P8-Q$5)/(1+$P8)^$H$10+$K$12+$K$13+$K$14)/$K$16 | R8: =(SUMPRODUCT($C$9:$H$9/(1+$P8)^$C$10:$H$10)+('Operating Model'!$I$29*(1+R$5)-R$5*'Operating Model'!$I$58)/($P8-R$5)/(1+$P8)^$H$10+$K$12+$K$13+$K$14)/$K$16 | S8: =(SUMPRODUCT($C$9:$H$9/(1+$P8)^$C$10:$H$10)+('Operating Model'!$I$29*(1+S$5)-S$5*'Operating Model'!$I$58)/($P8-S$5)/(1+$P8)^$H$10+$K$12+$K$13+$K$14)/$K$16 | T8: =(SUMPRODUCT($C$9:$H$9/(1+$P8)^$C$10:$H$10)+('Operating Model'!$I$29*(1+T$5)-T$5*'Operating Model'!$I$58)/($P8-T$5)/(1+$P8)^$H$10+$K$12+$K$13+$K$14)/$K$16 | U8: =(SUMPRODUCT($C$9:$H$9/(1+$P8)^$C$10:$H$10)+('Operating Model'!$I$29*(1+U$5)-U$5*'Operating Model'!$I$58)/($P8-U$5)/(1+$P8)^$H$10+$K$12+$K$13+$K$14)/$K$16
B9: UFCF in Period | C9: =C7*C8 | D9: =D7*D8 | E9: =E7*E8 | F9: =F7*F8 | G9: =G7*G8 | H9: =H7*H8 | J9: Terminal Value | K9: =K22/(K6-K8) | M9: Exit Multiple (EV / EBITDA) | N9: 13 | P9: =ROUND($K$6*200,0)/200+(0.005) | Q9: =(SUMPRODUCT($C$9:$H$9/(1+$P9)^$C$10:$H$10)+('Operating Model'!$I$29*(1+Q$5)-Q$5*'Operating Model'!$I$58)/($P9-Q$5)/(1+$P9)^$H$10+$K$12+$K$13+$K$14)/$K$16 | R9: =(SUMPRODUCT($C$9:$H$9/(1+$P9)^$C$10:$H$10)+('Operating Model'!$I$29*(1+R$5)-R$5*'Operating Model'!$I$58)/($P9-R$5)/(1+$P9)^$H$10+$K$12+$K$13+$K$14)/$K$16 | S9: =(SUMPRODUCT($C$9:$H$9/(1+$P9)^$C$10:$H$10)+('Operating Model'!$I$29*(1+S$5)-S$5*'Operating Model'!$I$58)/($P9-S$5)/(1+$P9)^$H$10+$K$12+$K$13+$K$14)/$K$16 | T9: =(SUMPRODUCT($C$9:$H$9/(1+$P9)^$C$10:$H$10)+('Operating Model'!$I$29*(1+T$5)-T$5*'Operating Model'!$I$58)/($P9-T$5)/(1+$P9)^$H$10+$K$12+$K$13+$K$14)/$K$16 | U9: =(SUMPRODUCT($C$9:$H$9/(1+$P9)^$C$10:$H$10)+('Operating Model'!$I$29*(1+U$5)-U$5*'Operating Model'!$I$58)/($P9-U$5)/(1+$P9)^$H$10+$K$12+$K$13+$K$14)/$K$16
B10: Discount Period (mid-year) | C10: =C8/2 | D10: =SUM($C$8:C8)+D8/2 | E10: =SUM($C$8:D8)+E8/2 | F10: =SUM($C$8:E8)+F8/2 | G10: =SUM($C$8:F8)+G8/2 | H10: =SUM($C$8:G8)+H8/2 | J10: PV of TV (mid-year) | K10: =K9/(1+K6)^H10 | M10: Terminal Value | N10: =N8*N9 | P10: =ROUND($K$6*200,0)/200+(0.01) | Q10: =(SUMPRODUCT($C$9:$H$9/(1+$P10)^$C$10:$H$10)+('Operating Model'!$I$29*(1+Q$5)-Q$5*'Operating Model'!$I$58)/($P10-Q$5)/(1+$P10)^$H$10+$K$12+$K$13+$K$14)/$K$16 | R10: =(SUMPRODUCT($C$9:$H$9/(1+$P10)^$C$10:$H$10)+('Operating Model'!$I$29*(1+R$5)-R$5*'Operating Model'!$I$58)/($P10-R$5)/(1+$P10)^$H$10+$K$12+$K$13+$K$14)/$K$16 | S10: =(SUMPRODUCT($C$9:$H$9/(1+$P10)^$C$10:$H$10)+('Operating Model'!$I$29*(1+S$5)-S$5*'Operating Model'!$I$58)/($P10-S$5)/(1+$P10)^$H$10+$K$12+$K$13+$K$14)/$K$16 | T10: =(SUMPRODUCT($C$9:$H$9/(1+$P10)^$C$10:$H$10)+('Operating Model'!$I$29*(1+T$5)-T$5*'Operating Model'!$I$58)/($P10-T$5)/(1+$P10)^$H$10+$K$12+$K$13+$K$14)/$K$16 | U10: =(SUMPRODUCT($C$9:$H$9/(1+$P10)^$C$10:$H$10)+('Operating Model'!$I$29*(1+U$5)-U$5*'Operating Model'!$I$58)/($P10-U$5)/(1+$P10)^$H$10+$K$12+$K$13+$K$14)/$K$16
B11: Discount Factor | C11: =1/(1+$K$6)^C10 | D11: =1/(1+$K$6)^D10 | E11: =1/(1+$K$6)^E10 | F11: =1/(1+$K$6)^F10 | G11: =1/(1+$K$6)^G10 | H11: =1/(1+$K$6)^H10 | J11: Enterprise Value | K11: =K7+K10 | M11: PV of TV | N11: =N10/(1+K6)^(H10+H8/2) | P11: =ROUND($K$6*200,0)/200+(0.015) | Q11: =(SUMPRODUCT($C$9:$H$9/(1+$P11)^$C$10:$H$10)+('Operating Model'!$I$29*(1+Q$5)-Q$5*'Operating Model'!$I$58)/($P11-Q$5)/(1+$P11)^$H$10+$K$12+$K$13+$K$14)/$K$16 | R11: =(SUMPRODUCT($C$9:$H$9/(1+$P11)^$C$10:$H$10)+('Operating Model'!$I$29*(1+R$5)-R$5*'Operating Model'!$I$58)/($P11-R$5)/(1+$P11)^$H$10+$K$12+$K$13+$K$14)/$K$16 | S11: =(SUMPRODUCT($C$9:$H$9/(1+$P11)^$C$10:$H$10)+('Operating Model'!$I$29*(1+S$5)-S$5*'Operating Model'!$I$58)/($P11-S$5)/(1+$P11)^$H$10+$K$12+$K$13+$K$14)/$K$16 | T11: =(SUMPRODUCT($C$9:$H$9/(1+$P11)^$C$10:$H$10)+('Operating Model'!$I$29*(1+T$5)-T$5*'Operating Model'!$I$58)/($P11-T$5)/(1+$P11)^$H$10+$K$12+$K$13+$K$14)/$K$16 | U11: =(SUMPRODUCT($C$9:$H$9/(1+$P11)^$C$10:$H$10)+('Operating Model'!$I$29*(1+U$5)-U$5*'Operating Model'!$I$58)/($P11-U$5)/(1+$P11)^$H$10+$K$12+$K$13+$K$14)/$K$16
B12: PV of UFCF | C12: =C9*C11 | D12: =D9*D11 | E12: =E9*E11 | F12: =F9*F11 | G12: =G9*G11 | H12: =H9*H11 | J12: (-) Debt | K12: -3453.32 | M12: Enterprise Value | N12: =N7+N11
J13: (-) Preferred Equity | K13: -65 | M13: (-) Debt | N13: =K12 | Q13: Exit Multiple (EV / EBITDA)
B14: Adj. EBITDA | C14: ='Operating Model'!D18 | D14: ='Operating Model'!E18 | E14: ='Operating Model'!F18 | F14: ='Operating Model'!G18 | G14: ='Operating Model'!H18 | H14: ='Operating Model'!I18 | J14: (+) Cash | K14: 337.195 | M14: (-) Preferred Equity | N14: =K13 | P14: =N18 | Q14: 11 | R14: 12 | S14: 13 | T14: 14 | U14: 15
J15: Equity Value | K15: =K11+K12+K13+K14 | M15: (+) Cash | N15: =K14 | P15: =P6 | Q15: =(SUMPRODUCT($C$9:$H$9/(1+$P15)^$C$10:$H$10)+$H$14*Q$14/(1+$P15)^($H$10+$H$8/2)+$K$12+$K$13+$K$14)/$K$16 | R15: =(SUMPRODUCT($C$9:$H$9/(1+$P15)^$C$10:$H$10)+$H$14*R$14/(1+$P15)^($H$10+$H$8/2)+$K$12+$K$13+$K$14)/$K$16 | S15: =(SUMPRODUCT($C$9:$H$9/(1+$P15)^$C$10:$H$10)+$H$14*S$14/(1+$P15)^($H$10+$H$8/2)+$K$12+$K$13+$K$14)/$K$16 | T15: =(SUMPRODUCT($C$9:$H$9/(1+$P15)^$C$10:$H$10)+$H$14*T$14/(1+$P15)^($H$10+$H$8/2)+$K$12+$K$13+$K$14)/$K$16 | U15: =(SUMPRODUCT($C$9:$H$9/(1+$P15)^$C$10:$H$10)+$H$14*U$14/(1+$P15)^($H$10+$H$8/2)+$K$12+$K$13+$K$14)/$K$16
J16: Diluted Shares (mm) | K16: 104.044 | M16: Equity Value | N16: =N12+N13+N14+N15 | P16: =P7 | Q16: =(SUMPRODUCT($C$9:$H$9/(1+$P16)^$C$10:$H$10)+$H$14*Q$14/(1+$P16)^($H$10+$H$8/2)+$K$12+$K$13+$K$14)/$K$16 | R16: =(SUMPRODUCT($C$9:$H$9/(1+$P16)^$C$10:$H$10)+$H$14*R$14/(1+$P16)^($H$10+$H$8/2)+$K$12+$K$13+$K$14)/$K$16 | S16: =(SUMPRODUCT($C$9:$H$9/(1+$P16)^$C$10:$H$10)+$H$14*S$14/(1+$P16)^($H$10+$H$8/2)+$K$12+$K$13+$K$14)/$K$16 | T16: =(SUMPRODUCT($C$9:$H$9/(1+$P16)^$C$10:$H$10)+$H$14*T$14/(1+$P16)^($H$10+$H$8/2)+$K$12+$K$13+$K$14)/$K$16 | U16: =(SUMPRODUCT($C$9:$H$9/(1+$P16)^$C$10:$H$10)+$H$14*U$14/(1+$P16)^($H$10+$H$8/2)+$K$12+$K$13+$K$14)/$K$16
B17: Sum of the Parts (FY27E) | C17: FY27E EBITDA | D17: EV / EBITDA | E17: EV ($mm) | F17: $ / Share | J17: Implied Share Price | K17: =K15/K16 | M17: Diluted Shares (mm) | N17: =K16 | O17: WACC | P17: =P8 | Q17: =(SUMPRODUCT($C$9:$H$9/(1+$P17)^$C$10:$H$10)+$H$14*Q$14/(1+$P17)^($H$10+$H$8/2)+$K$12+$K$13+$K$14)/$K$16 | R17: =(SUMPRODUCT($C$9:$H$9/(1+$P17)^$C$10:$H$10)+$H$14*R$14/(1+$P17)^($H$10+$H$8/2)+$K$12+$K$13+$K$14)/$K$16 | S17: =(SUMPRODUCT($C$9:$H$9/(1+$P17)^$C$10:$H$10)+$H$14*S$14/(1+$P17)^($H$10+$H$8/2)+$K$12+$K$13+$K$14)/$K$16 | T17: =(SUMPRODUCT($C$9:$H$9/(1+$P17)^$C$10:$H$10)+$H$14*T$14/(1+$P17)^($H$10+$H$8/2)+$K$12+$K$13+$K$14)/$K$16 | U17: =(SUMPRODUCT($C$9:$H$9/(1+$P17)^$C$10:$H$10)+$H$14*U$14/(1+$P17)^($H$10+$H$8/2)+$K$12+$K$13+$K$14)/$K$16
B18: Aerospace Products | C18: ='Operating Model'!E14 | D18: 16 | E18: =C18*D18 | F18: =E18/$K$16 | J18: Current Price | K18: 167.03 | M18: Implied Share Price | N18: =N16/N17 | P18: =P9 | Q18: =(SUMPRODUCT($C$9:$H$9/(1+$P18)^$C$10:$H$10)+$H$14*Q$14/(1+$P18)^($H$10+$H$8/2)+$K$12+$K$13+$K$14)/$K$16 | R18: =(SUMPRODUCT($C$9:$H$9/(1+$P18)^$C$10:$H$10)+$H$14*R$14/(1+$P18)^($H$10+$H$8/2)+$K$12+$K$13+$K$14)/$K$16 | S18: =(SUMPRODUCT($C$9:$H$9/(1+$P18)^$C$10:$H$10)+$H$14*S$14/(1+$P18)^($H$10+$H$8/2)+$K$12+$K$13+$K$14)/$K$16 | T18: =(SUMPRODUCT($C$9:$H$9/(1+$P18)^$C$10:$H$10)+$H$14*T$14/(1+$P18)^($H$10+$H$8/2)+$K$12+$K$13+$K$14)/$K$16 | U18: =(SUMPRODUCT($C$9:$H$9/(1+$P18)^$C$10:$H$10)+$H$14*U$14/(1+$P18)^($H$10+$H$8/2)+$K$12+$K$13+$K$14)/$K$16
B19: FTAI Power | C19: ='Operating Model'!E15 | D19: 12 | E19: =C19*D19 | F19: =E19/$K$16 | J19: % Upside | K19: =(K17-K18)/K18 | M19: Current Price | N19: =K18 | P19: =P10 | Q19: =(SUMPRODUCT($C$9:$H$9/(1+$P19)^$C$10:$H$10)+$H$14*Q$14/(1+$P19)^($H$10+$H$8/2)+$K$12+$K$13+$K$14)/$K$16 | R19: =(SUMPRODUCT($C$9:$H$9/(1+$P19)^$C$10:$H$10)+$H$14*R$14/(1+$P19)^($H$10+$H$8/2)+$K$12+$K$13+$K$14)/$K$16 | S19: =(SUMPRODUCT($C$9:$H$9/(1+$P19)^$C$10:$H$10)+$H$14*S$14/(1+$P19)^($H$10+$H$8/2)+$K$12+$K$13+$K$14)/$K$16 | T19: =(SUMPRODUCT($C$9:$H$9/(1+$P19)^$C$10:$H$10)+$H$14*T$14/(1+$P19)^($H$10+$H$8/2)+$K$12+$K$13+$K$14)/$K$16 | U19: =(SUMPRODUCT($C$9:$H$9/(1+$P19)^$C$10:$H$10)+$H$14*U$14/(1+$P19)^($H$10+$H$8/2)+$K$12+$K$13+$K$14)/$K$16
B20: Aviation Leasing + SCI | C20: ='Operating Model'!E16 | D20: 9 | E20: =C20*D20 | F20: =E20/$K$16 | M20: % Upside | N20: =(N18-N19)/N19 | P20: =P11 | Q20: =(SUMPRODUCT($C$9:$H$9/(1+$P20)^$C$10:$H$10)+$H$14*Q$14/(1+$P20)^($H$10+$H$8/2)+$K$12+$K$13+$K$14)/$K$16 | R20: =(SUMPRODUCT($C$9:$H$9/(1+$P20)^$C$10:$H$10)+$H$14*R$14/(1+$P20)^($H$10+$H$8/2)+$K$12+$K$13+$K$14)/$K$16 | S20: =(SUMPRODUCT($C$9:$H$9/(1+$P20)^$C$10:$H$10)+$H$14*S$14/(1+$P20)^($H$10+$H$8/2)+$K$12+$K$13+$K$14)/$K$16 | T20: =(SUMPRODUCT($C$9:$H$9/(1+$P20)^$C$10:$H$10)+$H$14*T$14/(1+$P20)^($H$10+$H$8/2)+$K$12+$K$13+$K$14)/$K$16 | U20: =(SUMPRODUCT($C$9:$H$9/(1+$P20)^$C$10:$H$10)+$H$14*U$14/(1+$P20)^($H$10+$H$8/2)+$K$12+$K$13+$K$14)/$K$16
B21: Corporate & Eliminations | C21: ='Operating Model'!E17 | D21: =SUMPRODUCT(C18:C20,D18:D20)/SUM(C18:C20) | E21: =C21*D21 | F21: =E21/$K$16 | J21: Stub Year Fraction (FY26) | K21: 0.5
B22: Enterprise Value | C22: =SUM(C18:C21) | D22: =E22/C22 | E22: =SUM(E18:E21) | F22: =E22/$K$16 | J22: Normalized Terminal UFCF | K22: ='Operating Model'!I29*(1+K8)-K8*'Operating Model'!I58 | M22: Implied Terminal Growth | N22: =(N10/(1+K6)^0.5*K6-'Operating Model'!I29)/(N10/(1+K6)^0.5+'Operating Model'!I29-'Operating Model'!I58)
B23: (-) Net Debt (YE27E) | E23: =-'Operating Model'!E79 | F23: =E23/$K$16 | M23: Implied Exit Multiple (Perpetuity) | N23: =K9*(1+K6)^0.5/H14
B24: (-) Preferred Equity | E24: =K13 | F24: =E24/$K$16
B25: Equity Value | E25: =E22+E23+E24 | F25: =E25/$K$16 | J25: R/R | M25: Blended Valuation
B26: Current Price | F26: =K18 | J26: Reward (Bull blended % upside) | K26: 1.319 | M26: Perpetuity Growth Method | N26: =K17
B27: SOTP % Upside | F27: =F25/F26-1 | J27: Risk (Bear blended % downside) | K27: -0.386 | M27: Exit Multiple Method | N27: =N18
J28: R/R Skew | K28: =IFERROR(K26/(-1*K27),0) | M28: Weight on Perpetuity Method | N28: 0.5
B29: SOTP Price ex-Power | F29: =(E25-E19)/$K$16 | M29: Blended Share Price | N29: =N26*N28+N27*(1-N28)
B30: SOTP % Upside ex-Power | F30: =F29/F26-1 | M30: Current Price | N30: =K18
M31: Blended % Upside | N31: =N29/N30-1

Sheet 1Y Valuation
B1: FTAI Aviation
B2: 1-Year Valuation (target date Oct-27) – matches the pitch deck
B3: Case follows DCF!C3. NTM = Q4'27–Q3'28 ≈ ¼ FY27E + ¾ FY28E; net debt interpolated YE26E → YE27E. $ in millions except per share.
B5: Case-specific multiples (EV / NTM EBITDA) | H5: Case outputs (pasted values from the case toggle)
B6: Segment | C6: Bear | D6: Base | E6: Bull | F6: Active | I6: Bear | J6: Base | K6: Bull
B7: Aerospace Products | C7: 10 | D7: 14 | E7: 16 | F7: =CHOOSE(MATCH(DCF!$C$3,{"Bear","Base","Bull"},0),C7,D7,E7) | H7: NTM adj. EBITDA ($M) | I7: 1562.1 | J7: 2843.4 | K7: 3402
B8: FTAI Power | C8: 8 | D8: 10 | E8: 12 | F8: =CHOOSE(MATCH(DCF!$C$3,{"Bear","Base","Bull"},0),C8,D8,E8) | H8: 1-year target ($ / share) | I8: 113.52 | J8: 309.32 | K8: 429.94
B9: Aviation Leasing + SCI | C9: 8 | D9: 9 | E9: 9 | F9: =CHOOSE(MATCH(DCF!$C$3,{"Bear","Base","Bull"},0),C9,D9,E9) | H9: Return vs. $167.03 | I9: -0.32 | J9: 0.852 | K9: 1.574
H10: Probability | I10: 0.2 | J10: 0.6 | K10: 0.2
B11: NTM weights | H11: Probability-weighted target | J11: =SUMPRODUCT(I8:K8,I10:K10)
B12: Weight on FY27E | C12: 0.25 | H12: Probability-weighted return | J12: =J11/F25-1
B13: Weight on FY28E | C13: =1-C12 | H13: Reward / risk (bull up / bear down) | J13: =K9/-I9
B15: Sum of the parts at Oct-27 (active case) | H15: Value bridge by thesis (base multiples)
B16: Segment | C16: NTM EBITDA | D16: EV / EBITDA | E16: EV | F16: $ / share | H16: Step | I16: $ / share | J16: Cumulative
B17: Aerospace Products | C17: =$C$12*'Operating Model'!E14+$C$13*'Operating Model'!F14 | D17: =F7 | E17: =C17*D17 | F17: =E17/DCF!$K$16 | H17: Bear-case outcomes (≈ today's $167) | I17: 161.2 | J17: =SUM($I$17:I17)
B18: FTAI Power | C18: =$C$12*'Operating Model'!E15+$C$13*'Operating Model'!F15 | D18: =F8 | E18: =C18*D18 | F18: =E18/DCF!$K$16 | H18: + Thesis I: margins (margin, PMA, pass-through, escalator, inventory) | I18: 22.3 | J18: =SUM($I$17:I18)
B19: Aviation Leasing + SCI | C19: =$C$12*'Operating Model'!E16+$C$13*'Operating Model'!F16 | D19: =F9 | E19: =C19*D19 | F19: =E19/DCF!$K$16 | H19: + Thesis II: share (retirements, SV rates, share, SCI fleet, leasing) | I19: 62.4 | J19: =SUM($I$17:I19)
B20: Corporate & eliminations (at blended multiple) | C20: =$C$12*'Operating Model'!E17+$C$13*'Operating Model'!F17 | D20: =SUM(E17:E19)/SUM(C17:C19) | E20: =C20*D20 | F20: =E20/DCF!$K$16 | H20: + Thesis III: Power (units, JV share, margin) | I20: 63.4 | J20: =SUM($I$17:I20)
B21: Enterprise value | C21: =SUM(C17:C20) | D21: =E21/C21 | E21: =SUM(E17:E20) | F21: =E21/DCF!$K$16 | H21: Base-case 1-year target | J21: =J20
B22: (–) Net debt (Sep-27E) | E22: =-($C$12*'Operating Model'!D79+$C$13*'Operating Model'!E79) | F22: =E22/DCF!$K$16 | H22: Method: starting from the Bear case, each thesis's Assumptions bear rows were set to base values in order (I → II → III) and the SOTP re-run at base multiples. Order-dependent; values pasted.
B23: (–) Preferred equity | E23: =DCF!K13 | F23: =E23/DCF!$K$16
B24: 1-year target (equity value / share) | E24: =SUM(E21:E23) | F24: =E24/DCF!$K$16
B25: Current price | F25: =DCF!K18
B26: Return | F26: =F24/F25-1
B28: Cross-checks (active case)
B29: EV / NTM EBITDA today (NTM ≈ ¼ FY26E + ¾ FY27E) | F29: =Cover!C21/($C$12*'Operating Model'!D18+$C$13*'Operating Model'!E18)
B30: EV / NTM EBITDA at target | F30: =D21
B31: Target ex-Power (Power multiple = 0) | F31: =((E17+E19)*(1+C20/SUM(C17:C19))+E22+E23)/DCF!$K$16
B32: Aerospace multiple implied by today's price | F32: =((F25*DCF!$K$16-E22-E23)/(1+C20/SUM(C17:C19))-E18-E19)/C17
B33: $ / share per 1x of Aerospace multiple | F33: =C17*(1+C20/SUM(C17:C19))/DCF!$K$16
B34: Blended DCF rolled forward 1 year (– dividends) | F34: =DCF!N29*(1+'WACC Calculation'!B19)-C35
B35: Dividends next 12 months ($ / share) | C35: 2
B37: Sensitivity: 1-year target, Aerospace × Power multiple (active case)
B38: Aero \ Power | C38: 6 | D38: 8 | E38: 10 | F38: 12
B39: 10 | C39: =(($B39*$C$17+C$38*$C$18+$D$19*$C$19)*(1+$C$20/SUM($C$17:$C$19))+$E$22+$E$23)/DCF!$K$16 | D39: =(($B39*$C$17+D$38*$C$18+$D$19*$C$19)*(1+$C$20/SUM($C$17:$C$19))+$E$22+$E$23)/DCF!$K$16 | E39: =(($B39*$C$17+E$38*$C$18+$D$19*$C$19)*(1+$C$20/SUM($C$17:$C$19))+$E$22+$E$23)/DCF!$K$16 | F39: =(($B39*$C$17+F$38*$C$18+$D$19*$C$19)*(1+$C$20/SUM($C$17:$C$19))+$E$22+$E$23)/DCF!$K$16
B40: 12 | C40: =(($B40*$C$17+C$38*$C$18+$D$19*$C$19)*(1+$C$20/SUM($C$17:$C$19))+$E$22+$E$23)/DCF!$K$16 | D40: =(($B40*$C$17+D$38*$C$18+$D$19*$C$19)*(1+$C$20/SUM($C$17:$C$19))+$E$22+$E$23)/DCF!$K$16 | E40: =(($B40*$C$17+E$38*$C$18+$D$19*$C$19)*(1+$C$20/SUM($C$17:$C$19))+$E$22+$E$23)/DCF!$K$16 | F40: =(($B40*$C$17+F$38*$C$18+$D$19*$C$19)*(1+$C$20/SUM($C$17:$C$19))+$E$22+$E$23)/DCF!$K$16
B41: 14 | C41: =(($B41*$C$17+C$38*$C$18+$D$19*$C$19)*(1+$C$20/SUM($C$17:$C$19))+$E$22+$E$23)/DCF!$K$16 | D41: =(($B41*$C$17+D$38*$C$18+$D$19*$C$19)*(1+$C$20/SUM($C$17:$C$19))+$E$22+$E$23)/DCF!$K$16 | E41: =(($B41*$C$17+E$38*$C$18+$D$19*$C$19)*(1+$C$20/SUM($C$17:$C$19))+$E$22+$E$23)/DCF!$K$16 | F41: =(($B41*$C$17+F$38*$C$18+$D$19*$C$19)*(1+$C$20/SUM($C$17:$C$19))+$E$22+$E$23)/DCF!$K$16
B42: 16 | C42: =(($B42*$C$17+C$38*$C$18+$D$19*$C$19)*(1+$C$20/SUM($C$17:$C$19))+$E$22+$E$23)/DCF!$K$16 | D42: =(($B42*$C$17+D$38*$C$18+$D$19*$C$19)*(1+$C$20/SUM($C$17:$C$19))+$E$22+$E$23)/DCF!$K$16 | E42: =(($B42*$C$17+E$38*$C$18+$D$19*$C$19)*(1+$C$20/SUM($C$17:$C$19))+$E$22+$E$23)/DCF!$K$16 | F42: =(($B42*$C$17+F$38*$C$18+$D$19*$C$19)*(1+$C$20/SUM($C$17:$C$19))+$E$22+$E$23)/DCF!$K$16

Sheet Diligence
B1: FTAI Aviation
B2: Diligence summary behind the Thesis II assumptions (search-based, Oct-26; counts are a floor)
B4: 1. CFM56 Outsourcing Flip Tracker – 14 tier-1 engine shops
B5: Shop type | C5: Reviewed | D5: Add LEAP | E5: Pull back CFM56 | F5: Win outside CFM56
B6: Airline-owned | C6: 8 | D6: 8 | E6: 1 | F6: 3
B7: OEM network | C7: 2 | D7: 2 | E7: 1 | F7: 2
B8: Independent | C8: 4 | D8: 4 | E8: 0 | F8: 4
B9: Total | C9: =SUM(C6:C8) | D9: =SUM(D6:D8) | E9: =SUM(E6:E8) | F9: =SUM(F6:F8)
B10: • OEMs: all new sites LEAP-only; CFM gives up Ryanair CFM56 labor from 2029 (keeps parts).
B11: • First airline flip: Lufthansa Group sends own CFM56 to FL Technics (Oct-26). EVA Air → MTU (May-26); United → FTAI CFM56-7B MRE (Oct-26).
B12: • Counter: Korean Air keeps CFM56, outsources LEAP; independents also add CFM56 (overflow is real but contested).
B14: 2. Test Cell Tracker – 18 engine test cells
B15: Category | C15: Cells
B16: Existing cells adapted to test LEAP (incl. 1 likely) | C16: 9
B17: …still testing CFM56, where disclosed | C17: 4 of 4
B18: …dropped CFM56 | C18: 0
B19: New cells built for LEAP | C19: 7
B20: New cell built first for CFM56 (Willis Lease + GEM) | C20: 1
B21: Unknown (LHT Hamburg, StandardAero) | C21: 2
B22: • 'Ongoing shortage of testing capacity' – Willis Lease; 'Europe-wide testing capacity constraints' – SR Technics. LEAP shares cells; no cell dropped CFM56.
B24: 3. Retirements, fuel and OEM capacity – evidence vs. model inputs
B25: Evidence | C25: Value | E25: Model input | F25: Model value | G25: Read-across
B26: GE 2026 CFM56 retirements (actual, Sep-26) | C26: 1.5–2.0% | E26: FY26 retirement -7B / -5B | F26: =TEXT(Assumptions!F10,"0.0%")&" / "&TEXT(Assumptions!F15,"0.0%") | G26: Consistent – base retained
B27: GE view of 2027 retirements | C27: ~3% | E27: FY27 retirement -7B / -5B | F27: =TEXT(Assumptions!K10,"0.0%")&" / "&TEXT(Assumptions!K15,"0.0%") | G27: Base ~2.2% blended is below GE's ~3%; GE has cut its view four times. Bear (2.5% / 4.0%) covers GE's number
B28: GE CFM56 shop visits 2026 / 2027 | C28: ~2,400 / ~2,400 | E28: Total shop visits FY26 / FY27 | F28: =TEXT(RPM!L26,"#,##0")&" / "&TEXT(RPM!Q26,"#,##0") | G28: Consistent – base retained
B29: Jet fuel peak (IATA, 3-Apr-26) / 15-Sep-26 | C29: $209 / $198 bbl | E29: Retirement rates | F29: No change | G29: Parked CFM56s down since March; 2022 analog shows no retirement spike
B30: FTAI 2026 module guide | C30: 1,200 | E30: FTAI modules FY26E | F30: =TEXT(RPM!L42,"#,##0") | G30: Consistent – base retained
B31: Mgmt share of CFM56 market (Q2'26) | C31: 14% | E31: 3rd-party share FY27E (base) | F31: =TEXT(Assumptions!K46,"0.0%") | G31: Tracker shows OEM / airline work moving to independents; base ramp retained, bull 25%
B32: GE LEAP internal shop visits (Q2'26) | C32: +50% y/y | E32: — | F32: — | G32: OEM growth capacity going to LEAP
B33: OEM share of LEAP vs. CFM56 shop visits | C33: ~85% vs. ~1/3 | E33: — | F33: — | G33: Two-thirds of CFM56 work already with independents
B35: Conclusion: the new diligence confirms the base-case Thesis II inputs; no driver changes were needed. Valuation updated to the 1-year framework on '1Y Valuation'.
B36: Sources: Flip Tracker and Test Cell Tracker workbooks (Oct-26); GE Aerospace (Q2'26, MS Laguna Sep-26, Reuters Jul-26); IATA / Platts; Safran H1'26; CFM; FTAI Q2'26.

Sheet Operating Model
B1: FTAI Aviation
B2: Operating Model & Cash Flow Build
B3: Amounts in $ millions, except share data
B4: Fiscal year ends December 31st
C6: FY25A | D6: FY26E | E6: FY27E | F6: FY28E | G6: FY29E | H6: FY30E | I6: FY31E
A7: x | B7: Operating Build
B8: Aerospace Products Revenue | C8: =RPM!G82 | D8: =RPM!L82 | E8: =RPM!Q82 | F8: =RPM!R82 | G8: =RPM!S82 | H8: =RPM!T82 | I8: =RPM!U82
B9: FTAI Power Revenue | C9: =RPM!G83 | D9: =RPM!L83 | E9: =RPM!Q83 | F9: =RPM!R83 | G9: =RPM!S83 | H9: =RPM!T83 | I9: =RPM!U83
B10: Aviation Leasing + SCI Revenue | C10: =RPM!G84 | D10: =RPM!L84 | E10: =RPM!Q84 | F10: =RPM!R84 | G10: =RPM!S84 | H10: =RPM!T84 | I10: =RPM!U84
B11: Total Revenue | C11: =SUM(C8:C10) | D11: =SUM(D8:D10) | E11: =SUM(E8:E10) | F11: =SUM(F8:F10) | G11: =SUM(G8:G10) | H11: =SUM(H8:H10) | I11: =SUM(I8:I10)
B12: YoY Growth | D12: =D11/C11-1 | E12: =E11/D11-1 | F12: =F11/E11-1 | G12: =G11/F11-1 | H12: =H11/G11-1 | I12: =I11/H11-1
B14: Aerospace Products Adj. EBITDA | C14: =RPM!G89 | D14: =RPM!L89 | E14: =RPM!Q89 | F14: =RPM!R89 | G14: =RPM!S89 | H14: =RPM!T89 | I14: =RPM!U89
B15: FTAI Power Adj. EBITDA | C15: =RPM!G90 | D15: =RPM!L90 | E15: =RPM!Q90 | F15: =RPM!R90 | G15: =RPM!S90 | H15: =RPM!T90 | I15: =RPM!U90
B16: Aviation Leasing + SCI Adj. EBITDA | C16: =RPM!G91 | D16: =RPM!L91 | E16: =RPM!Q91 | F16: =RPM!R91 | G16: =RPM!S91 | H16: =RPM!T91 | I16: =RPM!U91
B17: Corporate & Eliminations | C17: =RPM!G92 | D17: =RPM!L92 | E17: =RPM!Q92 | F17: =RPM!R92 | G17: =RPM!S92 | H17: =RPM!T92 | I17: =RPM!U92
B18: Total Adj. EBITDA | C18: =SUM(C14:C17) | D18: =SUM(D14:D17) | E18: =SUM(E14:E17) | F18: =SUM(F14:F17) | G18: =SUM(G14:G17) | H18: =SUM(H14:H17) | I18: =SUM(I14:I17)
B19: Adj. EBITDA Margin | C19: =IFERROR(C18/C11,0) | D19: =IFERROR(D18/D11,0) | E19: =IFERROR(E18/E11,0) | F19: =IFERROR(F18/F11,0) | G19: =IFERROR(G18/G11,0) | H19: =IFERROR(H18/H11,0) | I19: =IFERROR(I18/I11,0)
B20: (-) Non-cash Adj. EBITDA Items (SCI share, elims, other) | C20: -230.7 | D20: =-D18*Assumptions!F140 | E20: =-E18*Assumptions!K140 | F20: =-F18*Assumptions!L140 | G20: =-G18*Assumptions!M140 | H20: =-H18*Assumptions!N140 | I20: =-I18*Assumptions!O140
B21: (-) D&A | C21: =-C40 | D21: =-D40 | E21: =-E40 | F21: =-F40 | G21: =-G40 | H21: =-H40 | I21: =-I40
B22: (-) SBC | C22: =-C45 | D22: =-D45 | E22: =-E45 | F22: =-F45 | G22: =-G45 | H22: =-H45 | I22: =-I45
B23: EBIT | C23: =C18+C20+C21+C22 | D23: =D18+D20+D21+D22 | E23: =E18+E20+E21+E22 | F23: =F18+F20+F21+F22 | G23: =G18+G20+G21+G22 | H23: =H18+H20+H21+H22 | I23: =I18+I20+I21+I22
B24: EBIT Margin | C24: =IFERROR(C23/C11,0) | D24: =IFERROR(D23/D11,0) | E24: =IFERROR(E23/E11,0) | F24: =IFERROR(F23/F11,0) | G24: =IFERROR(G23/G11,0) | H24: =IFERROR(H23/H11,0) | I24: =IFERROR(I23/I11,0)
B26: Taxes | D26: =MAX(0,D23)*D27 | E26: =MAX(0,E23)*E27 | F26: =MAX(0,F23)*F27 | G26: =MAX(0,G23)*G27 | H26: =MAX(0,H23)*H27 | I26: =MAX(0,I23)*I27
B27: Tax Rate | D27: =Assumptions!F119 | E27: =Assumptions!K119 | F27: =Assumptions!L119 | G27: =Assumptions!M119 | H27: =Assumptions!N119 | I27: =Assumptions!O119
B29: NOPAT | D29: =D23-D26 | E29: =E23-E26 | F29: =F23-F26 | G29: =G23-G26 | H29: =H23-H26 | I29: =I23-I26
B31: Cash Flow Reconciliation
A32: x | B32: Leasing Equipment & PP&E Schedule
B33: Beginning Leasing Equipment & PP&E | D33: =C39 | E33: =D39 | F33: =E39 | G33: =F39 | H33: =G39 | I33: =H39
B34: (+) Acquisition of Leasing Equipment | C34: 658.8 | D34: =Assumptions!F111 | E34: =Assumptions!K111 | F34: =Assumptions!L111 | G34: =Assumptions!M111 | H34: =Assumptions!N111 | I34: =Assumptions!O111
B35: (+) PP&E CapEx | C35: 27.712 | D35: =D36*D11+D9*Assumptions!F115 | E35: =E36*E11+E9*Assumptions!K115 | F35: =F36*F11+F9*Assumptions!L115 | G35: =G36*G11+G9*Assumptions!M115 | H35: =H36*H11+H9*Assumptions!N115 | I35: =I36*I11+I9*Assumptions!O115
B36: % of Sales | C36: =C35/C11 | D36: =Assumptions!F109 | E36: =Assumptions!K109 | F36: =Assumptions!L109 | G36: =Assumptions!M109 | H36: =Assumptions!N109 | I36: =Assumptions!O109
B37: (-) Sale of Leasing Equipment (at book) | C37: -1712.5 | D37: =-Assumptions!F113 | E37: =-Assumptions!K113 | F37: =-Assumptions!L113 | G37: =-Assumptions!M113 | H37: =-Assumptions!N113 | I37: =-Assumptions!O113
B38: (-) Depreciation & Amortization | C38: -225.797 | D38: =-Assumptions!F107 | E38: =-Assumptions!K107 | F38: =-Assumptions!L107 | G38: =-Assumptions!M107 | H38: =-Assumptions!N107 | I38: =-Assumptions!O107
B39: Ending Leasing Equipment & PP&E | C39: 1665.872 | D39: =D33+D34+D35+D37+D38 | E39: =E33+E34+E35+E37+E38 | F39: =F33+F34+F35+F37+F38 | G39: =G33+G34+G35+G37+G38 | H39: =H33+H34+H35+H37+H38 | I39: =I33+I34+I35+I37+I38
B40: Total D&A | C40: =-C38 | D40: =-D38 | E40: =-E38 | F40: =-F38 | G40: =-G38 | H40: =-H38 | I40: =-I38
B41: Total CapEx | C41: =C34+C35 | D41: =D34+D35 | E41: =E34+E35 | F41: =F34+F35 | G41: =G34+G35 | H41: =H34+H35 | I41: =I34+I35
B43: Non-Cash Adjustments
B44: (+) D&A | C44: =C40 | D44: =D40 | E44: =E40 | F44: =F40 | G44: =G40 | H44: =H40 | I44: =I40
B45: (+) SBC | C45: 21.733 | D45: =D46*D11 | E45: =E46*E11 | F45: =F46*F11 | G45: =G46*G11 | H45: =H46*H11 | I45: =I46*I11
B46: % of Sales | C46: =C45/C11 | D46: =Assumptions!F117 | E46: =Assumptions!K117 | F46: =Assumptions!L117 | G46: =Assumptions!M117 | H46: =Assumptions!N117 | I46: =Assumptions!O117
B47: Total Adjustments | C47: =C44+C45 | D47: =D44+D45 | E47: =E44+E45 | F47: =F44+F45 | G47: =G44+G45 | H47: =H44+H45 | I47: =I44+I45
A49: x | B49: Working Capital Schedule
B50: Accounts Receivable | C50: 209.907 | D50: =D51*D11 | E50: =E51*E11 | F50: =F51*F11 | G50: =G51*G11 | H50: =H51*H11 | I50: =I51*I11
B51: % of Sales | C51: =C50/C11 | D51: =Assumptions!F126 | E51: =Assumptions!K126 | F51: =Assumptions!L126 | G51: =Assumptions!M126 | H51: =Assumptions!N126 | I51: =Assumptions!O126
B52: Inventory | C52: 1193.773 | D52: =D53*D8 | E52: =E53*E8 | F52: =F53*F8 | G52: =G53*G8 | H52: =H53*H8 | I52: =I53*I8
B53: % of Aerospace Products Revenue | C53: =C52/C8 | D53: =Assumptions!F121 | E53: =Assumptions!K121 | F53: =Assumptions!L121 | G53: =Assumptions!M121 | H53: =Assumptions!N121 | I53: =Assumptions!O121
B54: Other Operating Assets, net | C54: 383.8 | D54: =D55*D11 | E54: =E55*E11 | F54: =F55*F11 | G54: =G55*G11 | H54: =H55*H11 | I54: =I55*I11
B55: % of Sales | C55: =C54/C11 | D55: =Assumptions!F130 | E55: =Assumptions!K130 | F55: =Assumptions!L130 | G55: =Assumptions!M130 | H55: =Assumptions!N130 | I55: =Assumptions!O130
B56: AP & Accrued Liabilities | C56: 298.233 | D56: =D57*D11 | E56: =E57*E11 | F56: =F57*F11 | G56: =G57*G11 | H56: =H57*H11 | I56: =I57*I11
B57: % of Sales | C57: =C56/C11 | D57: =Assumptions!F128 | E57: =Assumptions!K128 | F57: =Assumptions!L128 | G57: =Assumptions!M128 | H57: =Assumptions!N128 | I57: =Assumptions!O128
B58: Net Working Capital | C58: =C50+C52+C54-C56 | D58: =D50+D52+D54-D56 | E58: =E50+E52+E54-E56 | F58: =F50+F52+F54-F56 | G58: =G50+G52+G54-G56 | H58: =H50+H52+H54-H56 | I58: =I50+I52+I54-I56
B59: Change in NWC | D59: =D58-C58 | E59: =E58-D58 | F59: =F58-E58 | G59: =G58-F58 | H59: =H58-G58 | I59: =I58-H58
A61: x | B61: Unlevered Free Cash Flow
B62: NOPAT | D62: =D29 | E62: =E29 | F62: =F29 | G62: =G29 | H62: =H29 | I62: =I29
B63: (+) Total Non-Cash Adjustments | D63: =D47 | E63: =E47 | F63: =F47 | G63: =G47 | H63: =H47 | I63: =I47
B64: (-) Change in Net Working Capital | D64: =-D59 | E64: =-E59 | F64: =-F59 | G64: =-G59 | H64: =-H59 | I64: =-I59
B65: (-) Capital Expenditures | D65: =-D41 | E65: =-E41 | F65: =-F41 | G65: =-G41 | H65: =-H41 | I65: =-I41
B66: (+) Proceeds from Sale of Leasing Equipment | D66: =-D37 | E66: =-E37 | F66: =-F37 | G66: =-G37 | H66: =-H37 | I66: =-I37
B67: (-) Investment in SCI / Unconsolidated Entities | C67: -301.4 | D67: =-Assumptions!F132*Assumptions!F32/Assumptions!F34 | E67: =-Assumptions!K132*Assumptions!K32/Assumptions!K34 | F67: =-Assumptions!L132*Assumptions!L32/Assumptions!L34 | G67: =-Assumptions!M132*Assumptions!M32/Assumptions!M34 | H67: =-Assumptions!N132*Assumptions!N32/Assumptions!N34 | I67: =-Assumptions!O132*Assumptions!O32/Assumptions!O34
B68: (+) SCI Distributions to FTAI | D68: =Assumptions!F142*Assumptions!F32/Assumptions!F34 | E68: =Assumptions!K142*Assumptions!K32/Assumptions!K34 | F68: =Assumptions!L142*Assumptions!L32/Assumptions!L34 | G68: =Assumptions!M142*Assumptions!M32/Assumptions!M34 | H68: =Assumptions!N142*Assumptions!N32/Assumptions!N34 | I68: =Assumptions!O142*Assumptions!O32/Assumptions!O34
B69: UFCF | D69: =SUM(D62:D68) | E69: =SUM(E62:E68) | F69: =SUM(F62:F68) | G69: =SUM(G62:G68) | H69: =SUM(H62:H68) | I69: =SUM(I62:I68)
B70: UFCF Conversion (% of Adj. EBITDA) | D70: =IFERROR(D69/D18,0) | E70: =IFERROR(E69/E18,0) | F70: =IFERROR(F69/F18,0) | G70: =IFERROR(G69/G18,0) | H70: =IFERROR(H69/H18,0) | I70: =IFERROR(I69/I18,0)
A71: x | B71: Levered Cash Flow & Net Debt
B72: UFCF | D72: =D69 | E72: =E69 | F72: =F69 | G72: =G69 | H72: =H69 | I72: =I69
B73: (-) After-tax Interest Expense | D73: =-Assumptions!F134*(1-D27) | E73: =-Assumptions!K134*(1-E27) | F73: =-Assumptions!L134*(1-F27) | G73: =-Assumptions!M134*(1-G27) | H73: =-Assumptions!N134*(1-H27) | I73: =-Assumptions!O134*(1-I27)
B74: (-) Common Dividends | D74: =-Assumptions!F136 | E74: =-Assumptions!K136 | F74: =-Assumptions!L136 | G74: =-Assumptions!M136 | H74: =-Assumptions!N136 | I74: =-Assumptions!O136
B75: (-) Preferred Dividends | D75: =-Assumptions!F138 | E75: =-Assumptions!K138 | F75: =-Assumptions!L138 | G75: =-Assumptions!M138 | H75: =-Assumptions!N138 | I75: =-Assumptions!O138
B76: Change in Cash | D76: =SUM(D72:D75) | E76: =SUM(E72:E75) | F76: =SUM(F72:F75) | G76: =SUM(G72:G75) | H76: =SUM(H72:H75) | I76: =SUM(I72:I75)
B77: Cash & Equivalents (EoP) | C77: 300.476 | D77: =C77+D76 | E77: =D77+E76 | F77: =E77+F76 | G77: =F77+G76 | H77: =G77+H76 | I77: =H77+I76
B78: Total Debt (EoP) | C78: 3448.891 | D78: =C78 | E78: =D78 | F78: =E78 | G78: =F78 | H78: =G78 | I78: =H78
B79: Net Debt | C79: =C78-C77 | D79: =D78-D77 | E79: =E78-E77 | F79: =F78-F77 | G79: =G78-G77 | H79: =H78-H77 | I79: =I78-I77
B80: Net Debt / Adj. EBITDA | C80: =IFERROR(C79/C18,0) | D80: =IFERROR(D79/D18,0) | E80: =IFERROR(E79/E18,0) | F80: =IFERROR(F79/F18,0) | G80: =IFERROR(G79/G18,0) | H80: =IFERROR(H79/H18,0) | I80: =IFERROR(I79/I18,0)
A82: x | B82: Jefferies Comparison (8/2/26)
B83: Jefferies Total Revenue | D83: 3907.6 | E83: 6126.6 | F83: 8415.6
B84: Model vs. Jefferies | D84: =D11-D83 | E84: =E11-E83 | F84: =F11-F83
B85: Jefferies Total Adj. EBITDA | D85: 1289.3 | E85: 2098.5 | F85: 3022.6
B86: Model vs. Jefferies | D86: =D18-D85 | E86: =E18-E85 | F86: =F18-F85
B87: Jefferies D&A | D87: 196.2 | E87: 191 | F87: 180.2
B88: Model vs. Jefferies | D88: =D40-D87 | E88: =E40-E87 | F88: =F40-F87
B89: Jefferies Total CapEx (Leasing + PP&E) | D89: 229.5 | E89: 155.3 | F89: 171
B90: Model vs. Jefferies | D90: =D41-D89 | E90: =E41-E89 | F90: =F41-F89
B91: Jefferies Change in Working Capital (cash) | D91: -386.3 | E91: -256.4 | F91: -157
B92: Model vs. Jefferies | D92: =-D59-D91 | E92: =-E59-E91 | F92: =-F59-F91
B93: Jefferies Inventory | D93: 1484.9 | E93: 1654.2 | F93: 1767.3
B94: Model vs. Jefferies | D94: =D52-D93 | E94: =E52-E93 | F94: =F52-F93
B95: Jefferies AP & Accrued Liabilities | D95: 351.7 | E95: 398.2 | F95: 462.9
B96: Model vs. Jefferies | D96: =D56-D95 | E96: =E56-E95 | F96: =F56-F95
B97: Jefferies Cash & Equivalents (EoP) | D97: 291 | E97: 859.9 | F97: 1933
B98: Model vs. Jefferies | D98: =D77-D97 | E98: =E77-E97 | F98: =F77-F97
B99: Jefferies UFCF (CFO + CFI + after-tax interest) | D99: 403.1 | E99: 978 | F99: 1503.8
B100: Model vs. Jefferies | D100: =D69-D99 | E100: =E69-E99 | F100: =F69-F99

Sheet WACC Calculation
A1: WACC Calculation
A3: Total Market Capitalization ($mm) | B3: =DCF!K18*DCF!K16
A4: Total Debt ($mm) | B4: =-DCF!K12
A6: Weight of Equity | B6: =B3/(B3+B4)
A7: Weight of Debt | B7: =B4/(B3+B4)
A8: Total Weight | B8: =B6+B7
A10: Pretax Cost of Debt | B10: 0.072
A11: Tax Rate | B11: =Assumptions!F119
A12: After-tax Cost of Debt | B12: =B10*(1-B11)
A14: Risk Free Rate | B14: 0.042
A15: Market Risk Premium | B15: 0.045
A16: Return on Market | B16: =B14+B15
A17: Raw Beta (5Y monthly) | B17: 1.51
A18: Adjusted Beta (Bloomberg: 0.67 x raw + 0.33) | B18: =0.67*B17+0.33
A19: Cost of Equity | B19: =B14+B18*B15
A20: WACC | B20: =B19*B6+B12*B7 | D20: CAPM with Bloomberg-adjusted beta; blue inputs - refresh from Bloomberg

Sheet RPM
B1: FTAI Aviation
B2: Revenue Build
B3: (in million $)
C5: Q1-25 | D5: Q2-25 | E5: Q3-25 | F5: Q4-25 | G5: FY25 | H5: Q1-26 | I5: Q2-26 | J5: Q3-26 | K5: Q4-26 | L5: FY26 | M5: Q1-27 | N5: Q2-27 | O5: Q3-27 | P5: Q4-27 | Q5: FY27 | R5: FY28 | S5: FY29 | T5: FY30 | U5: FY31
B6: Aerospace Products
A8: x | B8: CFM56 Fleet & Shop Demand
B9: CFM56-7B (737MG)
B10: BoP Engine Fleet | C10: 13984 | D10: 13940 | E10: 13896 | F10: 13853 | G10: 13984 | H10: 13809 | I10: 13810 | J10: =I13 | K10: =J13 | L10: =H10 | M10: =K13 | N10: =M13 | O10: =N13 | P10: =O13 | Q10: =M10 | R10: =P13 | S10: =R13 | T10: =S13 | U10: =T13
B11: Retirement Rate | C11: 0.0031 | D11: 0.0031 | E11: 0.0031 | F11: 0.0031 | G11: 0.0125 | H11: 0.0038 | I11: 0.0038 | J11: =Assumptions!D8 | K11: =Assumptions!E8 | L11: =IFERROR(L12/L10,0) | M11: =Assumptions!G8 | N11: =Assumptions!H8 | O11: =Assumptions!I8 | P11: =Assumptions!J8 | Q11: =IFERROR(Q12/Q10,0) | R11: =Assumptions!L8 | S11: =Assumptions!M8 | T11: =Assumptions!N8 | U11: =Assumptions!O8
B12: Retired Engines | C12: 44 | D12: 44 | E12: 44 | F12: 43 | G12: 175 | H12: 52 | I12: 52 | J12: =J10*J11 | K12: =K10*K11 | L12: =SUM(H12:K12) | M12: =M10*M11 | N12: =N10*N11 | O12: =O10*O11 | P12: =P10*P11 | Q12: =SUM(M12:P12) | R12: =R10*R11 | S12: =S10*S11 | T12: =T10*T11 | U12: =U10*U11
B13: EoP Engine Fleet | C13: 13940 | D13: 13896 | E13: 13853 | F13: 13809 | G13: 13809 | H13: 13757 | I13: 13758 | J13: =J10-J12 | K13: =K10-K12 | L13: =K13 | M13: =M10-M12 | N13: =N10-N12 | O13: =O10-O12 | P13: =P10-P12 | Q13: =P13 | R13: =R10-R12 | S13: =S10-S12 | T13: =T10-T12 | U13: =U10-U12
B14: Shop Visit Rate | C14: 0.0261 | D14: 0.0262 | E14: 0.0263 | F14: 0.0264 | G14: 0.1055 | H14: 0.027 | I14: 0.027 | J14: =Assumptions!D18 | K14: =Assumptions!E18 | L14: =SUM(H14:K14) | M14: =Assumptions!G18 | N14: =Assumptions!H18 | O14: =Assumptions!I18 | P14: =Assumptions!J18 | Q14: =SUM(M14:P14) | R14: =Assumptions!L18 | S14: =Assumptions!M18 | T14: =Assumptions!N18 | U14: =Assumptions!O18
B15: Shop Visits | C15: 364 | D15: 364 | E15: 364 | F15: 364 | G15: 1457 | H15: 372 | I15: 372 | J15: =J14*J13 | K15: =K14*K13 | L15: =SUM(H15:K15) | M15: =M14*M13 | N15: =N14*N13 | O15: =O14*O13 | P15: =P14*P13 | Q15: =SUM(M15:P15) | R15: =R14*R13 | S15: =S14*S13 | T15: =T14*T13 | U15: =U14*U13
B17: CFM56-5B (A320ceo)
B18: BoP Engine Fleet | C18: 9016 | D18: 8988 | E18: 8959 | F18: 8931 | G18: 9016 | H18: 8903 | I18: 8893 | J18: =I21 | K18: =J21 | L18: =H18 | M18: =K21 | N18: =M21 | O18: =N21 | P18: =O21 | Q18: =M18 | R18: =P21 | S18: =R21 | T18: =S21 | U18: =T21
B19: Retirement Rate | C19: 0.0031 | D19: 0.0031 | E19: 0.0031 | F19: 0.0031 | G19: 0.0125 | H19: 0.005 | I19: 0.005 | J19: =Assumptions!D13 | K19: =Assumptions!E13 | L19: =IFERROR(L20/L18,0) | M19: =Assumptions!G13 | N19: =Assumptions!H13 | O19: =Assumptions!I13 | P19: =Assumptions!J13 | Q19: =IFERROR(Q20/Q18,0) | R19: =Assumptions!L13 | S19: =Assumptions!M13 | T19: =Assumptions!N13 | U19: =Assumptions!O13
B20: Retired Engines | C20: 28 | D20: 28 | E20: 28 | F20: 28 | G20: 113 | H20: 45 | I20: 45 | J20: =J19*J18 | K20: =K19*K18 | L20: =SUM(H20:K20) | M20: =M19*M18 | N20: =N19*N18 | O20: =O19*O18 | P20: =P19*P18 | Q20: =SUM(M20:P20) | R20: =R19*R18 | S20: =S19*S18 | T20: =T19*T18 | U20: =U19*U18
B21: EoP Engine Fleet | C21: 8988 | D21: 8959 | E21: 8931 | F21: 8903 | G21: 8903 | H21: 8858 | I21: 8848 | J21: =J18-J20 | K21: =K18-K20 | L21: =K21 | M21: =M18-M20 | N21: =N18-N20 | O21: =O18-O20 | P21: =P18-P20 | Q21: =P21 | R21: =R18-R20 | S21: =S18-S20 | T21: =T18-T20 | U21: =U18-U20
B22: Shop Visit Rate | C22: 0.0248 | D22: 0.0249 | E22: 0.025 | F22: 0.0251 | G22: 0.1003 | H22: 0.0257 | I22: 0.0258 | J22: =Assumptions!D23 | K22: =Assumptions!E23 | L22: =SUM(H22:K22) | M22: =Assumptions!G23 | N22: =Assumptions!H23 | O22: =Assumptions!I23 | P22: =Assumptions!J23 | Q22: =SUM(M22:P22) | R22: =Assumptions!L23 | S22: =Assumptions!M23 | T22: =Assumptions!N23 | U22: =Assumptions!O23
B23: Shop Visits | C23: 223 | D23: 223 | E23: 223 | F23: 223 | G23: 893 | H23: 228 | I23: 228 | J23: =J21*J22 | K23: =K21*K22 | L23: =SUM(H23:K23) | M23: =M21*M22 | N23: =N21*N22 | O23: =O21*O22 | P23: =P21*P22 | Q23: =SUM(M23:P23) | R23: =R21*R22 | S23: =S21*S22 | T23: =T21*T22 | U23: =U21*U22
B25: Total EoP CFM56 Fleet | C25: 22928 | D25: 22856 | E25: 22784 | F25: 22713 | G25: 22713 | H25: 22616 | I25: 22606 | J25: =J13+J21 | K25: =K13+K21 | L25: =L13+L21 | M25: =M13+M21 | N25: =N13+N21 | O25: =O13+O21 | P25: =P13+P21 | Q25: =Q13+Q21 | ... U25: =U13+U21
B26: Total Shop Visits | C26: 588 | D26: 588 | E26: 588 | F26: 588 | G26: 2350 | H26: 600 | I26: 600 | J26: =J23+J15 | K26: =K23+K15 | L26: =SUM(H26:K26) | M26: =M23+M15 | N26: =N23+N15 | O26: =O23+O15 | P26: =P23+P15 | Q26: =SUM(M26:P26) | R26: =R23+R15 | S26: =S23+S15 | T26: =T23+T15 | U26: =U23+U15
B27: Modules per Shop Visit | C27: 3 | D27: 3 | E27: 3 | F27: 3 | G27: 3 | H27: 3 | I27: 3 | J27: =Assumptions!D28 | K27: =Assumptions!E28 | L27: =IFERROR(L28/L26,0) | M27: =Assumptions!G28 | N27: =Assumptions!H28 | O27: =Assumptions!I28 | P27: =Assumptions!J28 | Q27: =IFERROR(Q28/Q26,0) | R27: =Assumptions!L28 | S27: =Assumptions!M28 | T27: =Assumptions!N28 | U27: =Assumptions!O28
B28: Total Module Demand | C28: 1763 | D28: 1763 | E28: 1763 | F28: 1763 | G28: 7050 | H28: 1800 | I28: 1800 | J28: =J26*J27 | K28: =K26*K27 | L28: =SUM(H28:K28) | M28: =M26*M27 | N28: =N26*N27 | O28: =O26*O27 | P28: =P26*P27 | Q28: =SUM(M28:P28) | R28: =R26*R27 | S28: =S26*S27 | T28: =T26*T27 | U28: =U26*U27
A30: x | B30: SCI MRE Share
B31: SCI Owned Aircraft (EoP) | C31: 4 | D31: 37 | E31: 101 | F31: 130 | G31: 130 | H31: 200 | I31: 276 | J31: =Assumptions!D32 | K31: =Assumptions!E32 | L31: =K31 | M31: =Assumptions!G32 | N31: =Assumptions!H32 | O31: =Assumptions!I32 | P31: =Assumptions!J32 | Q31: =P31 | R31: =Assumptions!L32 | S31: =Assumptions!M32 | T31: =Assumptions!N32 | U31: =Assumptions!O32
B32: Engines per Aircraft | C32: 2 | D32: 2 | E32: 2 | F32: 2 | G32: 2 | H32: 2 | I32: 2 | J32: =Assumptions!D37 | K32: =Assumptions!E37 | L32: =Assumptions!F37 | M32: =Assumptions!G37 | N32: =Assumptions!H37 | O32: =Assumptions!I37 | P32: =Assumptions!J37 | Q32: =Assumptions!K37 | ... U32: =Assumptions!O37
B33: SCI Shop Visit Rate | C33: 0.05 | D33: 0.05 | E33: 0.05 | F33: 0.05 | G33: 0.2 | H33: 0.05 | I33: 0.05 | J33: =Assumptions!D39 | K33: =Assumptions!E39 | L33: =Assumptions!F39 | M33: =Assumptions!G39 | N33: =Assumptions!H39 | O33: =Assumptions!I39 | P33: =Assumptions!J39 | Q33: =Assumptions!K39 | ... U33: =Assumptions!O39
B34: SCI Shop Visits | C34: 0 | D34: 4 | E34: 10 | F34: 13 | G34: 27 | H34: 20 | I34: 28 | J34: =J31*J32*J33 | K34: =K31*K32*K33 | L34: =SUM(H34:K34) | M34: =M31*M32*M33 | N34: =N31*N32*N33 | O34: =O31*O32*O33 | P34: =P31*P32*P33 | Q34: =SUM(M34:P34) | R34: =R31*R32*R33 | S34: =S31*S32*S33 | T34: =T31*T32*T33 | U34: =U31*U32*U33
B35: SCI Module Demand | C35: 1 | D35: 11 | E35: 30 | F35: 39 | G35: 82 | H35: 60 | I35: 83 | J35: =J34*J27 | K35: =K34*K27 | L35: =SUM(H35:K35) | M35: =M34*M27 | N35: =N34*N27 | O35: =O34*O27 | P35: =P34*P27 | Q35: =SUM(M35:P35) | R35: =R34*R27 | S35: =S34*S27 | T35: =T34*T27 | U35: =U34*U27
A37: x | B37: MRO Demand
B38: Module Demand | J38: =J28 | K38: =K28 | L38: =L28 | M38: =M28 | N38: =N28 | O38: =O28 | P38: =P28 | Q38: =Q28 | ... U38: =U28
B39: FTAI Share of Module Demand | J39: =Assumptions!D44 | K39: =Assumptions!E44 | L39: =Assumptions!F44 | M39: =Assumptions!G44 | N39: =Assumptions!H44 | O39: =Assumptions!I44 | P39: =Assumptions!J44 | Q39: =Assumptions!K44 | ... U39: =Assumptions!O44
B40: MRO Modules | J40: =J38*J39 | K40: =K38*K39 | L40: =L38*L39 | M40: =M38*M39 | N40: =N38*N39 | O40: =O38*O39 | P40: =P38*P39 | Q40: =Q38*Q39 | ... U40: =U38*U39
B42: FTAI Modules Produced | C42: 138 | D42: 184 | E42: 207 | F42: 228 | G42: =SUM(C42:F42) | H42: 270 | I42: 296 | J42: =J40+J35 | K42: =K40+K35 | L42: =SUM(H42:K42) | M42: =M40+M35 | N42: =N40+N35 | O42: =O40+O35 | P42: =P40+P35 | Q42: =SUM(M42:P42) | R42: =R40+R35 | S42: =S40+S35 | T42: =T40+T35 | U42: =U40+U35
B43: y/y growth | H43: =H42/C42-1 | I43: =I42/D42-1 | J43: =J42/E42-1 | K43: =K42/F42-1 | L43: =L42/G42-1 | M43: =M42/H42-1 | N43: =N42/I42-1 | O43: =O42/J42-1 | ... Q43: =Q42/L42-1 | R43: =R42/Q42-1 | S43: =S42/R42-1 | T43: =T42/S42-1 | U43: =U42/T42-1
A45: x | B45: Aerospace Products Revenue
B46: CFM Annual Escalator | J46: =Assumptions!D49 | K46: =Assumptions!E49 | L46: =Assumptions!F49 | M46: =Assumptions!G49 | N46: =Assumptions!H49 | O46: =Assumptions!I49 | P46: =Assumptions!J49 | Q46: =Assumptions!K49 | ... U46: =Assumptions!O49
B47: FTAI Pass-Through (% of OEM escalator) | J47: =Assumptions!D54 | K47: =Assumptions!E54 | M47: =Assumptions!G54 | N47: =Assumptions!H54 | O47: =Assumptions!I54 | P47: =Assumptions!J54 | R47: =Assumptions!L54 | S47: =Assumptions!M54 | T47: =Assumptions!N54 | U47: =Assumptions!O54
B48: Revenue per Module Growth | J48: =J46*J47 | K48: =K46*K47 | M48: =M46*M47 | N48: =N46*N47 | O48: =O46*O47 | P48: =P46*P47 | R48: =R46*R47 | S48: =S46*S47 | T48: =T46*T47 | U48: =U46*U47
B49: Revenue per Module ($mm) | C49: =C50/C42 | D49: =D50/D42 | E49: =E50/E42 | F49: =F50/F42 | G49: =G50/G42 | H49: =H50/H42 | I49: =I50/I42 | J49: =I49*(1+J48) | K49: =J49*(1+K48) | L49: =IFERROR(L50/L42,0) | M49: =K49*(1+M48) | N49: =M49*(1+N48) | O49: =N49*(1+O48) | P49: =O49*(1+P48) | Q49: =IFERROR(Q50/Q42,0) | R49: =Q49*(1+R48) | S49: =R49*(1+S48) | T49: =S49*(1+T48) | U49: =T49*(1+U48)
B50: Total Aerospace Revenue | C50: 365.1 | D50: 490.3 | E50: 517.9 | F50: 563 | G50: =SUM(C50:F50) | H50: 743.8 | I50: 875 | J50: =J49*J42 | K50: =K49*K42 | L50: =SUM(H50:K50) | M50: =M49*M42 | N50: =N49*N42 | O50: =O49*O42 | P50: =P49*P42 | Q50: =SUM(M50:P50) | R50: =R49*R42 | S50: =S49*S42 | T50: =T49*T42 | U50: =U49*U42
B51: y/y growth | H51: =H50/C50-1 | I51: =I50/D50-1 | J51: =J50/E50-1 | K51: =K50/F50-1 | L51: =L50/G50-1 | M51: =M50/H50-1 | N51: =N50/I50-1 | O51: =O50/J50-1 | ... Q51: =Q50/L50-1 | R51: =R50/Q50-1 | S51: =S50/R50-1 | T51: =T50/S50-1 | U51: =U50/T50-1
A53: x | B53: Profitability
B54: Adj. EBITDA Margin (%) | C54: =C55/C50 | D54: =D55/D50 | E54: =E55/E50 | F54: =F55/F50 | G54: =G55/G50 | H54: =H55/H50 | I54: =I55/I50 | J54: =Assumptions!D61 | K54: =Assumptions!E61 | L54: =IFERROR(L55/L50,0) | M54: =Assumptions!G61 | N54: =Assumptions!H61 | O54: =Assumptions!I61 | P54: =Assumptions!J61 | Q54: =IFERROR(Q55/Q50,0) | R54: =Assumptions!L61 | S54: =Assumptions!M61 | T54: =Assumptions!N61 | U54: =Assumptions!O61
B55: Adj. EBITDA | C55: =C60-C59 | D55: =D60-D59 | E55: =E60-E59 | F55: =F60-F59 | G55: =G60-G59 | H55: =H60-H59 | I55: =I60-I59 | J55: =J54*J50 | K55: =K54*K50 | L55: =L60-L59 | M55: =M54*M50 | N55: =N54*N50 | O55: =O54*O50 | P55: =P54*P50 | Q55: =Q60-Q59 | R55: =R54*R50 | S55: =S54*S50 | T55: =T54*T50 | U55: =U54*U50
B56: PMA Penetration | J56: =Assumptions!D66 | K56: =Assumptions!E66 | L56: =IFERROR(L57/L42,0) | M56: =Assumptions!G66 | N56: =Assumptions!H66 | O56: =Assumptions!I66 | P56: =Assumptions!J66 | Q56: =IFERROR(Q57/Q42,0) | R56: =Assumptions!L66 | S56: =Assumptions!M66 | T56: =Assumptions!N66 | U56: =Assumptions!O66
B57: PMA Modules | C57: 0 | D57: 0 | E57: 0 | F57: 0 | G57: 0 | H57: 0 | I57: 0 | J57: =J56*J42 | K57: =K56*K42 | L57: =SUM(H57:K57) | M57: =M56*M42 | N57: =N56*N42 | O57: =O56*O42 | P57: =P56*P42 | Q57: =SUM(M57:P57) | R57: =R56*R42 | S57: =S56*S42 | T57: =T56*T42 | U57: =U56*U42
B58: PMA EBITDA uplift per module ($mm) | J58: =Assumptions!D71 | K58: =Assumptions!E71 | L58: =Assumptions!F71 | M58: =Assumptions!G71 | N58: =Assumptions!H71 | O58: =Assumptions!I71 | P58: =Assumptions!J71 | Q58: =Assumptions!K71 | ... U58: =Assumptions!O71
B59: PMA EBITDA uplift | C59: =C58*C57 | D59: =D58*D57 | E59: =E58*E57 | F59: =F58*F57 | G59: =G58*G57 | H59: =H58*H57 | I59: =I58*I57 | J59: =J58*J57 | K59: =K58*K57 | L59: =SUM(H59:K59) | M59: =M58*M57 | N59: =N58*N57 | O59: =O58*O57 | P59: =P58*P57 | Q59: =SUM(M59:P59) | R59: =R58*R57 | S59: =S58*S57 | T59: =T58*T57 | U59: =U58*U57
B60: Aerospace Products adj. EBITDA | C60: 130.9 | D60: 164.9 | E60: 180.4 | F60: 195 | G60: =SUM(C60:F60) | H60: 222.6 | I60: 249.7 | J60: =J59+J55 | K60: =K59+K55 | L60: =SUM(H60:K60) | M60: =M59+M55 | N60: =N59+N55 | O60: =O59+O55 | P60: =P59+P55 | Q60: =SUM(M60:P60) | R60: =R59+R55 | S60: =S59+S55 | T60: =T59+T55 | U60: =U59+U55
B61: EBITDA margin (%) | J61: =J60/J50 | K61: =K60/K50 | L61: =L60/L50 | M61: =M60/M50 | N61: =N60/N50 | O61: =O60/O50 | P61: =P60/P50 | Q61: =Q60/Q50 | ... U61: =U60/U50
B62: y/y growth | H62: =H60/C60-1 | I62: =I60/D60-1 | J62: =J60/E60-1 | K62: =K60/F60-1 | L62: =L60/G60-1 | M62: =M60/H60-1 | N62: =N60/I60-1 | O62: =O60/J60-1 | ... Q62: =Q60/L60-1 | R62: =R60/Q60-1 | S62: =S60/R60-1 | T62: =T60/S60-1 | U62: =U60/T60-1
B63: EBITDA per Module ($mm) | C63: =IFERROR(C60/C42,0) | D63: =IFERROR(D60/D42,0) | E63: =IFERROR(E60/E42,0) | F63: =IFERROR(F60/F42,0) | G63: =IFERROR(G60/G42,0) | H63: =IFERROR(H60/H42,0) | I63: =IFERROR(I60/I42,0) | J63: =IFERROR(J60/J42,0) | ... U63: =IFERROR(U60/U42,0)
B65: FTAI Power
A67: x | B67: Mod-1 Build
B68: Units Delivered | C68: 0 | D68: 0 | E68: 0 | F68: 0 | G68: 0 | H68: 0 | I68: 0 | J68: =Assumptions!D75 | K68: =Assumptions!E75 | L68: =SUM(H68:K68) | M68: =Assumptions!G75 | N68: =Assumptions!H75 | O68: =Assumptions!I75 | P68: =Assumptions!J75 | Q68: =SUM(M68:P68) | R68: =Assumptions!L75 | S68: =Assumptions!M75 | T68: =Assumptions!N75 | U68: =Assumptions!O75
B69: MW per unit | J69: =Assumptions!D80 | K69: =Assumptions!E80 | L69: =Assumptions!F80 | M69: =Assumptions!G80 | N69: =Assumptions!H80 | O69: =Assumptions!I80 | P69: =Assumptions!J80 | Q69: =Assumptions!K80 | ... U69: =Assumptions!O80
B70: MW delivered | C70: =C69*C68 | D70: =D69*D68 | E70: =E69*E68 | F70: =F69*F68 | G70: =G69*G68 | H70: =H69*H68 | I70: =I69*I68 | J70: =J69*J68 | ... U70: =U69*U68
B71: $mm per MW | J71: =Assumptions!D82 | K71: =Assumptions!E82 | L71: =Assumptions!F82 | M71: =Assumptions!G82 | N71: =Assumptions!H82 | O71: =Assumptions!I82 | P71: =Assumptions!J82 | Q71: =Assumptions!K82 | ... U71: =Assumptions!O82
B72: FTAI capture of JV | J72: =Assumptions!D84 | K72: =Assumptions!E84 | L72: =Assumptions!F84 | M72: =Assumptions!G84 | N72: =Assumptions!H84 | O72: =Assumptions!I84 | P72: =Assumptions!J84 | Q72: =Assumptions!K84 | ... U72: =Assumptions!O84
B73: FTAI Power Revenue | C73: =C72*C70*C71 | D73: =D72*D70*D71 | E73: =E72*E70*E71 | F73: =F72*F70*F71 | G73: =G72*G70*G71 | H73: =H72*H70*H71 | I73: =I72*I70*I71 | J73: =J72*J70*J71 | ... U73: =U72*U70*U71
B74: EBITDA margin (%) | J74: =Assumptions!D89 | K74: =Assumptions!E89 | L74: =Assumptions!F89 | M74: =Assumptions!G89 | N74: =Assumptions!H89 | O74: =Assumptions!I89 | P74: =Assumptions!J89 | Q74: =Assumptions!K89 | ... U74: =Assumptions!O89
B75: FTAI Adj. EBITDA | C75: =C73*C74 | D75: =D73*D74 | E75: =E73*E74 | F75: =F73*F74 | G75: =G73*G74 | H75: =H73*H74 | I75: =I73*I74 | J75: =J73*J74 | ... U75: =U73*U74
A77: x | B77: Aviation Leasing + SCI
B78: Aviation Leasing Revenue | C78: 137 | D78: 186 | E78: 149.2 | F78: 99 | G78: =SUM(C78:F78) | H78: 86.9 | I78: 78.1 | J78: =Assumptions!D96 | K78: =Assumptions!E96 | L78: =SUM(H78:K78) | M78: =Assumptions!G96 | N78: =Assumptions!H96 | O78: =Assumptions!I96 | P78: =Assumptions!J96 | Q78: =SUM(M78:P78) | R78: =Assumptions!L96 | S78: =Assumptions!M96 | T78: =Assumptions!N96 | U78: =Assumptions!O96
B79: Aviation Leasing + SCI EBITDA | C79: 162 | D79: 199.3 | E79: 134.4 | F79: 113.2 | G79: =SUM(C79:F79) | H79: 153 | I79: 88.2 | J79: =Assumptions!D98 | K79: =Assumptions!E98 | L79: =SUM(H79:K79) | M79: =Assumptions!G98 | N79: =Assumptions!H98 | O79: =Assumptions!I98 | P79: =Assumptions!J98 | Q79: =SUM(M79:P79) | R79: =Assumptions!L98 | S79: =Assumptions!M98 | T79: =Assumptions!N98 | U79: =Assumptions!O98
A81: x | B81: Consolidated
B82: Aerospace Products Revenue | C82: =C50 | D82: =D50 | E82: =E50 | F82: =F50 | G82: =G50 | H82: =H50 | I82: =I50 | J82: =J50 | ... U82: =U50
B83: FTAI Power Revenue | C83: =C73 | D83: =D73 | E83: =E73 | F83: =F73 | G83: =G73 | H83: =H73 | I83: =I73 | J83: =J73 | ... U83: =U73
B84: Aviation + SCI Revenue | C84: =C78 | D84: =D78 | E84: =E78 | F84: =F78 | G84: =G78 | H84: =H78 | I84: =I78 | J84: =J78 | ... U84: =U78
B85: Total Revenue | C85: =SUM(C82:C84) | D85: =SUM(D82:D84) | E85: =SUM(E82:E84) | F85: =SUM(F82:F84) | G85: =SUM(G82:G84) | H85: =SUM(H82:H84) | I85: =SUM(I82:I84) | J85: =SUM(J82:J84) | ... U85: =SUM(U82:U84)
B86: y/y growth | H86: =H85/C85-1 | I86: =I85/D85-1 | J86: =J85/E85-1 | K86: =K85/F85-1 | L86: =L85/G85-1 | M86: =M85/H85-1 | N86: =N85/I85-1 | O86: =O85/J85-1 | ... Q86: =Q85/L85-1 | R86: =R85/Q85-1 | S86: =S85/R85-1 | T86: =T85/S85-1 | U86: =U85/T85-1
B88: Adj. EBITDA
B89: Aerospace Products | C89: =C60 | D89: =D60 | E89: =E60 | F89: =F60 | G89: =G60 | H89: =H60 | I89: =I60 | J89: =J60 | ... U89: =U60
B90: FTAI Power | C90: =C75 | D90: =D75 | E90: =E75 | F90: =F75 | G90: =G75 | H90: =H75 | I90: =I75 | J90: =J75 | ... U90: =U75
B91: Aviation Leasing + SCI | C91: =C79 | D91: =D79 | E91: =E79 | F91: =F79 | G91: =G79 | H91: =H79 | I91: =I79 | J91: =J79 | ... U91: =U79
B92: Corporate & Eliminations | C92: -17.4 | D92: -16.4 | E92: -17.4 | F92: -31.1 | G92: =SUM(C92:F92) | H92: -50 | I92: -46.5 | J92: =Assumptions!D103 | K92: =Assumptions!E103 | L92: =SUM(H92:K92) | M92: =Assumptions!G103 | N92: =Assumptions!H103 | O92: =Assumptions!I103 | P92: =Assumptions!J103 | Q92: =SUM(M92:P92) | R92: =Assumptions!L103 | S92: =Assumptions!M103 | T92: =Assumptions!N103 | U92: =Assumptions!O103
B93: Total Adj. EBITDA | C93: =SUM(C89:C92) | D93: =SUM(D89:D92) | E93: =SUM(E89:E92) | F93: =SUM(F89:F92) | G93: =SUM(G89:G92) | H93: =SUM(H89:H92) | I93: =SUM(I89:I92) | J93: =SUM(J89:J92) | ... U93: =SUM(U89:U92)
B94: y/y growth | H94: =H93/C93-1 | I94: =I93/D93-1 | J94: =J93/E93-1 | K94: =K93/F93-1 | L94: =L93/G93-1 | M94: =M93/H93-1 | N94: =N93/I93-1 | O94: =O93/J93-1 | ... Q94: =Q93/L93-1 | R94: =R93/Q93-1 | S94: =S93/R93-1 | T94: =T93/S93-1 | U94: =U93/T93-1

Sheet Assumptions
B1: FTAI Aviation
B2: Assumptions
D4: Q3-26 | E4: Q4-26 | F4: FY26 | G4: Q1-27 | H4: Q2-27 | I4: Q3-27 | J4: Q4-27 | K4: FY27 | L4: FY28 | M4: FY29 | N4: FY30 | O4: FY31
B6: Revenue Assumptions - CFM56 Fleet & Shop Visit Demand
B8: CFM56-7B Retirement Rate (% of BoP fleet) | D8: =CHOOSE(MATCH(DCF!$C$3, {"Bear","Base","Bull"}, 0),D9, D10,D11) | E8: =CHOOSE(MATCH(DCF!$C$3, {"Bear","Base","Bull"}, 0),E9, E10,E11) | F8: =CHOOSE(MATCH(DCF!$C$3, {"Bear","Base","Bull"}, 0),F9, F10,F11) | G8: =CHOOSE(MATCH(DCF!$C$3, {"Bear","Base","Bull"}, 0),G9, G10,G11) | H8: =CHOOSE(MATCH(DCF!$C$3, {"Bear","Base","Bull"}, 0),H9, H10,H11) | I8: =CHOOSE(MATCH(DCF!$C$3, {"Bear","Base","Bull"}, 0),I9, I10,I11) | J8: =CHOOSE(MATCH(DCF!$C$3, {"Bear","Base","Bull"}, 0),J9, J10,J11) | K8: =CHOOSE(MATCH(DCF!$C$3, {"Bear","Base","Bull"}, 0),K9, K10,K11) | ... O8: =CHOOSE(MATCH(DCF!$C$3, {"Bear","Base","Bull"}, 0),O9, O10,O11)
B9: Bear | D9: =1-(1-F9)^(1/4) | E9: =1-(1-F9)^(1/4) | F9: 0.015 | G9: =1-(1-K9)^(1/4) | H9: =1-(1-K9)^(1/4) | I9: =1-(1-K9)^(1/4) | J9: =1-(1-K9)^(1/4) | K9: 0.025 | L9: 0.025 | M9: 0.03 | N9: 0.03 | O9: 0.035
B10: Base | D10: =1-(1-F10)^(1/4) | E10: =1-(1-F10)^(1/4) | F10: 0.015 | G10: =1-(1-K10)^(1/4) | H10: =1-(1-K10)^(1/4) | I10: =1-(1-K10)^(1/4) | J10: =1-(1-K10)^(1/4) | K10: 0.02 | L10: 0.02 | M10: 0.025 | N10: 0.025 | O10: 0.03
B11: Bull | D11: =1-(1-F11)^(1/4) | E11: =1-(1-F11)^(1/4) | F11: =F10 | G11: =1-(1-K11)^(1/4) | H11: =1-(1-K11)^(1/4) | I11: =1-(1-K11)^(1/4) | J11: =1-(1-K11)^(1/4) | K11: =K10 | L11: =L10 | M11: =M10 | N11: =N10 | O11: =O10
B13: CFM56-5B Retirement Rate (% of BoP fleet) | D13: =CHOOSE(MATCH(DCF!$C$3, {"Bear","Base","Bull"}, 0),D14, D15,D16) | E13: =CHOOSE(MATCH(DCF!$C$3, {"Bear","Base","Bull"}, 0),E14, E15,E16) | F13: =CHOOSE(MATCH(DCF!$C$3, {"Bear","Base","Bull"}, 0),F14, F15,F16) | G13: =CHOOSE(MATCH(DCF!$C$3, {"Bear","Base","Bull"}, 0),G14, G15,G16) | H13: =CHOOSE(MATCH(DCF!$C$3, {"Bear","Base","Bull"}, 0),H14, H15,H16) | I13: =CHOOSE(MATCH(DCF!$C$3, {"Bear","Base","Bull"}, 0),I14, I15,I16) | J13: =CHOOSE(MATCH(DCF!$C$3, {"Bear","Base","Bull"}, 0),J14, J15,J16) | K13: =CHOOSE(MATCH(DCF!$C$3, {"Bear","Base","Bull"}, 0),K14, K15,K16) | ... O13: =CHOOSE(MATCH(DCF!$C$3, {"Bear","Base","Bull"}, 0),O14, O15,O16)
B14: Bear | D14: =1-(1-F14)^(1/4) | E14: =1-(1-F14)^(1/4) | F14: 0.02 | G14: =1-(1-K14)^(1/4) | H14: =1-(1-K14)^(1/4) | I14: =1-(1-K14)^(1/4) | J14: =1-(1-K14)^(1/4) | K14: 0.04 | L14: 0.04 | M14: 0.045 | N14: 0.045 | O14: 0.05
B15: Base | D15: =1-(1-F15)^(1/4) | E15: =1-(1-F15)^(1/4) | F15: 0.02 | G15: =1-(1-K15)^(1/4) | H15: =1-(1-K15)^(1/4) | I15: =1-(1-K15)^(1/4) | J15: =1-(1-K15)^(1/4) | K15: 0.025 | L15: 0.03 | M15: 0.035 | N15: 0.035 | O15: 0.04
B16: Bull | D16: =1-(1-F16)^(1/4) | E16: =1-(1-F16)^(1/4) | F16: =F15 | G16: =1-(1-K16)^(1/4) | H16: =1-(1-K16)^(1/4) | I16: =1-(1-K16)^(1/4) | J16: =1-(1-K16)^(1/4) | K16: =K15 | L16: =L15 | M16: =M15 | N16: =N15 | O16: =O15
B18: CFM56-7B Shop Visit Rate | D18: =CHOOSE(MATCH(DCF!$C$3, {"Bear","Base","Bull"}, 0),D19, D20,D21) | E18: =CHOOSE(MATCH(DCF!$C$3, {"Bear","Base","Bull"}, 0),E19, E20,E21) | F18: =CHOOSE(MATCH(DCF!$C$3, {"Bear","Base","Bull"}, 0),F19, F20,F21) | G18: =CHOOSE(MATCH(DCF!$C$3, {"Bear","Base","Bull"}, 0),G19, G20,G21) | H18: =CHOOSE(MATCH(DCF!$C$3, {"Bear","Base","Bull"}, 0),H19, H20,H21) | I18: =CHOOSE(MATCH(DCF!$C$3, {"Bear","Base","Bull"}, 0),I19, I20,I21) | J18: =CHOOSE(MATCH(DCF!$C$3, {"Bear","Base","Bull"}, 0),J19, J20,J21) | K18: =CHOOSE(MATCH(DCF!$C$3, {"Bear","Base","Bull"}, 0),K19, K20,K21) | ... O18: =CHOOSE(MATCH(DCF!$C$3, {"Bear","Base","Bull"}, 0),O19, O20,O21)
B19: Bear | D19: =F19/4 | E19: =F19/4 | F19: ='SV Analysis'!E33 | G19: =K19/4 | H19: =K19/4 | I19: =K19/4 | J19: =K19/4 | K19: ='SV Analysis'!F33 | L19: ='SV Analysis'!G33 | M19: ='SV Analysis'!H33 | N19: ='SV Analysis'!I33 | O19: ='SV Analysis'!J33
B20: Base | D20: =F20/4 | E20: =F20/4 | F20: ='SV Analysis'!E34 | G20: =K20/4 | H20: =K20/4 | I20: =K20/4 | J20: =K20/4 | K20: ='SV Analysis'!F34 | L20: ='SV Analysis'!G34 | M20: ='SV Analysis'!H34 | N20: ='SV Analysis'!I34 | O20: ='SV Analysis'!J34
B21: Bull | D21: =F21/4 | E21: =F21/4 | F21: =F20 | G21: =K21/4 | H21: =K21/4 | I21: =K21/4 | J21: =K21/4 | K21: =K20 | L21: =L20 | M21: =M20 | N21: =N20 | O21: =O20
B23: CFM56-5B Shop Visit Rate | D23: =CHOOSE(MATCH(DCF!$C$3, {"Bear","Base","Bull"}, 0),D24, D25,D26) | E23: =CHOOSE(MATCH(DCF!$C$3, {"Bear","Base","Bull"}, 0),E24, E25,E26) | F23: =CHOOSE(MATCH(DCF!$C$3, {"Bear","Base","Bull"}, 0),F24, F25,F26) | G23: =CHOOSE(MATCH(DCF!$C$3, {"Bear","Base","Bull"}, 0),G24, G25,G26) | H23: =CHOOSE(MATCH(DCF!$C$3, {"Bear","Base","Bull"}, 0),H24, H25,H26) | I23: =CHOOSE(MATCH(DCF!$C$3, {"Bear","Base","Bull"}, 0),I24, I25,I26) | J23: =CHOOSE(MATCH(DCF!$C$3, {"Bear","Base","Bull"}, 0),J24, J25,J26) | K23: =CHOOSE(MATCH(DCF!$C$3, {"Bear","Base","Bull"}, 0),K24, K25,K26) | ... O23: =CHOOSE(MATCH(DCF!$C$3, {"Bear","Base","Bull"}, 0),O24, O25,O26)
B24: Bear | D24: =F24/4 | E24: =F24/4 | F24: =F19-0.005 | G24: =K24/4 | H24: =K24/4 | I24: =K24/4 | J24: =K24/4 | K24: =K19-0.005 | L24: =L19-0.005 | M24: =M19-0.005 | N24: =N19-0.005 | O24: =O19-0.005
B25: Base | D25: =F25/4 | E25: =F25/4 | F25: =F20-0.005 | G25: =K25/4 | H25: =K25/4 | I25: =K25/4 | J25: =K25/4 | K25: =K20-0.005 | L25: =L20-0.005 | M25: =M20-0.005 | N25: =N20-0.005 | O25: =O20-0.005
B26: Bull | D26: =F26/4 | E26: =F26/4 | F26: =F21-0.005 | G26: =K26/4 | H26: =K26/4 | I26: =K26/4 | J26: =K26/4 | K26: =K21-0.005 | L26: =L21-0.005 | M26: =M21-0.005 | N26: =N21-0.005 | O26: =O21-0.005
B28: Modules per Shop Visit | D28: 3 | E28: 3 | F28: 3 | G28: 3 | H28: 3 | I28: 3 | J28: 3 | K28: 3 | L28: 3 | M28: 3 | N28: 3 | O28: 3
B30: Revenue Assumptions - SCI Captive Demand
B32: SCI Owned Aircraft | D32: =CHOOSE(MATCH(DCF!$C$3, {"Bear","Base","Bull"}, 0),D33, D34,D35) | E32: =CHOOSE(MATCH(DCF!$C$3, {"Bear","Base","Bull"}, 0),E33, E34,E35) | F32: =CHOOSE(MATCH(DCF!$C$3, {"Bear","Base","Bull"}, 0),F33, F34,F35) | G32: =CHOOSE(MATCH(DCF!$C$3, {"Bear","Base","Bull"}, 0),G33, G34,G35) | H32: =CHOOSE(MATCH(DCF!$C$3, {"Bear","Base","Bull"}, 0),H33, H34,H35) | I32: =CHOOSE(MATCH(DCF!$C$3, {"Bear","Base","Bull"}, 0),I33, I34,I35) | J32: =CHOOSE(MATCH(DCF!$C$3, {"Bear","Base","Bull"}, 0),J33, J34,J35) | K32: =CHOOSE(MATCH(DCF!$C$3, {"Bear","Base","Bull"}, 0),K33, K34,K35) | ... O32: =CHOOSE(MATCH(DCF!$C$3, {"Bear","Base","Bull"}, 0),O33, O34,O35)
B33: Bear | D33: =D34 | E33: =E34 | F33: =F34 | G33: 325 | H33: 335 | I33: 345 | J33: 350 | K33: =J33 | L33: 375 | M33: 400 | N33: 400 | O33: 400
B34: Base | D34: 300 | E34: 316 | F34: =E34 | G34: 350 | H34: 385 | I34: 420 | J34: 450 | K34: =J34 | L34: 550 | M34: 650 | N34: 700 | O34: 750
B35: Bull | D35: =D34 | E35: =E34 | F35: =F34 | G35: =G34 | H35: =H34 | I35: =I34 | J35: =J34 | K35: =J35 | L35: =L34 | M35: =M34 | N35: =N34 | O35: =O34
B37: Engines per Aircraft | D37: 2 | E37: 2 | F37: 2 | G37: 2 | H37: 2 | I37: 2 | J37: 2 | K37: 2 | L37: 2 | M37: 2 | N37: 2 | O37: 2
B39: SCI Shop Visit Rate | D39: =CHOOSE(MATCH(DCF!$C$3, {"Bear","Base","Bull"}, 0),D40, D41,D42) | E39: =CHOOSE(MATCH(DCF!$C$3, {"Bear","Base","Bull"}, 0),E40, E41,E42) | F39: =CHOOSE(MATCH(DCF!$C$3, {"Bear","Base","Bull"}, 0),F40, F41,F42) | G39: =CHOOSE(MATCH(DCF!$C$3, {"Bear","Base","Bull"}, 0),G40, G41,G42) | H39: =CHOOSE(MATCH(DCF!$C$3, {"Bear","Base","Bull"}, 0),H40, H41,H42) | I39: =CHOOSE(MATCH(DCF!$C$3, {"Bear","Base","Bull"}, 0),I40, I41,I42) | J39: =CHOOSE(MATCH(DCF!$C$3, {"Bear","Base","Bull"}, 0),J40, J41,J42) | K39: =CHOOSE(MATCH(DCF!$C$3, {"Bear","Base","Bull"}, 0),K40, K41,K42) | ... O39: =CHOOSE(MATCH(DCF!$C$3, {"Bear","Base","Bull"}, 0),O40, O41,O42)
B40: Bear | D40: =D41 | E40: =E41 | F40: =F41 | G40: =G41 | H40: =H41 | I40: =I41 | J40: =J41 | K40: =K41 | ... O40: =O41
B41: Base | D41: 0.05 | E41: 0.05 | F41: 0.2 | G41: 0.05 | H41: 0.05 | I41: 0.05 | J41: 0.05 | K41: 0.2 | L41: 0.2 | M41: 0.2 | N41: 0.2 | O41: 0.2
B42: Bull | D42: =D41 | E42: =E41 | F42: =F41 | G42: =G41 | H42: =H41 | I42: =I41 | J42: =J41 | K42: =K41 | ... O42: =O41
B44: FTAI Share of MRO (%) | D44: =CHOOSE(MATCH(DCF!$C$3, {"Bear","Base","Bull"}, 0),D45, D46,D47) | E44: =CHOOSE(MATCH(DCF!$C$3, {"Bear","Base","Bull"}, 0),E45, E46,E47) | F44: =CHOOSE(MATCH(DCF!$C$3, {"Bear","Base","Bull"}, 0),F45, F46,F47) | G44: =CHOOSE(MATCH(DCF!$C$3, {"Bear","Base","Bull"}, 0),G45, G46,G47) | H44: =CHOOSE(MATCH(DCF!$C$3, {"Bear","Base","Bull"}, 0),H45, H46,H47) | I44: =CHOOSE(MATCH(DCF!$C$3, {"Bear","Base","Bull"}, 0),I45, I46,I47) | J44: =CHOOSE(MATCH(DCF!$C$3, {"Bear","Base","Bull"}, 0),J45, J46,J47) | K44: =CHOOSE(MATCH(DCF!$C$3, {"Bear","Base","Bull"}, 0),K45, K46,K47) | ... O44: =CHOOSE(MATCH(DCF!$C$3, {"Bear","Base","Bull"}, 0),O45, O46,O47)
B45: Bear | D45: =D46 | E45: =E46 | F45: =AVERAGE(D45:E45) | G45: 0.135 | H45: 0.14 | I45: 0.145 | J45: 0.15 | K45: =AVERAGE(G45:J45) | L45: 0.15 | M45: 0.15 | N45: 0.15 | O45: 0.15
B46: Base | D46: 0.119 | E46: 0.13 | F46: =AVERAGE(D46:E46) | G46: 0.15 | H46: 0.163 | I46: 0.175 | J46: 0.186 | K46: =AVERAGE(G46:J46) | L46: 0.19 | M46: 0.195 | N46: 0.2 | O46: 0.2
B47: Bull | D47: =D46 | E47: =E46 | F47: =AVERAGE(D47:E47) | G47: 0.155 | H47: 0.17 | I47: 0.185 | J47: 0.2 | K47: =AVERAGE(G47:J47) | L47: 0.21 | M47: 0.23 | N47: 0.24 | O47: 0.25
B49: OEM Price Escalator | D49: =CHOOSE(MATCH(DCF!$C$3, {"Bear","Base","Bull"}, 0),D50, D51,D52) | E49: =CHOOSE(MATCH(DCF!$C$3, {"Bear","Base","Bull"}, 0),E50, E51,E52) | F49: =CHOOSE(MATCH(DCF!$C$3, {"Bear","Base","Bull"}, 0),F50, F51,F52) | G49: =CHOOSE(MATCH(DCF!$C$3, {"Bear","Base","Bull"}, 0),G50, G51,G52) | H49: =CHOOSE(MATCH(DCF!$C$3, {"Bear","Base","Bull"}, 0),H50, H51,H52) | I49: =CHOOSE(MATCH(DCF!$C$3, {"Bear","Base","Bull"}, 0),I50, I51,I52) | J49: =CHOOSE(MATCH(DCF!$C$3, {"Bear","Base","Bull"}, 0),J50, J51,J52) | K49: =CHOOSE(MATCH(DCF!$C$3, {"Bear","Base","Bull"}, 0),K50, K51,K52) | ... O49: =CHOOSE(MATCH(DCF!$C$3, {"Bear","Base","Bull"}, 0),O50, O51,O52)
B50: Bear | D50: 0.07 | E50: 0 | F50: 0.07 | G50: 0 | H50: 0 | I50: 0.07 | J50: 0 | K50: 0.07 | L50: =L51-0.02 | M50: =M51-0.02 | N50: =N51-0.02 | O50: =O51-0.02
B51: Base | D51: 0.07 | E51: 0 | F51: 0.07 | G51: 0.065 | H51: 0 | I51: 0.07 | J51: 0 | K51: 0.07 | L51: 0.07 | M51: 0.07 | N51: 0.07 | O51: 0.07
B52: Bull | D52: =D51 | E52: =E51 | F52: =F51 | G52: =G51 | H52: =H51 | I52: =I51 | J52: =J51 | K52: =K51 | ... O52: =O51
B54: FTAI Pass-Through | D54: =CHOOSE(MATCH(DCF!$C$3, {"Bear","Base","Bull"}, 0),D55, D56,D57) | E54: =CHOOSE(MATCH(DCF!$C$3, {"Bear","Base","Bull"}, 0),E55, E56,E57) | F54: =CHOOSE(MATCH(DCF!$C$3, {"Bear","Base","Bull"}, 0),F55, F56,F57) | G54: =CHOOSE(MATCH(DCF!$C$3, {"Bear","Base","Bull"}, 0),G55, G56,G57) | H54: =CHOOSE(MATCH(DCF!$C$3, {"Bear","Base","Bull"}, 0),H55, H56,H57) | I54: =CHOOSE(MATCH(DCF!$C$3, {"Bear","Base","Bull"}, 0),I55, I56,I57) | J54: =CHOOSE(MATCH(DCF!$C$3, {"Bear","Base","Bull"}, 0),J55, J56,J57) | K54: =CHOOSE(MATCH(DCF!$C$3, {"Bear","Base","Bull"}, 0),K55, K56,K57) | ... O54: =CHOOSE(MATCH(DCF!$C$3, {"Bear","Base","Bull"}, 0),O55, O56,O57)
B55: Bear | D55: 0 | E55: 0 | F55: 0 | G55: 1 | H55: 0 | I55: 0 | J55: 0 | K55: 0 | L55: =L56-0.2 | M55: =M56-0.2 | N55: =N56-0.2 | O55: =O56-0.2
B56: Base | D56: 0 | E56: 0 | F56: 0 | G56: 0.5 | H56: 0 | I56: 0 | J56: 0 | K56: 0 | L56: 0.5 | M56: 0.5 | N56: 0.5 | O56: 0.5
B57: Bull | D57: =D56 | E57: =E56 | F57: =F56 | G57: =G56 | H57: =H56 | I57: =I56 | J57: =J56 | K57: =K56 | ... O57: =O56
B59: Cost Assumptions - Aerospace Products
B61: Adj. EBITDA Margin (ex PMA) | D61: =CHOOSE(MATCH(DCF!$C$3, {"Bear","Base","Bull"}, 0),D62, D63,D64) | E61: =CHOOSE(MATCH(DCF!$C$3, {"Bear","Base","Bull"}, 0),E62, E63,E64) | F61: =CHOOSE(MATCH(DCF!$C$3, {"Bear","Base","Bull"}, 0),F62, F63,F64) | G61: =CHOOSE(MATCH(DCF!$C$3, {"Bear","Base","Bull"}, 0),G62, G63,G64) | H61: =CHOOSE(MATCH(DCF!$C$3, {"Bear","Base","Bull"}, 0),H62, H63,H64) | I61: =CHOOSE(MATCH(DCF!$C$3, {"Bear","Base","Bull"}, 0),I62, I63,I64) | J61: =CHOOSE(MATCH(DCF!$C$3, {"Bear","Base","Bull"}, 0),J62, J63,J64) | K61: =CHOOSE(MATCH(DCF!$C$3, {"Bear","Base","Bull"}, 0),K62, K63,K64) | ... O61: =CHOOSE(MATCH(DCF!$C$3, {"Bear","Base","Bull"}, 0),O62, O63,O64)
B62: Bear | D62: 0.29 | E62: 0.29 | F62: =AVERAGE(D62:E62) | G62: 0.285 | H62: 0.285 | I62: 0.285 | J62: 0.285 | K62: =AVERAGE(G62:J62) | L62: 0.285 | M62: 0.285 | N62: 0.285 | O62: 0.285
B63: Base | D63: 0.309 | E63: 0.309 | F63: =AVERAGE(D63:E63) | G63: 0.298 | H63: 0.298 | I63: 0.298 | J63: 0.298 | K63: =AVERAGE(G63:J63) | L63: 0.303 | M63: 0.308 | N63: 0.312 | O63: 0.315
B64: Bull | D64: =D63 | E64: =E63 | F64: =AVERAGE(D64:E64) | G64: =G63+0.005 | H64: =H63+0.01 | I64: =I63+0.015 | J64: =J63+0.02 | K64: =AVERAGE(G64:J64) | L64: =L63+0.02 | M64: =M63+0.02 | N64: =N63+0.02 | O64: =O63+0.02
B66: PMA Penetration (% of modules) | D66: =CHOOSE(MATCH(DCF!$C$3, {"Bear","Base","Bull"}, 0),D67, D68,D69) | E66: =CHOOSE(MATCH(DCF!$C$3, {"Bear","Base","Bull"}, 0),E67, E68,E69) | F66: =CHOOSE(MATCH(DCF!$C$3, {"Bear","Base","Bull"}, 0),F67, F68,F69) | G66: =CHOOSE(MATCH(DCF!$C$3, {"Bear","Base","Bull"}, 0),G67, G68,G69) | H66: =CHOOSE(MATCH(DCF!$C$3, {"Bear","Base","Bull"}, 0),H67, H68,H69) | I66: =CHOOSE(MATCH(DCF!$C$3, {"Bear","Base","Bull"}, 0),I67, I68,I69) | J66: =CHOOSE(MATCH(DCF!$C$3, {"Bear","Base","Bull"}, 0),J67, J68,J69) | K66: =CHOOSE(MATCH(DCF!$C$3, {"Bear","Base","Bull"}, 0),K67, K68,K69) | ... O66: =CHOOSE(MATCH(DCF!$C$3, {"Bear","Base","Bull"}, 0),O67, O68,O69)
B67: Bear | D67: 0 | E67: 0 | F67: 0 | G67: 0 | H67: 0 | I67: 0 | J67: 0 | K67: 0 | L67: 0 | M67: 0 | N67: 0 | O67: 0
B68: Base | D68: 0 | E68: 0 | F68: 0 | G68: 0.005 | H68: 0.0075 | I68: 0.01 | J68: 0.0125 | K68: =AVERAGE(G68:J68) | L68: 0.03 | M68: 0.05 | N68: 0.07 | O68: 0.09
B69: Bull | D69: =D68 | E69: =E68 | F69: =F68 | G69: =G68 | H69: =H68 | I69: =I68 | J69: =J68 | K69: =K68 | ... O69: =O68
B71: PMA Uplift per Module | D71: 0.4 | E71: 0.4 | F71: 0.4 | G71: 0.4 | H71: 0.4 | I71: 0.4 | J71: 0.4 | K71: 0.4 | L71: 0.4 | M71: 0.4 | N71: 0.4 | O71: 0.4
B73: FTAI Power
B75: Units Delivered | D75: =CHOOSE(MATCH(DCF!$C$3, {"Bear","Base","Bull"}, 0),D76, D77,D78) | E75: =CHOOSE(MATCH(DCF!$C$3, {"Bear","Base","Bull"}, 0),E76, E77,E78) | F75: =CHOOSE(MATCH(DCF!$C$3, {"Bear","Base","Bull"}, 0),F76, F77,F78) | G75: =CHOOSE(MATCH(DCF!$C$3, {"Bear","Base","Bull"}, 0),G76, G77,G78) | H75: =CHOOSE(MATCH(DCF!$C$3, {"Bear","Base","Bull"}, 0),H76, H77,H78) | I75: =CHOOSE(MATCH(DCF!$C$3, {"Bear","Base","Bull"}, 0),I76, I77,I78) | J75: =CHOOSE(MATCH(DCF!$C$3, {"Bear","Base","Bull"}, 0),J76, J77,J78) | K75: =CHOOSE(MATCH(DCF!$C$3, {"Bear","Base","Bull"}, 0),K76, K77,K78) | ... O75: =CHOOSE(MATCH(DCF!$C$3, {"Bear","Base","Bull"}, 0),O76, O77,O78)
B76: Bear | D76: 0 | E76: 0 | F76: =SUM(D76:E76) | G76: 5 | H76: 7 | I76: 8 | J76: 10 | K76: =SUM(G76:J76) | L76: 45 | M76: 50 | N76: 50 | O76: 50
B77: Base | D77: 0 | E77: 2 | F77: =SUM(D77:E77) | G77: 8 | H77: 10 | I77: 12 | J77: 15 | K77: =SUM(G77:J77) | L77: 90 | M77: 110 | N77: 120 | O77: 130
B78: Bull | D78: 0 | E78: 2 | F78: =SUM(D78:E78) | G78: 10 | H78: 12 | I78: 15 | J78: 18 | K78: =SUM(G78:J78) | L78: 130 | M78: 150 | N78: 160 | O78: 170
B80: MW per Unit | D80: 25 | E80: 25 | F80: 25 | G80: 25 | H80: 25 | I80: 25 | J80: 25 | K80: 25 | L80: 25 | M80: 25 | N80: 25 | O80: 25
B82: $ per MW | D82: 1 | E82: 1 | F82: 1 | G82: 1 | H82: 1 | I82: 1 | J82: 1 | K82: 1 | L82: 1 | M82: 1 | N82: 1 | O82: 1
B84: FTAI Share of JV | D84: =CHOOSE(MATCH(DCF!$C$3, {"Bear","Base","Bull"}, 0),D85, D86,D87) | E84: =CHOOSE(MATCH(DCF!$C$3, {"Bear","Base","Bull"}, 0),E85, E86,E87) | F84: =CHOOSE(MATCH(DCF!$C$3, {"Bear","Base","Bull"}, 0),F85, F86,F87) | G84: =CHOOSE(MATCH(DCF!$C$3, {"Bear","Base","Bull"}, 0),G85, G86,G87) | H84: =CHOOSE(MATCH(DCF!$C$3, {"Bear","Base","Bull"}, 0),H85, H86,H87) | I84: =CHOOSE(MATCH(DCF!$C$3, {"Bear","Base","Bull"}, 0),I85, I86,I87) | J84: =CHOOSE(MATCH(DCF!$C$3, {"Bear","Base","Bull"}, 0),J85, J86,J87) | K84: =CHOOSE(MATCH(DCF!$C$3, {"Bear","Base","Bull"}, 0),K85, K86,K87) | ... O84: =CHOOSE(MATCH(DCF!$C$3, {"Bear","Base","Bull"}, 0),O85, O86,O87)
B85: Bear | D85: 0.5 | E85: 0.5 | F85: 0.5 | G85: 0.5 | H85: 0.5 | I85: 0.5 | J85: 0.5 | K85: 0.5 | L85: 0.5 | M85: 0.5 | N85: 0.5 | O85: 0.5
B86: Base | D86: 1 | E86: 1 | F86: 1 | G86: 1 | H86: 1 | I86: 1 | J86: 1 | K86: 1 | L86: 1 | M86: 1 | N86: 1 | O86: 1
B87: Bull | D87: =D86 | E87: =E86 | F87: =F86 | G87: =G86 | H87: =H86 | I87: =I86 | J87: =J86 | K87: =K86 | ... O87: =O86
B89: FTAI Power Adj. EBITA Margin (%) | D89: =CHOOSE(MATCH(DCF!$C$3, {"Bear","Base","Bull"}, 0),D90, D91,D92) | E89: =CHOOSE(MATCH(DCF!$C$3, {"Bear","Base","Bull"}, 0),E90, E91,E92) | F89: =CHOOSE(MATCH(DCF!$C$3, {"Bear","Base","Bull"}, 0),F90, F91,F92) | G89: =CHOOSE(MATCH(DCF!$C$3, {"Bear","Base","Bull"}, 0),G90, G91,G92) | H89: =CHOOSE(MATCH(DCF!$C$3, {"Bear","Base","Bull"}, 0),H90, H91,H92) | I89: =CHOOSE(MATCH(DCF!$C$3, {"Bear","Base","Bull"}, 0),I90, I91,I92) | J89: =CHOOSE(MATCH(DCF!$C$3, {"Bear","Base","Bull"}, 0),J90, J91,J92) | K89: =CHOOSE(MATCH(DCF!$C$3, {"Bear","Base","Bull"}, 0),K90, K91,K92) | ... O89: =CHOOSE(MATCH(DCF!$C$3, {"Bear","Base","Bull"}, 0),O90, O91,O92)
B90: Bear | D90: 0.3 | E90: 0.3 | F90: 0.3 | G90: 0.3 | H90: 0.3 | I90: 0.3 | J90: 0.3 | K90: 0.3 | L90: 0.3 | M90: 0.3 | N90: 0.3 | O90: 0.3
B91: Base | D91: 0.4 | E91: 0.4 | F91: 0.4 | G91: 0.4 | H91: 0.4 | I91: 0.4 | J91: 0.4 | K91: 0.4 | L91: 0.4 | M91: 0.4 | N91: 0.4 | O91: 0.4
B92: Bull | D92: 0.4 | E92: 0.4 | F92: 0.4 | G92: 0.4 | H92: 0.4 | I92: 0.4 | J92: 0.4 | K92: 0.4 | L92: 0.4 | M92: 0.4 | N92: 0.4 | O92: 0.4
B94: Aviation Leasing & SCI
B96: Aviation Leasing Revenue | D96: 82.5 | E96: 82.5 | F96: =SUM(D96:E96) | G96: 75 | H96: 75 | I96: 75 | J96: 75 | K96: =SUM(G96:J96) | L96: 285 | M96: 275 | N96: 265 | O96: 255
B98: Aviation Leasing + SCI EBITDA | D98: =CHOOSE(MATCH(DCF!$C$3, {"Bear","Base","Bull"}, 0),D99, D100,D101) | E98: =CHOOSE(MATCH(DCF!$C$3, {"Bear","Base","Bull"}, 0),E99, E100,E101) | F98: =CHOOSE(MATCH(DCF!$C$3, {"Bear","Base","Bull"}, 0),F99, F100,F101) | G98: =CHOOSE(MATCH(DCF!$C$3, {"Bear","Base","Bull"}, 0),G99, G100,G101) | H98: =CHOOSE(MATCH(DCF!$C$3, {"Bear","Base","Bull"}, 0),H99, H100,H101) | I98: =CHOOSE(MATCH(DCF!$C$3, {"Bear","Base","Bull"}, 0),I99, I100,I101) | J98: =CHOOSE(MATCH(DCF!$C$3, {"Bear","Base","Bull"}, 0),J99, J100,J101) | K98: =CHOOSE(MATCH(DCF!$C$3, {"Bear","Base","Bull"}, 0),K99, K100,K101) | ... O98: =CHOOSE(MATCH(DCF!$C$3, {"Bear","Base","Bull"}, 0),O99, O100,O101)
B99: Bear | D99: =D100 | E99: =E100 | F99: =SUM(D99:E99) | G99: 100 | H99: 100 | I99: 100 | J99: 100 | K99: =SUM(G99:J99) | L99: 380 | M99: 360 | N99: 350 | O99: 340
B100: Base | D100: 116.9 | E100: 116.9 | F100: =SUM(D100:E100) | G100: 113.75 | H100: 113.75 | I100: 113.75 | J100: 113.75 | K100: =SUM(G100:J100) | L100: 440 | M100: 430 | N100: 420 | O100: 410
B101: Bull | D101: =D100 | E101: =E100 | F101: =SUM(D101:E101) | G101: =G100 | H101: =H100 | I101: =I100 | J101: =J100 | K101: =SUM(G101:J101) | L101: =L100 | M101: =M100 | N101: =N100 | O101: =O100
B103: Corporate & Eliminations | D103: -66.8 | E103: -66.8 | F103: =SUM(D103:E103) | G103: -51.75 | H103: -51.75 | I103: -51.75 | J103: -51.75 | K103: =SUM(G103:J103) | L103: -215 | M103: -225 | N103: -235 | O103: -245
B105: Operating Model Assumptions - Cash Flow
B107: D&A ($mm) | F107: 196.2 | K107: 191 | L107: 180.2 | M107: 180.2 | N107: 180.2 | O107: 180.2
B109: PP&E CapEx (% of Revenue) | F109: 0.003 | K109: 0.0025 | L109: 0.0025 | M109: 0.0025 | N109: 0.0025 | O109: 0.0025
B111: Acquisition of Leasing Equipment ($mm) | F111: 217.8 | K111: 140 | L111: 150 | M111: 150 | N111: 150 | O111: 150
B113: Proceeds from Sale of Leasing Equipment ($mm) | F113: 409.6 | K113: 250 | L113: 25 | M113: 0 | N113: 0 | O113: 0
B115: FTAI Power Growth CapEx (% of Power Revenue) | F115: 0 | K115: 0 | L115: 0 | M115: 0 | N115: 0 | O115: 0
B117: SBC (% of Revenue) | F117: 0.0075 | K117: 0.006 | L117: 0.0055 | M117: 0.005 | N117: 0.005 | O117: 0.005
B119: Tax Rate (% of EBIT) | F119: 0.2145 | K119: 0.2101 | L119: 0.2138 | M119: 0.2138 | N119: 0.2138 | O119: 0.2138
B121: Inventory (% of Aerospace Products Revenue ex-Power) | F121: =CHOOSE(MATCH(DCF!$C$3, {"Bear","Base","Bull"}, 0),F122, F123,F124) | K121: =CHOOSE(MATCH(DCF!$C$3, {"Bear","Base","Bull"}, 0),K122, K123,K124) | L121: =CHOOSE(MATCH(DCF!$C$3, {"Bear","Base","Bull"}, 0),L122, L123,L124) | M121: =CHOOSE(MATCH(DCF!$C$3, {"Bear","Base","Bull"}, 0),M122, M123,M124) | N121: =CHOOSE(MATCH(DCF!$C$3, {"Bear","Base","Bull"}, 0),N122, N123,N124) | O121: =CHOOSE(MATCH(DCF!$C$3, {"Bear","Base","Bull"}, 0),O122, O123,O124)
B122: Bear | F122: 0.45 | K122: 0.41 | L122: 0.39 | M122: 0.38 | N122: 0.37 | O122: 0.37
B123: Base | F123: 0.42 | K123: 0.351 | L123: 0.314 | M123: 0.314 | N123: 0.314 | O123: 0.314
B124: Bull | F124: =F123 | K124: =K123 | L124: =L123 | M124: =M123 | N124: =N123 | O124: =O123
B126: Accounts Receivable (% of Revenue) | F126: 0.08 | K126: 0.07 | L126: 0.06 | M126: 0.06 | N126: 0.06 | O126: 0.06
B128: AP & Accrued Liabilities (% of Revenue) | F128: 0.09 | K128: 0.065 | L128: 0.055 | M128: 0.055 | N128: 0.055 | O128: 0.055
B130: Other Operating Assets, net (% of Revenue) | F130: 0.11 | K130: 0.073 | L130: 0.057 | M130: 0.057 | N130: 0.057 | O130: 0.057
B132: Investment in SCI / Unconsolidated Entities ($mm, Base; scales with SCI fleet) | F132: 285 | K132: 380 | L132: 380 | M132: 380 | N132: 380 | O132: 380
B134: Interest Expense ($mm) | F134: 249.8 | K134: 229.5 | L134: 229.5 | M134: 229.5 | N134: 229.5 | O134: 229.5
B136: Common Dividends ($mm) | F136: 200.6 | K136: 221.1 | L136: 243.9 | M136: =L136*1.1 | N136: =M136*1.1 | O136: =N136*1.1
B138: Preferred Dividends ($mm) | F138: 10.5 | K138: 6.2 | L138: 6.2 | M138: 6.2 | N138: 6.2 | O138: 6.2
B140: Non-cash Adj. EBITDA Items (% of Adj. EBITDA) | F140: 0.1647 | K140: 0.1121 | L140: 0.1001 | M140: 0.1001 | N140: 0.1001 | O140: 0.1001
B142: SCI Cash Distributions to FTAI ($mm, Base; scales with SCI fleet) | F142: 64.1 | K142: 189.5 | L142: 291.3 | M142: 291.3 | N142: 291.3 | O142: 291.3

Sheet Data

Sheet CFM56 Data
B1: FTAI Aviation
B2: CFM56 Data
B4: OEM CFM56 shop visits (-5B/-7B)
D5: 2025 | E5: 2026 | F5: 2027 | G5: 2028 | H5: 2029 | I5: 2030 | J5: 2031 | K5: Source
B6: Central | D6: 2350 | E6: 2400 | F6: 2400 | G6: 2350 | H6: 2250 | I6: 2150 | J6: 2085 | K6: C01, C02
B7: Low | D7: 2300 | E7: 2400 | F7: 2400 | G7: 2300 | K7: C02
B8: High | D8: 2400 | E8: 2400 | F8: 2400 | G8: 2400 | K8: C01, C02
B10: Fleet counts
C11: Scope | D11: Engines | E11: Year | K11: Source
B12: Safran | C12: -5B/-7B, incl. stored | D12: 23000 | E12: 2024 | K12: C03
B13: Safran | C13: -5B/-7B | D13: 22800 | E13: 2025 | K13: K15
B14: MTU | C14: -7B | D14: 13000 | E14: 2024 | K14: P02
B15: MTU | C15: -5B | D15: 7000 | E15: 2024 | K15: P02
B16: GE | C16: Installed | D16: 19000 | E16: 2026 | K16: P01
B18: Fleet by completed shop visits
D19: 0 | E19: 1 | F19: 2+ | K19: Source
B20: 2024 actual | D20: 0.4 | E20: 0.29 | F20: 0.31 | K20: C03
B21: 2028 OEM projection | D21: 0.26 | E21: 0.31 | F21: 0.43 | K21: C03
B23: Cohort roll-forward (central)
D24: 2025 | E24: 2026 | F24: 2027 | G24: 2028 | H24: 2029 | I24: 2030 | K24: Source
B25: First visits | D25: 975.8292 | E25: 912.14652 | F25: 844.50639 | G25: 763.04959 | H25: 676.20212 | I25: 598.30441 | K25: Cohort Forecast
B26: Second visits | D26: 842.38455 | E26: 890.6853 | F26: 914.28543 | G26: 908.12258 | H26: 874.08453 | I26: 832.09451 | K26: Cohort Forecast
B27: Third+ visits | D27: 531.78625 | E27: 597.16818 | F27: 641.20819 | G27: 678.82784 | H27: 699.71335 | I27: 719.60109 | K27: Cohort Forecast
B28: Repeat-visit share | D28: 0.58475353 | E28: 0.61993895 | F28: 0.64812234 | G28: 0.67529805 | H28: 0.69946573 | I28: 0.72171888 | K28: Cohort Forecast
B29: Broader-work share | D29: 0.48203453 | E29: 0.49209662 | F29: 0.50012581 | G29: 0.50746803 | H29: 0.51371463 | I29: 0.51913179 | K29: Cohort Forecast
B30: Stock: 2+ prior visits | D30: 0.33895981 | E30: 0.36987276 | F30: 0.39502433 | G30: 0.42233464 | H30: 0.44844219 | I30: 0.47526972 | K30: Cohort Forecast
B31: Stock: 0 prior visits | D31: 0.36301791 | E31: 0.32850426 | F31: 0.30110204 | G31: 0.27520982 | H31: 0.25269449 | I31: 0.23190294 | K31: Cohort Forecast
B33: Engine shop-visit history: completed intervals (scraped)
B34: ESN | C34: Model | D34: From | E34: To | F34: Scope (to) | G34: Years | H34: Cycles | I34: Major | K34: Source
B35: 877356 | C35: CFM56-7B27 | D35: 39305 | E35: 41817 | F35: Not stated | G35: =(E35-D35)/365.25 | I35: 1 | K35: D042/D043
B36: 877356 | C36: CFM56-7B27 | D36: 41817 | E36: 43917 | F36: Not stated | G36: =(E36-D36)/365.25 | I36: 1 | K36: D043/D044
B37: 888804 | C37: CFM56-7B27 | D37: 42486 | E37: 44617 | F37: Not stated | G37: =(E37-D37)/365.25 | I37: 1 | K37: D040/D041
B38: 891647 | C38: CFM56-7B24 | D38: 40287 | E38: 40617 | F38: Oil leak repair | G38: =(E38-D38)/365.25 | I38: 0 | K38: D045/D046
B39: 891647 | C39: CFM56-7B24 | D39: 40617 | E39: 42331 | F39: Perf. restoration | G39: =(E39-D39)/365.25 | I39: 1 | K39: D046/D047
B40: 890669 | C40: CFM56-7B24 | D40: 40236 | E40: 41856 | F40: Perf. restoration | G40: =(E40-D40)/365.25 | I40: 1 | K40: D048/D049
B41: 890669 | C41: CFM56-7B24 | D41: 41856 | E41: 42912 | F41: Perf. restoration | G41: =(E41-D41)/365.25 | I41: 1 | K41: D049/D050
B42: 889728 | C42: CFM56-7B22 | D42: 39630 | E42: 41456 | F42: Not stated | G42: =(E42-D42)/365.25 | I42: 1 | K42: D024/D025
B43: 894206 | C43: CFM56-7B24 | D43: 41239 | E43: 42114 | F43: Repair | G43: =(E43-D43)/365.25 | H43: 4649 | I43: 0 | K43: E02
B44: 894206 | C44: CFM56-7B24 | D44: 42114 | E44: 42555 | F44: Repair | G44: =(E44-D44)/365.25 | H44: 2821 | I44: 0 | K44: E02
B45: 894206 | C45: CFM56-7B24 | D45: 42555 | E45: 44033 | F45: Overhaul | G45: =(E45-D45)/365.25 | H45: 5018 | I45: 1 | K45: E02
B46: 894207 | C46: CFM56-7B24 | D46: 41537 | E46: 42726 | F46: Repair | G46: =(E46-D46)/365.25 | H46: 6767 | I46: 0 | K46: E02
B47: 894207 | C47: CFM56-7B24 | D47: 42726 | E47: 43994 | F47: Overhaul | G47: =(E47-D47)/365.25 | H47: 6422 | I47: 1 | K47: E02
B48: 894207 | C48: CFM56-7B24 | D48: 43994 | E48: 45217 | F48: Overhaul | G48: =(E48-D48)/365.25 | H48: 2857 | I48: 1 | K48: E02
B50: Engine shop-visit history: major-to-major intervals
B51: ESN | C51: Model | D51: From | E51: To | G51: Years | H51: Cycles | K51: Source
B52: 877356 | C52: CFM56-7B27 | D52: 39305 | E52: 41817 | G52: =(E52-D52)/365.25 | K52: D042/D043
B53: 877356 | C53: CFM56-7B27 | D53: 41817 | E53: 43917 | G53: =(E53-D53)/365.25 | K53: D043/D044
B54: 888804 | C54: CFM56-7B27 | D54: 42486 | E54: 44617 | G54: =(E54-D54)/365.25 | K54: D040/D041
B55: 891647 | C55: CFM56-7B24 | D55: 40287 | E55: 42331 | G55: =(E55-D55)/365.25 | K55: D045/D047
B56: 890669 | C56: CFM56-7B24 | D56: 40236 | E56: 41856 | G56: =(E56-D56)/365.25 | K56: D048/D049
B57: 890669 | C57: CFM56-7B24 | D57: 41856 | E57: 42912 | G57: =(E57-D57)/365.25 | K57: D049/D050
B58: 889728 | C58: CFM56-7B22 | D58: 39630 | E58: 41456 | G58: =(E58-D58)/365.25 | K58: D024/D025
B59: 894207 | C59: CFM56-7B24 | D59: 41537 | E59: 43994 | G59: =(E59-D59)/365.25 | H59: 13189 | K59: E02
B60: 894207 | C60: CFM56-7B24 | D60: 43994 | E60: 45217 | G60: =(E60-D60)/365.25 | H60: 2857 | K60: E02
B62: Time on wing since last shop visit at snapshot (scraped)
B63: ESN | C63: Model | D63: Last visit | E63: Snapshot | F63: Scope | G63: Years | H63: Cycles | I63: Hours | K63: Source
B64: 875134 | C64: CFM56-7B24 | D64: 41227 | E64: 43207 | F64: Overhaul | G64: =(E64-D64)/365.25 | H64: 10712 | I64: 18088 | K64: D007
B65: 889632 | C65: CFM56-7B24 | D65: 40060 | E65: 43207 | F65: Overhaul | G65: =(E65-D65)/365.25 | H65: 17201 | I65: 28954 | K65: D008
B66: 891647 | C66: CFM56-7B24 | D66: 42331 | E66: 44413 | F66: Perf. restoration | G66: =(E66-D66)/365.25 | H66: 9585 | I66: 19505 | K66: D047
B67: 890669 | C67: CFM56-7B24 | D67: 42912 | E67: 44404 | F67: Perf. restoration | G67: =(E67-D67)/365.25 | H67: 6854 | I67: 10841 | K67: D050
B69: Engine utilization: repeated FAA reports, same ESN (scraped)
B70: ESN | C70: Family | D70: First report | E70: Last report | G70: Years | H70: Cycles start | I70: Cycles end | J70: Cycles / yr | K70: Hours / yr
B71: 569208 | C71: CFM56-5B | D71: 44688 | E71: 45586 | G71: =(E71-D71)/365.25 | H71: 12889 | I71: 18103 | J71: =(I71-H71)/G71 | K71: 2494
B72: 569578 | C72: CFM56-5B | D72: 45182 | E72: 46251 | G72: =(E72-D72)/365.25 | H72: 14669 | I72: 17526 | J72: =(I72-H72)/G72 | K72: 1204
B73: 569976 | C73: CFM56-5B | D73: 44606 | E73: 45888 | G73: =(E73-D73)/365.25 | H73: 11002 | I73: 17188 | J73: =(I73-H73)/G73 | K73: 2333
B74: 569982 | C74: CFM56-5B | D74: 44343 | E74: 45006 | G74: =(E74-D74)/365.25 | H74: 9257 | I74: 12502 | J74: =(I74-H74)/G74 | K74: 2748
B75: 573199 | C75: CFM56-5B | D75: 44646 | E75: 45642 | G75: =(E75-D75)/365.25 | H75: 10607 | I75: 16146 | J75: =(I75-H75)/G75 | K75: 2881
B76: 573261 | C76: CFM56-5B | D76: 42969 | E76: 44664 | G76: =(E76-D76)/365.25 | H76: 2657 | I76: 8568 | J76: =(I76-H76)/G76 | K76: 3007
B77: 573511 | C77: CFM56-5B | D77: 45072 | E77: 45881 | G77: =(E77-D77)/365.25 | H77: 12543 | I77: 17226 | J77: =(I77-H77)/G77 | K77: 2760
B78: 573955 | C78: CFM56-5B | D78: 44532 | E78: 45889 | G78: =(E78-D78)/365.25 | H78: 6012 | I78: 19700 | J78: =(I78-H78)/G78 | K78: 8535
B79: 575103 | C79: CFM56-5B | D79: 40640 | E79: 42780 | G79: =(E79-D79)/365.25 | H79: 11660 | I79: 18830 | J79: =(I79-H79)/G79 | K79: 2788
B80: 575114 | C80: CFM56-5B | D80: 44517 | E80: 45316 | G80: =(E80-D80)/365.25 | H80: 28811 | I80: 30707 | J80: =(I80-H80)/G80 | K80: 1637
B81: 575115 | C81: CFM56-5B | D81: 41687 | E81: 44670 | G81: =(E81-D81)/365.25 | H81: 18385 | I81: 27508 | J81: =(I81-H81)/G81 | K81: 1995
B82: 575124 | C82: CFM56-5B | D82: 43845 | E82: 44877 | G82: =(E82-D82)/365.25 | H82: 28421 | I82: 32229 | J82: =(I82-H82)/G82 | K82: 2228
... B101: 645326 | C101: CFM56-5B | D101: 43275 | E101: 45017 | G101: =(E101-D101)/365.25 | H101: 7879 | I101: 12286 | J101: =(I101-H101)/G101 | K101: 2416
B102: 645460 | C102: CFM56-5B | D102: 41766 | E102: 45225 | G102: =(E102-D102)/365.25 | H102: 2101 | I102: 19367 | J102: =(I102-H102)/G102
B103: 645506 | C103: CFM56-5B | D103: 43462 | E103: 45197 | G103: =(E103-D103)/365.25 | H103: 8140 | I103: 13271 | J103: =(I103-H103)/G103 | K103: 2417
B104: 645656 | C104: CFM56-5B | D104: 44768 | E104: 45414 | G104: =(E104-D104)/365.25 | H104: 13055 | I104: 15481 | J104: =(I104-H104)/G104 | K104: 2205
B105: 697927 | C105: CFM56-5B | D105: 41299 | E105: 46249 | G105: =(E105-D105)/365.25 | H105: 6815 | I105: 28452 | J105: =(I105-H105)/G105
B106: 697977 | C106: CFM56-5B | D106: 44985 | E106: 46176 | G106: =(E106-D106)/365.25 | H106: 22016 | I106: 27985 | J106: =(I106-H106)/G106 | K106: 2322
B107: 699102 | C107: CFM56-5B | D107: 42841 | E107: 43906 | G107: =(E107-D107)/365.25 | H107: 17568 | I107: 23144 | J107: =(I107-H107)/G107 | K107: 2074
B108: 699467 | C108: CFM56-5B | D108: 44502 | E108: 45768 | G108: =(E108-D108)/365.25 | H108: 24191 | I108: 31663 | J108: =(I108-H108)/G108 | K108: 2318
B109: 699474 | C109: CFM56-5B | D109: 41796 | E109: 44192 | G109: =(E109-D109)/365.25 | H109: 11751 | I109: 24740 | J109: =(I109-H109)/G109
B110: 699485 | C110: CFM56-5B | D110: 44562 | E110: 45907 | G110: =(E110-D110)/365.25 | H110: 25036 | I110: 31660 | J110: =(I110-H110)/G110 | K110: 1821
B111: 699532 | C111: CFM56-5B | D111: 43709 | E111: 44384 | G111: =(E111-D111)/365.25 | H111: 13611 | I111: 15413 | J111: =(I111-H111)/G111 | K111: 1739
B112: 699543 | C112: CFM56-5B | D112: 44293 | E112: 45564 | G112: =(E112-D112)/365.25 | H112: 24999 | I112: 30096 | J112: =(I112-H112)/G112 | K112: 1886
B113: 699611 | C113: CFM56-5B | D113: 42410 | E113: 46219 | G113: =(E113-D113)/365.25 | H113: 8800 | I113: 22651 | J113: =(I113-H113)/G113 | K113: 2243
B114: 699661 | C114: CFM56-5B | D114: 45327 | E114: 45976 | G114: =(E114-D114)/365.25 | H114: 22391 | I114: 26757 | J114: =(I114-H114)/G114 | K114: 2751
B115: 699685 | C115: CFM56-5B | D115: 43653 | E115: 45308 | G115: =(E115-D115)/365.25 | H115: 12743 | I115: 18623 | J115: =(I115-H115)/G115 | K115: 2176
B116: 699715 | C116: CFM56-5B | D116: 45400 | E116: 45880 | G116: =(E116-D116)/365.25 | H116: 29309 | I116: 32273 | J116: =(I116-H116)/G116 | K116: 2542
B117: 699716 | C117: CFM56-5B | D117: 45177 | E117: 46138 | G117: =(E117-D117)/365.25 | H117: 25541 | I117: 30138 | J117: =(I117-H117)/G117 | K117: 3286
B118: 699774 | C118: CFM56-5B | D118: 44220 | E118: 44636 | G118: =(E118-D118)/365.25 | H118: 18006 | I118: 18526 | J118: =(I118-H118)/G118 | K118: 1200
B119: 699851 | C119: CFM56-5B | D119: 43032 | E119: 45538 | G119: =(E119-D119)/365.25 | H119: 11057 | I119: 17970 | J119: =(I119-H119)/G119 | K119: 1941
B120: 699865 | C120: CFM56-5B | D120: 44132 | E120: 45952 | G120: =(E120-D120)/365.25 | H120: 23030 | I120: 28925 | J120: =(I120-H120)/G120 | K120: 2118
B121: 699868 | C121: CFM56-5B | D121: 41977 | E121: 45738 | G121: =(E121-D121)/365.25 | H121: 11731 | I121: 27405 | J121: =(I121-H121)/G121 | K121: 1565
... B221: 962907 | C221: CFM56-7B | D221: 45519 | E221: 45985 | G221: =(E221-D221)/365.25 | H221: 13300 | I221: 14036 | J221: =(I221-H221)/G221 | K221: 1192

Sheet SV Analysis
B1: FTAI Aviation
B2: Shop Visit Analysis
B4: Engine-level evidence (scraped records)
D5: All visits | E5: Major visits | F5: Time on wing | G5: Utilization -7B | H5: Utilization -5B
B6: Observations | D6: =COUNT('CFM56 Data'!G35:G48) | E6: =COUNT('CFM56 Data'!G52:G60) | F6: =COUNT('CFM56 Data'!G64:G67) | G6: =COUNTIF('CFM56 Data'!C71:C221,"CFM56-7B") | H6: =COUNTIF('CFM56 Data'!C71:C221,"CFM56-5B")
B7: Median years between visits / on wing | D7: =MEDIAN('CFM56 Data'!G35:G48) | E7: =MEDIAN('CFM56 Data'!G52:G60) | F7: =MEDIAN('CFM56 Data'!G64:G67)
B8: Average years | D8: =AVERAGE('CFM56 Data'!G35:G48) | E8: =AVERAGE('CFM56 Data'!G52:G60) | F8: =AVERAGE('CFM56 Data'!G64:G67)
B9: Median cycles between visits / on wing | D9: =MEDIAN('CFM56 Data'!H35:H48) | E9: =MEDIAN('CFM56 Data'!H52:H60) | F9: =MEDIAN('CFM56 Data'!H64:H67)
B10: Median cycles / year | F10: =MEDIAN('CFM56 Data'!H64:H67)/MEDIAN('CFM56 Data'!G64:G67) | G10: {=MEDIAN(IF('CFM56 Data'!C71:C221="CFM56-7B",'CFM56 Data'!J71:J221))} | H10: {=MEDIAN(IF('CFM56 Data'!C71:C221="CFM56-5B",'CFM56 Data'!J71:J221))}
B11: Implied annual shop-visit probability (1 / median years) | D11: =1/D7 | E11: =1/E7 | F11: =1/F7
B13: Shop visits by case
D14: FY25A | E14: FY26E | F14: FY27E | G14: FY28E | H14: FY29E | I14: FY30E | J14: FY31E
B15: Base | D15: ='CFM56 Data'!D6 | E15: ='CFM56 Data'!E6 | F15: ='CFM56 Data'!F6 | G15: ='CFM56 Data'!G6 | H15: ='CFM56 Data'!H6 | I15: ='CFM56 Data'!I6 | J15: ='CFM56 Data'!J6
B16: Bull | D16: =D15 | E16: =E15 | F16: 2550 | G16: 2500 | H16: 2400 | I16: 2300 | J16: 2200
B17: Bear | D17: =D15 | E17: =E15 | F17: 2300 | G17: 2300 | H17: =G17*0.94 | I17: =H17*0.94 | J17: =I17*0.94
B19: Year-end fleet by case (RPM basis)
D20: FY25A | E20: FY26E | F20: FY27E | G20: FY28E | H20: FY29E | I20: FY30E | J20: FY31E
B21: Bear -7B | D21: =RPM!$G$13 | E21: =D21*(1-Assumptions!F9) | F21: =E21*(1-Assumptions!K9) | G21: =F21*(1-Assumptions!L9) | H21: =G21*(1-Assumptions!M9) | I21: =H21*(1-Assumptions!N9) | J21: =I21*(1-Assumptions!O9)
B22: Bear -5B | D22: =RPM!$G$21 | E22: =D22*(1-Assumptions!F14) | F22: =E22*(1-Assumptions!K14) | G22: =F22*(1-Assumptions!L14) | H22: =G22*(1-Assumptions!M14) | I22: =H22*(1-Assumptions!N14) | J22: =I22*(1-Assumptions!O14)
B23: Bear total | D23: =D21+D22 | E23: =E21+E22 | F23: =F21+F22 | G23: =G21+G22 | H23: =H21+H22 | I23: =I21+I22 | J23: =J21+J22
B24: Base -7B | D24: =RPM!$G$13 | E24: =D24*(1-Assumptions!F10) | F24: =E24*(1-Assumptions!K10) | G24: =F24*(1-Assumptions!L10) | H24: =G24*(1-Assumptions!M10) | I24: =H24*(1-Assumptions!N10) | J24: =I24*(1-Assumptions!O10)
B25: Base -5B | D25: =RPM!$G$21 | E25: =D25*(1-Assumptions!F15) | F25: =E25*(1-Assumptions!K15) | G25: =F25*(1-Assumptions!L15) | H25: =G25*(1-Assumptions!M15) | I25: =H25*(1-Assumptions!N15) | J25: =I25*(1-Assumptions!O15)
B26: Base total | D26: =D24+D25 | E26: =E24+E25 | F26: =F24+F25 | G26: =G24+G25 | H26: =H24+H25 | I26: =I24+I25 | J26: =J24+J25
B27: Bull -7B | D27: =RPM!$G$13 | E27: =D27*(1-Assumptions!F11) | F27: =E27*(1-Assumptions!K11) | G27: =F27*(1-Assumptions!L11) | H27: =G27*(1-Assumptions!M11) | I27: =H27*(1-Assumptions!N11) | J27: =I27*(1-Assumptions!O11)
B28: Bull -5B | D28: =RPM!$G$21 | E28: =D28*(1-Assumptions!F16) | F28: =E28*(1-Assumptions!K16) | G28: =F28*(1-Assumptions!L16) | H28: =G28*(1-Assumptions!M16) | I28: =H28*(1-Assumptions!N16) | J28: =I28*(1-Assumptions!O16)
B29: Bull total | D29: =D27+D28 | E29: =E27+E28 | F29: =F27+F28 | G29: =G27+G28 | H29: =H27+H28 | I29: =I27+I28 | J29: =J27+J28
B31: Shop-visit rate
D32: FY25A | E32: FY26E | F32: FY27E | G32: FY28E | H32: FY29E | I32: FY30E | J32: FY31E
B33: Bear (visits / RPM fleet) | D33: =D17/D23 | E33: =E17/E23 | F33: =F17/F23 | G33: =G17/G23 | H33: =H17/H23 | I33: =I17/I23 | J33: =J17/J23
B34: Base (visits / RPM fleet) | D34: =D15/D26 | E34: =E15/E26 | F34: =F15/F26 | G34: =G15/G26 | H34: =H15/H26 | I34: =I15/I26 | J34: =J15/J26
B35: Bull (visits / RPM fleet) | D35: =D16/D29 | E35: =E16/E29 | F35: =F16/F29 | G35: =G16/G29 | H35: =H16/H29 | I35: =I16/I29 | J35: =J16/J29
B36: Base on GE installed fleet (19,000) | D36: =D15/'CFM56 Data'!D16 | E36: =E15/'CFM56 Data'!D16 | F36: =F15/'CFM56 Data'!D16 | G36: =G15/'CFM56 Data'!D16 | H36: =H15/'CFM56 Data'!D16 | I36: =I15/'CFM56 Data'!D16 | J36: =J15/'CFM56 Data'!D16
B37: Engine records: major visits | D37: =$E$11 | E37: =$E$11 | F37: =$E$11 | G37: =$E$11 | H37: =$E$11 | I37: =$E$11 | J37: =$E$11
B38: Engine records: all visits | D38: =$D$11 | E38: =$D$11 | F38: =$D$11 | G38: =$D$11 | H38: =$D$11 | I38: =$D$11 | J38: =$D$11
B40: Fleet visit history (cohort)
D41: FY25A | E41: FY26E | F41: FY27E | G41: FY28E | H41: FY29E | I41: FY30E
B42: Repeat-visit share | D42: ='CFM56 Data'!D28 | E42: ='CFM56 Data'!E28 | F42: ='CFM56 Data'!F28 | G42: ='CFM56 Data'!G28 | H42: ='CFM56 Data'!H28 | I42: ='CFM56 Data'!I28
B43: Broader-work share | D43: ='CFM56 Data'!D29 | E43: ='CFM56 Data'!E29 | F43: ='CFM56 Data'!F29 | G43: ='CFM56 Data'!G29 | H43: ='CFM56 Data'!H29 | I43: ='CFM56 Data'!I29
B44: Stock: 2+ prior visits | D44: ='CFM56 Data'!D30 | E44: ='CFM56 Data'!E30 | F44: ='CFM56 Data'!F30 | G44: ='CFM56 Data'!G30 | H44: ='CFM56 Data'!H30 | I44: ='CFM56 Data'!I30
B45: Stock: 0 prior visits | D45: ='CFM56 Data'!D31 | E45: ='CFM56 Data'!E31 | F45: ='CFM56 Data'!F31 | G45: ='CFM56 Data'!G31 | H45: ='CFM56 Data'!H31 | I45: ='CFM56 Data'!I31

Sheet Pricing Data
B1: FTAI Aviation
B2: CFM56 Repair Pricing
B4: Summary
B5: Family | C5: Period | D5: Matched | E5: Median change | F5: Average change | G5: Higher | H5: Lower | I5: Unchanged
B6: CFM56-5B | C6: 2024-2025 | D6: =COUNTIFS($B$31:$B$3434,"CFM56-5B",$C$31:$C$3434,"2024-2025") | E6: {=MEDIAN(IF(($B$31:$B$3434="CFM56-5B")*($C$31:$C$3434="2024-2025"),$J$31:$J$3434))} | F6: =AVERAGEIFS($J$31:$J$3434,$B$31:$B$3434,"CFM56-5B",$C$31:$C$3434,"2024-2025") | G6: =COUNTIFS($B$31:$B$3434,"CFM56-5B",$C$31:$C$3434,"2024-2025",$J$31:$J$3434,">0") | H6: =COUNTIFS($B$31:$B$3434,"CFM56-5B",$C$31:$C$3434,"2024-2025",$J$31:$J$3434,"<0") | I6: =COUNTIFS($B$31:$B$3434,"CFM56-5B",$C$31:$C$3434,"2024-2025",$J$31:$J$3434,0)
B7: CFM56-5B | C7: 2025-2026 | D7: =COUNTIFS($B$31:$B$3434,"CFM56-5B",$C$31:$C$3434,"2025-2026") | E7: {=MEDIAN(IF(($B$31:$B$3434="CFM56-5B")*($C$31:$C$3434="2025-2026"),$J$31:$J$3434))} | F7: =AVERAGEIFS($J$31:$J$3434,$B$31:$B$3434,"CFM56-5B",$C$31:$C$3434,"2025-2026") | G7: =COUNTIFS($B$31:$B$3434,"CFM56-5B",$C$31:$C$3434,"2025-2026",$J$31:$J$3434,">0") | H7: =COUNTIFS($B$31:$B$3434,"CFM56-5B",$C$31:$C$3434,"2025-2026",$J$31:$J$3434,"<0") | I7: =COUNTIFS($B$31:$B$3434,"CFM56-5B",$C$31:$C$3434,"2025-2026",$J$31:$J$3434,0)
B8: CFM56-7B | C8: 2025-2026 | D8: =COUNTIFS($B$31:$B$3434,"CFM56-7B",$C$31:$C$3434,"2025-2026") | E8: {=MEDIAN(IF(($B$31:$B$3434="CFM56-7B")*($C$31:$C$3434="2025-2026"),$J$31:$J$3434))} | F8: =AVERAGEIFS($J$31:$J$3434,$B$31:$B$3434,"CFM56-7B",$C$31:$C$3434,"2025-2026") | G8: =COUNTIFS($B$31:$B$3434,"CFM56-7B",$C$31:$C$3434,"2025-2026",$J$31:$J$3434,">0") | H8: =COUNTIFS($B$31:$B$3434,"CFM56-7B",$C$31:$C$3434,"2025-2026",$J$31:$J$3434,"<0") | I8: =COUNTIFS($B$31:$B$3434,"CFM56-7B",$C$31:$C$3434,"2025-2026",$J$31:$J$3434,0)
B10: Median change by part category
B11: Part category | D11: CFM56-5B | E11: CFM56-7B | F11: Packages
B12: Combustor | D12: {=IFERROR(MEDIAN(IF(($B$31:$B$3434="CFM56-5B")*($C$31:$C$3434="2025-2026")*($G$31:$G$3434="Combustor"),$J$31:$J$3434)),"")} | E12: {=IFERROR(MEDIAN(IF(($B$31:$B$3434="CFM56-7B")*($C$31:$C$3434="2025-2026")*($G$31:$G$3434="Combustor"),$J$31:$J$3434)),"")} | F12: =COUNTIFS($C$31:$C$3434,"2025-2026",$G$31:$G$3434,"Combustor")
B13: Compressor | D13: {=IFERROR(MEDIAN(IF(($B$31:$B$3434="CFM56-5B")*($C$31:$C$3434="2025-2026")*($G$31:$G$3434="Compressor"),$J$31:$J$3434)),"")} | E13: {=IFERROR(MEDIAN(IF(($B$31:$B$3434="CFM56-7B")*($C$31:$C$3434="2025-2026")*($G$31:$G$3434="Compressor"),$J$31:$J$3434)),"")} | F13: =COUNTIFS($C$31:$C$3434,"2025-2026",$G$31:$G$3434,"Compressor")
B14: Fan / booster | D14: {=IFERROR(MEDIAN(IF(($B$31:$B$3434="CFM56-5B")*($C$31:$C$3434="2025-2026")*($G$31:$G$3434="Fan / booster"),$J$31:$J$3434)),"")} | E14: {=IFERROR(MEDIAN(IF(($B$31:$B$3434="CFM56-7B")*($C$31:$C$3434="2025-2026")*($G$31:$G$3434="Fan / booster"),$J$31:$J$3434)),"")} | F14: =COUNTIFS($C$31:$C$3434,"2025-2026",$G$31:$G$3434,"Fan / booster")
B15: Fuel system | D15: {=IFERROR(MEDIAN(IF(($B$31:$B$3434="CFM56-5B")*($C$31:$C$3434="2025-2026")*($G$31:$G$3434="Fuel system"),$J$31:$J$3434)),"")} | E15: {=IFERROR(MEDIAN(IF(($B$31:$B$3434="CFM56-7B")*($C$31:$C$3434="2025-2026")*($G$31:$G$3434="Fuel system"),$J$31:$J$3434)),"")} | F15: =COUNTIFS($C$31:$C$3434,"2025-2026",$G$31:$G$3434,"Fuel system")
B16: Gearbox | D16: {=IFERROR(MEDIAN(IF(($B$31:$B$3434="CFM56-5B")*($C$31:$C$3434="2025-2026")*($G$31:$G$3434="Gearbox"),$J$31:$J$3434)),"")} | E16: {=IFERROR(MEDIAN(IF(($B$31:$B$3434="CFM56-7B")*($C$31:$C$3434="2025-2026")*($G$31:$G$3434="Gearbox"),$J$31:$J$3434)),"")} | F16: =COUNTIFS($C$31:$C$3434,"2025-2026",$G$31:$G$3434,"Gearbox")
B17: HPT / nozzle | D17: {=IFERROR(MEDIAN(IF(($B$31:$B$3434="CFM56-5B")*($C$31:$C$3434="2025-2026")*($G$31:$G$3434="HPT / nozzle"),$J$31:$J$3434)),"")} | E17: {=IFERROR(MEDIAN(IF(($B$31:$B$3434="CFM56-7B")*($C$31:$C$3434="2025-2026")*($G$31:$G$3434="HPT / nozzle"),$J$31:$J$3434)),"")} | F17: =COUNTIFS($C$31:$C$3434,"2025-2026",$G$31:$G$3434,"HPT / nozzle")
B18: LPT | D18: {=IFERROR(MEDIAN(IF(($B$31:$B$3434="CFM56-5B")*($C$31:$C$3434="2025-2026")*($G$31:$G$3434="LPT"),$J$31:$J$3434)),"")} | E18: {=IFERROR(MEDIAN(IF(($B$31:$B$3434="CFM56-7B")*($C$31:$C$3434="2025-2026")*($G$31:$G$3434="LPT"),$J$31:$J$3434)),"")} | F18: =COUNTIFS($C$31:$C$3434,"2025-2026",$G$31:$G$3434,"LPT")
B19: Other / assembly | D19: {=IFERROR(MEDIAN(IF(($B$31:$B$3434="CFM56-5B")*($C$31:$C$3434="2025-2026")*($G$31:$G$3434="Other / assembly"),$J$31:$J$3434)),"")} | E19: {=IFERROR(MEDIAN(IF(($B$31:$B$3434="CFM56-7B")*($C$31:$C$3434="2025-2026")*($G$31:$G$3434="Other / assembly"),$J$31:$J$3434)),"")} | F19: =COUNTIFS($C$31:$C$3434,"2025-2026",$G$31:$G$3434,"Other / assembly")
B21: Price-catalogue sources
B22: Source ID | C22: Family | D22: Year | E22: Edition | F22: Rows parsed | G22: Packages | I22: URL
B23: S1 | C23: CFM56-5B | D23: 2024 | E23: 45460 | F23: 1929 | G23: 1516 | I23: https://www.srtechnics.com/media/nwzlxnyn/cfm-5b-sr-technics-capabilities-price-catalogue-17062024.pdf
B24: S2 | C24: CFM56-5B | D24: 2025 | E24: 45751 | F24: 1877 | G24: 1473 | I24: https://www.srtechnics.com/media/fmiaxdl2/cfm-5b-sr-technics-capabilitiesprice-catalogue-04042025.pdf
B25: S3 | C25: CFM56-7B | D25: 2025 | E25: 45751 | F25: 1994 | G25: 1465 | I25: https://www.srtechnics.com/media/ixnkubbj/cfm-7b-sr-technics-capabilitiesprice-catalogue-04042025.pdf
B26: S4 | C26: CFM56-5B | D26: 2026 | E26: 46289 | F26: 1834 | G26: 1446 | I26: https://www.srtechnics.com/media/y4rpn3jg/cfm56-5b-sr-technics-capabilitiesprice-catalogue-24092026.pdf
B27: S5 | C27: CFM56-7B | D27: 2026 | E27: 46289 | F27: 1969 | G27: 1466 | I27: https://www.srtechnics.com/media/lgln23vl/cfm56-7b-sr-technics-capabilitiesprice-catalogue-24092026.pdf
B29: Matched packages
B30: Family | C30: Period | D30: Quotation ID | E30: ATA | F30: Package | G30: Part category | H30: Prior price ($) | I30: Later price ($) | J30: Change | K30: Prior pg | L30: Later pg | M30: Prior src | N30: Later src | O30: Listed MPN | P30: Facility
B31: CFM56-5B | C31: 2024-2025 | D31: 11542 | E31: 72-23-35 | F31: A | G31: Fan / booster | H31: 70 | I31: 140 | J31: =I31/H31-1 | K31: 34 | L31: 35 | M31: S1 | N31: S2 | O31: 301-792-202-0 | P31: SR Technics Switzerland
B32: CFM56-5B | C32: 2024-2025 | D32: 125452 | E32: 73-11-14 | F32: B | G32: Fuel system | H32: 660 | I32: 700 | J32: =I32/H32-1 | K32: 8 | L32: 8 | M32: S1 | N32: S2 | O32: 215788 | P32: SR Technics Switzerland
B33: CFM56-5B | C33: 2024-2025 | D33: 12552 | E33: 71-00-01 | F33: B | G33: Other / assembly | H33: 1010 | I33: 1075 | J33: =I33/H33-1 | K33: 38 | L33: 38 | M33: S1 | N33: S2 | O33: ALL450-001-0 | P33: SR Technics Switzerland
B34: CFM56-5B | C34: 2024-2025 | D34: 13451 | E34: 72-23-10 | F34: A | G34: Fan / booster | H34: 135 | I34: 145 | J34: =I34/H34-1 | K34: 38 | L34: 38 | M34: S1 | N34: S2 | O34: 301-566-807-0 | P34: SR Technics Switzerland
B35: CFM56-5B | C35: 2024-2025 | D35: 13459 | E35: 72-23-12 | F35: A | G35: Fan / booster | H35: 570 | I35: 605 | J35: =I35/H35-1 | K35: 38 | L35: 38 | M35: S1 | N35: S2 | O35: 301-417-104-0 | P35: SR Technics Switzerland
B36: CFM56-5B | C36: 2024-2025 | D36: 13471 | E36: 72-23-15 | F36: A | G36: Fan / booster | H36: 515 | I36: 550 | J36: =I36/H36-1 | K36: 5 | L36: 5 | M36: S1 | N36: S2 | O36: 337-100-804-0 | P36: SR Technics Switzerland
B37: CFM56-5B | C37: 2024-2025 | D37: 13471 | E37: 72-23-15 | F37: C | G37: Fan / booster | H37: 1105 | I37: 1175 | J37: =I37/H37-1 | K37: 5 | L37: 5 | M37: S1 | N37: S2 | O37: 337-100-804-0 | P37: SR Technics Switzerland
B38: CFM56-5B | C38: 2024-2025 | D38: 13471 | E38: 72-23-15 | F38: D | G38: Fan / booster | H38: 410 | I38: 435 | J38: =I38/H38-1 | K38: 5 | L38: 5 | M38: S1 | N38: S2 | O38: 337-100-804-0 | P38: SR Technics Switzerland
B39: CFM56-5B | C39: 2024-2025 | D39: 13473 | E39: 72-23-16 | F39: A | G39: Fan / booster | H39: 245 | I39: 260 | J39: =I39/H39-1 | K39: 38 | L39: 39 | M39: S1 | N39: S2 | O39: 336-053-701-0 | P39: SR Technics Switzerland
B40: CFM56-5B | C40: 2024-2025 | D40: 134895 | E40: 24-19-10 | F40: A | G40: Other / assembly | H40: 800 | I40: 850 | J40: =I40/H40-1 | K40: 42 | L40: 42 | M40: S1 | N40: S2 | O40: 740123 | P40: SR Technics Switzerland
B41: CFM56-5B | C41: 2024-2025 | D41: 135024 | E41: 71-22-07 | F41: C | G41: Other / assembly | H41: 2355 | I41: 2500 | J41: =I41/H41-1 | K41: 8 | L41: 8 | M41: S1 | N41: S2 | O41: 238-0230-15 | P41: SR Technics Switzerland
B42: CFM56-5B | C42: 2024-2025 | D42: 135024 | E42: 71-22-07 | F42: D | G42: Other / assembly | H42: 970 | I42: 1030 | J42: =I42/H42-1 | K42: 8 | L42: 8 | M42: S1 | N42: S2 | O42: 238-0230-15 | P42: SR Technics Switzerland
... B3434: CFM56-7B | C3434: 2025-2026 | D3434: 9941 | E3434: 72-23-31 | F3434: Y | G3434: Fan / booster | H3434: 1145 | I3434: 1215 | J3434: =I3434/H3434-1 | K3434: 7 | L3434: 6 | M3434: S3 | N3434: S5 | O3434: 340-059-917-0 | P3434: SR Technics Switzerland

Sheet Power outlook
B1: FTAI Aviation
B2: Power Build | H2: ='Power Market Assumptions'!K4
B3: (in GW, except where noted)
C5: 2026 | D5: 2027 | E5: 2028 | F5: 2029 | G5: 2030 | H5: 2031
B6: Power Market
A8: x | B8: Power Demand & Supply
B9: Reserve Shortfall | C9: =SUMIF('Regional model'!$C$6:$C$95,C$5,'Regional model'!$O$6:$O$95) | D9: =SUMIF('Regional model'!$C$6:$C$95,D$5,'Regional model'!$O$6:$O$95) | E9: =SUMIF('Regional model'!$C$6:$C$95,E$5,'Regional model'!$O$6:$O$95) | F9: =SUMIF('Regional model'!$C$6:$C$95,F$5,'Regional model'!$O$6:$O$95) | G9: =SUMIF('Regional model'!$C$6:$C$95,G$5,'Regional model'!$O$6:$O$95) | H9: =SUMIF('Regional model'!$C$6:$C$95,H$5,'Regional model'!$O$6:$O$95)
B10: Regions Below Requirement | C10: =COUNTIFS('Regional model'!$C$6:$C$95,C$5,'Regional model'!$O$6:$O$95,">0") | D10: =COUNTIFS('Regional model'!$C$6:$C$95,D$5,'Regional model'!$O$6:$O$95,">0") | E10: =COUNTIFS('Regional model'!$C$6:$C$95,E$5,'Regional model'!$O$6:$O$95,">0") | F10: =COUNTIFS('Regional model'!$C$6:$C$95,F$5,'Regional model'!$O$6:$O$95,">0") | G10: =COUNTIFS('Regional model'!$C$6:$C$95,G$5,'Regional model'!$O$6:$O$95,">0") | H10: =COUNTIFS('Regional model'!$C$6:$C$95,H$5,'Regional model'!$O$6:$O$95,">0")
B12: Tracked Planning Capacity | C12: =SUM('Power agreements'!R6:R72)/1000 | D12: =SUM('Power agreements'!S6:S72)/1000 | E12: =SUM('Power agreements'!T6:T72)/1000 | F12: =SUM('Power agreements'!U6:U72)/1000 | G12: =SUM('Power agreements'!V6:V72)/1000 | H12: =SUM('Power agreements'!W6:W72)/1000
B13: Incremental Capacity to NERC | C13: =SUMIF('Regional model'!$C$6:$C$95,C$5,'Regional model'!$M$6:$M$95)/1000 | D13: =SUMIF('Regional model'!$C$6:$C$95,D$5,'Regional model'!$M$6:$M$95)/1000 | E13: =SUMIF('Regional model'!$C$6:$C$95,E$5,'Regional model'!$M$6:$M$95)/1000 | F13: =SUMIF('Regional model'!$C$6:$C$95,F$5,'Regional model'!$M$6:$M$95)/1000 | G13: =SUMIF('Regional model'!$C$6:$C$95,G$5,'Regional model'!$M$6:$M$95)/1000 | H13: =SUMIF('Regional model'!$C$6:$C$95,H$5,'Regional model'!$M$6:$M$95)/1000
B14: US DC Energy Demand (TWh) | C14: ='Regional model'!C103 | D14: ='Regional model'!C104 | E14: ='Regional model'!C105 | F14: ='Regional model'!C106 | G14: ='Regional model'!C107 | H14: ='Regional model'!C108
A17: x | B17: Regional Reserve Shortfall
B19: MISO | C19: =SUMIFS('Regional model'!$O$6:$O$95,'Regional model'!$B$6:$B$95,$B19,'Regional model'!$C$6:$C$95,C$5) | D19: =SUMIFS('Regional model'!$O$6:$O$95,'Regional model'!$B$6:$B$95,$B19,'Regional model'!$C$6:$C$95,D$5) | E19: =SUMIFS('Regional model'!$O$6:$O$95,'Regional model'!$B$6:$B$95,$B19,'Regional model'!$C$6:$C$95,E$5) | F19: =SUMIFS('Regional model'!$O$6:$O$95,'Regional model'!$B$6:$B$95,$B19,'Regional model'!$C$6:$C$95,F$5) | G19: =SUMIFS('Regional model'!$O$6:$O$95,'Regional model'!$B$6:$B$95,$B19,'Regional model'!$C$6:$C$95,G$5) | H19: =SUMIFS('Regional model'!$O$6:$O$95,'Regional model'!$B$6:$B$95,$B19,'Regional model'!$C$6:$C$95,H$5)
B20: MRO-SPP | C20: =SUMIFS('Regional model'!$O$6:$O$95,'Regional model'!$B$6:$B$95,$B20,'Regional model'!$C$6:$C$95,C$5) | D20: =SUMIFS('Regional model'!$O$6:$O$95,'Regional model'!$B$6:$B$95,$B20,'Regional model'!$C$6:$C$95,D$5) | E20: =SUMIFS('Regional model'!$O$6:$O$95,'Regional model'!$B$6:$B$95,$B20,'Regional model'!$C$6:$C$95,E$5) | F20: =SUMIFS('Regional model'!$O$6:$O$95,'Regional model'!$B$6:$B$95,$B20,'Regional model'!$C$6:$C$95,F$5) | G20: =SUMIFS('Regional model'!$O$6:$O$95,'Regional model'!$B$6:$B$95,$B20,'Regional model'!$C$6:$C$95,G$5) | H20: =SUMIFS('Regional model'!$O$6:$O$95,'Regional model'!$B$6:$B$95,$B20,'Regional model'!$C$6:$C$95,H$5)
B21: NPCC-New England | C21: =SUMIFS('Regional model'!$O$6:$O$95,'Regional model'!$B$6:$B$95,$B21,'Regional model'!$C$6:$C$95,C$5) | D21: =SUMIFS('Regional model'!$O$6:$O$95,'Regional model'!$B$6:$B$95,$B21,'Regional model'!$C$6:$C$95,D$5) | E21: =SUMIFS('Regional model'!$O$6:$O$95,'Regional model'!$B$6:$B$95,$B21,'Regional model'!$C$6:$C$95,E$5) | F21: =SUMIFS('Regional model'!$O$6:$O$95,'Regional model'!$B$6:$B$95,$B21,'Regional model'!$C$6:$C$95,F$5) | G21: =SUMIFS('Regional model'!$O$6:$O$95,'Regional model'!$B$6:$B$95,$B21,'Regional model'!$C$6:$C$95,G$5) | H21: =SUMIFS('Regional model'!$O$6:$O$95,'Regional model'!$B$6:$B$95,$B21,'Regional model'!$C$6:$C$95,H$5)
B22: NPCC-New York | C22: =SUMIFS('Regional model'!$O$6:$O$95,'Regional model'!$B$6:$B$95,$B22,'Regional model'!$C$6:$C$95,C$5) | D22: =SUMIFS('Regional model'!$O$6:$O$95,'Regional model'!$B$6:$B$95,$B22,'Regional model'!$C$6:$C$95,D$5) | E22: =SUMIFS('Regional model'!$O$6:$O$95,'Regional model'!$B$6:$B$95,$B22,'Regional model'!$C$6:$C$95,E$5) | F22: =SUMIFS('Regional model'!$O$6:$O$95,'Regional model'!$B$6:$B$95,$B22,'Regional model'!$C$6:$C$95,F$5) | G22: =SUMIFS('Regional model'!$O$6:$O$95,'Regional model'!$B$6:$B$95,$B22,'Regional model'!$C$6:$C$95,G$5) | H22: =SUMIFS('Regional model'!$O$6:$O$95,'Regional model'!$B$6:$B$95,$B22,'Regional model'!$C$6:$C$95,H$5)
B23: PJM | C23: =SUMIFS('Regional model'!$O$6:$O$95,'Regional model'!$B$6:$B$95,$B23,'Regional model'!$C$6:$C$95,C$5) | D23: =SUMIFS('Regional model'!$O$6:$O$95,'Regional model'!$B$6:$B$95,$B23,'Regional model'!$C$6:$C$95,D$5) | E23: =SUMIFS('Regional model'!$O$6:$O$95,'Regional model'!$B$6:$B$95,$B23,'Regional model'!$C$6:$C$95,E$5) | F23: =SUMIFS('Regional model'!$O$6:$O$95,'Regional model'!$B$6:$B$95,$B23,'Regional model'!$C$6:$C$95,F$5) | G23: =SUMIFS('Regional model'!$O$6:$O$95,'Regional model'!$B$6:$B$95,$B23,'Regional model'!$C$6:$C$95,G$5) | H23: =SUMIFS('Regional model'!$O$6:$O$95,'Regional model'!$B$6:$B$95,$B23,'Regional model'!$C$6:$C$95,H$5)
B24: SERC-Central | C24: =SUMIFS('Regional model'!$O$6:$O$95,'Regional model'!$B$6:$B$95,$B24,'Regional model'!$C$6:$C$95,C$5) | D24: =SUMIFS('Regional model'!$O$6:$O$95,'Regional model'!$B$6:$B$95,$B24,'Regional model'!$C$6:$C$95,D$5) | E24: =SUMIFS('Regional model'!$O$6:$O$95,'Regional model'!$B$6:$B$95,$B24,'Regional model'!$C$6:$C$95,E$5) | F24: =SUMIFS('Regional model'!$O$6:$O$95,'Regional model'!$B$6:$B$95,$B24,'Regional model'!$C$6:$C$95,F$5) | G24: =SUMIFS('Regional model'!$O$6:$O$95,'Regional model'!$B$6:$B$95,$B24,'Regional model'!$C$6:$C$95,G$5) | H24: =SUMIFS('Regional model'!$O$6:$O$95,'Regional model'!$B$6:$B$95,$B24,'Regional model'!$C$6:$C$95,H$5)
B25: SERC-East | C25: =SUMIFS('Regional model'!$O$6:$O$95,'Regional model'!$B$6:$B$95,$B25,'Regional model'!$C$6:$C$95,C$5) | D25: =SUMIFS('Regional model'!$O$6:$O$95,'Regional model'!$B$6:$B$95,$B25,'Regional model'!$C$6:$C$95,D$5) | E25: =SUMIFS('Regional model'!$O$6:$O$95,'Regional model'!$B$6:$B$95,$B25,'Regional model'!$C$6:$C$95,E$5) | F25: =SUMIFS('Regional model'!$O$6:$O$95,'Regional model'!$B$6:$B$95,$B25,'Regional model'!$C$6:$C$95,F$5) | G25: =SUMIFS('Regional model'!$O$6:$O$95,'Regional model'!$B$6:$B$95,$B25,'Regional model'!$C$6:$C$95,G$5) | H25: =SUMIFS('Regional model'!$O$6:$O$95,'Regional model'!$B$6:$B$95,$B25,'Regional model'!$C$6:$C$95,H$5)
B26: SERC-Florida Peninsula | C26: =SUMIFS('Regional model'!$O$6:$O$95,'Regional model'!$B$6:$B$95,$B26,'Regional model'!$C$6:$C$95,C$5) | D26: =SUMIFS('Regional model'!$O$6:$O$95,'Regional model'!$B$6:$B$95,$B26,'Regional model'!$C$6:$C$95,D$5) | E26: =SUMIFS('Regional model'!$O$6:$O$95,'Regional model'!$B$6:$B$95,$B26,'Regional model'!$C$6:$C$95,E$5) | F26: =SUMIFS('Regional model'!$O$6:$O$95,'Regional model'!$B$6:$B$95,$B26,'Regional model'!$C$6:$C$95,F$5) | G26: =SUMIFS('Regional model'!$O$6:$O$95,'Regional model'!$B$6:$B$95,$B26,'Regional model'!$C$6:$C$95,G$5) | H26: =SUMIFS('Regional model'!$O$6:$O$95,'Regional model'!$B$6:$B$95,$B26,'Regional model'!$C$6:$C$95,H$5)
B27: SERC-Southeast | C27: =SUMIFS('Regional model'!$O$6:$O$95,'Regional model'!$B$6:$B$95,$B27,'Regional model'!$C$6:$C$95,C$5) | D27: =SUMIFS('Regional model'!$O$6:$O$95,'Regional model'!$B$6:$B$95,$B27,'Regional model'!$C$6:$C$95,D$5) | E27: =SUMIFS('Regional model'!$O$6:$O$95,'Regional model'!$B$6:$B$95,$B27,'Regional model'!$C$6:$C$95,E$5) | F27: =SUMIFS('Regional model'!$O$6:$O$95,'Regional model'!$B$6:$B$95,$B27,'Regional model'!$C$6:$C$95,F$5) | G27: =SUMIFS('Regional model'!$O$6:$O$95,'Regional model'!$B$6:$B$95,$B27,'Regional model'!$C$6:$C$95,G$5) | H27: =SUMIFS('Regional model'!$O$6:$O$95,'Regional model'!$B$6:$B$95,$B27,'Regional model'!$C$6:$C$95,H$5)
B28: Texas RE-ERCOT | C28: =SUMIFS('Regional model'!$O$6:$O$95,'Regional model'!$B$6:$B$95,$B28,'Regional model'!$C$6:$C$95,C$5) | D28: =SUMIFS('Regional model'!$O$6:$O$95,'Regional model'!$B$6:$B$95,$B28,'Regional model'!$C$6:$C$95,D$5) | E28: =SUMIFS('Regional model'!$O$6:$O$95,'Regional model'!$B$6:$B$95,$B28,'Regional model'!$C$6:$C$95,E$5) | F28: =SUMIFS('Regional model'!$O$6:$O$95,'Regional model'!$B$6:$B$95,$B28,'Regional model'!$C$6:$C$95,F$5) | G28: =SUMIFS('Regional model'!$O$6:$O$95,'Regional model'!$B$6:$B$95,$B28,'Regional model'!$C$6:$C$95,G$5) | H28: =SUMIFS('Regional model'!$O$6:$O$95,'Regional model'!$B$6:$B$95,$B28,'Regional model'!$C$6:$C$95,H$5)
B29: WECC-Basin | C29: =SUMIFS('Regional model'!$O$6:$O$95,'Regional model'!$B$6:$B$95,$B29,'Regional model'!$C$6:$C$95,C$5) | D29: =SUMIFS('Regional model'!$O$6:$O$95,'Regional model'!$B$6:$B$95,$B29,'Regional model'!$C$6:$C$95,D$5) | E29: =SUMIFS('Regional model'!$O$6:$O$95,'Regional model'!$B$6:$B$95,$B29,'Regional model'!$C$6:$C$95,E$5) | F29: =SUMIFS('Regional model'!$O$6:$O$95,'Regional model'!$B$6:$B$95,$B29,'Regional model'!$C$6:$C$95,F$5) | G29: =SUMIFS('Regional model'!$O$6:$O$95,'Regional model'!$B$6:$B$95,$B29,'Regional model'!$C$6:$C$95,G$5) | H29: =SUMIFS('Regional model'!$O$6:$O$95,'Regional model'!$B$6:$B$95,$B29,'Regional model'!$C$6:$C$95,H$5)
B30: WECC-California | C30: =SUMIFS('Regional model'!$O$6:$O$95,'Regional model'!$B$6:$B$95,$B30,'Regional model'!$C$6:$C$95,C$5) | D30: =SUMIFS('Regional model'!$O$6:$O$95,'Regional model'!$B$6:$B$95,$B30,'Regional model'!$C$6:$C$95,D$5) | E30: =SUMIFS('Regional model'!$O$6:$O$95,'Regional model'!$B$6:$B$95,$B30,'Regional model'!$C$6:$C$95,E$5) | F30: =SUMIFS('Regional model'!$O$6:$O$95,'Regional model'!$B$6:$B$95,$B30,'Regional model'!$C$6:$C$95,F$5) | G30: =SUMIFS('Regional model'!$O$6:$O$95,'Regional model'!$B$6:$B$95,$B30,'Regional model'!$C$6:$C$95,G$5) | H30: =SUMIFS('Regional model'!$O$6:$O$95,'Regional model'!$B$6:$B$95,$B30,'Regional model'!$C$6:$C$95,H$5)
... B33: WECC-Southwest | C33: =SUMIFS('Regional model'!$O$6:$O$95,'Regional model'!$B$6:$B$95,$B33,'Regional model'!$C$6:$C$95,C$5) | D33: =SUMIFS('Regional model'!$O$6:$O$95,'Regional model'!$B$6:$B$95,$B33,'Regional model'!$C$6:$C$95,D$5) | E33: =SUMIFS('Regional model'!$O$6:$O$95,'Regional model'!$B$6:$B$95,$B33,'Regional model'!$C$6:$C$95,E$5) | F33: =SUMIFS('Regional model'!$O$6:$O$95,'Regional model'!$B$6:$B$95,$B33,'Regional model'!$C$6:$C$95,F$5) | G33: =SUMIFS('Regional model'!$O$6:$O$95,'Regional model'!$B$6:$B$95,$B33,'Regional model'!$C$6:$C$95,G$5) | H33: =SUMIFS('Regional model'!$O$6:$O$95,'Regional model'!$B$6:$B$95,$B33,'Regional model'!$C$6:$C$95,H$5)
A36: x | B36: Capex & Power Contracts
B38: Big Four CY2026 Capex ($bn) | C38: ='Capex plans'!G15
B39: Capex / PPA Corr. — Levels | C39: =History!C21
B40: Capex / PPA Corr. — Log Growth | C40: =History!E21
B41: Build / PPA Corr. — Log Growth | C41: =History!E22
B42: Power Agreement Components | C42: 67
B43: US Corporate PPAs, 2025 (GW) | C43: =History!I16
B44: PJM Auction Gap, 2028–29 (GW) | C44: 6.831
A47: x | B47: FTAI Power — Illustrative
B49: Annual Nameplate Output | C49: ='Power Market Assumptions'!D64*'Power Market Assumptions'!D65/1000
B50: Load Served After Redundancy | C50: =C49/(1+'Power Market Assumptions'!D66)

Sheet Power Market Assumptions
B1: FTAI Aviation
B2: Power Assumptions
J3: Case | K3: 2
D4: 2026 | E4: 2027 | F4: 2028 | G4: 2029 | H4: 2030 | I4: 2031 | J4: Active | K4: =CHOOSE(K3,"Lower gap","Base","Higher gap")
B6: Power Assumptions — Demand & Supply
B8: Load growth / NERC forecast | D8: =CHOOSE($K$3,D9,D10,D11) | E8: =CHOOSE($K$3,E9,E10,E11) | F8: =CHOOSE($K$3,F9,F10,F11) | G8: =CHOOSE($K$3,G9,G10,G11) | H8: =CHOOSE($K$3,H9,H10,H11) | I8: =CHOOSE($K$3,I9,I10,I11)
B9: Lower gap | D9: 0.8 | E9: 0.8 | F9: 0.8 | G9: 0.8 | H9: 0.8 | I9: 0.8
B10: Base | D10: 1 | E10: 1 | F10: 1 | G10: 1 | H10: 1 | I10: 1
B11: Higher gap | D11: 1.15 | E11: 1.15 | F11: 1.15 | G11: 1.15 | H11: 1.15 | I11: 1.15
B13: Prospective capacity conversion | D13: =CHOOSE($K$3,D14,D15,D16) | E13: =CHOOSE($K$3,E14,E15,E16) | F13: =CHOOSE($K$3,F14,F15,F16) | G13: =CHOOSE($K$3,G14,G15,G16) | H13: =CHOOSE($K$3,H14,H15,H16) | I13: =CHOOSE($K$3,I14,I15,I16)
B14: Lower gap | D14: 0.25 | E14: 0.25 | F14: 0.25 | G14: 0.25 | H14: 0.25 | I14: 0.25
B15: Base | D15: 0 | E15: 0 | F15: 0 | G15: 0 | H15: 0 | I15: 0
B16: Higher gap | D16: 0 | E16: 0 | F16: 0 | G16: 0 | H16: 0 | I16: 0
B18: Tier 1 delivery haircut | D18: =CHOOSE($K$3,D19,D20,D21) | E18: =CHOOSE($K$3,E19,E20,E21) | F18: =CHOOSE($K$3,F19,F20,F21) | G18: =CHOOSE($K$3,G19,G20,G21) | H18: =CHOOSE($K$3,H19,H20,H21) | I18: =CHOOSE($K$3,I19,I20,I21)
B19: Lower gap | D19: 0 | E19: 0 | F19: 0 | G19: 0 | H19: 0 | I19: 0
B20: Base | D20: 0 | E20: 0 | F20: 0 | G20: 0 | H20: 0 | I20: 0
B21: Higher gap | D21: 0.2 | E21: 0.2 | F21: 0.2 | G21: 0.2 | H21: 0.2 | I21: 0.2
B23: Contract delay (years) | D23: =CHOOSE($K$3,D24,D25,D26) | E23: =CHOOSE($K$3,E24,E25,E26) | F23: =CHOOSE($K$3,F24,F25,F26) | G23: =CHOOSE($K$3,G24,G25,G26) | H23: =CHOOSE($K$3,H24,H25,H26) | I23: =CHOOSE($K$3,I24,I25,I26)
B24: Lower gap | D24: 0 | E24: 0 | F24: 0 | G24: 0 | H24: 0 | I24: 0
B25: Base | D25: 0 | E25: 0 | F25: 0 | G25: 0 | H25: 0 | I25: 0
B26: Higher gap | D26: 1 | E26: 1 | F26: 1 | G26: 1 | H26: 1 | I26: 1
B29: Data Center Energy
B31: 2024 energy (TWh) | D31: 192 | F31: S090
B32: 2028 energy (TWh) | D32: 464
B33: 2030 energy (TWh) | D33: 649
B34: 2030 low / high (TWh) | D34: 521 / 843
B35: 2031 energy growth | D35: 0.15
B36: Grid utilization | D36: 0.5
B39: Capacity Credit Assumptions
B40: Technology | D40: Credit
B41: Nuclear | D41: 0.9
B42: Advanced nuclear | D42: 0.9
B43: Geothermal | D43: 0.9
B44: Gas | D44: 0.9
B45: Fuel cells | D45: 0.85
B46: Hydro | D46: 0.9
B47: Solar | D47: 0.15
B48: Wind | D48: 0.15
B49: Mixed renewables | D49: 0.15
B50: Fusion | D50: 0
B51: Storage | D51: 0
B52: Demand response | D52: 0
B55: Capex Intensity Assumptions
B57: US share of global spend | D57: 0.65
B58: Incremental facility spend share | D58: 0.25
B59: Facility cost ($m / MW) | D59: 12
B62: FTAI Power Assumptions
B64: Annual output (units) | D64: 100 | F64: S091
B65: Output per unit (MW) | D65: 25
B66: Redundancy allowance | D66: 0.5 | F66: S092

Sheet Regional model
B1: FTAI Aviation
B2: Regional Capacity
B3: (MW, except shortfall in GW)
B4: Regional Forecast
B5: Region | C5: Year | D5: NERC Demand | E5: 2026 Demand | F5: Load Factor | G5: Adj. Demand | H5: Reserve (%) | I5: Req. Capacity | J5: Ant. Capacity | K5: Tier 1 Haircut | L5: Prospective | M5: Contracts | N5: Adj. Capacity | O5: Gap (GW)
B6: ='NERC source'!B6 | C6: ='NERC source'!C6 | D6: ='NERC source'!E6 | E6: =SUMIFS('NERC source'!$E$6:$E$95,'NERC source'!$B$6:$B$95,B6,'NERC source'!$C$6:$C$95,2026) | F6: ='Power Market Assumptions'!D$8 | G6: =E6+(D6-E6)*F6 | H6: ='NERC source'!H6 | I6: =G6*(1+H6) | J6: =D6*(1+'NERC source'!F6) | K6: ='NERC source'!I6*'Power Market Assumptions'!D$18 | L6: =D6*('NERC source'!G6-'NERC source'!F6)*'Power Market Assumptions'!D$13 | M6: =SUMIFS('Power agreements'!R$6:R$72,'Power agreements'!$F$6:$F$72,B6,'Power agreements'!$P$6:$P$72,1) | N6: =J6-K6+L6+M6 | O6: =MAX(0,I6-N6)/1000
B7: ='NERC source'!B7 | C7: ='NERC source'!C7 | D7: ='NERC source'!E7 | E7: =SUMIFS('NERC source'!$E$6:$E$95,'NERC source'!$B$6:$B$95,B7,'NERC source'!$C$6:$C$95,2026) | F7: ='Power Market Assumptions'!E$8 | G7: =E7+(D7-E7)*F7 | H7: ='NERC source'!H7 | I7: =G7*(1+H7) | J7: =D7*(1+'NERC source'!F7) | K7: ='NERC source'!I7*'Power Market Assumptions'!E$18 | L7: =D7*('NERC source'!G7-'NERC source'!F7)*'Power Market Assumptions'!E$13 | M7: =SUMIFS('Power agreements'!S$6:S$72,'Power agreements'!$F$6:$F$72,B7,'Power agreements'!$P$6:$P$72,1) | N7: =J7-K7+L7+M7 | O7: =MAX(0,I7-N7)/1000
B8: ='NERC source'!B8 | C8: ='NERC source'!C8 | D8: ='NERC source'!E8 | E8: =SUMIFS('NERC source'!$E$6:$E$95,'NERC source'!$B$6:$B$95,B8,'NERC source'!$C$6:$C$95,2026) | F8: ='Power Market Assumptions'!F$8 | G8: =E8+(D8-E8)*F8 | H8: ='NERC source'!H8 | I8: =G8*(1+H8) | J8: =D8*(1+'NERC source'!F8) | K8: ='NERC source'!I8*'Power Market Assumptions'!F$18 | L8: =D8*('NERC source'!G8-'NERC source'!F8)*'Power Market Assumptions'!F$13 | M8: =SUMIFS('Power agreements'!T$6:T$72,'Power agreements'!$F$6:$F$72,B8,'Power agreements'!$P$6:$P$72,1) | N8: =J8-K8+L8+M8 | O8: =MAX(0,I8-N8)/1000
B9: ='NERC source'!B9 | C9: ='NERC source'!C9 | D9: ='NERC source'!E9 | E9: =SUMIFS('NERC source'!$E$6:$E$95,'NERC source'!$B$6:$B$95,B9,'NERC source'!$C$6:$C$95,2026) | F9: ='Power Market Assumptions'!G$8 | G9: =E9+(D9-E9)*F9 | H9: ='NERC source'!H9 | I9: =G9*(1+H9) | J9: =D9*(1+'NERC source'!F9) | K9: ='NERC source'!I9*'Power Market Assumptions'!G$18 | L9: =D9*('NERC source'!G9-'NERC source'!F9)*'Power Market Assumptions'!G$13 | M9: =SUMIFS('Power agreements'!U$6:U$72,'Power agreements'!$F$6:$F$72,B9,'Power agreements'!$P$6:$P$72,1) | N9: =J9-K9+L9+M9 | O9: =MAX(0,I9-N9)/1000
B10: ='NERC source'!B10 | C10: ='NERC source'!C10 | D10: ='NERC source'!E10 | E10: =SUMIFS('NERC source'!$E$6:$E$95,'NERC source'!$B$6:$B$95,B10,'NERC source'!$C$6:$C$95,2026) | F10: ='Power Market Assumptions'!H$8 | G10: =E10+(D10-E10)*F10 | H10: ='NERC source'!H10 | I10: =G10*(1+H10) | J10: =D10*(1+'NERC source'!F10) | K10: ='NERC source'!I10*'Power Market Assumptions'!H$18 | L10: =D10*('NERC source'!G10-'NERC source'!F10)*'Power Market Assumptions'!H$13 | M10: =SUMIFS('Power agreements'!V$6:V$72,'Power agreements'!$F$6:$F$72,B10,'Power agreements'!$P$6:$P$72,1) | N10: =J10-K10+L10+M10 | O10: =MAX(0,I10-N10)/1000
B11: ='NERC source'!B11 | C11: ='NERC source'!C11 | D11: ='NERC source'!E11 | E11: =SUMIFS('NERC source'!$E$6:$E$95,'NERC source'!$B$6:$B$95,B11,'NERC source'!$C$6:$C$95,2026) | F11: ='Power Market Assumptions'!I$8 | G11: =E11+(D11-E11)*F11 | H11: ='NERC source'!H11 | I11: =G11*(1+H11) | J11: =D11*(1+'NERC source'!F11) | K11: ='NERC source'!I11*'Power Market Assumptions'!I$18 | L11: =D11*('NERC source'!G11-'NERC source'!F11)*'Power Market Assumptions'!I$13 | M11: =SUMIFS('Power agreements'!W$6:W$72,'Power agreements'!$F$6:$F$72,B11,'Power agreements'!$P$6:$P$72,1) | N11: =J11-K11+L11+M11 | O11: =MAX(0,I11-N11)/1000
B12: ='NERC source'!B12 | C12: ='NERC source'!C12 | D12: ='NERC source'!E12 | E12: =SUMIFS('NERC source'!$E$6:$E$95,'NERC source'!$B$6:$B$95,B12,'NERC source'!$C$6:$C$95,2026) | F12: ='Power Market Assumptions'!D$8 | G12: =E12+(D12-E12)*F12 | H12: ='NERC source'!H12 | I12: =G12*(1+H12) | J12: =D12*(1+'NERC source'!F12) | K12: ='NERC source'!I12*'Power Market Assumptions'!D$18 | L12: =D12*('NERC source'!G12-'NERC source'!F12)*'Power Market Assumptions'!D$13 | M12: =SUMIFS('Power agreements'!R$6:R$72,'Power agreements'!$F$6:$F$72,B12,'Power agreements'!$P$6:$P$72,1) | N12: =J12-K12+L12+M12 | O12: =MAX(0,I12-N12)/1000
B13: ='NERC source'!B13 | C13: ='NERC source'!C13 | D13: ='NERC source'!E13 | E13: =SUMIFS('NERC source'!$E$6:$E$95,'NERC source'!$B$6:$B$95,B13,'NERC source'!$C$6:$C$95,2026) | F13: ='Power Market Assumptions'!E$8 | G13: =E13+(D13-E13)*F13 | H13: ='NERC source'!H13 | I13: =G13*(1+H13) | J13: =D13*(1+'NERC source'!F13) | K13: ='NERC source'!I13*'Power Market Assumptions'!E$18 | L13: =D13*('NERC source'!G13-'NERC source'!F13)*'Power Market Assumptions'!E$13 | M13: =SUMIFS('Power agreements'!S$6:S$72,'Power agreements'!$F$6:$F$72,B13,'Power agreements'!$P$6:$P$72,1) | N13: =J13-K13+L13+M13 | O13: =MAX(0,I13-N13)/1000
B14: ='NERC source'!B14 | C14: ='NERC source'!C14 | D14: ='NERC source'!E14 | E14: =SUMIFS('NERC source'!$E$6:$E$95,'NERC source'!$B$6:$B$95,B14,'NERC source'!$C$6:$C$95,2026) | F14: ='Power Market Assumptions'!F$8 | G14: =E14+(D14-E14)*F14 | H14: ='NERC source'!H14 | I14: =G14*(1+H14) | J14: =D14*(1+'NERC source'!F14) | K14: ='NERC source'!I14*'Power Market Assumptions'!F$18 | L14: =D14*('NERC source'!G14-'NERC source'!F14)*'Power Market Assumptions'!F$13 | M14: =SUMIFS('Power agreements'!T$6:T$72,'Power agreements'!$F$6:$F$72,B14,'Power agreements'!$P$6:$P$72,1) | N14: =J14-K14+L14+M14 | O14: =MAX(0,I14-N14)/1000
B15: ='NERC source'!B15 | C15: ='NERC source'!C15 | D15: ='NERC source'!E15 | E15: =SUMIFS('NERC source'!$E$6:$E$95,'NERC source'!$B$6:$B$95,B15,'NERC source'!$C$6:$C$95,2026) | F15: ='Power Market Assumptions'!G$8 | G15: =E15+(D15-E15)*F15 | H15: ='NERC source'!H15 | I15: =G15*(1+H15) | J15: =D15*(1+'NERC source'!F15) | K15: ='NERC source'!I15*'Power Market Assumptions'!G$18 | L15: =D15*('NERC source'!G15-'NERC source'!F15)*'Power Market Assumptions'!G$13 | M15: =SUMIFS('Power agreements'!U$6:U$72,'Power agreements'!$F$6:$F$72,B15,'Power agreements'!$P$6:$P$72,1) | N15: =J15-K15+L15+M15 | O15: =MAX(0,I15-N15)/1000
B16: ='NERC source'!B16 | C16: ='NERC source'!C16 | D16: ='NERC source'!E16 | E16: =SUMIFS('NERC source'!$E$6:$E$95,'NERC source'!$B$6:$B$95,B16,'NERC source'!$C$6:$C$95,2026) | F16: ='Power Market Assumptions'!H$8 | G16: =E16+(D16-E16)*F16 | H16: ='NERC source'!H16 | I16: =G16*(1+H16) | J16: =D16*(1+'NERC source'!F16) | K16: ='NERC source'!I16*'Power Market Assumptions'!H$18 | L16: =D16*('NERC source'!G16-'NERC source'!F16)*'Power Market Assumptions'!H$13 | M16: =SUMIFS('Power agreements'!V$6:V$72,'Power agreements'!$F$6:$F$72,B16,'Power agreements'!$P$6:$P$72,1) | N16: =J16-K16+L16+M16 | O16: =MAX(0,I16-N16)/1000
B17: ='NERC source'!B17 | C17: ='NERC source'!C17 | D17: ='NERC source'!E17 | E17: =SUMIFS('NERC source'!$E$6:$E$95,'NERC source'!$B$6:$B$95,B17,'NERC source'!$C$6:$C$95,2026) | F17: ='Power Market Assumptions'!I$8 | G17: =E17+(D17-E17)*F17 | H17: ='NERC source'!H17 | I17: =G17*(1+H17) | J17: =D17*(1+'NERC source'!F17) | K17: ='NERC source'!I17*'Power Market Assumptions'!I$18 | L17: =D17*('NERC source'!G17-'NERC source'!F17)*'Power Market Assumptions'!I$13 | M17: =SUMIFS('Power agreements'!W$6:W$72,'Power agreements'!$F$6:$F$72,B17,'Power agreements'!$P$6:$P$72,1) | N17: =J17-K17+L17+M17 | O17: =MAX(0,I17-N17)/1000
B18: ='NERC source'!B18 | C18: ='NERC source'!C18 | D18: ='NERC source'!E18 | E18: =SUMIFS('NERC source'!$E$6:$E$95,'NERC source'!$B$6:$B$95,B18,'NERC source'!$C$6:$C$95,2026) | F18: ='Power Market Assumptions'!D$8 | G18: =E18+(D18-E18)*F18 | H18: ='NERC source'!H18 | I18: =G18*(1+H18) | J18: =D18*(1+'NERC source'!F18) | K18: ='NERC source'!I18*'Power Market Assumptions'!D$18 | L18: =D18*('NERC source'!G18-'NERC source'!F18)*'Power Market Assumptions'!D$13 | M18: =SUMIFS('Power agreements'!R$6:R$72,'Power agreements'!$F$6:$F$72,B18,'Power agreements'!$P$6:$P$72,1) | N18: =J18-K18+L18+M18 | O18: =MAX(0,I18-N18)/1000
B19: ='NERC source'!B19 | C19: ='NERC source'!C19 | D19: ='NERC source'!E19 | E19: =SUMIFS('NERC source'!$E$6:$E$95,'NERC source'!$B$6:$B$95,B19,'NERC source'!$C$6:$C$95,2026) | F19: ='Power Market Assumptions'!E$8 | G19: =E19+(D19-E19)*F19 | H19: ='NERC source'!H19 | I19: =G19*(1+H19) | J19: =D19*(1+'NERC source'!F19) | K19: ='NERC source'!I19*'Power Market Assumptions'!E$18 | L19: =D19*('NERC source'!G19-'NERC source'!F19)*'Power Market Assumptions'!E$13 | M19: =SUMIFS('Power agreements'!S$6:S$72,'Power agreements'!$F$6:$F$72,B19,'Power agreements'!$P$6:$P$72,1) | N19: =J19-K19+L19+M19 | O19: =MAX(0,I19-N19)/1000
B20: ='NERC source'!B20 | C20: ='NERC source'!C20 | D20: ='NERC source'!E20 | E20: =SUMIFS('NERC source'!$E$6:$E$95,'NERC source'!$B$6:$B$95,B20,'NERC source'!$C$6:$C$95,2026) | F20: ='Power Market Assumptions'!F$8 | G20: =E20+(D20-E20)*F20 | H20: ='NERC source'!H20 | I20: =G20*(1+H20) | J20: =D20*(1+'NERC source'!F20) | K20: ='NERC source'!I20*'Power Market Assumptions'!F$18 | L20: =D20*('NERC source'!G20-'NERC source'!F20)*'Power Market Assumptions'!F$13 | M20: =SUMIFS('Power agreements'!T$6:T$72,'Power agreements'!$F$6:$F$72,B20,'Power agreements'!$P$6:$P$72,1) | N20: =J20-K20+L20+M20 | O20: =MAX(0,I20-N20)/1000
B21: ='NERC source'!B21 | C21: ='NERC source'!C21 | D21: ='NERC source'!E21 | E21: =SUMIFS('NERC source'!$E$6:$E$95,'NERC source'!$B$6:$B$95,B21,'NERC source'!$C$6:$C$95,2026) | F21: ='Power Market Assumptions'!G$8 | G21: =E21+(D21-E21)*F21 | H21: ='NERC source'!H21 | I21: =G21*(1+H21) | J21: =D21*(1+'NERC source'!F21) | K21: ='NERC source'!I21*'Power Market Assumptions'!G$18 | L21: =D21*('NERC source'!G21-'NERC source'!F21)*'Power Market Assumptions'!G$13 | M21: =SUMIFS('Power agreements'!U$6:U$72,'Power agreements'!$F$6:$F$72,B21,'Power agreements'!$P$6:$P$72,1) | N21: =J21-K21+L21+M21 | O21: =MAX(0,I21-N21)/1000
B22: ='NERC source'!B22 | C22: ='NERC source'!C22 | D22: ='NERC source'!E22 | E22: =SUMIFS('NERC source'!$E$6:$E$95,'NERC source'!$B$6:$B$95,B22,'NERC source'!$C$6:$C$95,2026) | F22: ='Power Market Assumptions'!H$8 | G22: =E22+(D22-E22)*F22 | H22: ='NERC source'!H22 | I22: =G22*(1+H22) | J22: =D22*(1+'NERC source'!F22) | K22: ='NERC source'!I22*'Power Market Assumptions'!H$18 | L22: =D22*('NERC source'!G22-'NERC source'!F22)*'Power Market Assumptions'!H$13 | M22: =SUMIFS('Power agreements'!V$6:V$72,'Power agreements'!$F$6:$F$72,B22,'Power agreements'!$P$6:$P$72,1) | N22: =J22-K22+L22+M22 | O22: =MAX(0,I22-N22)/1000
B23: ='NERC source'!B23 | C23: ='NERC source'!C23 | D23: ='NERC source'!E23 | E23: =SUMIFS('NERC source'!$E$6:$E$95,'NERC source'!$B$6:$B$95,B23,'NERC source'!$C$6:$C$95,2026) | F23: ='Power Market Assumptions'!I$8 | G23: =E23+(D23-E23)*F23 | H23: ='NERC source'!H23 | I23: =G23*(1+H23) | J23: =D23*(1+'NERC source'!F23) | K23: ='NERC source'!I23*'Power Market Assumptions'!I$18 | L23: =D23*('NERC source'!G23-'NERC source'!F23)*'Power Market Assumptions'!I$13 | M23: =SUMIFS('Power agreements'!W$6:W$72,'Power agreements'!$F$6:$F$72,B23,'Power agreements'!$P$6:$P$72,1) | N23: =J23-K23+L23+M23 | O23: =MAX(0,I23-N23)/1000
B24: ='NERC source'!B24 | C24: ='NERC source'!C24 | D24: ='NERC source'!E24 | E24: =SUMIFS('NERC source'!$E$6:$E$95,'NERC source'!$B$6:$B$95,B24,'NERC source'!$C$6:$C$95,2026) | F24: ='Power Market Assumptions'!D$8 | G24: =E24+(D24-E24)*F24 | H24: ='NERC source'!H24 | I24: =G24*(1+H24) | J24: =D24*(1+'NERC source'!F24) | K24: ='NERC source'!I24*'Power Market Assumptions'!D$18 | L24: =D24*('NERC source'!G24-'NERC source'!F24)*'Power Market Assumptions'!D$13 | M24: =SUMIFS('Power agreements'!R$6:R$72,'Power agreements'!$F$6:$F$72,B24,'Power agreements'!$P$6:$P$72,1) | N24: =J24-K24+L24+M24 | O24: =MAX(0,I24-N24)/1000
B25: ='NERC source'!B25 | C25: ='NERC source'!C25 | D25: ='NERC source'!E25 | E25: =SUMIFS('NERC source'!$E$6:$E$95,'NERC source'!$B$6:$B$95,B25,'NERC source'!$C$6:$C$95,2026) | F25: ='Power Market Assumptions'!E$8 | G25: =E25+(D25-E25)*F25 | H25: ='NERC source'!H25 | I25: =G25*(1+H25) | J25: =D25*(1+'NERC source'!F25) | K25: ='NERC source'!I25*'Power Market Assumptions'!E$18 | L25: =D25*('NERC source'!G25-'NERC source'!F25)*'Power Market Assumptions'!E$13 | M25: =SUMIFS('Power agreements'!S$6:S$72,'Power agreements'!$F$6:$F$72,B25,'Power agreements'!$P$6:$P$72,1) | N25: =J25-K25+L25+M25 | O25: =MAX(0,I25-N25)/1000
B26: ='NERC source'!B26 | C26: ='NERC source'!C26 | D26: ='NERC source'!E26 | E26: =SUMIFS('NERC source'!$E$6:$E$95,'NERC source'!$B$6:$B$95,B26,'NERC source'!$C$6:$C$95,2026) | F26: ='Power Market Assumptions'!F$8 | G26: =E26+(D26-E26)*F26 | H26: ='NERC source'!H26 | I26: =G26*(1+H26) | J26: =D26*(1+'NERC source'!F26) | K26: ='NERC source'!I26*'Power Market Assumptions'!F$18 | L26: =D26*('NERC source'!G26-'NERC source'!F26)*'Power Market Assumptions'!F$13 | M26: =SUMIFS('Power agreements'!T$6:T$72,'Power agreements'!$F$6:$F$72,B26,'Power agreements'!$P$6:$P$72,1) | N26: =J26-K26+L26+M26 | O26: =MAX(0,I26-N26)/1000
B27: ='NERC source'!B27 | C27: ='NERC source'!C27 | D27: ='NERC source'!E27 | E27: =SUMIFS('NERC source'!$E$6:$E$95,'NERC source'!$B$6:$B$95,B27,'NERC source'!$C$6:$C$95,2026) | F27: ='Power Market Assumptions'!G$8 | G27: =E27+(D27-E27)*F27 | H27: ='NERC source'!H27 | I27: =G27*(1+H27) | J27: =D27*(1+'NERC source'!F27) | K27: ='NERC source'!I27*'Power Market Assumptions'!G$18 | L27: =D27*('NERC source'!G27-'NERC source'!F27)*'Power Market Assumptions'!G$13 | M27: =SUMIFS('Power agreements'!U$6:U$72,'Power agreements'!$F$6:$F$72,B27,'Power agreements'!$P$6:$P$72,1) | N27: =J27-K27+L27+M27 | O27: =MAX(0,I27-N27)/1000
B28: ='NERC source'!B28 | C28: ='NERC source'!C28 | D28: ='NERC source'!E28 | E28: =SUMIFS('NERC source'!$E$6:$E$95,'NERC source'!$B$6:$B$95,B28,'NERC source'!$C$6:$C$95,2026) | F28: ='Power Market Assumptions'!H$8 | G28: =E28+(D28-E28)*F28 | H28: ='NERC source'!H28 | I28: =G28*(1+H28) | J28: =D28*(1+'NERC source'!F28) | K28: ='NERC source'!I28*'Power Market Assumptions'!H$18 | L28: =D28*('NERC source'!G28-'NERC source'!F28)*'Power Market Assumptions'!H$13 | M28: =SUMIFS('Power agreements'!V$6:V$72,'Power agreements'!$F$6:$F$72,B28,'Power agreements'!$P$6:$P$72,1) | N28: =J28-K28+L28+M28 | O28: =MAX(0,I28-N28)/1000
B29: ='NERC source'!B29 | C29: ='NERC source'!C29 | D29: ='NERC source'!E29 | E29: =SUMIFS('NERC source'!$E$6:$E$95,'NERC source'!$B$6:$B$95,B29,'NERC source'!$C$6:$C$95,2026) | F29: ='Power Market Assumptions'!I$8 | G29: =E29+(D29-E29)*F29 | H29: ='NERC source'!H29 | I29: =G29*(1+H29) | J29: =D29*(1+'NERC source'!F29) | K29: ='NERC source'!I29*'Power Market Assumptions'!I$18 | L29: =D29*('NERC source'!G29-'NERC source'!F29)*'Power Market Assumptions'!I$13 | M29: =SUMIFS('Power agreements'!W$6:W$72,'Power agreements'!$F$6:$F$72,B29,'Power agreements'!$P$6:$P$72,1) | N29: =J29-K29+L29+M29 | O29: =MAX(0,I29-N29)/1000
B30: ='NERC source'!B30 | C30: ='NERC source'!C30 | D30: ='NERC source'!E30 | E30: =SUMIFS('NERC source'!$E$6:$E$95,'NERC source'!$B$6:$B$95,B30,'NERC source'!$C$6:$C$95,2026) | F30: ='Power Market Assumptions'!D$8 | G30: =E30+(D30-E30)*F30 | H30: ='NERC source'!H30 | I30: =G30*(1+H30) | J30: =D30*(1+'NERC source'!F30) | K30: ='NERC source'!I30*'Power Market Assumptions'!D$18 | L30: =D30*('NERC source'!G30-'NERC source'!F30)*'Power Market Assumptions'!D$13 | M30: =SUMIFS('Power agreements'!R$6:R$72,'Power agreements'!$F$6:$F$72,B30,'Power agreements'!$P$6:$P$72,1) | N30: =J30-K30+L30+M30 | O30: =MAX(0,I30-N30)/1000
B31: ='NERC source'!B31 | C31: ='NERC source'!C31 | D31: ='NERC source'!E31 | E31: =SUMIFS('NERC source'!$E$6:$E$95,'NERC source'!$B$6:$B$95,B31,'NERC source'!$C$6:$C$95,2026) | F31: ='Power Market Assumptions'!E$8 | G31: =E31+(D31-E31)*F31 | H31: ='NERC source'!H31 | I31: =G31*(1+H31) | J31: =D31*(1+'NERC source'!F31) | K31: ='NERC source'!I31*'Power Market Assumptions'!E$18 | L31: =D31*('NERC source'!G31-'NERC source'!F31)*'Power Market Assumptions'!E$13 | M31: =SUMIFS('Power agreements'!S$6:S$72,'Power agreements'!$F$6:$F$72,B31,'Power agreements'!$P$6:$P$72,1) | N31: =J31-K31+L31+M31 | O31: =MAX(0,I31-N31)/1000
B32: ='NERC source'!B32 | C32: ='NERC source'!C32 | D32: ='NERC source'!E32 | E32: =SUMIFS('NERC source'!$E$6:$E$95,'NERC source'!$B$6:$B$95,B32,'NERC source'!$C$6:$C$95,2026) | F32: ='Power Market Assumptions'!F$8 | G32: =E32+(D32-E32)*F32 | H32: ='NERC source'!H32 | I32: =G32*(1+H32) | J32: =D32*(1+'NERC source'!F32) | K32: ='NERC source'!I32*'Power Market Assumptions'!F$18 | L32: =D32*('NERC source'!G32-'NERC source'!F32)*'Power Market Assumptions'!F$13 | M32: =SUMIFS('Power agreements'!T$6:T$72,'Power agreements'!$F$6:$F$72,B32,'Power agreements'!$P$6:$P$72,1) | N32: =J32-K32+L32+M32 | O32: =MAX(0,I32-N32)/1000
B33: ='NERC source'!B33 | C33: ='NERC source'!C33 | D33: ='NERC source'!E33 | E33: =SUMIFS('NERC source'!$E$6:$E$95,'NERC source'!$B$6:$B$95,B33,'NERC source'!$C$6:$C$95,2026) | F33: ='Power Market Assumptions'!G$8 | G33: =E33+(D33-E33)*F33 | H33: ='NERC source'!H33 | I33: =G33*(1+H33) | J33: =D33*(1+'NERC source'!F33) | K33: ='NERC source'!I33*'Power Market Assumptions'!G$18 | L33: =D33*('NERC source'!G33-'NERC source'!F33)*'Power Market Assumptions'!G$13 | M33: =SUMIFS('Power agreements'!U$6:U$72,'Power agreements'!$F$6:$F$72,B33,'Power agreements'!$P$6:$P$72,1) | N33: =J33-K33+L33+M33 | O33: =MAX(0,I33-N33)/1000
B34: ='NERC source'!B34 | C34: ='NERC source'!C34 | D34: ='NERC source'!E34 | E34: =SUMIFS('NERC source'!$E$6:$E$95,'NERC source'!$B$6:$B$95,B34,'NERC source'!$C$6:$C$95,2026) | F34: ='Power Market Assumptions'!H$8 | G34: =E34+(D34-E34)*F34 | H34: ='NERC source'!H34 | I34: =G34*(1+H34) | J34: =D34*(1+'NERC source'!F34) | K34: ='NERC source'!I34*'Power Market Assumptions'!H$18 | L34: =D34*('NERC source'!G34-'NERC source'!F34)*'Power Market Assumptions'!H$13 | M34: =SUMIFS('Power agreements'!V$6:V$72,'Power agreements'!$F$6:$F$72,B34,'Power agreements'!$P$6:$P$72,1) | N34: =J34-K34+L34+M34 | O34: =MAX(0,I34-N34)/1000
B35: ='NERC source'!B35 | C35: ='NERC source'!C35 | D35: ='NERC source'!E35 | E35: =SUMIFS('NERC source'!$E$6:$E$95,'NERC source'!$B$6:$B$95,B35,'NERC source'!$C$6:$C$95,2026) | F35: ='Power Market Assumptions'!I$8 | G35: =E35+(D35-E35)*F35 | H35: ='NERC source'!H35 | I35: =G35*(1+H35) | J35: =D35*(1+'NERC source'!F35) | K35: ='NERC source'!I35*'Power Market Assumptions'!I$18 | L35: =D35*('NERC source'!G35-'NERC source'!F35)*'Power Market Assumptions'!I$13 | M35: =SUMIFS('Power agreements'!W$6:W$72,'Power agreements'!$F$6:$F$72,B35,'Power agreements'!$P$6:$P$72,1) | N35: =J35-K35+L35+M35 | O35: =MAX(0,I35-N35)/1000
B36: ='NERC source'!B36 | C36: ='NERC source'!C36 | D36: ='NERC source'!E36 | E36: =SUMIFS('NERC source'!$E$6:$E$95,'NERC source'!$B$6:$B$95,B36,'NERC source'!$C$6:$C$95,2026) | F36: ='Power Market Assumptions'!D$8 | G36: =E36+(D36-E36)*F36 | H36: ='NERC source'!H36 | I36: =G36*(1+H36) | J36: =D36*(1+'NERC source'!F36) | K36: ='NERC source'!I36*'Power Market Assumptions'!D$18 | L36: =D36*('NERC source'!G36-'NERC source'!F36)*'Power Market Assumptions'!D$13 | M36: =SUMIFS('Power agreements'!R$6:R$72,'Power agreements'!$F$6:$F$72,B36,'Power agreements'!$P$6:$P$72,1) | N36: =J36-K36+L36+M36 | O36: =MAX(0,I36-N36)/1000
B37: ='NERC source'!B37 | C37: ='NERC source'!C37 | D37: ='NERC source'!E37 | E37: =SUMIFS('NERC source'!$E$6:$E$95,'NERC source'!$B$6:$B$95,B37,'NERC source'!$C$6:$C$95,2026) | F37: ='Power Market Assumptions'!E$8 | G37: =E37+(D37-E37)*F37 | H37: ='NERC source'!H37 | I37: =G37*(1+H37) | J37: =D37*(1+'NERC source'!F37) | K37: ='NERC source'!I37*'Power Market Assumptions'!E$18 | L37: =D37*('NERC source'!G37-'NERC source'!F37)*'Power Market Assumptions'!E$13 | M37: =SUMIFS('Power agreements'!S$6:S$72,'Power agreements'!$F$6:$F$72,B37,'Power agreements'!$P$6:$P$72,1) | N37: =J37-K37+L37+M37 | O37: =MAX(0,I37-N37)/1000
B38: ='NERC source'!B38 | C38: ='NERC source'!C38 | D38: ='NERC source'!E38 | E38: =SUMIFS('NERC source'!$E$6:$E$95,'NERC source'!$B$6:$B$95,B38,'NERC source'!$C$6:$C$95,2026) | F38: ='Power Market Assumptions'!F$8 | G38: =E38+(D38-E38)*F38 | H38: ='NERC source'!H38 | I38: =G38*(1+H38) | J38: =D38*(1+'NERC source'!F38) | K38: ='NERC source'!I38*'Power Market Assumptions'!F$18 | L38: =D38*('NERC source'!G38-'NERC source'!F38)*'Power Market Assumptions'!F$13 | M38: =SUMIFS('Power agreements'!T$6:T$72,'Power agreements'!$F$6:$F$72,B38,'Power agreements'!$P$6:$P$72,1) | N38: =J38-K38+L38+M38 | O38: =MAX(0,I38-N38)/1000
B39: ='NERC source'!B39 | C39: ='NERC source'!C39 | D39: ='NERC source'!E39 | E39: =SUMIFS('NERC source'!$E$6:$E$95,'NERC source'!$B$6:$B$95,B39,'NERC source'!$C$6:$C$95,2026) | F39: ='Power Market Assumptions'!G$8 | G39: =E39+(D39-E39)*F39 | H39: ='NERC source'!H39 | I39: =G39*(1+H39) | J39: =D39*(1+'NERC source'!F39) | K39: ='NERC source'!I39*'Power Market Assumptions'!G$18 | L39: =D39*('NERC source'!G39-'NERC source'!F39)*'Power Market Assumptions'!G$13 | M39: =SUMIFS('Power agreements'!U$6:U$72,'Power agreements'!$F$6:$F$72,B39,'Power agreements'!$P$6:$P$72,1) | N39: =J39-K39+L39+M39 | O39: =MAX(0,I39-N39)/1000
B40: ='NERC source'!B40 | C40: ='NERC source'!C40 | D40: ='NERC source'!E40 | E40: =SUMIFS('NERC source'!$E$6:$E$95,'NERC source'!$B$6:$B$95,B40,'NERC source'!$C$6:$C$95,2026) | F40: ='Power Market Assumptions'!H$8 | G40: =E40+(D40-E40)*F40 | H40: ='NERC source'!H40 | I40: =G40*(1+H40) | J40: =D40*(1+'NERC source'!F40) | K40: ='NERC source'!I40*'Power Market Assumptions'!H$18 | L40: =D40*('NERC source'!G40-'NERC source'!F40)*'Power Market Assumptions'!H$13 | M40: =SUMIFS('Power agreements'!V$6:V$72,'Power agreements'!$F$6:$F$72,B40,'Power agreements'!$P$6:$P$72,1) | N40: =J40-K40+L40+M40 | O40: =MAX(0,I40-N40)/1000
B41: ='NERC source'!B41 | C41: ='NERC source'!C41 | D41: ='NERC source'!E41 | E41: =SUMIFS('NERC source'!$E$6:$E$95,'NERC source'!$B$6:$B$95,B41,'NERC source'!$C$6:$C$95,2026) | F41: ='Power Market Assumptions'!I$8 | G41: =E41+(D41-E41)*F41 | H41: ='NERC source'!H41 | I41: =G41*(1+H41) | J41: =D41*(1+'NERC source'!F41) | K41: ='NERC source'!I41*'Power Market Assumptions'!I$18 | L41: =D41*('NERC source'!G41-'NERC source'!F41)*'Power Market Assumptions'!I$13 | M41: =SUMIFS('Power agreements'!W$6:W$72,'Power agreements'!$F$6:$F$72,B41,'Power agreements'!$P$6:$P$72,1) | N41: =J41-K41+L41+M41 | O41: =MAX(0,I41-N41)/1000
B42: ='NERC source'!B42 | C42: ='NERC source'!C42 | D42: ='NERC source'!E42 | E42: =SUMIFS('NERC source'!$E$6:$E$95,'NERC source'!$B$6:$B$95,B42,'NERC source'!$C$6:$C$95,2026) | F42: ='Power Market Assumptions'!D$8 | G42: =E42+(D42-E42)*F42 | H42: ='NERC source'!H42 | I42: =G42*(1+H42) | J42: =D42*(1+'NERC source'!F42) | K42: ='NERC source'!I42*'Power Market Assumptions'!D$18 | L42: =D42*('NERC source'!G42-'NERC source'!F42)*'Power Market Assumptions'!D$13 | M42: =SUMIFS('Power agreements'!R$6:R$72,'Power agreements'!$F$6:$F$72,B42,'Power agreements'!$P$6:$P$72,1) | N42: =J42-K42+L42+M42 | O42: =MAX(0,I42-N42)/1000
B43: ='NERC source'!B43 | C43: ='NERC source'!C43 | D43: ='NERC source'!E43 | E43: =SUMIFS('NERC source'!$E$6:$E$95,'NERC source'!$B$6:$B$95,B43,'NERC source'!$C$6:$C$95,2026) | F43: ='Power Market Assumptions'!E$8 | G43: =E43+(D43-E43)*F43 | H43: ='NERC source'!H43 | I43: =G43*(1+H43) | J43: =D43*(1+'NERC source'!F43) | K43: ='NERC source'!I43*'Power Market Assumptions'!E$18 | L43: =D43*('NERC source'!G43-'NERC source'!F43)*'Power Market Assumptions'!E$13 | M43: =SUMIFS('Power agreements'!S$6:S$72,'Power agreements'!$F$6:$F$72,B43,'Power agreements'!$P$6:$P$72,1) | N43: =J43-K43+L43+M43 | O43: =MAX(0,I43-N43)/1000
B44: ='NERC source'!B44 | C44: ='NERC source'!C44 | D44: ='NERC source'!E44 | E44: =SUMIFS('NERC source'!$E$6:$E$95,'NERC source'!$B$6:$B$95,B44,'NERC source'!$C$6:$C$95,2026) | F44: ='Power Market Assumptions'!F$8 | G44: =E44+(D44-E44)*F44 | H44: ='NERC source'!H44 | I44: =G44*(1+H44) | J44: =D44*(1+'NERC source'!F44) | K44: ='NERC source'!I44*'Power Market Assumptions'!F$18 | L44: =D44*('NERC source'!G44-'NERC source'!F44)*'Power Market Assumptions'!F$13 | M44: =SUMIFS('Power agreements'!T$6:T$72,'Power agreements'!$F$6:$F$72,B44,'Power agreements'!$P$6:$P$72,1) | N44: =J44-K44+L44+M44 | O44: =MAX(0,I44-N44)/1000
B45: ='NERC source'!B45 | C45: ='NERC source'!C45 | D45: ='NERC source'!E45 | E45: =SUMIFS('NERC source'!$E$6:$E$95,'NERC source'!$B$6:$B$95,B45,'NERC source'!$C$6:$C$95,2026) | F45: ='Power Market Assumptions'!G$8 | G45: =E45+(D45-E45)*F45 | H45: ='NERC source'!H45 | I45: =G45*(1+H45) | J45: =D45*(1+'NERC source'!F45) | K45: ='NERC source'!I45*'Power Market Assumptions'!G$18 | L45: =D45*('NERC source'!G45-'NERC source'!F45)*'Power Market Assumptions'!G$13 | M45: =SUMIFS('Power agreements'!U$6:U$72,'Power agreements'!$F$6:$F$72,B45,'Power agreements'!$P$6:$P$72,1) | N45: =J45-K45+L45+M45 | O45: =MAX(0,I45-N45)/1000
B46: ='NERC source'!B46 | C46: ='NERC source'!C46 | D46: ='NERC source'!E46 | E46: =SUMIFS('NERC source'!$E$6:$E$95,'NERC source'!$B$6:$B$95,B46,'NERC source'!$C$6:$C$95,2026) | F46: ='Power Market Assumptions'!H$8 | G46: =E46+(D46-E46)*F46 | H46: ='NERC source'!H46 | I46: =G46*(1+H46) | J46: =D46*(1+'NERC source'!F46) | K46: ='NERC source'!I46*'Power Market Assumptions'!H$18 | L46: =D46*('NERC source'!G46-'NERC source'!F46)*'Power Market Assumptions'!H$13 | M46: =SUMIFS('Power agreements'!V$6:V$72,'Power agreements'!$F$6:$F$72,B46,'Power agreements'!$P$6:$P$72,1) | N46: =J46-K46+L46+M46 | O46: =MAX(0,I46-N46)/1000
B47: ='NERC source'!B47 | C47: ='NERC source'!C47 | D47: ='NERC source'!E47 | E47: =SUMIFS('NERC source'!$E$6:$E$95,'NERC source'!$B$6:$B$95,B47,'NERC source'!$C$6:$C$95,2026) | F47: ='Power Market Assumptions'!I$8 | G47: =E47+(D47-E47)*F47 | H47: ='NERC source'!H47 | I47: =G47*(1+H47) | J47: =D47*(1+'NERC source'!F47) | K47: ='NERC source'!I47*'Power Market Assumptions'!I$18 | L47: =D47*('NERC source'!G47-'NERC source'!F47)*'Power Market Assumptions'!I$13 | M47: =SUMIFS('Power agreements'!W$6:W$72,'Power agreements'!$F$6:$F$72,B47,'Power agreements'!$P$6:$P$72,1) | N47: =J47-K47+L47+M47 | O47: =MAX(0,I47-N47)/1000
B48: ='NERC source'!B48 | C48: ='NERC source'!C48 | D48: ='NERC source'!E48 | E48: =SUMIFS('NERC source'!$E$6:$E$95,'NERC source'!$B$6:$B$95,B48,'NERC source'!$C$6:$C$95,2026) | F48: ='Power Market Assumptions'!D$8 | G48: =E48+(D48-E48)*F48 | H48: ='NERC source'!H48 | I48: =G48*(1+H48) | J48: =D48*(1+'NERC source'!F48) | K48: ='NERC source'!I48*'Power Market Assumptions'!D$18 | L48: =D48*('NERC source'!G48-'NERC source'!F48)*'Power Market Assumptions'!D$13 | M48: =SUMIFS('Power agreements'!R$6:R$72,'Power agreements'!$F$6:$F$72,B48,'Power agreements'!$P$6:$P$72,1) | N48: =J48-K48+L48+M48 | O48: =MAX(0,I48-N48)/1000
B49: ='NERC source'!B49 | C49: ='NERC source'!C49 | D49: ='NERC source'!E49 | E49: =SUMIFS('NERC source'!$E$6:$E$95,'NERC source'!$B$6:$B$95,B49,'NERC source'!$C$6:$C$95,2026) | F49: ='Power Market Assumptions'!E$8 | G49: =E49+(D49-E49)*F49 | H49: ='NERC source'!H49 | I49: =G49*(1+H49) | J49: =D49*(1+'NERC source'!F49) | K49: ='NERC source'!I49*'Power Market Assumptions'!E$18 | L49: =D49*('NERC source'!G49-'NERC source'!F49)*'Power Market Assumptions'!E$13 | M49: =SUMIFS('Power agreements'!S$6:S$72,'Power agreements'!$F$6:$F$72,B49,'Power agreements'!$P$6:$P$72,1) | N49: =J49-K49+L49+M49 | O49: =MAX(0,I49-N49)/1000
B50: ='NERC source'!B50 | C50: ='NERC source'!C50 | D50: ='NERC source'!E50 | E50: =SUMIFS('NERC source'!$E$6:$E$95,'NERC source'!$B$6:$B$95,B50,'NERC source'!$C$6:$C$95,2026) | F50: ='Power Market Assumptions'!F$8 | G50: =E50+(D50-E50)*F50 | H50: ='NERC source'!H50 | I50: =G50*(1+H50) | J50: =D50*(1+'NERC source'!F50) | K50: ='NERC source'!I50*'Power Market Assumptions'!F$18 | L50: =D50*('NERC source'!G50-'NERC source'!F50)*'Power Market Assumptions'!F$13 | M50: =SUMIFS('Power agreements'!T$6:T$72,'Power agreements'!$F$6:$F$72,B50,'Power agreements'!$P$6:$P$72,1) | N50: =J50-K50+L50+M50 | O50: =MAX(0,I50-N50)/1000
B51: ='NERC source'!B51 | C51: ='NERC source'!C51 | D51: ='NERC source'!E51 | E51: =SUMIFS('NERC source'!$E$6:$E$95,'NERC source'!$B$6:$B$95,B51,'NERC source'!$C$6:$C$95,2026) | F51: ='Power Market Assumptions'!G$8 | G51: =E51+(D51-E51)*F51 | H51: ='NERC source'!H51 | I51: =G51*(1+H51) | J51: =D51*(1+'NERC source'!F51) | K51: ='NERC source'!I51*'Power Market Assumptions'!G$18 | L51: =D51*('NERC source'!G51-'NERC source'!F51)*'Power Market Assumptions'!G$13 | M51: =SUMIFS('Power agreements'!U$6:U$72,'Power agreements'!$F$6:$F$72,B51,'Power agreements'!$P$6:$P$72,1) | N51: =J51-K51+L51+M51 | O51: =MAX(0,I51-N51)/1000
B52: ='NERC source'!B52 | C52: ='NERC source'!C52 | D52: ='NERC source'!E52 | E52: =SUMIFS('NERC source'!$E$6:$E$95,'NERC source'!$B$6:$B$95,B52,'NERC source'!$C$6:$C$95,2026) | F52: ='Power Market Assumptions'!H$8 | G52: =E52+(D52-E52)*F52 | H52: ='NERC source'!H52 | I52: =G52*(1+H52) | J52: =D52*(1+'NERC source'!F52) | K52: ='NERC source'!I52*'Power Market Assumptions'!H$18 | L52: =D52*('NERC source'!G52-'NERC source'!F52)*'Power Market Assumptions'!H$13 | M52: =SUMIFS('Power agreements'!V$6:V$72,'Power agreements'!$F$6:$F$72,B52,'Power agreements'!$P$6:$P$72,1) | N52: =J52-K52+L52+M52 | O52: =MAX(0,I52-N52)/1000
B53: ='NERC source'!B53 | C53: ='NERC source'!C53 | D53: ='NERC source'!E53 | E53: =SUMIFS('NERC source'!$E$6:$E$95,'NERC source'!$B$6:$B$95,B53,'NERC source'!$C$6:$C$95,2026) | F53: ='Power Market Assumptions'!I$8 | G53: =E53+(D53-E53)*F53 | H53: ='NERC source'!H53 | I53: =G53*(1+H53) | J53: =D53*(1+'NERC source'!F53) | K53: ='NERC source'!I53*'Power Market Assumptions'!I$18 | L53: =D53*('NERC source'!G53-'NERC source'!F53)*'Power Market Assumptions'!I$13 | M53: =SUMIFS('Power agreements'!W$6:W$72,'Power agreements'!$F$6:$F$72,B53,'Power agreements'!$P$6:$P$72,1) | N53: =J53-K53+L53+M53 | O53: =MAX(0,I53-N53)/1000
B54: ='NERC source'!B54 | C54: ='NERC source'!C54 | D54: ='NERC source'!E54 | E54: =SUMIFS('NERC source'!$E$6:$E$95,'NERC source'!$B$6:$B$95,B54,'NERC source'!$C$6:$C$95,2026) | F54: ='Power Market Assumptions'!D$8 | G54: =E54+(D54-E54)*F54 | H54: ='NERC source'!H54 | I54: =G54*(1+H54) | J54: =D54*(1+'NERC source'!F54) | K54: ='NERC source'!I54*'Power Market Assumptions'!D$18 | L54: =D54*('NERC source'!G54-'NERC source'!F54)*'Power Market Assumptions'!D$13 | M54: =SUMIFS('Power agreements'!R$6:R$72,'Power agreements'!$F$6:$F$72,B54,'Power agreements'!$P$6:$P$72,1) | N54: =J54-K54+L54+M54 | O54: =MAX(0,I54-N54)/1000
B55: ='NERC source'!B55 | C55: ='NERC source'!C55 | D55: ='NERC source'!E55 | E55: =SUMIFS('NERC source'!$E$6:$E$95,'NERC source'!$B$6:$B$95,B55,'NERC source'!$C$6:$C$95,2026) | F55: ='Power Market Assumptions'!E$8 | G55: =E55+(D55-E55)*F55 | H55: ='NERC source'!H55 | I55: =G55*(1+H55) | J55: =D55*(1+'NERC source'!F55) | K55: ='NERC source'!I55*'Power Market Assumptions'!E$18 | L55: =D55*('NERC source'!G55-'NERC source'!F55)*'Power Market Assumptions'!E$13 | M55: =SUMIFS('Power agreements'!S$6:S$72,'Power agreements'!$F$6:$F$72,B55,'Power agreements'!$P$6:$P$72,1) | N55: =J55-K55+L55+M55 | O55: =MAX(0,I55-N55)/1000
B56: ='NERC source'!B56 | C56: ='NERC source'!C56 | D56: ='NERC source'!E56 | E56: =SUMIFS('NERC source'!$E$6:$E$95,'NERC source'!$B$6:$B$95,B56,'NERC source'!$C$6:$C$95,2026) | F56: ='Power Market Assumptions'!F$8 | G56: =E56+(D56-E56)*F56 | H56: ='NERC source'!H56 | I56: =G56*(1+H56) | J56: =D56*(1+'NERC source'!F56) | K56: ='NERC source'!I56*'Power Market Assumptions'!F$18 | L56: =D56*('NERC source'!G56-'NERC source'!F56)*'Power Market Assumptions'!F$13 | M56: =SUMIFS('Power agreements'!T$6:T$72,'Power agreements'!$F$6:$F$72,B56,'Power agreements'!$P$6:$P$72,1) | N56: =J56-K56+L56+M56 | O56: =MAX(0,I56-N56)/1000
B57: ='NERC source'!B57 | C57: ='NERC source'!C57 | D57: ='NERC source'!E57 | E57: =SUMIFS('NERC source'!$E$6:$E$95,'NERC source'!$B$6:$B$95,B57,'NERC source'!$C$6:$C$95,2026) | F57: ='Power Market Assumptions'!G$8 | G57: =E57+(D57-E57)*F57 | H57: ='NERC source'!H57 | I57: =G57*(1+H57) | J57: =D57*(1+'NERC source'!F57) | K57: ='NERC source'!I57*'Power Market Assumptions'!G$18 | L57: =D57*('NERC source'!G57-'NERC source'!F57)*'Power Market Assumptions'!G$13 | M57: =SUMIFS('Power agreements'!U$6:U$72,'Power agreements'!$F$6:$F$72,B57,'Power agreements'!$P$6:$P$72,1) | N57: =J57-K57+L57+M57 | O57: =MAX(0,I57-N57)/1000
B58: ='NERC source'!B58 | C58: ='NERC source'!C58 | D58: ='NERC source'!E58 | E58: =SUMIFS('NERC source'!$E$6:$E$95,'NERC source'!$B$6:$B$95,B58,'NERC source'!$C$6:$C$95,2026) | F58: ='Power Market Assumptions'!H$8 | G58: =E58+(D58-E58)*F58 | H58: ='NERC source'!H58 | I58: =G58*(1+H58) | J58: =D58*(1+'NERC source'!F58) | K58: ='NERC source'!I58*'Power Market Assumptions'!H$18 | L58: =D58*('NERC source'!G58-'NERC source'!F58)*'Power Market Assumptions'!H$13 | M58: =SUMIFS('Power agreements'!V$6:V$72,'Power agreements'!$F$6:$F$72,B58,'Power agreements'!$P$6:$P$72,1) | N58: =J58-K58+L58+M58 | O58: =MAX(0,I58-N58)/1000
B59: ='NERC source'!B59 | C59: ='NERC source'!C59 | D59: ='NERC source'!E59 | E59: =SUMIFS('NERC source'!$E$6:$E$95,'NERC source'!$B$6:$B$95,B59,'NERC source'!$C$6:$C$95,2026) | F59: ='Power Market Assumptions'!I$8 | G59: =E59+(D59-E59)*F59 | H59: ='NERC source'!H59 | I59: =G59*(1+H59) | J59: =D59*(1+'NERC source'!F59) | K59: ='NERC source'!I59*'Power Market Assumptions'!I$18 | L59: =D59*('NERC source'!G59-'NERC source'!F59)*'Power Market Assumptions'!I$13 | M59: =SUMIFS('Power agreements'!W$6:W$72,'Power agreements'!$F$6:$F$72,B59,'Power agreements'!$P$6:$P$72,1) | N59: =J59-K59+L59+M59 | O59: =MAX(0,I59-N59)/1000
B60: ='NERC source'!B60 | C60: ='NERC source'!C60 | D60: ='NERC source'!E60 | E60: =SUMIFS('NERC source'!$E$6:$E$95,'NERC source'!$B$6:$B$95,B60,'NERC source'!$C$6:$C$95,2026) | F60: ='Power Market Assumptions'!D$8 | G60: =E60+(D60-E60)*F60 | H60: ='NERC source'!H60 | I60: =G60*(1+H60) | J60: =D60*(1+'NERC source'!F60) | K60: ='NERC source'!I60*'Power Market Assumptions'!D$18 | L60: =D60*('NERC source'!G60-'NERC source'!F60)*'Power Market Assumptions'!D$13 | M60: =SUMIFS('Power agreements'!R$6:R$72,'Power agreements'!$F$6:$F$72,B60,'Power agreements'!$P$6:$P$72,1) | N60: =J60-K60+L60+M60 | O60: =MAX(0,I60-N60)/1000
B61: ='NERC source'!B61 | C61: ='NERC source'!C61 | D61: ='NERC source'!E61 | E61: =SUMIFS('NERC source'!$E$6:$E$95,'NERC source'!$B$6:$B$95,B61,'NERC source'!$C$6:$C$95,2026) | F61: ='Power Market Assumptions'!E$8 | G61: =E61+(D61-E61)*F61 | H61: ='NERC source'!H61 | I61: =G61*(1+H61) | J61: =D61*(1+'NERC source'!F61) | K61: ='NERC source'!I61*'Power Market Assumptions'!E$18 | L61: =D61*('NERC source'!G61-'NERC source'!F61)*'Power Market Assumptions'!E$13 | M61: =SUMIFS('Power agreements'!S$6:S$72,'Power agreements'!$F$6:$F$72,B61,'Power agreements'!$P$6:$P$72,1) | N61: =J61-K61+L61+M61 | O61: =MAX(0,I61-N61)/1000
B62: ='NERC source'!B62 | C62: ='NERC source'!C62 | D62: ='NERC source'!E62 | E62: =SUMIFS('NERC source'!$E$6:$E$95,'NERC source'!$B$6:$B$95,B62,'NERC source'!$C$6:$C$95,2026) | F62: ='Power Market Assumptions'!F$8 | G62: =E62+(D62-E62)*F62 | H62: ='NERC source'!H62 | I62: =G62*(1+H62) | J62: =D62*(1+'NERC source'!F62) | K62: ='NERC source'!I62*'Power Market Assumptions'!F$18 | L62: =D62*('NERC source'!G62-'NERC source'!F62)*'Power Market Assumptions'!F$13 | M62: =SUMIFS('Power agreements'!T$6:T$72,'Power agreements'!$F$6:$F$72,B62,'Power agreements'!$P$6:$P$72,1) | N62: =J62-K62+L62+M62 | O62: =MAX(0,I62-N62)/1000
B63: ='NERC source'!B63 | C63: ='NERC source'!C63 | D63: ='NERC source'!E63 | E63: =SUMIFS('NERC source'!$E$6:$E$95,'NERC source'!$B$6:$B$95,B63,'NERC source'!$C$6:$C$95,2026) | F63: ='Power Market Assumptions'!G$8 | G63: =E63+(D63-E63)*F63 | H63: ='NERC source'!H63 | I63: =G63*(1+H63) | J63: =D63*(1+'NERC source'!F63) | K63: ='NERC source'!I63*'Power Market Assumptions'!G$18 | L63: =D63*('NERC source'!G63-'NERC source'!F63)*'Power Market Assumptions'!G$13 | M63: =SUMIFS('Power agreements'!U$6:U$72,'Power agreements'!$F$6:$F$72,B63,'Power agreements'!$P$6:$P$72,1) | N63: =J63-K63+L63+M63 | O63: =MAX(0,I63-N63)/1000
B64: ='NERC source'!B64 | C64: ='NERC source'!C64 | D64: ='NERC source'!E64 | E64: =SUMIFS('NERC source'!$E$6:$E$95,'NERC source'!$B$6:$B$95,B64,'NERC source'!$C$6:$C$95,2026) | F64: ='Power Market Assumptions'!H$8 | G64: =E64+(D64-E64)*F64 | H64: ='NERC source'!H64 | I64: =G64*(1+H64) | J64: =D64*(1+'NERC source'!F64) | K64: ='NERC source'!I64*'Power Market Assumptions'!H$18 | L64: =D64*('NERC source'!G64-'NERC source'!F64)*'Power Market Assumptions'!H$13 | M64: =SUMIFS('Power agreements'!V$6:V$72,'Power agreements'!$F$6:$F$72,B64,'Power agreements'!$P$6:$P$72,1) | N64: =J64-K64+L64+M64 | O64: =MAX(0,I64-N64)/1000
B65: ='NERC source'!B65 | C65: ='NERC source'!C65 | D65: ='NERC source'!E65 | E65: =SUMIFS('NERC source'!$E$6:$E$95,'NERC source'!$B$6:$B$95,B65,'NERC source'!$C$6:$C$95,2026) | F65: ='Power Market Assumptions'!I$8 | G65: =E65+(D65-E65)*F65 | H65: ='NERC source'!H65 | I65: =G65*(1+H65) | J65: =D65*(1+'NERC source'!F65) | K65: ='NERC source'!I65*'Power Market Assumptions'!I$18 | L65: =D65*('NERC source'!G65-'NERC source'!F65)*'Power Market Assumptions'!I$13 | M65: =SUMIFS('Power agreements'!W$6:W$72,'Power agreements'!$F$6:$F$72,B65,'Power agreements'!$P$6:$P$72,1) | N65: =J65-K65+L65+M65 | O65: =MAX(0,I65-N65)/1000
B66: ='NERC source'!B66 | C66: ='NERC source'!C66 | D66: ='NERC source'!E66 | E66: =SUMIFS('NERC source'!$E$6:$E$95,'NERC source'!$B$6:$B$95,B66,'NERC source'!$C$6:$C$95,2026) | F66: ='Power Market Assumptions'!D$8 | G66: =E66+(D66-E66)*F66 | H66: ='NERC source'!H66 | I66: =G66*(1+H66) | J66: =D66*(1+'NERC source'!F66) | K66: ='NERC source'!I66*'Power Market Assumptions'!D$18 | L66: =D66*('NERC source'!G66-'NERC source'!F66)*'Power Market Assumptions'!D$13 | M66: =SUMIFS('Power agreements'!R$6:R$72,'Power agreements'!$F$6:$F$72,B66,'Power agreements'!$P$6:$P$72,1) | N66: =J66-K66+L66+M66 | O66: =MAX(0,I66-N66)/1000
B67: ='NERC source'!B67 | C67: ='NERC source'!C67 | D67: ='NERC source'!E67 | E67: =SUMIFS('NERC source'!$E$6:$E$95,'NERC source'!$B$6:$B$95,B67,'NERC source'!$C$6:$C$95,2026) | F67: ='Power Market Assumptions'!E$8 | G67: =E67+(D67-E67)*F67 | H67: ='NERC source'!H67 | I67: =G67*(1+H67) | J67: =D67*(1+'NERC source'!F67) | K67: ='NERC source'!I67*'Power Market Assumptions'!E$18 | L67: =D67*('NERC source'!G67-'NERC source'!F67)*'Power Market Assumptions'!E$13 | M67: =SUMIFS('Power agreements'!S$6:S$72,'Power agreements'!$F$6:$F$72,B67,'Power agreements'!$P$6:$P$72,1) | N67: =J67-K67+L67+M67 | O67: =MAX(0,I67-N67)/1000
B68: ='NERC source'!B68 | C68: ='NERC source'!C68 | D68: ='NERC source'!E68 | E68: =SUMIFS('NERC source'!$E$6:$E$95,'NERC source'!$B$6:$B$95,B68,'NERC source'!$C$6:$C$95,2026) | F68: ='Power Market Assumptions'!F$8 | G68: =E68+(D68-E68)*F68 | H68: ='NERC source'!H68 | I68: =G68*(1+H68) | J68: =D68*(1+'NERC source'!F68) | K68: ='NERC source'!I68*'Power Market Assumptions'!F$18 | L68: =D68*('NERC source'!G68-'NERC source'!F68)*'Power Market Assumptions'!F$13 | M68: =SUMIFS('Power agreements'!T$6:T$72,'Power agreements'!$F$6:$F$72,B68,'Power agreements'!$P$6:$P$72,1) | N68: =J68-K68+L68+M68 | O68: =MAX(0,I68-N68)/1000
B69: ='NERC source'!B69 | C69: ='NERC source'!C69 | D69: ='NERC source'!E69 | E69: =SUMIFS('NERC source'!$E$6:$E$95,'NERC source'!$B$6:$B$95,B69,'NERC source'!$C$6:$C$95,2026) | F69: ='Power Market Assumptions'!G$8 | G69: =E69+(D69-E69)*F69 | H69: ='NERC source'!H69 | I69: =G69*(1+H69) | J69: =D69*(1+'NERC source'!F69) | K69: ='NERC source'!I69*'Power Market Assumptions'!G$18 | L69: =D69*('NERC source'!G69-'NERC source'!F69)*'Power Market Assumptions'!G$13 | M69: =SUMIFS('Power agreements'!U$6:U$72,'Power agreements'!$F$6:$F$72,B69,'Power agreements'!$P$6:$P$72,1) | N69: =J69-K69+L69+M69 | O69: =MAX(0,I69-N69)/1000
B70: ='NERC source'!B70 | C70: ='NERC source'!C70 | D70: ='NERC source'!E70 | E70: =SUMIFS('NERC source'!$E$6:$E$95,'NERC source'!$B$6:$B$95,B70,'NERC source'!$C$6:$C$95,2026) | F70: ='Power Market Assumptions'!H$8 | G70: =E70+(D70-E70)*F70 | H70: ='NERC source'!H70 | I70: =G70*(1+H70) | J70: =D70*(1+'NERC source'!F70) | K70: ='NERC source'!I70*'Power Market Assumptions'!H$18 | L70: =D70*('NERC source'!G70-'NERC source'!F70)*'Power Market Assumptions'!H$13 | M70: =SUMIFS('Power agreements'!V$6:V$72,'Power agreements'!$F$6:$F$72,B70,'Power agreements'!$P$6:$P$72,1) | N70: =J70-K70+L70+M70 | O70: =MAX(0,I70-N70)/1000
B71: ='NERC source'!B71 | C71: ='NERC source'!C71 | D71: ='NERC source'!E71 | E71: =SUMIFS('NERC source'!$E$6:$E$95,'NERC source'!$B$6:$B$95,B71,'NERC source'!$C$6:$C$95,2026) | F71: ='Power Market Assumptions'!I$8 | G71: =E71+(D71-E71)*F71 | H71: ='NERC source'!H71 | I71: =G71*(1+H71) | J71: =D71*(1+'NERC source'!F71) | K71: ='NERC source'!I71*'Power Market Assumptions'!I$18 | L71: =D71*('NERC source'!G71-'NERC source'!F71)*'Power Market Assumptions'!I$13 | M71: =SUMIFS('Power agreements'!W$6:W$72,'Power agreements'!$F$6:$F$72,B71,'Power agreements'!$P$6:$P$72,1) | N71: =J71-K71+L71+M71 | O71: =MAX(0,I71-N71)/1000
B72: ='NERC source'!B72 | C72: ='NERC source'!C72 | D72: ='NERC source'!E72 | E72: =SUMIFS('NERC source'!$E$6:$E$95,'NERC source'!$B$6:$B$95,B72,'NERC source'!$C$6:$C$95,2026) | F72: ='Power Market Assumptions'!D$8 | G72: =E72+(D72-E72)*F72 | H72: ='NERC source'!H72 | I72: =G72*(1+H72) | J72: =D72*(1+'NERC source'!F72) | K72: ='NERC source'!I72*'Power Market Assumptions'!D$18 | L72: =D72*('NERC source'!G72-'NERC source'!F72)*'Power Market Assumptions'!D$13 | M72: =SUMIFS('Power agreements'!R$6:R$72,'Power agreements'!$F$6:$F$72,B72,'Power agreements'!$P$6:$P$72,1) | N72: =J72-K72+L72+M72 | O72: =MAX(0,I72-N72)/1000
B73: ='NERC source'!B73 | C73: ='NERC source'!C73 | D73: ='NERC source'!E73 | E73: =SUMIFS('NERC source'!$E$6:$E$95,'NERC source'!$B$6:$B$95,B73,'NERC source'!$C$6:$C$95,2026) | F73: ='Power Market Assumptions'!E$8 | G73: =E73+(D73-E73)*F73 | H73: ='NERC source'!H73 | I73: =G73*(1+H73) | J73: =D73*(1+'NERC source'!F73) | K73: ='NERC source'!I73*'Power Market Assumptions'!E$18 | L73: =D73*('NERC source'!G73-'NERC source'!F73)*'Power Market Assumptions'!E$13 | M73: =SUMIFS('Power agreements'!S$6:S$72,'Power agreements'!$F$6:$F$72,B73,'Power agreements'!$P$6:$P$72,1) | N73: =J73-K73+L73+M73 | O73: =MAX(0,I73-N73)/1000
B74: ='NERC source'!B74 | C74: ='NERC source'!C74 | D74: ='NERC source'!E74 | E74: =SUMIFS('NERC source'!$E$6:$E$95,'NERC source'!$B$6:$B$95,B74,'NERC source'!$C$6:$C$95,2026) | F74: ='Power Market Assumptions'!F$8 | G74: =E74+(D74-E74)*F74 | H74: ='NERC source'!H74 | I74: =G74*(1+H74) | J74: =D74*(1+'NERC source'!F74) | K74: ='NERC source'!I74*'Power Market Assumptions'!F$18 | L74: =D74*('NERC source'!G74-'NERC source'!F74)*'Power Market Assumptions'!F$13 | M74: =SUMIFS('Power agreements'!T$6:T$72,'Power agreements'!$F$6:$F$72,B74,'Power agreements'!$P$6:$P$72,1) | N74: =J74-K74+L74+M74 | O74: =MAX(0,I74-N74)/1000
B75: ='NERC source'!B75 | C75: ='NERC source'!C75 | D75: ='NERC source'!E75 | E75: =SUMIFS('NERC source'!$E$6:$E$95,'NERC source'!$B$6:$B$95,B75,'NERC source'!$C$6:$C$95,2026) | F75: ='Power Market Assumptions'!G$8 | G75: =E75+(D75-E75)*F75 | H75: ='NERC source'!H75 | I75: =G75*(1+H75) | J75: =D75*(1+'NERC source'!F75) | K75: ='NERC source'!I75*'Power Market Assumptions'!G$18 | L75: =D75*('NERC source'!G75-'NERC source'!F75)*'Power Market Assumptions'!G$13 | M75: =SUMIFS('Power agreements'!U$6:U$72,'Power agreements'!$F$6:$F$72,B75,'Power agreements'!$P$6:$P$72,1) | N75: =J75-K75+L75+M75 | O75: =MAX(0,I75-N75)/1000
B76: ='NERC source'!B76 | C76: ='NERC source'!C76 | D76: ='NERC source'!E76 | E76: =SUMIFS('NERC source'!$E$6:$E$95,'NERC source'!$B$6:$B$95,B76,'NERC source'!$C$6:$C$95,2026) | F76: ='Power Market Assumptions'!H$8 | G76: =E76+(D76-E76)*F76 | H76: ='NERC source'!H76 | I76: =G76*(1+H76) | J76: =D76*(1+'NERC source'!F76) | K76: ='NERC source'!I76*'Power Market Assumptions'!H$18 | L76: =D76*('NERC source'!G76-'NERC source'!F76)*'Power Market Assumptions'!H$13 | M76: =SUMIFS('Power agreements'!V$6:V$72,'Power agreements'!$F$6:$F$72,B76,'Power agreements'!$P$6:$P$72,1) | N76: =J76-K76+L76+M76 | O76: =MAX(0,I76-N76)/1000
B77: ='NERC source'!B77 | C77: ='NERC source'!C77 | D77: ='NERC source'!E77 | E77: =SUMIFS('NERC source'!$E$6:$E$95,'NERC source'!$B$6:$B$95,B77,'NERC source'!$C$6:$C$95,2026) | F77: ='Power Market Assumptions'!I$8 | G77: =E77+(D77-E77)*F77 | H77: ='NERC source'!H77 | I77: =G77*(1+H77) | J77: =D77*(1+'NERC source'!F77) | K77: ='NERC source'!I77*'Power Market Assumptions'!I$18 | L77: =D77*('NERC source'!G77-'NERC source'!F77)*'Power Market Assumptions'!I$13 | M77: =SUMIFS('Power agreements'!W$6:W$72,'Power agreements'!$F$6:$F$72,B77,'Power agreements'!$P$6:$P$72,1) | N77: =J77-K77+L77+M77 | O77: =MAX(0,I77-N77)/1000
B78: ='NERC source'!B78 | C78: ='NERC source'!C78 | D78: ='NERC source'!E78 | E78: =SUMIFS('NERC source'!$E$6:$E$95,'NERC source'!$B$6:$B$95,B78,'NERC source'!$C$6:$C$95,2026) | F78: ='Power Market Assumptions'!D$8 | G78: =E78+(D78-E78)*F78 | H78: ='NERC source'!H78 | I78: =G78*(1+H78) | J78: =D78*(1+'NERC source'!F78) | K78: ='NERC source'!I78*'Power Market Assumptions'!D$18 | L78: =D78*('NERC source'!G78-'NERC source'!F78)*'Power Market Assumptions'!D$13 | M78: =SUMIFS('Power agreements'!R$6:R$72,'Power agreements'!$F$6:$F$72,B78,'Power agreements'!$P$6:$P$72,1) | N78: =J78-K78+L78+M78 | O78: =MAX(0,I78-N78)/1000
B79: ='NERC source'!B79 | C79: ='NERC source'!C79 | D79: ='NERC source'!E79 | E79: =SUMIFS('NERC source'!$E$6:$E$95,'NERC source'!$B$6:$B$95,B79,'NERC source'!$C$6:$C$95,2026) | F79: ='Power Market Assumptions'!E$8 | G79: =E79+(D79-E79)*F79 | H79: ='NERC source'!H79 | I79: =G79*(1+H79) | J79: =D79*(1+'NERC source'!F79) | K79: ='NERC source'!I79*'Power Market Assumptions'!E$18 | L79: =D79*('NERC source'!G79-'NERC source'!F79)*'Power Market Assumptions'!E$13 | M79: =SUMIFS('Power agreements'!S$6:S$72,'Power agreements'!$F$6:$F$72,B79,'Power agreements'!$P$6:$P$72,1) | N79: =J79-K79+L79+M79 | O79: =MAX(0,I79-N79)/1000
B80: ='NERC source'!B80 | C80: ='NERC source'!C80 | D80: ='NERC source'!E80 | E80: =SUMIFS('NERC source'!$E$6:$E$95,'NERC source'!$B$6:$B$95,B80,'NERC source'!$C$6:$C$95,2026) | F80: ='Power Market Assumptions'!F$8 | G80: =E80+(D80-E80)*F80 | H80: ='NERC source'!H80 | I80: =G80*(1+H80) | J80: =D80*(1+'NERC source'!F80) | K80: ='NERC source'!I80*'Power Market Assumptions'!F$18 | L80: =D80*('NERC source'!G80-'NERC source'!F80)*'Power Market Assumptions'!F$13 | M80: =SUMIFS('Power agreements'!T$6:T$72,'Power agreements'!$F$6:$F$72,B80,'Power agreements'!$P$6:$P$72,1) | N80: =J80-K80+L80+M80 | O80: =MAX(0,I80-N80)/1000
B81: ='NERC source'!B81 | C81: ='NERC source'!C81 | D81: ='NERC source'!E81 | E81: =SUMIFS('NERC source'!$E$6:$E$95,'NERC source'!$B$6:$B$95,B81,'NERC source'!$C$6:$C$95,2026) | F81: ='Power Market Assumptions'!G$8 | G81: =E81+(D81-E81)*F81 | H81: ='NERC source'!H81 | I81: =G81*(1+H81) | J81: =D81*(1+'NERC source'!F81) | K81: ='NERC source'!I81*'Power Market Assumptions'!G$18 | L81: =D81*('NERC source'!G81-'NERC source'!F81)*'Power Market Assumptions'!G$13 | M81: =SUMIFS('Power agreements'!U$6:U$72,'Power agreements'!$F$6:$F$72,B81,'Power agreements'!$P$6:$P$72,1) | N81: =J81-K81+L81+M81 | O81: =MAX(0,I81-N81)/1000
B82: ='NERC source'!B82 | C82: ='NERC source'!C82 | D82: ='NERC source'!E82 | E82: =SUMIFS('NERC source'!$E$6:$E$95,'NERC source'!$B$6:$B$95,B82,'NERC source'!$C$6:$C$95,2026) | F82: ='Power Market Assumptions'!H$8 | G82: =E82+(D82-E82)*F82 | H82: ='NERC source'!H82 | I82: =G82*(1+H82) | J82: =D82*(1+'NERC source'!F82) | K82: ='NERC source'!I82*'Power Market Assumptions'!H$18 | L82: =D82*('NERC source'!G82-'NERC source'!F82)*'Power Market Assumptions'!H$13 | M82: =SUMIFS('Power agreements'!V$6:V$72,'Power agreements'!$F$6:$F$72,B82,'Power agreements'!$P$6:$P$72,1) | N82: =J82-K82+L82+M82 | O82: =MAX(0,I82-N82)/1000
B83: ='NERC source'!B83 | C83: ='NERC source'!C83 | D83: ='NERC source'!E83 | E83: =SUMIFS('NERC source'!$E$6:$E$95,'NERC source'!$B$6:$B$95,B83,'NERC source'!$C$6:$C$95,2026) | F83: ='Power Market Assumptions'!I$8 | G83: =E83+(D83-E83)*F83 | H83: ='NERC source'!H83 | I83: =G83*(1+H83) | J83: =D83*(1+'NERC source'!F83) | K83: ='NERC source'!I83*'Power Market Assumptions'!I$18 | L83: =D83*('NERC source'!G83-'NERC source'!F83)*'Power Market Assumptions'!I$13 | M83: =SUMIFS('Power agreements'!W$6:W$72,'Power agreements'!$F$6:$F$72,B83,'Power agreements'!$P$6:$P$72,1) | N83: =J83-K83+L83+M83 | O83: =MAX(0,I83-N83)/1000
B84: ='NERC source'!B84 | C84: ='NERC source'!C84 | D84: ='NERC source'!E84 | E84: =SUMIFS('NERC source'!$E$6:$E$95,'NERC source'!$B$6:$B$95,B84,'NERC source'!$C$6:$C$95,2026) | F84: ='Power Market Assumptions'!D$8 | G84: =E84+(D84-E84)*F84 | H84: ='NERC source'!H84 | I84: =G84*(1+H84) | J84: =D84*(1+'NERC source'!F84) | K84: ='NERC source'!I84*'Power Market Assumptions'!D$18 | L84: =D84*('NERC source'!G84-'NERC source'!F84)*'Power Market Assumptions'!D$13 | M84: =SUMIFS('Power agreements'!R$6:R$72,'Power agreements'!$F$6:$F$72,B84,'Power agreements'!$P$6:$P$72,1) | N84: =J84-K84+L84+M84 | O84: =MAX(0,I84-N84)/1000
B85: ='NERC source'!B85 | C85: ='NERC source'!C85 | D85: ='NERC source'!E85 | E85: =SUMIFS('NERC source'!$E$6:$E$95,'NERC source'!$B$6:$B$95,B85,'NERC source'!$C$6:$C$95,2026) | F85: ='Power Market Assumptions'!E$8 | G85: =E85+(D85-E85)*F85 | H85: ='NERC source'!H85 | I85: =G85*(1+H85) | J85: =D85*(1+'NERC source'!F85) | K85: ='NERC source'!I85*'Power Market Assumptions'!E$18 | L85: =D85*('NERC source'!G85-'NERC source'!F85)*'Power Market Assumptions'!E$13 | M85: =SUMIFS('Power agreements'!S$6:S$72,'Power agreements'!$F$6:$F$72,B85,'Power agreements'!$P$6:$P$72,1) | N85: =J85-K85+L85+M85 | O85: =MAX(0,I85-N85)/1000
B86: ='NERC source'!B86 | C86: ='NERC source'!C86 | D86: ='NERC source'!E86 | E86: =SUMIFS('NERC source'!$E$6:$E$95,'NERC source'!$B$6:$B$95,B86,'NERC source'!$C$6:$C$95,2026) | F86: ='Power Market Assumptions'!F$8 | G86: =E86+(D86-E86)*F86 | H86: ='NERC source'!H86 | I86: =G86*(1+H86) | J86: =D86*(1+'NERC source'!F86) | K86: ='NERC source'!I86*'Power Market Assumptions'!F$18 | L86: =D86*('NERC source'!G86-'NERC source'!F86)*'Power Market Assumptions'!F$13 | M86: =SUMIFS('Power agreements'!T$6:T$72,'Power agreements'!$F$6:$F$72,B86,'Power agreements'!$P$6:$P$72,1) | N86: =J86-K86+L86+M86 | O86: =MAX(0,I86-N86)/1000
B87: ='NERC source'!B87 | C87: ='NERC source'!C87 | D87: ='NERC source'!E87 | E87: =SUMIFS('NERC source'!$E$6:$E$95,'NERC source'!$B$6:$B$95,B87,'NERC source'!$C$6:$C$95,2026) | F87: ='Power Market Assumptions'!G$8 | G87: =E87+(D87-E87)*F87 | H87: ='NERC source'!H87 | I87: =G87*(1+H87) | J87: =D87*(1+'NERC source'!F87) | K87: ='NERC source'!I87*'Power Market Assumptions'!G$18 | L87: =D87*('NERC source'!G87-'NERC source'!F87)*'Power Market Assumptions'!G$13 | M87: =SUMIFS('Power agreements'!U$6:U$72,'Power agreements'!$F$6:$F$72,B87,'Power agreements'!$P$6:$P$72,1) | N87: =J87-K87+L87+M87 | O87: =MAX(0,I87-N87)/1000
B88: ='NERC source'!B88 | C88: ='NERC source'!C88 | D88: ='NERC source'!E88 | E88: =SUMIFS('NERC source'!$E$6:$E$95,'NERC source'!$B$6:$B$95,B88,'NERC source'!$C$6:$C$95,2026) | F88: ='Power Market Assumptions'!H$8 | G88: =E88+(D88-E88)*F88 | H88: ='NERC source'!H88 | I88: =G88*(1+H88) | J88: =D88*(1+'NERC source'!F88) | K88: ='NERC source'!I88*'Power Market Assumptions'!H$18 | L88: =D88*('NERC source'!G88-'NERC source'!F88)*'Power Market Assumptions'!H$13 | M88: =SUMIFS('Power agreements'!V$6:V$72,'Power agreements'!$F$6:$F$72,B88,'Power agreements'!$P$6:$P$72,1) | N88: =J88-K88+L88+M88 | O88: =MAX(0,I88-N88)/1000
B89: ='NERC source'!B89 | C89: ='NERC source'!C89 | D89: ='NERC source'!E89 | E89: =SUMIFS('NERC source'!$E$6:$E$95,'NERC source'!$B$6:$B$95,B89,'NERC source'!$C$6:$C$95,2026) | F89: ='Power Market Assumptions'!I$8 | G89: =E89+(D89-E89)*F89 | H89: ='NERC source'!H89 | I89: =G89*(1+H89) | J89: =D89*(1+'NERC source'!F89) | K89: ='NERC source'!I89*'Power Market Assumptions'!I$18 | L89: =D89*('NERC source'!G89-'NERC source'!F89)*'Power Market Assumptions'!I$13 | M89: =SUMIFS('Power agreements'!W$6:W$72,'Power agreements'!$F$6:$F$72,B89,'Power agreements'!$P$6:$P$72,1) | N89: =J89-K89+L89+M89 | O89: =MAX(0,I89-N89)/1000
B90: ='NERC source'!B90 | C90: ='NERC source'!C90 | D90: ='NERC source'!E90 | E90: =SUMIFS('NERC source'!$E$6:$E$95,'NERC source'!$B$6:$B$95,B90,'NERC source'!$C$6:$C$95,2026) | F90: ='Power Market Assumptions'!D$8 | G90: =E90+(D90-E90)*F90 | H90: ='NERC source'!H90 | I90: =G90*(1+H90) | J90: =D90*(1+'NERC source'!F90) | K90: ='NERC source'!I90*'Power Market Assumptions'!D$18 | L90: =D90*('NERC source'!G90-'NERC source'!F90)*'Power Market Assumptions'!D$13 | M90: =SUMIFS('Power agreements'!R$6:R$72,'Power agreements'!$F$6:$F$72,B90,'Power agreements'!$P$6:$P$72,1) | N90: =J90-K90+L90+M90 | O90: =MAX(0,I90-N90)/1000
B91: ='NERC source'!B91 | C91: ='NERC source'!C91 | D91: ='NERC source'!E91 | E91: =SUMIFS('NERC source'!$E$6:$E$95,'NERC source'!$B$6:$B$95,B91,'NERC source'!$C$6:$C$95,2026) | F91: ='Power Market Assumptions'!E$8 | G91: =E91+(D91-E91)*F91 | H91: ='NERC source'!H91 | I91: =G91*(1+H91) | J91: =D91*(1+'NERC source'!F91) | K91: ='NERC source'!I91*'Power Market Assumptions'!E$18 | L91: =D91*('NERC source'!G91-'NERC source'!F91)*'Power Market Assumptions'!E$13 | M91: =SUMIFS('Power agreements'!S$6:S$72,'Power agreements'!$F$6:$F$72,B91,'Power agreements'!$P$6:$P$72,1) | N91: =J91-K91+L91+M91 | O91: =MAX(0,I91-N91)/1000
B92: ='NERC source'!B92 | C92: ='NERC source'!C92 | D92: ='NERC source'!E92 | E92: =SUMIFS('NERC source'!$E$6:$E$95,'NERC source'!$B$6:$B$95,B92,'NERC source'!$C$6:$C$95,2026) | F92: ='Power Market Assumptions'!F$8 | G92: =E92+(D92-E92)*F92 | H92: ='NERC source'!H92 | I92: =G92*(1+H92) | J92: =D92*(1+'NERC source'!F92) | K92: ='NERC source'!I92*'Power Market Assumptions'!F$18 | L92: =D92*('NERC source'!G92-'NERC source'!F92)*'Power Market Assumptions'!F$13 | M92: =SUMIFS('Power agreements'!T$6:T$72,'Power agreements'!$F$6:$F$72,B92,'Power agreements'!$P$6:$P$72,1) | N92: =J92-K92+L92+M92 | O92: =MAX(0,I92-N92)/1000
B93: ='NERC source'!B93 | C93: ='NERC source'!C93 | D93: ='NERC source'!E93 | E93: =SUMIFS('NERC source'!$E$6:$E$95,'NERC source'!$B$6:$B$95,B93,'NERC source'!$C$6:$C$95,2026) | F93: ='Power Market Assumptions'!G$8 | G93: =E93+(D93-E93)*F93 | H93: ='NERC source'!H93 | I93: =G93*(1+H93) | J93: =D93*(1+'NERC source'!F93) | K93: ='NERC source'!I93*'Power Market Assumptions'!G$18 | L93: =D93*('NERC source'!G93-'NERC source'!F93)*'Power Market Assumptions'!G$13 | M93: =SUMIFS('Power agreements'!U$6:U$72,'Power agreements'!$F$6:$F$72,B93,'Power agreements'!$P$6:$P$72,1) | N93: =J93-K93+L93+M93 | O93: =MAX(0,I93-N93)/1000
B94: ='NERC source'!B94 | C94: ='NERC source'!C94 | D94: ='NERC source'!E94 | E94: =SUMIFS('NERC source'!$E$6:$E$95,'NERC source'!$B$6:$B$95,B94,'NERC source'!$C$6:$C$95,2026) | F94: ='Power Market Assumptions'!H$8 | G94: =E94+(D94-E94)*F94 | H94: ='NERC source'!H94 | I94: =G94*(1+H94) | J94: =D94*(1+'NERC source'!F94) | K94: ='NERC source'!I94*'Power Market Assumptions'!H$18 | L94: =D94*('NERC source'!G94-'NERC source'!F94)*'Power Market Assumptions'!H$13 | M94: =SUMIFS('Power agreements'!V$6:V$72,'Power agreements'!$F$6:$F$72,B94,'Power agreements'!$P$6:$P$72,1) | N94: =J94-K94+L94+M94 | O94: =MAX(0,I94-N94)/1000
B95: ='NERC source'!B95 | C95: ='NERC source'!C95 | D95: ='NERC source'!E95 | E95: =SUMIFS('NERC source'!$E$6:$E$95,'NERC source'!$B$6:$B$95,B95,'NERC source'!$C$6:$C$95,2026) | F95: ='Power Market Assumptions'!I$8 | G95: =E95+(D95-E95)*F95 | H95: ='NERC source'!H95 | I95: =G95*(1+H95) | J95: =D95*(1+'NERC source'!F95) | K95: ='NERC source'!I95*'Power Market Assumptions'!I$18 | L95: =D95*('NERC source'!G95-'NERC source'!F95)*'Power Market Assumptions'!I$13 | M95: =SUMIFS('Power agreements'!W$6:W$72,'Power agreements'!$F$6:$F$72,B95,'Power agreements'!$P$6:$P$72,1) | N95: =J95-K95+L95+M95 | O95: =MAX(0,I95-N95)/1000
B98: US Data Center Energy
B100: Year | C100: Energy (TWh) | D100: Avg. GW | E100: Grid GW | F100: Δ Avg. GW | G100: Basis
B101: 2024 | C101: ='Power Market Assumptions'!D31 | D101: =C101/8.76 | E101: =D101/'Power Market Assumptions'!$D$36 | F101: =D101-$D$101 | G101: Source
B102: 2025 | C102: ='Power Market Assumptions'!$D$31*('Power Market Assumptions'!$D$32/'Power Market Assumptions'!$D$31)^((2025-2024)/4) | D102: =C102/8.76 | E102: =D102/'Power Market Assumptions'!$D$36 | F102: =D102-$D$101 | G102: Interpolated
B103: 2026 | C103: ='Power Market Assumptions'!$D$31*('Power Market Assumptions'!$D$32/'Power Market Assumptions'!$D$31)^((2026-2024)/4) | D103: =C103/8.76 | E103: =D103/'Power Market Assumptions'!$D$36 | F103: =D103-$D$101 | G103: Interpolated
...

Sheet Power agreements
B1: FTAI Aviation
B2: Power Agreements
B4: Public Power Agreements
B5: ID | C5: Announced | D5: Buyer | E5: Project | F5: Region | G5: Status | H5: Technology | I5: Headline MW | J5: Basis | K5: New / Restart | L5: Include | M5: First COD | N5: Full COD | O5: Delivery (%) | P5: Add to NERC | Q5: Source | R5: 2026 | S5: 2027 | T5: 2028 | U5: 2029 | V5: 2030 | W5: 2031
B6: P001 | C6: 2026-10 | D6: Google | E6: Constellation: 11 reactor uprates | F6: PJM | G6: Signed PPA | H6: Nuclear | I6: 890 | J6: MW | K6: 890 | L6: 1 | M6: 2028 | N6: 2031 | O6: 1 | P6: 0 | Q6: S001 | R6: =IF(OR($K6="",$L6=0),0,$K6*$L6*$O6*VLOOKUP($H6,'Power Market Assumptions'!$B$41:$D$52,3,FALSE)*MAX(0,MIN(1,(R$5-'Power Market Assumptions'!D$23-$M6+1)/($N6-$M6+1)))) | S6: =IF(OR($K6="",$L6=0),0,$K6*$L6*$O6*VLOOKUP($H6,'Power Market Assumptions'!$B$41:$D$52,3,FALSE)*MAX(0,MIN(1,(S$5-'Power Market Assumptions'!E$23-$M6+1)/($N6-$M6+1)))) | T6: =IF(OR($K6="",$L6=0),0,$K6*$L6*$O6*VLOOKUP($H6,'Power Market Assumptions'!$B$41:$D$52,3,FALSE)*MAX(0,MIN(1,(T$5-'Power Market Assumptions'!F$23-$M6+1)/($N6-$M6+1)))) | U6: =IF(OR($K6="",$L6=0),0,$K6*$L6*$O6*VLOOKUP($H6,'Power Market Assumptions'!$B$41:$D$52,3,FALSE)*MAX(0,MIN(1,(U$5-'Power Market Assumptions'!G$23-$M6+1)/($N6-$M6+1)))) | V6: =IF(OR($K6="",$L6=0),0,$K6*$L6*$O6*VLOOKUP($H6,'Power Market Assumptions'!$B$41:$D$52,3,FALSE)*MAX(0,MIN(1,(V$5-'Power Market Assumptions'!H$23-$M6+1)/($N6-$M6+1)))) | W6: =IF(OR($K6="",$L6=0),0,$K6*$L6*$O6*VLOOKUP($H6,'Power Market Assumptions'!$B$41:$D$52,3,FALSE)*MAX(0,MIN(1,(W$5-'Power Market Assumptions'!I$23-$M6+1)/($N6-$M6+1))))
B7: P002 | C7: 2026-10 | D7: Google | E7: Constellation: existing fleet | F7: PJM | G7: Signed PPA / existing | H7: Nuclear | I7: 2700 | J7: MW | K7: 0 | L7: 1 | M7: 2026 | N7: 2026 | O7: 1 | P7: 0 | Q7: S001 | R7: =IF(OR($K7="",$L7=0),0,$K7*$L7*$O7*VLOOKUP($H7,'Power Market Assumptions'!$B$41:$D$52,3,FALSE)*MAX(0,MIN(1,(R$5-'Power Market Assumptions'!D$23-$M7+1)/($N7-$M7+1)))) | S7: =IF(OR($K7="",$L7=0),0,$K7*$L7*$O7*VLOOKUP($H7,'Power Market Assumptions'!$B$41:$D$52,3,FALSE)*MAX(0,MIN(1,(S$5-'Power Market Assumptions'!E$23-$M7+1)/($N7-$M7+1)))) | T7: =IF(OR($K7="",$L7=0),0,$K7*$L7*$O7*VLOOKUP($H7,'Power Market Assumptions'!$B$41:$D$52,3,FALSE)*MAX(0,MIN(1,(T$5-'Power Market Assumptions'!F$23-$M7+1)/($N7-$M7+1)))) | U7: =IF(OR($K7="",$L7=0),0,$K7*$L7*$O7*VLOOKUP($H7,'Power Market Assumptions'!$B$41:$D$52,3,FALSE)*MAX(0,MIN(1,(U$5-'Power Market Assumptions'!G$23-$M7+1)/($N7-$M7+1)))) | V7: =IF(OR($K7="",$L7=0),0,$K7*$L7*$O7*VLOOKUP($H7,'Power Market Assumptions'!$B$41:$D$52,3,FALSE)*MAX(0,MIN(1,(V$5-'Power Market Assumptions'!H$23-$M7+1)/($N7-$M7+1)))) | W7: =IF(OR($K7="",$L7=0),0,$K7*$L7*$O7*VLOOKUP($H7,'Power Market Assumptions'!$B$41:$D$52,3,FALSE)*MAX(0,MIN(1,(W$5-'Power Market Assumptions'!I$23-$M7+1)/($N7-$M7+1))))
B8: P003 | C8: 2026-09 | D8: Amazon | E8: Calvert Cliffs: uprate | F8: PJM | G8: Signed PPA | H8: Nuclear | I8: 190 | J8: MW | K8: 190 | L8: 1 | M8: 2030 | N8: 2032 | O8: 1 | P8: 0 | Q8: S002 | R8: =IF(OR($K8="",$L8=0),0,$K8*$L8*$O8*VLOOKUP($H8,'Power Market Assumptions'!$B$41:$D$52,3,FALSE)*MAX(0,MIN(1,(R$5-'Power Market Assumptions'!D$23-$M8+1)/($N8-$M8+1)))) | S8: =IF(OR($K8="",$L8=0),0,$K8*$L8*$O8*VLOOKUP($H8,'Power Market Assumptions'!$B$41:$D$52,3,FALSE)*MAX(0,MIN(1,(S$5-'Power Market Assumptions'!E$23-$M8+1)/($N8-$M8+1)))) | T8: =IF(OR($K8="",$L8=0),0,$K8*$L8*$O8*VLOOKUP($H8,'Power Market Assumptions'!$B$41:$D$52,3,FALSE)*MAX(0,MIN(1,(T$5-'Power Market Assumptions'!F$23-$M8+1)/($N8-$M8+1)))) | U8: =IF(OR($K8="",$L8=0),0,$K8*$L8*$O8*VLOOKUP($H8,'Power Market Assumptions'!$B$41:$D$52,3,FALSE)*MAX(0,MIN(1,(U$5-'Power Market Assumptions'!G$23-$M8+1)/($N8-$M8+1)))) | V8: =IF(OR($K8="",$L8=0),0,$K8*$L8*$O8*VLOOKUP($H8,'Power Market Assumptions'!$B$41:$D$52,3,FALSE)*MAX(0,MIN(1,(V$5-'Power Market Assumptions'!H$23-$M8+1)/($N8-$M8+1)))) | W8: =IF(OR($K8="",$L8=0),0,$K8*$L8*$O8*VLOOKUP($H8,'Power Market Assumptions'!$B$41:$D$52,3,FALSE)*MAX(0,MIN(1,(W$5-'Power Market Assumptions'!I$23-$M8+1)/($N8-$M8+1))))
B9: P004 | C9: 2026-09 | D9: Amazon | E9: Calvert Cliffs: existing output | F9: PJM | G9: Signed PPA / existing | H9: Nuclear | I9: 500 | J9: MW | K9: 0 | L9: 1 | M9: 2026 | N9: 2026 | O9: 1 | P9: 0 | Q9: S002 | R9: =IF(OR($K9="",$L9=0),0,$K9*$L9*$O9*VLOOKUP($H9,'Power Market Assumptions'!$B$41:$D$52,3,FALSE)*MAX(0,MIN(1,(R$5-'Power Market Assumptions'!D$23-$M9+1)/($N9-$M9+1)))) | S9: =IF(OR($K9="",$L9=0),0,$K9*$L9*$O9*VLOOKUP($H9,'Power Market Assumptions'!$B$41:$D$52,3,FALSE)*MAX(0,MIN(1,(S$5-'Power Market Assumptions'!E$23-$M9+1)/($N9-$M9+1)))) | T9: =IF(OR($K9="",$L9=0),0,$K9*$L9*$O9*VLOOKUP($H9,'Power Market Assumptions'!$B$41:$D$52,3,FALSE)*MAX(0,MIN(1,(T$5-'Power Market Assumptions'!F$23-$M9+1)/($N9-$M9+1)))) | U9: =IF(OR($K9="",$L9=0),0,$K9*$L9*$O9*VLOOKUP($H9,'Power Market Assumptions'!$B$41:$D$52,3,FALSE)*MAX(0,MIN(1,(U$5-'Power Market Assumptions'!G$23-$M9+1)/($N9-$M9+1)))) | V9: =IF(OR($K9="",$L9=0),0,$K9*$L9*$O9*VLOOKUP($H9,'Power Market Assumptions'!$B$41:$D$52,3,FALSE)*MAX(0,MIN(1,(V$5-'Power Market Assumptions'!H$23-$M9+1)/($N9-$M9+1)))) | W9: =IF(OR($K9="",$L9=0),0,$K9*$L9*$O9*VLOOKUP($H9,'Power Market Assumptions'!$B$41:$D$52,3,FALSE)*MAX(0,MIN(1,(W$5-'Power Market Assumptions'!I$23-$M9+1)/($N9-$M9+1))))
B10: P005 | C10: 2026-01 | D10: Meta | E10: Vistra: three plant uprates | F10: PJM | G10: Signed PPA | H10: Nuclear | I10: 433 | J10: MW | K10: 433 | L10: 1 | M10: 2031 | N10: 2034 | O10: 1 | P10: 0 | Q10: S003 | R10: =IF(OR($K10="",$L10=0),0,$K10*$L10*$O10*VLOOKUP($H10,'Power Market Assumptions'!$B$41:$D$52,3,FALSE)*MAX(0,MIN(1,(R$5-'Power Market Assumptions'!D$23-$M10+1)/($N10-$M10+1)))) | S10: =IF(OR($K10="",$L10=0),0,$K10*$L10*$O10*VLOOKUP($H10,'Power Market Assumptions'!$B$41:$D$52,3,FALSE)*MAX(0,MIN(1,(S$5-'Power Market Assumptions'!E$23-$M10+1)/($N10-$M10+1)))) | T10: =IF(OR($K10="",$L10=0),0,$K10*$L10*$O10*VLOOKUP($H10,'Power Market Assumptions'!$B$41:$D$52,3,FALSE)*MAX(0,MIN(1,(T$5-'Power Market Assumptions'!F$23-$M10+1)/($N10-$M10+1)))) | U10: =IF(OR($K10="",$L10=0),0,$K10*$L10*$O10*VLOOKUP($H10,'Power Market Assumptions'!$B$41:$D$52,3,FALSE)*MAX(0,MIN(1,(U$5-'Power Market Assumptions'!G$23-$M10+1)/($N10-$M10+1)))) | V10: =IF(OR($K10="",$L10=0),0,$K10*$L10*$O10*VLOOKUP($H10,'Power Market Assumptions'!$B$41:$D$52,3,FALSE)*MAX(0,MIN(1,(V$5-'Power Market Assumptions'!H$23-$M10+1)/($N10-$M10+1)))) | W10: =IF(OR($K10="",$L10=0),0,$K10*$L10*$O10*VLOOKUP($H10,'Power Market Assumptions'!$B$41:$D$52,3,FALSE)*MAX(0,MIN(1,(W$5-'Power Market Assumptions'!I$23-$M10+1)/($N10-$M10+1))))
B11: P006 | C11: 2026-01 | D11: Meta | E11: Vistra: Perry / Davis-Besse existing | F11: PJM | G11: Signed PPA / existing | H11: Nuclear | I11: 2176 | J11: MW | K11: 0 | L11: 1 | M11: 2026 | N11: 2026 | O11: 1 | P11: 0 | Q11: S003 | R11: =IF(OR($K11="",$L11=0),0,$K11*$L11*$O11*VLOOKUP($H11,'Power Market Assumptions'!$B$41:$D$52,3,FALSE)*MAX(0,MIN(1,(R$5-'Power Market Assumptions'!D$23-$M11+1)/($N11-$M11+1)))) | S11: =IF(OR($K11="",$L11=0),0,$K11*$L11*$O11*VLOOKUP($H11,'Power Market Assumptions'!$B$41:$D$52,3,FALSE)*MAX(0,MIN(1,(S$5-'Power Market Assumptions'!E$23-$M11+1)/($N11-$M11+1)))) | T11: =IF(OR($K11="",$L11=0),0,$K11*$L11*$O11*VLOOKUP($H11,'Power Market Assumptions'!$B$41:$D$52,3,FALSE)*MAX(0,MIN(1,(T$5-'Power Market Assumptions'!F$23-$M11+1)/($N11-$M11+1)))) | U11: =IF(OR($K11="",$L11=0),0,$K11*$L11*$O11*VLOOKUP($H11,'Power Market Assumptions'!$B$41:$D$52,3,FALSE)*MAX(0,MIN(1,(U$5-'Power Market Assumptions'!G$23-$M11+1)/($N11-$M11+1)))) | V11: =IF(OR($K11="",$L11=0),0,$K11*$L11*$O11*VLOOKUP($H11,'Power Market Assumptions'!$B$41:$D$52,3,FALSE)*MAX(0,MIN(1,(V$5-'Power Market Assumptions'!H$23-$M11+1)/($N11-$M11+1)))) | W11: =IF(OR($K11="",$L11=0),0,$K11*$L11*$O11*VLOOKUP($H11,'Power Market Assumptions'!$B$41:$D$52,3,FALSE)*MAX(0,MIN(1,(W$5-'Power Market Assumptions'!I$23-$M11+1)/($N11-$M11+1))))
B12: P007 | C12: 2025-06 | D12: Meta | E12: Constellation: Clinton plus uprate | F12: MISO | G12: Signed PPA / existing + uprate | H12: Nuclear | I12: 1121 | J12: Reported PPA MW | K12: 30 | L12: 1 | M12: 2027 | N12: 2027 | O12: 1 | P12: 0 | Q12: S004 | R12: =IF(OR($K12="",$L12=0),0,$K12*$L12*$O12*VLOOKUP($H12,'Power Market Assumptions'!$B$41:$D$52,3,FALSE)*MAX(0,MIN(1,(R$5-'Power Market Assumptions'!D$23-$M12+1)/($N12-$M12+1)))) | S12: =IF(OR($K12="",$L12=0),0,$K12*$L12*$O12*VLOOKUP($H12,'Power Market Assumptions'!$B$41:$D$52,3,FALSE)*MAX(0,MIN(1,(S$5-'Power Market Assumptions'!E$23-$M12+1)/($N12-$M12+1)))) | T12: =IF(OR($K12="",$L12=0),0,$K12*$L12*$O12*VLOOKUP($H12,'Power Market Assumptions'!$B$41:$D$52,3,FALSE)*MAX(0,MIN(1,(T$5-'Power Market Assumptions'!F$23-$M12+1)/($N12-$M12+1)))) | U12: =IF(OR($K12="",$L12=0),0,$K12*$L12*$O12*VLOOKUP($H12,'Power Market Assumptions'!$B$41:$D$52,3,FALSE)*MAX(0,MIN(1,(U$5-'Power Market Assumptions'!G$23-$M12+1)/($N12-$M12+1)))) | V12: =IF(OR($K12="",$L12=0),0,$K12*$L12*$O12*VLOOKUP($H12,'Power Market Assumptions'!$B$41:$D$52,3,FALSE)*MAX(0,MIN(1,(V$5-'Power Market Assumptions'!H$23-$M12+1)/($N12-$M12+1)))) | W12: =IF(OR($K12="",$L12=0),0,$K12*$L12*$O12*VLOOKUP($H12,'Power Market Assumptions'!$B$41:$D$52,3,FALSE)*MAX(0,MIN(1,(W$5-'Power Market Assumptions'!I$23-$M12+1)/($N12-$M12+1))))
B13: P008 | C13: 2025-10 | D13: Google | E13: NextEra: Duane Arnold restart | F13: MISO | G13: Signed PPA / restart | H13: Nuclear | I13: 615 | J13: MW | K13: 615 | L13: 1 | M13: 2029 | N13: 2029 | O13: 1 | P13: 0 | Q13: S005 | R13: =IF(OR($K13="",$L13=0),0,$K13*$L13*$O13*VLOOKUP($H13,'Power Market Assumptions'!$B$41:$D$52,3,FALSE)*MAX(0,MIN(1,(R$5-'Power Market Assumptions'!D$23-$M13+1)/($N13-$M13+1)))) | S13: =IF(OR($K13="",$L13=0),0,$K13*$L13*$O13*VLOOKUP($H13,'Power Market Assumptions'!$B$41:$D$52,3,FALSE)*MAX(0,MIN(1,(S$5-'Power Market Assumptions'!E$23-$M13+1)/($N13-$M13+1)))) | T13: =IF(OR($K13="",$L13=0),0,$K13*$L13*$O13*VLOOKUP($H13,'Power Market Assumptions'!$B$41:$D$52,3,FALSE)*MAX(0,MIN(1,(T$5-'Power Market Assumptions'!F$23-$M13+1)/($N13-$M13+1)))) | U13: =IF(OR($K13="",$L13=0),0,$K13*$L13*$O13*VLOOKUP($H13,'Power Market Assumptions'!$B$41:$D$52,3,FALSE)*MAX(0,MIN(1,(U$5-'Power Market Assumptions'!G$23-$M13+1)/($N13-$M13+1)))) | V13: =IF(OR($K13="",$L13=0),0,$K13*$L13*$O13*VLOOKUP($H13,'Power Market Assumptions'!$B$41:$D$52,3,FALSE)*MAX(0,MIN(1,(V$5-'Power Market Assumptions'!H$23-$M13+1)/($N13-$M13+1)))) | W13: =IF(OR($K13="",$L13=0),0,$K13*$L13*$O13*VLOOKUP($H13,'Power Market Assumptions'!$B$41:$D$52,3,FALSE)*MAX(0,MIN(1,(W$5-'Power Market Assumptions'!I$23-$M13+1)/($N13-$M13+1))))
B14: P009 | C14: 2024-09 | D14: Microsoft | E14: Constellation: Crane restart | F14: PJM | G14: Signed PPA / restart | H14: Nuclear | I14: 835 | J14: MW | K14: 835 | L14: 1 | M14: 2027 | N14: 2027 | O14: 1 | P14: 0 | Q14: S006 | R14: =IF(OR($K14="",$L14=0),0,$K14*$L14*$O14*VLOOKUP($H14,'Power Market Assumptions'!$B$41:$D$52,3,FALSE)*MAX(0,MIN(1,(R$5-'Power Market Assumptions'!D$23-$M14+1)/($N14-$M14+1)))) | S14: =IF(OR($K14="",$L14=0),0,$K14*$L14*$O14*VLOOKUP($H14,'Power Market Assumptions'!$B$41:$D$52,3,FALSE)*MAX(0,MIN(1,(S$5-'Power Market Assumptions'!E$23-$M14+1)/($N14-$M14+1)))) | T14: =IF(OR($K14="",$L14=0),0,$K14*$L14*$O14*VLOOKUP($H14,'Power Market Assumptions'!$B$41:$D$52,3,FALSE)*MAX(0,MIN(1,(T$5-'Power Market Assumptions'!F$23-$M14+1)/($N14-$M14+1)))) | U14: =IF(OR($K14="",$L14=0),0,$K14*$L14*$O14*VLOOKUP($H14,'Power Market Assumptions'!$B$41:$D$52,3,FALSE)*MAX(0,MIN(1,(U$5-'Power Market Assumptions'!G$23-$M14+1)/($N14-$M14+1)))) | V14: =IF(OR($K14="",$L14=0),0,$K14*$L14*$O14*VLOOKUP($H14,'Power Market Assumptions'!$B$41:$D$52,3,FALSE)*MAX(0,MIN(1,(V$5-'Power Market Assumptions'!H$23-$M14+1)/($N14-$M14+1)))) | W14: =IF(OR($K14="",$L14=0),0,$K14*$L14*$O14*VLOOKUP($H14,'Power Market Assumptions'!$B$41:$D$52,3,FALSE)*MAX(0,MIN(1,(W$5-'Power Market Assumptions'!I$23-$M14+1)/($N14-$M14+1))))
B15: P010 | C15: 2025-06 | D15: Amazon | E15: Talen: Susquehanna | F15: PJM | G15: Signed PPA / existing | H15: Nuclear | I15: 1920 | J15: MW | K15: 0 | L15: 1 | M15: 2026 | N15: 2032 | O15: 1 | P15: 0 | Q15: S007 | R15: =IF(OR($K15="",$L15=0),0,$K15*$L15*$O15*VLOOKUP($H15,'Power Market Assumptions'!$B$41:$D$52,3,FALSE)*MAX(0,MIN(1,(R$5-'Power Market Assumptions'!D$23-$M15+1)/($N15-$M15+1)))) | S15: =IF(OR($K15="",$L15=0),0,$K15*$L15*$O15*VLOOKUP($H15,'Power Market Assumptions'!$B$41:$D$52,3,FALSE)*MAX(0,MIN(1,(S$5-'Power Market Assumptions'!E$23-$M15+1)/($N15-$M15+1)))) | T15: =IF(OR($K15="",$L15=0),0,$K15*$L15*$O15*VLOOKUP($H15,'Power Market Assumptions'!$B$41:$D$52,3,FALSE)*MAX(0,MIN(1,(T$5-'Power Market Assumptions'!F$23-$M15+1)/($N15-$M15+1)))) | U15: =IF(OR($K15="",$L15=0),0,$K15*$L15*$O15*VLOOKUP($H15,'Power Market Assumptions'!$B$41:$D$52,3,FALSE)*MAX(0,MIN(1,(U$5-'Power Market Assumptions'!G$23-$M15+1)/($N15-$M15+1)))) | V15: =IF(OR($K15="",$L15=0),0,$K15*$L15*$O15*VLOOKUP($H15,'Power Market Assumptions'!$B$41:$D$52,3,FALSE)*MAX(0,MIN(1,(V$5-'Power Market Assumptions'!H$23-$M15+1)/($N15-$M15+1)))) | W15: =IF(OR($K15="",$L15=0),0,$K15*$L15*$O15*VLOOKUP($H15,'Power Market Assumptions'!$B$41:$D$52,3,FALSE)*MAX(0,MIN(1,(W$5-'Power Market Assumptions'!I$23-$M15+1)/($N15-$M15+1))))
B16: P011 | C16: 2025-09 | D16: Amazon | E16: Vistra: Comanche Peak | F16: Texas RE-ERCOT | G16: Signed PPA / existing | H16: Nuclear | I16: 1200 | J16: MW | K16: 0 | L16: 1 | M16: 2027 | N16: 2027 | O16: 1 | P16: 0 | Q16: S008 | R16: =IF(OR($K16="",$L16=0),0,$K16*$L16*$O16*VLOOKUP($H16,'Power Market Assumptions'!$B$41:$D$52,3,FALSE)*MAX(0,MIN(1,(R$5-'Power Market Assumptions'!D$23-$M16+1)/($N16-$M16+1)))) | S16: =IF(OR($K16="",$L16=0),0,$K16*$L16*$O16*VLOOKUP($H16,'Power Market Assumptions'!$B$41:$D$52,3,FALSE)*MAX(0,MIN(1,(S$5-'Power Market Assumptions'!E$23-$M16+1)/($N16-$M16+1)))) | T16: =IF(OR($K16="",$L16=0),0,$K16*$L16*$O16*VLOOKUP($H16,'Power Market Assumptions'!$B$41:$D$52,3,FALSE)*MAX(0,MIN(1,(T$5-'Power Market Assumptions'!F$23-$M16+1)/($N16-$M16+1)))) | U16: =IF(OR($K16="",$L16=0),0,$K16*$L16*$O16*VLOOKUP($H16,'Power Market Assumptions'!$B$41:$D$52,3,FALSE)*MAX(0,MIN(1,(U$5-'Power Market Assumptions'!G$23-$M16+1)/($N16-$M16+1)))) | V16: =IF(OR($K16="",$L16=0),0,$K16*$L16*$O16*VLOOKUP($H16,'Power Market Assumptions'!$B$41:$D$52,3,FALSE)*MAX(0,MIN(1,(V$5-'Power Market Assumptions'!H$23-$M16+1)/($N16-$M16+1)))) | W16: =IF(OR($K16="",$L16=0),0,$K16*$L16*$O16*VLOOKUP($H16,'Power Market Assumptions'!$B$41:$D$52,3,FALSE)*MAX(0,MIN(1,(W$5-'Power Market Assumptions'!I$23-$M16+1)/($N16-$M16+1))))
B17: P012 | C17: 2026-01 | D17: Meta | E17: TerraPower: first two Natrium units | F17: US unallocated | G17: Development agreement | H17: Advanced nuclear | I17: 690 | J17: MW | K17: 690 | L17: 1 | M17: 2032 | N17: 2032 | O17: 0.5 | P17: 0 | Q17: S009 | R17: =IF(OR($K17="",$L17=0),0,$K17*$L17*$O17*VLOOKUP($H17,'Power Market Assumptions'!$B$41:$D$52,3,FALSE)*MAX(0,MIN(1,(R$5-'Power Market Assumptions'!D$23-$M17+1)/($N17-$M17+1)))) | S17: =IF(OR($K17="",$L17=0),0,$K17*$L17*$O17*VLOOKUP($H17,'Power Market Assumptions'!$B$41:$D$52,3,FALSE)*MAX(0,MIN(1,(S$5-'Power Market Assumptions'!E$23-$M17+1)/($N17-$M17+1)))) | T17: =IF(OR($K17="",$L17=0),0,$K17*$L17*$O17*VLOOKUP($H17,'Power Market Assumptions'!$B$41:$D$52,3,FALSE)*MAX(0,MIN(1,(T$5-'Power Market Assumptions'!F$23-$M17+1)/($N17-$M17+1)))) | U17: =IF(OR($K17="",$L17=0),0,$K17*$L17*$O17*VLOOKUP($H17,'Power Market Assumptions'!$B$41:$D$52,3,FALSE)*MAX(0,MIN(1,(U$5-'Power Market Assumptions'!G$23-$M17+1)/($N17-$M17+1)))) | V17: =IF(OR($K17="",$L17=0),0,$K17*$L17*$O17*VLOOKUP($H17,'Power Market Assumptions'!$B$41:$D$52,3,FALSE)*MAX(0,MIN(1,(V$5-'Power Market Assumptions'!H$23-$M17+1)/($N17-$M17+1)))) | W17: =IF(OR($K17="",$L17=0),0,$K17*$L17*$O17*VLOOKUP($H17,'Power Market Assumptions'!$B$41:$D$52,3,FALSE)*MAX(0,MIN(1,(W$5-'Power Market Assumptions'!I$23-$M17+1)/($N17-$M17+1))))
... B32: P027 | C32: 2025-07 | D32: Google | E32: Brookfield: Pennsylvania hydro | F32: PJM | G32: Signed PPA / existing | H32: Hydro | I32: 665 | J32: MW | K32: 0 | L32: 1 | M32: 2026 | N32: 2026 | O32: 1 | P32: 0 | Q32: S018 | R32: =IF(OR($K32="",$L32=0),0,$K32*$L32*$O32*VLOOKUP($H32,'Power Market Assumptions'!$B$41:$D$52,3,FALSE)*MAX(0,MIN(1,(R$5-'Power Market Assumptions'!D$23-$M32+1)/($N32-$M32+1)))) | S32: =IF(OR($K32="",$L32=0),0,$K32*$L32*$O32*VLOOKUP($H32,'Power Market Assumptions'!$B$41:$D$52,3,FALSE)*MAX(0,MIN(1,(S$5-'Power Market Assumptions'!E$23-$M32+1)/($N32-$M32+1)))) | T32: =IF(OR($K32="",$L32=0),0,$K32*$L32*$O32*VLOOKUP($H32,'Power Market Assumptions'!$B$41:$D$52,3,FALSE)*MAX(0,MIN(1,(T$5-'Power Market Assumptions'!F$23-$M32+1)/($N32-$M32+1)))) | U32: =IF(OR($K32="",$L32=0),0,$K32*$L32*$O32*VLOOKUP($H32,'Power Market Assumptions'!$B$41:$D$52,3,FALSE)*MAX(0,MIN(1,(U$5-'Power Market Assumptions'!G$23-$M32+1)/($N32-$M32+1)))) | V32: =IF(OR($K32="",$L32=0),0,$K32*$L32*$O32*VLOOKUP($H32,'Power Market Assumptions'!$B$41:$D$52,3,FALSE)*MAX(0,MIN(1,(V$5-'Power Market Assumptions'!H$23-$M32+1)/($N32-$M32+1)))) | W32: =IF(OR($K32="",$L32=0),0,$K32*$L32*$O32*VLOOKUP($H32,'Power Market Assumptions'!$B$41:$D$52,3,FALSE)*MAX(0,MIN(1,(W$5-'Power Market Assumptions'!I$23-$M32+1)/($N32-$M32+1))))
B33: P028 | C33: 2025-07 | D33: Google | E33: Brookfield: remaining hydro framework | F33: US unallocated | G33: Framework | H33: Hydro | I33: 2335 | J33: MW | L33: 0 | M33: 2035 | N33: 2035 | O33: 0 | P33: 0 | Q33: S018 | R33: =IF(OR($K33="",$L33=0),0,$K33*$L33*$O33*VLOOKUP($H33,'Power Market Assumptions'!$B$41:$D$52,3,FALSE)*MAX(0,MIN(1,(R$5-'Power Market Assumptions'!D$23-$M33+1)/($N33-$M33+1)))) | S33: =IF(OR($K33="",$L33=0),0,$K33*$L33*$O33*VLOOKUP($H33,'Power Market Assumptions'!$B$41:$D$52,3,FALSE)*MAX(0,MIN(1,(S$5-'Power Market Assumptions'!E$23-$M33+1)/($N33-$M33+1)))) | T33: =IF(OR($K33="",$L33=0),0,$K33*$L33*$O33*VLOOKUP($H33,'Power Market Assumptions'!$B$41:$D$52,3,FALSE)*MAX(0,MIN(1,(T$5-'Power Market Assumptions'!F$23-$M33+1)/($N33-$M33+1)))) | U33: =IF(OR($K33="",$L33=0),0,$K33*$L33*$O33*VLOOKUP($H33,'Power Market Assumptions'!$B$41:$D$52,3,FALSE)*MAX(0,MIN(1,(U$5-'Power Market Assumptions'!G$23-$M33+1)/($N33-$M33+1)))) | V33: =IF(OR($K33="",$L33=0),0,$K33*$L33*$O33*VLOOKUP($H33,'Power Market Assumptions'!$B$41:$D$52,3,FALSE)*MAX(0,MIN(1,(V$5-'Power Market Assumptions'!H$23-$M33+1)/($N33-$M33+1)))) | W33: =IF(OR($K33="",$L33=0),0,$K33*$L33*$O33*VLOOKUP($H33,'Power Market Assumptions'!$B$41:$D$52,3,FALSE)*MAX(0,MIN(1,(W$5-'Power Market Assumptions'!I$23-$M33+1)/($N33-$M33+1))))
B34: P029 | C34: 2024-05 | D34: Microsoft | E34: Brookfield: global renewables framework | F34: US / Europe unallocated | G34: Framework | H34: Mixed renewables | I34: 10500 | J34: MW | L34: 0 | M34: 2026 | N34: 2030 | O34: 0 | P34: 0 | Q34: S019 | R34: =IF(OR($K34="",$L34=0),0,$K34*$L34*$O34*VLOOKUP($H34,'Power Market Assumptions'!$B$41:$D$52,3,FALSE)*MAX(0,MIN(1,(R$5-'Power Market Assumptions'!D$23-$M34+1)/($N34-$M34+1)))) | S34: =IF(OR($K34="",$L34=0),0,$K34*$L34*$O34*VLOOKUP($H34,'Power Market Assumptions'!$B$41:$D$52,3,FALSE)*MAX(0,MIN(1,(S$5-'Power Market Assumptions'!E$23-$M34+1)/($N34-$M34+1)))) | T34: =IF(OR($K34="",$L34=0),0,$K34*$L34*$O34*VLOOKUP($H34,'Power Market Assumptions'!$B$41:$D$52,3,FALSE)*MAX(0,MIN(1,(T$5-'Power Market Assumptions'!F$23-$M34+1)/($N34-$M34+1)))) | U34: =IF(OR($K34="",$L34=0),0,$K34*$L34*$O34*VLOOKUP($H34,'Power Market Assumptions'!$B$41:$D$52,3,FALSE)*MAX(0,MIN(1,(U$5-'Power Market Assumptions'!G$23-$M34+1)/($N34-$M34+1)))) | V34: =IF(OR($K34="",$L34=0),0,$K34*$L34*$O34*VLOOKUP($H34,'Power Market Assumptions'!$B$41:$D$52,3,FALSE)*MAX(0,MIN(1,(V$5-'Power Market Assumptions'!H$23-$M34+1)/($N34-$M34+1)))) | W34: =IF(OR($K34="",$L34=0),0,$K34*$L34*$O34*VLOOKUP($H34,'Power Market Assumptions'!$B$41:$D$52,3,FALSE)*MAX(0,MIN(1,(W$5-'Power Market Assumptions'!I$23-$M34+1)/($N34-$M34+1))))
B35: P030 | C35: 2025-08 | D35: Meta | E35: Entergy: three Louisiana gas plants | F35: MISO | G35: Approved utility service | H35: Gas | I35: 2262 | J35: MW | K35: 2262 | L35: 1 | M35: 2028 | N35: 2029 | O35: 1 | P35: 0 | Q35: S020 | R35: =IF(OR($K35="",$L35=0),0,$K35*$L35*$O35*VLOOKUP($H35,'Power Market Assumptions'!$B$41:$D$52,3,FALSE)*MAX(0,MIN(1,(R$5-'Power Market Assumptions'!D$23-$M35+1)/($N35-$M35+1)))) | S35: =IF(OR($K35="",$L35=0),0,$K35*$L35*$O35*VLOOKUP($H35,'Power Market Assumptions'!$B$41:$D$52,3,FALSE)*MAX(0,MIN(1,(S$5-'Power Market Assumptions'!E$23-$M35+1)/($N35-$M35+1)))) | T35: =IF(OR($K35="",$L35=0),0,$K35*$L35*$O35*VLOOKUP($H35,'Power Market Assumptions'!$B$41:$D$52,3,FALSE)*MAX(0,MIN(1,(T$5-'Power Market Assumptions'!F$23-$M35+1)/($N35-$M35+1)))) | U35: =IF(OR($K35="",$L35=0),0,$K35*$L35*$O35*VLOOKUP($H35,'Power Market Assumptions'!$B$41:$D$52,3,FALSE)*MAX(0,MIN(1,(U$5-'Power Market Assumptions'!G$23-$M35+1)/($N35-$M35+1)))) | V35: =IF(OR($K35="",$L35=0),0,$K35*$L35*$O35*VLOOKUP($H35,'Power Market Assumptions'!$B$41:$D$52,3,FALSE)*MAX(0,MIN(1,(V$5-'Power Market Assumptions'!H$23-$M35+1)/($N35-$M35+1)))) | W35: =IF(OR($K35="",$L35=0),0,$K35*$L35*$O35*VLOOKUP($H35,'Power Market Assumptions'!$B$41:$D$52,3,FALSE)*MAX(0,MIN(1,(W$5-'Power Market Assumptions'!I$23-$M35+1)/($N35-$M35+1))))
B36: P031 | C36: 2026-03 | D36: Meta | E36: Entergy: seven additional gas plants | F36: MISO | G36: Utility service / proposed | H36: Gas | I36: 5278 | J36: MW | K36: 5278 | L36: 1 | M36: 2030 | N36: 2031 | O36: 0.5 | P36: 0 | Q36: S021 | R36: =IF(OR($K36="",$L36=0),0,$K36*$L36*$O36*VLOOKUP($H36,'Power Market Assumptions'!$B$41:$D$52,3,FALSE)*MAX(0,MIN(1,(R$5-'Power Market Assumptions'!D$23-$M36+1)/($N36-$M36+1)))) | S36: =IF(OR($K36="",$L36=0),0,$K36*$L36*$O36*VLOOKUP($H36,'Power Market Assumptions'!$B$41:$D$52,3,FALSE)*MAX(0,MIN(1,(S$5-'Power Market Assumptions'!E$23-$M36+1)/($N36-$M36+1)))) | T36: =IF(OR($K36="",$L36=0),0,$K36*$L36*$O36*VLOOKUP($H36,'Power Market Assumptions'!$B$41:$D$52,3,FALSE)*MAX(0,MIN(1,(T$5-'Power Market Assumptions'!F$23-$M36+1)/($N36-$M36+1)))) | U36: =IF(OR($K36="",$L36=0),0,$K36*$L36*$O36*VLOOKUP($H36,'Power Market Assumptions'!$B$41:$D$52,3,FALSE)*MAX(0,MIN(1,(U$5-'Power Market Assumptions'!G$23-$M36+1)/($N36-$M36+1)))) | V36: =IF(OR($K36="",$L36=0),0,$K36*$L36*$O36*VLOOKUP($H36,'Power Market Assumptions'!$B$41:$D$52,3,FALSE)*MAX(0,MIN(1,(V$5-'Power Market Assumptions'!H$23-$M36+1)/($N36-$M36+1)))) | W36: =IF(OR($K36="",$L36=0),0,$K36*$L36*$O36*VLOOKUP($H36,'Power Market Assumptions'!$B$41:$D$52,3,FALSE)*MAX(0,MIN(1,(W$5-'Power Market Assumptions'!I$23-$M36+1)/($N36-$M36+1))))
B37: P032 | C37: 2026-03 | D37: Meta | E37: Entergy: additional solar procurement | F37: MISO | G37: Procurement support / RFP | H37: Solar | I37: 2500 | J37: MW | K37: 2500 | L37: 0 | M37: 2030 | N37: 2031 | O37: 0 | P37: 0 | Q37: S022 | R37: =IF(OR($K37="",$L37=0),0,$K37*$L37*$O37*VLOOKUP($H37,'Power Market Assumptions'!$B$41:$D$52,3,FALSE)*MAX(0,MIN(1,(R$5-'Power Market Assumptions'!D$23-$M37+1)/($N37-$M37+1)))) | S37: =IF(OR($K37="",$L37=0),0,$K37*$L37*$O37*VLOOKUP($H37,'Power Market Assumptions'!$B$41:$D$52,3,FALSE)*MAX(0,MIN(1,(S$5-'Power Market Assumptions'!E$23-$M37+1)/($N37-$M37+1)))) | T37: =IF(OR($K37="",$L37=0),0,$K37*$L37*$O37*VLOOKUP($H37,'Power Market Assumptions'!$B$41:$D$52,3,FALSE)*MAX(0,MIN(1,(T$5-'Power Market Assumptions'!F$23-$M37+1)/($N37-$M37+1)))) | U37: =IF(OR($K37="",$L37=0),0,$K37*$L37*$O37*VLOOKUP($H37,'Power Market Assumptions'!$B$41:$D$52,3,FALSE)*MAX(0,MIN(1,(U$5-'Power Market Assumptions'!G$23-$M37+1)/($N37-$M37+1)))) | V37: =IF(OR($K37="",$L37=0),0,$K37*$L37*$O37*VLOOKUP($H37,'Power Market Assumptions'!$B$41:$D$52,3,FALSE)*MAX(0,MIN(1,(V$5-'Power Market Assumptions'!H$23-$M37+1)/($N37-$M37+1)))) | W37: =IF(OR($K37="",$L37=0),0,$K37*$L37*$O37*VLOOKUP($H37,'Power Market Assumptions'!$B$41:$D$52,3,FALSE)*MAX(0,MIN(1,(W$5-'Power Market Assumptions'!I$23-$M37+1)/($N37-$M37+1))))
B38: P033 | C38: 2026-04 | D38: Oracle | E38: Bloom: contracted fuel cells | F38: US unallocated | G38: Equipment / deployment order | H38: Fuel cells | I38: 1200 | J38: MW | K38: 1200 | L38: 1 | M38: 2026 | N38: 2027 | O38: 1 | P38: 0 | Q38: S023 | R38: =IF(OR($K38="",$L38=0),0,$K38*$L38*$O38*VLOOKUP($H38,'Power Market Assumptions'!$B$41:$D$52,3,FALSE)*MAX(0,MIN(1,(R$5-'Power Market Assumptions'!D$23-$M38+1)/($N38-$M38+1)))) | S38: =IF(OR($K38="",$L38=0),0,$K38*$L38*$O38*VLOOKUP($H38,'Power Market Assumptions'!$B$41:$D$52,3,FALSE)*MAX(0,MIN(1,(S$5-'Power Market Assumptions'!E$23-$M38+1)/($N38-$M38+1)))) | T38: =IF(OR($K38="",$L38=0),0,$K38*$L38*$O38*VLOOKUP($H38,'Power Market Assumptions'!$B$41:$D$52,3,FALSE)*MAX(0,MIN(1,(T$5-'Power Market Assumptions'!F$23-$M38+1)/($N38-$M38+1)))) | U38: =IF(OR($K38="",$L38=0),0,$K38*$L38*$O38*VLOOKUP($H38,'Power Market Assumptions'!$B$41:$D$52,3,FALSE)*MAX(0,MIN(1,(U$5-'Power Market Assumptions'!G$23-$M38+1)/($N38-$M38+1)))) | V38: =IF(OR($K38="",$L38=0),0,$K38*$L38*$O38*VLOOKUP($H38,'Power Market Assumptions'!$B$41:$D$52,3,FALSE)*MAX(0,MIN(1,(V$5-'Power Market Assumptions'!H$23-$M38+1)/($N38-$M38+1)))) | W38: =IF(OR($K38="",$L38=0),0,$K38*$L38*$O38*VLOOKUP($H38,'Power Market Assumptions'!$B$41:$D$52,3,FALSE)*MAX(0,MIN(1,(W$5-'Power Market Assumptions'!I$23-$M38+1)/($N38-$M38+1))))
B39: P034 | C39: 2026-04 | D39: Oracle | E39: Bloom: remaining framework | F39: US unallocated | G39: Option | H39: Fuel cells | I39: 1600 | J39: MW | K39: 1600 | L39: 0 | M39: 2028 | N39: 2028 | O39: 0 | P39: 0 | Q39: S023 | R39: =IF(OR($K39="",$L39=0),0,$K39*$L39*$O39*VLOOKUP($H39,'Power Market Assumptions'!$B$41:$D$52,3,FALSE)*MAX(0,MIN(1,(R$5-'Power Market Assumptions'!D$23-$M39+1)/($N39-$M39+1)))) | S39: =IF(OR($K39="",$L39=0),0,$K39*$L39*$O39*VLOOKUP($H39,'Power Market Assumptions'!$B$41:$D$52,3,FALSE)*MAX(0,MIN(1,(S$5-'Power Market Assumptions'!E$23-$M39+1)/($N39-$M39+1)))) | T39: =IF(OR($K39="",$L39=0),0,$K39*$L39*$O39*VLOOKUP($H39,'Power Market Assumptions'!$B$41:$D$52,3,FALSE)*MAX(0,MIN(1,(T$5-'Power Market Assumptions'!F$23-$M39+1)/($N39-$M39+1)))) | U39: =IF(OR($K39="",$L39=0),0,$K39*$L39*$O39*VLOOKUP($H39,'Power Market Assumptions'!$B$41:$D$52,3,FALSE)*MAX(0,MIN(1,(U$5-'Power Market Assumptions'!G$23-$M39+1)/($N39-$M39+1)))) | V39: =IF(OR($K39="",$L39=0),0,$K39*$L39*$O39*VLOOKUP($H39,'Power Market Assumptions'!$B$41:$D$52,3,FALSE)*MAX(0,MIN(1,(V$5-'Power Market Assumptions'!H$23-$M39+1)/($N39-$M39+1)))) | W39: =IF(OR($K39="",$L39=0),0,$K39*$L39*$O39*VLOOKUP($H39,'Power Market Assumptions'!$B$41:$D$52,3,FALSE)*MAX(0,MIN(1,(W$5-'Power Market Assumptions'!I$23-$M39+1)/($N39-$M39+1))))
